Workbook

Sheet Promo Form
A1: AUSTRALIAN Claim Number | D1: Name of Promotion. | F1: Rebate | G1: 6 | S1: Rebate | T1: 6 | AF1: Rebate | AG1: 6 | AS1: Rebate | AT1: 6 | BF1: Rebate | BG1: 6 | BS1: Rebate | BT1: 6 | CF1: Rebate | CG1: 6
A2: Brand | F2: =_xlfn.XLOOKUP(F$3,'Data Validation'!$A:$A,'Data Validation'!$B:$B) -> 0.135 | N2: Growth Expectation | O2: 0.2 | S2: =_xlfn.XLOOKUP(S$3,'Data Validation'!$A:$A,'Data Validation'!$B:$B) -> 0.19 | AA2: Growth Expectation | AB2: 0.2 | AF2: =_xlfn.XLOOKUP(AF$3,'Data Validation'!$A:$A,'Data Validation'!$B:$B) -> 0.125 | AN2: Growth Expectation | AO2: 0.2 | AS2: =_xlfn.XLOOKUP(AS$3,'Data Validation'!$A:$A,'Data Validation'!$B:$B) -> 0.15 | BA2: Growth Expectation | BB2: 0.2 | BF2: =_xlfn.XLOOKUP(BF$3,'Data Validation'!$A:$A,'Data Validation'!$B:$B) -> 0.2 | BN2: Growth Expectation | BO2: 0.2 | BS2: =_xlfn.XLOOKUP(BS$3,'Data Validation'!$A:$A,'Data Validation'!$B:$B) -> 0.17 | CA2: Growth Expectation | CB2: 0.2 | CF2: =_xlfn.XLOOKUP(CF$3,'Data Validation'!$A:$A,'Data Validation'!$B:$B) -> 0.17 | CN2: Growth Expectation | CO2: 0.2
A3: Promo Date(s) | B3: =(B5-A5+1)/7 -> 2 | C3: Code | D3: Product Description | F3: AU - Officeworks | G3: <-- Select | J3: =F3 -> AU - Officeworks | S3: JB HIFI | T3: <-- Select | W3: =S3 -> JB HIFI | AF3: AU - Amazon | AG3: <-- Select | AJ3: =AF3 -> AU - Amazon | AS3: AU - The Good Guys | AT3: <-- Select | AW3: =AS3 -> AU - The Good Guys | BF3: Bing Lee | BG3: <-- Select | BJ3: =BF3 -> Bing Lee | BS3: Harvey Norman | BT3: <-- Select | BW3: =BS3 -> Harvey Norman | CF3: Harvey Norman | CG3: <-- Select | CJ3: =CF3 -> Harvey Norman
A4: From | B4: To | F4: Customer Code | G4: Retailer Buy ex | H4: Supplier Support | I4: MG Support | J4: Total Support | K4: End to End Standard Margin | L4: End to End Promo Margin | M4: Customer SOH | N4: Customer 6wk Avg | O4: Expected Sales / Actual Sales | P4: Supplier Claim Amount | Q4: MacGear Claim Amount | S4: Customer Code | T4: Retailer Buy ex | U4: Supplier Support | V4: MG Support | W4: Total Support | X4: End to End Standard Margin | Y4: End to End Promo Margin | Z4: Customer SOH | AA4: Customer 6wk Avg | AB4: Expected Sales / Actual Sales | AC4: Supplier Claim Amount | AD4: MacGear Claim Amount | AF4: Customer Code | AG4: Retailer Buy ex | AH4: Supplier Support | AI4: MG Support | AJ4: Total Support | AK4: End to End Standard Margin | AL4: End to End Promo Margin | AM4: Customer SOH | AN4: Customer 6wk Avg | AO4: Expected Sales / Actual Sales | AP4: Supplier Claim Amount | AQ4: MacGear Claim Amount | AS4: Customer Code | AT4: Retailer Buy ex | AU4: Supplier Support | AV4: MG Support | AW4: Total Support | AX4: End to End Standard Margin | AY4: End to End Promo Margin | AZ4: Customer SOH | BA4: Customer 6wk Avg | BB4: Expected Sales / Actual Sales | BC4: Supplier Claim Amount | BD4: MacGear Claim Amount | BF4: Customer Code | BG4: Retailer Buy ex | BH4: Supplier Support | BI4: MG Support | BJ4: Total Support | BK4: End to End Standard Margin | BL4: End to End Promo Margin | BM4: Customer SOH | BN4: Customer 6wk Avg | BO4: Expected Sales / Actual Sales | BP4: Supplier Claim Amount | BQ4: MacGear Claim Amount | BS4: Customer Code | BT4: Retailer Buy ex | BU4: Supplier Support | BV4: MG Support | BW4: Total Support | BX4: End to End Standard Margin | BY4: End to End Promo Margin | BZ4: Customer SOH | CA4: Customer 6wk Avg | CB4: Expected Sales / Actual Sales | CC4: Supplier Claim Amount | CD4: MacGear Claim Amount | CF4: Customer Code | CG4: Retailer Buy ex | CH4: Supplier Support | CI4: MG Support | CJ4: Total Support | CK4: End to End Standard Margin | CL4: End to End Promo Margin | CM4: Customer SOH | CN4: Customer 6wk Avg | CO4: Expected Sales / Actual Sales | CP4: Supplier Claim Amount | CQ4: MacGear Claim Amount | CS4: RRP Inc | CT4: Recommended Sale Inc | CU4: Recommended % Off | CV4: Recommended $ Off | CW4: Comments
A5: 45809 | B5: 45822 | C5: A1902T11 | D5: =IF(C5="", "",_xlfn.XLOOKUP(C5,'Master Price Level'!C:C,'Master Price Level'!D:D)) -> ANKER 100W Charging Base for ANKER Prime Power Bank | F5: {=IFERROR(_xlfn._xlws.FILTER(ST[Customer Code],(ST[Code]=$C5) * (ST[Customer Name]=F$3),"" ),"")} | G5: {=IFERROR(_xlfn.XLOOKUP($C5,Query[Code], _xlfn.XLOOKUP('Promo Form'!F$3,Query[[#Headers],[Code]:[Bing Lee]],Query[[Code]:[Bing Lee]])),"")} -> 84.98 | H5: =IFERROR(((G5*(1-F$2))*$CU5)*F$61,"") -> 4.8956128 | I5: =IFERROR(((G5*(1-F$2))*$CU5)*F$60,"") -> 4.8956128 | J5: =IFERROR(IF(H5+I5=0,"",H5+I5),"") -> 9.7912256 | K5: =IFERROR((($CS5/1.1)-(G5-(G5*F$2)))/($CS5/1.1),"") -> 0.52422201 | L5: =IFERROR((($CT5/1.1)+(H5+I5)-(G5-(G5*F$2)))/($CT5/1.1),"") -> 0.48449454 | M5: {=IFERROR(_xlfn._xlws.FILTER(ST[SOH],(ST[Code]=$C5) * (ST[Customer Name]=F$3),"" ),"")} | N5: {=IFERROR( _xlfn.LET( _xlpm.result, INDEX(_xlfn._xlws.FILTER(ST[6wk avg], (ST[Code]=$C5)*(ST[Customer Name]=F$3), ""), 1), IF(_xlpm.result=0, "", _xlpm.result) ), "")} | O5: =IFERROR(IF(CEILING(N5 + (N5 * $O$2), 1) = 0, "", CEILING(N5 + (N5 * $O$2), 1))*$B$3, "") | P5: =IFERROR((O5*H5),"") | Q5: =IFERROR((O5*I5),"") | S5: {=IFERROR(_xlfn._xlws.FILTER(ST[Customer Code],(ST[Code]=$C5) * (ST[Customer Name]=S$3),"" ),"")} | T5: {=IFERROR(_xlfn.XLOOKUP($C5,Query[Code], _xlfn.XLOOKUP('Promo Form'!S$3,Query[[#Headers],[Code]:[Bing Lee]],Query[[Code]:[Bing Lee]])),"")} -> 0 | U5: =IFERROR(((T5*(1-S$2))*$CU5)*S$61,"") -> 0 | V5: =IFERROR(((T5*(1-S$2))*$CU5)*S$60,"") -> 0 | W5: =IFERROR(IF(U5+V5=0,"",U5+V5),"") | X5: =IFERROR((($CS5/1.1)-(T5-(T5*S$2)))/($CS5/1.1),"") -> 1 | Y5: =IFERROR((($CT5/1.1)+(U5+V5)-(T5-(T5*S$2)))/($CT5/1.1),"") -> 1 | Z5: {=IFERROR(_xlfn._xlws.FILTER(ST[SOH],(ST[Code]=$C5) * (ST[Customer Name]=S$3),"" ),"")} | AA5: {=IFERROR( _xlfn.LET( _xlpm.result, INDEX(_xlfn._xlws.FILTER(ST[6wk avg], (ST[Code]=$C5)*(ST[Customer Name]=S$3), ""), 1), IF(_xlpm.result=0, "", _xlpm.result) ), "")} | AB5: =IFERROR(IF(CEILING(AA5 + (AA5 * $AB$2), 1) = 0, "", CEILING(AA5 + (AA5 * $AB$2), 1))*$B$3, "") | AC5: =IFERROR((AB5*U5),"") | AD5: =IFERROR((AB5*V5),"") | AF5: {=IFERROR(_xlfn._xlws.FILTER(ST[Customer Code],(ST[Code]=$C5) * (ST[Customer Name]=AF$3),"" ),"")} | AG5: {=IFERROR(_xlfn.XLOOKUP($C5,Query[Code], _xlfn.XLOOKUP('Promo Form'!AF$3,Query[[#Headers],[Code]:[Bing Lee]],Query[[Code]:[Bing Lee]])),"")} -> 0 | AH5: =IFERROR(((AG5*(1-AF$2))*$CU5)*AF$61,"") -> 0 | AI5: =IFERROR(((AG5*(1-AF$2))*$CU5)*AF$60,"") -> 0 | AJ5: =IFERROR(IF(AH5+AI5=0,"",AH5+AI5),"") | AK5: =IFERROR((($CS5/1.1)-(AG5-(AG5*AF$2)))/($CS5/1.1),"") -> 1 | AL5: =IFERROR((($CT5/1.1)+(AH5+AI5)-(AG5-(AG5*AF$2)))/($CT5/1.1),"") -> 1 | AM5: {=IFERROR(_xlfn._xlws.FILTER(ST[SOH],(ST[Code]=$C5) * (ST[Customer Name]=AF$3),"" ),"")} | AN5: {=IFERROR( _xlfn.LET( _xlpm.result, INDEX(_xlfn._xlws.FILTER(ST[6wk avg], (ST[Code]=$C5)*(ST[Customer Name]=AF$3), ""), 1), IF(_xlpm.result=0, "", _xlpm.result) ), "")} | AO5: =IFERROR(IF(CEILING(AN5 + (AN5 * $AO$2), 1) = 0, "", CEILING(AN5 + (AN5 * $AO$2), 1))*$B$3, "") | AP5: =IFERROR((AO5*AH5),"") | AQ5: =IFERROR((AO5*AI5),"") | AS5: {=IFERROR(_xlfn._xlws.FILTER(ST[Customer Code],(ST[Code]=$C5) * (ST[Customer Name]=AS$3),"" ),"")} | AT5: {=IFERROR(_xlfn.XLOOKUP($C5,Query[Code], _xlfn.XLOOKUP('Promo Form'!AS$3,Query[[#Headers],[Code]:[Bing Lee]],Query[[Code]:[Bing Lee]])),"")} -> 0 | AU5: =IFERROR(((AT5*(1-AS$2))*$CU5)*AS$61,"") -> 0 | AV5: =IFERROR(((AT5*(1-AS$2))*$CU5)*AS$60,"") -> 0 | AW5: =IFERROR(IF(AU5+AV5=0,"",AU5+AV5),"") | AX5: =IFERROR((($CS5/1.1)-(AT5-(AT5*AS$2)))/($CS5/1.1),"") -> 1 | AY5: =IFERROR((($CT5/1.1)+(AU5+AV5)-(AT5-(AT5*AS$2)))/($CT5/1.1),"") -> 1 | AZ5: {=IFERROR(_xlfn._xlws.FILTER(ST[SOH],(ST[Code]=$C5) * (ST[Customer Name]=AS$3),"" ),"")} | BA5: {=IFERROR( _xlfn.LET( _xlpm.result, INDEX(_xlfn._xlws.FILTER(ST[6wk avg], (ST[Code]=$C5)*(ST[Customer Name]=AS$3), ""), 1), IF(_xlpm.result=0, "", _xlpm.result) ), "")} | BB5: =IFERROR(IF(CEILING(BA5 + (BA5 * $BB$2), 1) = 0, "", CEILING(BA5 + (BA5 * $BB$2), 1))*$B$3, "") | BC5: =IFERROR((BB5*AU5),"") | BD5: =IFERROR((BB5*AV5),"") | BF5: {=IFERROR(_xlfn._xlws.FILTER(ST[Customer Code],(ST[Code]=$C5) * (ST[Customer Name]=BF$3),"" ),"")} | BG5: {=IFERROR(_xlfn.XLOOKUP($C5,Query[Code], _xlfn.XLOOKUP('Promo Form'!BF$3,Query[[#Headers],[Code]:[Bing Lee]],Query[[Code]:[Bing Lee]])),"")} -> 0 | BH5: =IFERROR(((BG5*(1-BF$2))*$CU5)*BF$61,"") -> 0 | BI5: =IFERROR(((BG5*(1-BF$2))*$CU5)*BF$60,"") -> 0 | BJ5: =IFERROR(IF(BH5+BI5=0,"",BH5+BI5),"") | BK5: =IFERROR((($CS5/1.1)-(BG5-(BG5*BF$2)))/($CS5/1.1),"") -> 1 | BL5: =IFERROR((($CT5/1.1)+(BH5+BI5)-(BG5-(BG5*BF$2)))/($CT5/1.1),"") -> 1 | BM5: {=IFERROR(_xlfn._xlws.FILTER(ST[SOH],(ST[Code]=$C5) * (ST[Customer Name]=BF$3),"" ),"")} | BN5: {=IFERROR( _xlfn.LET( _xlpm.result, INDEX(_xlfn._xlws.FILTER(ST[6wk avg], (ST[Code]=$C5)*(ST[Customer Name]=BF$3), ""), 1), IF(_xlpm.result=0, "", _xlpm.result) ), "")} | BO5: =IFERROR(IF(CEILING(BN5 + (BN5 * $BO$2), 1) = 0, "", CEILING(BN5 + (BN5 * $BO$2), 1))*$B$3, "") | BP5: =IFERROR((BO5*BH5),"") | BQ5: =IFERROR((BO5*BI5),"") | BS5: {=IFERROR(_xlfn._xlws.FILTER(ST[Customer Code],(ST[Code]=$C5) * (ST[Customer Name]=BS$3),"" ),"")} | BT5: {=IFERROR(_xlfn.XLOOKUP($C5,Query[Code], _xlfn.XLOOKUP('Promo Form'!BS$3,Query[[#Headers],[Code]:[Bing Lee]],Query[[Code]:[Bing Lee]])),"")} -> 92.7 | BU5: =IFERROR(((BT5*(1-BS$2))*$CU5)*BS$61,"") -> 5.1242706 | BV5: =IFERROR(((BT5*(1-BS$2))*$CU5)*BS$60,"") -> 5.1242706 | BW5: =IFERROR(IF(BU5+BV5=0,"",BU5+BV5),"") -> 10.248541 | BX5: =IFERROR((($CS5/1.1)-(BT5-(BT5*BS$2)))/($CS5/1.1),"") -> 0.502 | BY5: =IFERROR((($CT5/1.1)+(BU5+BV5)-(BT5-(BT5*BS$2)))/($CT5/1.1),"") -> 0.460417 | BZ5: {=IFERROR(_xlfn._xlws.FILTER(ST[SOH],(ST[Code]=$C5) * (ST[Customer Name]=BS$3),"" ),"")} | CA5: {=IFERROR( _xlfn.LET( _xlpm.result, INDEX(_xlfn._xlws.FILTER(ST[6wk avg], (ST[Code]=$C5)*(ST[Customer Name]=BS$3), ""), 1), IF(_xlpm.result=0, "", _xlpm.result) ), "")} | CB5: =IFERROR(IF(CEILING(CA5 + (CA5 * $CB$2), 1) = 0, "", CEILING(CA5 + (CA5 * $CB$2), 1))*$B$3, "") | CC5: =IFERROR((CB5*BU5),"") | CD5: =IFERROR((CB5*BV5),"") | CF5: {=IFERROR(_xlfn._xlws.FILTER(ST[Customer Code],(ST[Code]=$C5) * (ST[Customer Name]=CF$3),"" ),"")} | CG5: {=IFERROR(_xlfn.XLOOKUP($C5,Query[Code], _xlfn.XLOOKUP('Promo Form'!CF$3,Query[[#Headers],[Code]:[Bing Lee]],Query[[Code]:[Bing Lee]])),"")} -> 92.7 | CH5: =IFERROR(((CG5*(1-CF$2))*$CU5)*CF$61,"") -> 5.1242706 | CI5: =IFERROR(((CG5*(1-CF$2))*$CU5)*CF$60,"") -> 5.1242706 | CJ5: =IFERROR(IF(CH5+CI5=0,"",CH5+CI5),"") -> 10.248541 | CK5: =IFERROR((($CS5/1.1)-(CG5-(CG5*CF$2)))/($CS5/1.1),"") -> 0.502 | CL5: =IFERROR((($CT5/1.1)+(CH5+CI5)-(CG5-(CG5*CF$2)))/($CT5/1.1),"") -> 0.460417 | CM5: {=IFERROR(_xlfn._xlws.FILTER(ST[SOH],(ST[Code]=$C5) * (ST[Customer Name]=CF$3),"" ),"")} | CN5: {=IFERROR( _xlfn.LET( _xlpm.result, INDEX(_xlfn._xlws.FILTER(ST[6wk avg], (ST[Code]=$C5)*(ST[Customer Name]=CF$3), ""), 1), IF(_xlpm.result=0, "", _xlpm.result) ), "")} | CO5: =IFERROR(IF(CEILING(CN5 + (CN5 * $CO$2), 1) = 0, "", CEILING(CN5 + (CN5 * $CO$2), 1))*$B$3, "") | CP5: =IFERROR((CO5*CH5),"") | CQ5: =IFERROR((CO5*CI5),"") | CS5: =IFERROR(_xlfn.XLOOKUP(C5,Query[Code],Query[Base (RRP Inc)]),"") -> 169.95 | CT5: =IFERROR(CS5-(CS5*CU5),"") -> 135.96 | CU5: 0.2 | CV5: =IFERROR((CS5-CT5),"") -> 33.99
A6: =IF(C6="","",$A$5) | B6: =IF(C6="","",$B$5) | D6: =IF(C6="", "",_xlfn.XLOOKUP(C6,'Master Price Level'!C:C,'Master Price Level'!D:D)) | F6: {=IFERROR(_xlfn._xlws.FILTER(ST[Customer Code],(ST[Code]=$C6) * (ST[Customer Name]=F$3),"" ),"")} | G6: {=IFERROR(_xlfn.XLOOKUP($C6,Query[Code], _xlfn.XLOOKUP('Promo Form'!F$3,Query[[#Headers],[Code]:[Bing Lee]],Query[[Code]:[Bing Lee]])),"")} | H6: =IFERROR(((G6*(1-F$2))*$CU6)*F$61,"") | I6: =IFERROR(((G6*(1-F$2))*$CU6)*F$60,"") | J6: =IFERROR(IF(H6+I6=0,"",H6+I6),"") | K6: =IFERROR((($CS6/1.1)-(G6-(G6*F$2)))/($CS6/1.1),"") | L6: =IFERROR((($CT6/1.1)+(H6+I6)-(G6-(G6*F$2)))/($CT6/1.1),"") | M6: {=IFERROR(_xlfn._xlws.FILTER(ST[SOH],(ST[Code]=$C6) * (ST[Customer Name]=F$3),"" ),"")} | N6: {=IFERROR( _xlfn.LET( _xlpm.result, INDEX(_xlfn._xlws.FILTER(ST[6wk avg], (ST[Code]=$C6)*(ST[Customer Name]=F$3), ""), 1), IF(_xlpm.result=0, "", _xlpm.result) ), "")} | O6: =IFERROR(IF(CEILING(N6 + (N6 * $O$2), 1) = 0, "", CEILING(N6 + (N6 * $O$2), 1))*$B$3, "") | P6: =IFERROR((O6*H6),"") | Q6: =IFERROR((O6*I6),"") | S6: {=IFERROR(_xlfn._xlws.FILTER(ST[Customer Code],(ST[Code]=$C6) * (ST[Customer Name]=S$3),"" ),"")} | T6: {=IFERROR(_xlfn.XLOOKUP($C6,Query[Code], _xlfn.XLOOKUP('Promo Form'!S$3,Query[[#Headers],[Code]:[Bing Lee]],Query[[Code]:[Bing Lee]])),"")} | U6: =IFERROR(((T6*(1-S$2))*$CU6)*S$61,"") | V6: =IFERROR(((T6*(1-S$2))*$CU6)*S$60,"") | W6: =IFERROR(IF(U6+V6=0,"",U6+V6),"") | X6: =IFERROR((($CS6/1.1)-(T6-(T6*S$2)))/($CS6/1.1),"") | Y6: =IFERROR((($CT6/1.1)+(U6+V6)-(T6-(T6*S$2)))/($CT6/1.1),"") | Z6: {=IFERROR(_xlfn._xlws.FILTER(ST[SOH],(ST[Code]=$C6) * (ST[Customer Name]=S$3),"" ),"")} | AA6: {=IFERROR( _xlfn.LET( _xlpm.result, INDEX(_xlfn._xlws.FILTER(ST[6wk avg], (ST[Code]=$C6)*(ST[Customer Name]=S$3), ""), 1), IF(_xlpm.result=0, "", _xlpm.result) ), "")} | AB6: =IFERROR(IF(CEILING(AA6 + (AA6 * $AB$2), 1) = 0, "", CEILING(AA6 + (AA6 * $AB$2), 1))*$B$3, "") | AC6: =IFERROR((AB6*U6),"") | AD6: =IFERROR((AB6*V6),"") | AF6: {=IFERROR(_xlfn._xlws.FILTER(ST[Customer Code],(ST[Code]=$C6) * (ST[Customer Name]=AF$3),"" ),"")} | AG6: {=IFERROR(_xlfn.XLOOKUP($C6,Query[Code], _xlfn.XLOOKUP('Promo Form'!AF$3,Query[[#Headers],[Code]:[Bing Lee]],Query[[Code]:[Bing Lee]])),"")} | AH6: =IFERROR(((AG6*(1-AF$2))*$CU6)*AF$61,"") | AI6: =IFERROR(((AG6*(1-AF$2))*$CU6)*AF$60,"") | AJ6: =IFERROR(IF(AH6+AI6=0,"",AH6+AI6),"") | AK6: =IFERROR((($CS6/1.1)-(AG6-(AG6*AF$2)))/($CS6/1.1),"") | AL6: =IFERROR((($CT6/1.1)+(AH6+AI6)-(AG6-(AG6*AF$2)))/($CT6/1.1),"") | AM6: {=IFERROR(_xlfn._xlws.FILTER(ST[SOH],(ST[Code]=$C6) * (ST[Customer Name]=AF$3),"" ),"")} | AN6: {=IFERROR( _xlfn.LET( _xlpm.result, INDEX(_xlfn._xlws.FILTER(ST[6wk avg], (ST[Code]=$C6)*(ST[Customer Name]=AF$3), ""), 1), IF(_xlpm.result=0, "", _xlpm.result) ), "")} | AO6: =IFERROR(IF(CEILING(AN6 + (AN6 * $AO$2), 1) = 0, "", CEILING(AN6 + (AN6 * $AO$2), 1))*$B$3, "") | AP6: =IFERROR((AO6*AH6),"") | AQ6: =IFERROR((AO6*AI6),"") | AS6: {=IFERROR(_xlfn._xlws.FILTER(ST[Customer Code],(ST[Code]=$C6) * (ST[Customer Name]=AS$3),"" ),"")} | AT6: {=IFERROR(_xlfn.XLOOKUP($C6,Query[Code], _xlfn.XLOOKUP('Promo Form'!AS$3,Query[[#Headers],[Code]:[Bing Lee]],Query[[Code]:[Bing Lee]])),"")} | AU6: =IFERROR(((AT6*(1-AS$2))*$CU6)*AS$61,"") | AV6: =IFERROR(((AT6*(1-AS$2))*$CU6)*AS$60,"") | AW6: =IFERROR(IF(AU6+AV6=0,"",AU6+AV6),"") | AX6: =IFERROR((($CS6/1.1)-(AT6-(AT6*AS$2)))/($CS6/1.1),"") | AY6: =IFERROR((($CT6/1.1)+(AU6+AV6)-(AT6-(AT6*AS$2)))/($CT6/1.1),"") | AZ6: {=IFERROR(_xlfn._xlws.FILTER(ST[SOH],(ST[Code]=$C6) * (ST[Customer Name]=AS$3),"" ),"")} | BA6: {=IFERROR( _xlfn.LET( _xlpm.result, INDEX(_xlfn._xlws.FILTER(ST[6wk avg], (ST[Code]=$C6)*(ST[Customer Name]=AS$3), ""), 1), IF(_xlpm.result=0, "", _xlpm.result) ), "")} | BB6: =IFERROR(IF(CEILING(BA6 + (BA6 * $BB$2), 1) = 0, "", CEILING(BA6 + (BA6 * $BB$2), 1))*$B$3, "") | BC6: =IFERROR((BB6*AU6),"") | BD6: =IFERROR((BB6*AV6),"") | BF6: {=IFERROR(_xlfn._xlws.FILTER(ST[Customer Code],(ST[Code]=$C6) * (ST[Customer Name]=BF$3),"" ),"")} | BG6: {=IFERROR(_xlfn.XLOOKUP($C6,Query[Code], _xlfn.XLOOKUP('Promo Form'!BF$3,Query[[#Headers],[Code]:[Bing Lee]],Query[[Code]:[Bing Lee]])),"")} | BH6: =IFERROR(((BG6*(1-BF$2))*$CU6)*BF$61,"") | BI6: =IFERROR(((BG6*(1-BF$2))*$CU6)*BF$60,"") | BJ6: =IFERROR(IF(BH6+BI6=0,"",BH6+BI6),"") | BK6: =IFERROR((($CS6/1.1)-(BG6-(BG6*BF$2)))/($CS6/1.1),"") | BL6: =IFERROR((($CT6/1.1)+(BH6+BI6)-(BG6-(BG6*BF$2)))/($CT6/1.1),"") | BM6: {=IFERROR(_xlfn._xlws.FILTER(ST[SOH],(ST[Code]=$C6) * (ST[Customer Name]=BF$3),"" ),"")} | BN6: {=IFERROR( _xlfn.LET( _xlpm.result, INDEX(_xlfn._xlws.FILTER(ST[6wk avg], (ST[Code]=$C6)*(ST[Customer Name]=BF$3), ""), 1), IF(_xlpm.result=0, "", _xlpm.result) ), "")} | BO6: =IFERROR(IF(CEILING(BN6 + (BN6 * $BO$2), 1) = 0, "", CEILING(BN6 + (BN6 * $BO$2), 1))*$B$3, "") | BP6: =IFERROR((BO6*BH6),"") | BQ6: =IFERROR((BO6*BI6),"") | BS6: {=IFERROR(_xlfn._xlws.FILTER(ST[Customer Code],(ST[Code]=$C6) * (ST[Customer Name]=BS$3),"" ),"")} | BT6: {=IFERROR(_xlfn.XLOOKUP($C6,Query[Code], _xlfn.XLOOKUP('Promo Form'!BS$3,Query[[#Headers],[Code]:[Bing Lee]],Query[[Code]:[Bing Lee]])),"")} | BU6: =IFERROR(((BT6*(1-BS$2))*$CU6)*BS$61,"") | BV6: =IFERROR(((BT6*(1-BS$2))*$CU6)*BS$60,"") | BW6: =IFERROR(IF(BU6+BV6=0,"",BU6+BV6),"") | BX6: =IFERROR((($CS6/1.1)-(BT6-(BT6*BS$2)))/($CS6/1.1),"") | BY6: =IFERROR((($CT6/1.1)+(BU6+BV6)-(BT6-(BT6*BS$2)))/($CT6/1.1),"") | BZ6: {=IFERROR(_xlfn._xlws.FILTER(ST[SOH],(ST[Code]=$C6) * (ST[Customer Name]=BS$3),"" ),"")} | CA6: {=IFERROR( _xlfn.LET( _xlpm.result, INDEX(_xlfn._xlws.FILTER(ST[6wk avg], (ST[Code]=$C6)*(ST[Customer Name]=BS$3), ""), 1), IF(_xlpm.result=0, "", _xlpm.result) ), "")} | CB6: =IFERROR(IF(CEILING(CA6 + (CA6 * $CB$2), 1) = 0, "", CEILING(CA6 + (CA6 * $CB$2), 1))*$B$3, "") | CC6: =IFERROR((CB6*BU6),"") | CD6: =IFERROR((CB6*BV6),"") | CF6: {=IFERROR(_xlfn._xlws.FILTER(ST[Customer Code],(ST[Code]=$C6) * (ST[Customer Name]=CF$3),"" ),"")} | CG6: {=IFERROR(_xlfn.XLOOKUP($C6,Query[Code], _xlfn.XLOOKUP('Promo Form'!CF$3,Query[[#Headers],[Code]:[Bing Lee]],Query[[Code]:[Bing Lee]])),"")} | CH6: =IFERROR(((CG6*(1-CF$2))*$CU6)*CF$61,"") | CI6: =IFERROR(((CG6*(1-CF$2))*$CU6)*CF$60,"") | CJ6: =IFERROR(IF(CH6+CI6=0,"",CH6+CI6),"") | CK6: =IFERROR((($CS6/1.1)-(CG6-(CG6*CF$2)))/($CS6/1.1),"") | CL6: =IFERROR((($CT6/1.1)+(CH6+CI6)-(CG6-(CG6*CF$2)))/($CT6/1.1),"") | CM6: {=IFERROR(_xlfn._xlws.FILTER(ST[SOH],(ST[Code]=$C6) * (ST[Customer Name]=CF$3),"" ),"")} | CN6: {=IFERROR( _xlfn.LET( _xlpm.result, INDEX(_xlfn._xlws.FILTER(ST[6wk avg], (ST[Code]=$C6)*(ST[Customer Name]=CF$3), ""), 1), IF(_xlpm.result=0, "", _xlpm.result) ), "")} | CO6: =IFERROR(IF(CEILING(CN6 + (CN6 * $CO$2), 1) = 0, "", CEILING(CN6 + (CN6 * $CO$2), 1))*$B$3, "") | CP6: =IFERROR((CO6*CH6),"") | CQ6: =IFERROR((CO6*CI6),"") | CS6: =IFERROR(_xlfn.XLOOKUP(C6,Query[Code],Query[Base (RRP Inc)]),"") | CT6: =IFERROR(CS6-(CS6*CU6),"") | CU6: =IF(C6="", "",CU5) | CV6: =IFERROR((CS6-CT6),"")
A7: =IF(C7="","",A6) | B7: =IF(C7="","",B6) | D7: =IF(C7="", "",_xlfn.XLOOKUP(C7,'Master Price Level'!C:C,'Master Price Level'!D:D)) | F7: {=IFERROR(_xlfn._xlws.FILTER(ST[Customer Code],(ST[Code]=$C7) * (ST[Customer Name]=F$3),"" ),"")} | G7: {=IFERROR(_xlfn.XLOOKUP($C7,Query[Code], _xlfn.XLOOKUP('Promo Form'!F$3,Query[[#Headers],[Code]:[Bing Lee]],Query[[Code]:[Bing Lee]])),"")} | H7: =IFERROR(((G7*(1-F$2))*$CU7)*F$61,"") | I7: =IFERROR(((G7*(1-F$2))*$CU7)*F$60,"") | J7: =IFERROR(IF(H7+I7=0,"",H7+I7),"") | K7: =IFERROR((($CS7/1.1)-(G7-(G7*F$2)))/($CS7/1.1),"") | L7: =IFERROR((($CT7/1.1)+(H7+I7)-(G7-(G7*F$2)))/($CT7/1.1),"") | M7: {=IFERROR(_xlfn._xlws.FILTER(ST[SOH],(ST[Code]=$C7) * (ST[Customer Name]=F$3),"" ),"")} | N7: {=IFERROR( _xlfn.LET( _xlpm.result, INDEX(_xlfn._xlws.FILTER(ST[6wk avg], (ST[Code]=$C7)*(ST[Customer Name]=F$3), ""), 1), IF(_xlpm.result=0, "", _xlpm.result) ), "")} | O7: =IFERROR(IF(CEILING(N7 + (N7 * $O$2), 1) = 0, "", CEILING(N7 + (N7 * $O$2), 1))*$B$3, "") | P7: =IFERROR((O7*H7),"") | Q7: =IFERROR((O7*I7),"") | S7: {=IFERROR(_xlfn._xlws.FILTER(ST[Customer Code],(ST[Code]=$C7) * (ST[Customer Name]=S$3),"" ),"")} | T7: {=IFERROR(_xlfn.XLOOKUP($C7,Query[Code], _xlfn.XLOOKUP('Promo Form'!S$3,Query[[#Headers],[Code]:[Bing Lee]],Query[[Code]:[Bing Lee]])),"")} | U7: =IFERROR(((T7*(1-S$2))*$CU7)*S$61,"") | V7: =IFERROR(((T7*(1-S$2))*$CU7)*S$60,"") | W7: =IFERROR(IF(U7+V7=0,"",U7+V7),"") | X7: =IFERROR((($CS7/1.1)-(T7-(T7*S$2)))/($CS7/1.1),"") | Y7: =IFERROR((($CT7/1.1)+(U7+V7)-(T7-(T7*S$2)))/($CT7/1.1),"") | Z7: {=IFERROR(_xlfn._xlws.FILTER(ST[SOH],(ST[Code]=$C7) * (ST[Customer Name]=S$3),"" ),"")} | AA7: {=IFERROR( _xlfn.LET( _xlpm.result, INDEX(_xlfn._xlws.FILTER(ST[6wk avg], (ST[Code]=$C7)*(ST[Customer Name]=S$3), ""), 1), IF(_xlpm.result=0, "", _xlpm.result) ), "")} | AB7: =IFERROR(IF(CEILING(AA7 + (AA7 * $AB$2), 1) = 0, "", CEILING(AA7 + (AA7 * $AB$2), 1))*$B$3, "") | AC7: =IFERROR((AB7*U7),"") | AD7: =IFERROR((AB7*V7),"") | AF7: {=IFERROR(_xlfn._xlws.FILTER(ST[Customer Code],(ST[Code]=$C7) * (ST[Customer Name]=AF$3),"" ),"")} | AG7: {=IFERROR(_xlfn.XLOOKUP($C7,Query[Code], _xlfn.XLOOKUP('Promo Form'!AF$3,Query[[#Headers],[Code]:[Bing Lee]],Query[[Code]:[Bing Lee]])),"")} | AH7: =IFERROR(((AG7*(1-AF$2))*$CU7)*AF$61,"") | AI7: =IFERROR(((AG7*(1-AF$2))*$CU7)*AF$60,"") | AJ7: =IFERROR(IF(AH7+AI7=0,"",AH7+AI7),"") | AK7: =IFERROR((($CS7/1.1)-(AG7-(AG7*AF$2)))/($CS7/1.1),"") | AL7: =IFERROR((($CT7/1.1)+(AH7+AI7)-(AG7-(AG7*AF$2)))/($CT7/1.1),"") | AM7: {=IFERROR(_xlfn._xlws.FILTER(ST[SOH],(ST[Code]=$C7) * (ST[Customer Name]=AF$3),"" ),"")} | AN7: {=IFERROR( _xlfn.LET( _xlpm.result, INDEX(_xlfn._xlws.FILTER(ST[6wk avg], (ST[Code]=$C7)*(ST[Customer Name]=AF$3), ""), 1), IF(_xlpm.result=0, "", _xlpm.result) ), "")} | AO7: =IFERROR(IF(CEILING(AN7 + (AN7 * $AO$2), 1) = 0, "", CEILING(AN7 + (AN7 * $AO$2), 1))*$B$3, "") | AP7: =IFERROR((AO7*AH7),"") | AQ7: =IFERROR((AO7*AI7),"") | AS7: {=IFERROR(_xlfn._xlws.FILTER(ST[Customer Code],(ST[Code]=$C7) * (ST[Customer Name]=AS$3),"" ),"")} | AT7: {=IFERROR(_xlfn.XLOOKUP($C7,Query[Code], _xlfn.XLOOKUP('Promo Form'!AS$3,Query[[#Headers],[Code]:[Bing Lee]],Query[[Code]:[Bing Lee]])),"")} | AU7: =IFERROR(((AT7*(1-AS$2))*$CU7)*AS$61,"") | AV7: =IFERROR(((AT7*(1-AS$2))*$CU7)*AS$60,"") | AW7: =IFERROR(IF(AU7+AV7=0,"",AU7+AV7),"") | AX7: =IFERROR((($CS7/1.1)-(AT7-(AT7*AS$2)))/($CS7/1.1),"") | AY7: =IFERROR((($CT7/1.1)+(AU7+AV7)-(AT7-(AT7*AS$2)))/($CT7/1.1),"") | AZ7: {=IFERROR(_xlfn._xlws.FILTER(ST[SOH],(ST[Code]=$C7) * (ST[Customer Name]=AS$3),"" ),"")} | BA7: {=IFERROR( _xlfn.LET( _xlpm.result, INDEX(_xlfn._xlws.FILTER(ST[6wk avg], (ST[Code]=$C7)*(ST[Customer Name]=AS$3), ""), 1), IF(_xlpm.result=0, "", _xlpm.result) ), "")} | BB7: =IFERROR(IF(CEILING(BA7 + (BA7 * $BB$2), 1) = 0, "", CEILING(BA7 + (BA7 * $BB$2), 1))*$B$3, "") | BC7: =IFERROR((BB7*AU7),"") | BD7: =IFERROR((BB7*AV7),"") | BF7: {=IFERROR(_xlfn._xlws.FILTER(ST[Customer Code],(ST[Code]=$C7) * (ST[Customer Name]=BF$3),"" ),"")} | BG7: {=IFERROR(_xlfn.XLOOKUP($C7,Query[Code], _xlfn.XLOOKUP('Promo Form'!BF$3,Query[[#Headers],[Code]:[Bing Lee]],Query[[Code]:[Bing Lee]])),"")} | BH7: =IFERROR(((BG7*(1-BF$2))*$CU7)*BF$61,"") | BI7: =IFERROR(((BG7*(1-BF$2))*$CU7)*BF$60,"") | BJ7: =IFERROR(IF(BH7+BI7=0,"",BH7+BI7),"") | BK7: =IFERROR((($CS7/1.1)-(BG7-(BG7*BF$2)))/($CS7/1.1),"") | BL7: =IFERROR((($CT7/1.1)+(BH7+BI7)-(BG7-(BG7*BF$2)))/($CT7/1.1),"") | BM7: {=IFERROR(_xlfn._xlws.FILTER(ST[SOH],(ST[Code]=$C7) * (ST[Customer Name]=BF$3),"" ),"")} | BN7: {=IFERROR( _xlfn.LET( _xlpm.result, INDEX(_xlfn._xlws.FILTER(ST[6wk avg], (ST[Code]=$C7)*(ST[Customer Name]=BF$3), ""), 1), IF(_xlpm.result=0, "", _xlpm.result) ), "")} | BO7: =IFERROR(IF(CEILING(BN7 + (BN7 * $BO$2), 1) = 0, "", CEILING(BN7 + (BN7 * $BO$2), 1))*$B$3, "") | BP7: =IFERROR((BO7*BH7),"") | BQ7: =IFERROR((BO7*BI7),"") | BS7: {=IFERROR(_xlfn._xlws.FILTER(ST[Customer Code],(ST[Code]=$C7) * (ST[Customer Name]=BS$3),"" ),"")} | BT7: {=IFERROR(_xlfn.XLOOKUP($C7,Query[Code], _xlfn.XLOOKUP('Promo Form'!BS$3,Query[[#Headers],[Code]:[Bing Lee]],Query[[Code]:[Bing Lee]])),"")} | BU7: =IFERROR(((BT7*(1-BS$2))*$CU7)*BS$61,"") | BV7: =IFERROR(((BT7*(1-BS$2))*$CU7)*BS$60,"") | BW7: =IFERROR(IF(BU7+BV7=0,"",BU7+BV7),"") | BX7: =IFERROR((($CS7/1.1)-(BT7-(BT7*BS$2)))/($CS7/1.1),"") | BY7: =IFERROR((($CT7/1.1)+(BU7+BV7)-(BT7-(BT7*BS$2)))/($CT7/1.1),"") | BZ7: {=IFERROR(_xlfn._xlws.FILTER(ST[SOH],(ST[Code]=$C7) * (ST[Customer Name]=BS$3),"" ),"")} | CA7: {=IFERROR( _xlfn.LET( _xlpm.result, INDEX(_xlfn._xlws.FILTER(ST[6wk avg], (ST[Code]=$C7)*(ST[Customer Name]=BS$3), ""), 1), IF(_xlpm.result=0, "", _xlpm.result) ), "")} | CB7: =IFERROR(IF(CEILING(CA7 + (CA7 * $CB$2), 1) = 0, "", CEILING(CA7 + (CA7 * $CB$2), 1))*$B$3, "") | CC7: =IFERROR((CB7*BU7),"") | CD7: =IFERROR((CB7*BV7),"") | CF7: {=IFERROR(_xlfn._xlws.FILTER(ST[Customer Code],(ST[Code]=$C7) * (ST[Customer Name]=CF$3),"" ),"")} | CG7: {=IFERROR(_xlfn.XLOOKUP($C7,Query[Code], _xlfn.XLOOKUP('Promo Form'!CF$3,Query[[#Headers],[Code]:[Bing Lee]],Query[[Code]:[Bing Lee]])),"")} | CH7: =IFERROR(((CG7*(1-CF$2))*$CU7)*CF$61,"") | CI7: =IFERROR(((CG7*(1-CF$2))*$CU7)*CF$60,"") | CJ7: =IFERROR(IF(CH7+CI7=0,"",CH7+CI7),"") | CK7: =IFERROR((($CS7/1.1)-(CG7-(CG7*CF$2)))/($CS7/1.1),"") | CL7: =IFERROR((($CT7/1.1)+(CH7+CI7)-(CG7-(CG7*CF$2)))/($CT7/1.1),"") | CM7: {=IFERROR(_xlfn._xlws.FILTER(ST[SOH],(ST[Code]=$C7) * (ST[Customer Name]=CF$3),"" ),"")} | CN7: {=IFERROR( _xlfn.LET( _xlpm.result, INDEX(_xlfn._xlws.FILTER(ST[6wk avg], (ST[Code]=$C7)*(ST[Customer Name]=CF$3), ""), 1), IF(_xlpm.result=0, "", _xlpm.result) ), "")} | CO7: =IFERROR(IF(CEILING(CN7 + (CN7 * $CO$2), 1) = 0, "", CEILING(CN7 + (CN7 * $CO$2), 1))*$B$3, "") | CP7: =IFERROR((CO7*CH7),"") | CQ7: =IFERROR((CO7*CI7),"") | CS7: =IFERROR(_xlfn.XLOOKUP(C7,Query[Code],Query[Base (RRP Inc)]),"") | CT7: =IFERROR(CS7-(CS7*CU7),"") | CU7: =IF(C7="", "",CU6) | CV7: =IFERROR((CS7-CT7),"")
A8: =IF(C8="","",A7) | B8: =IF(C8="","",B7) | D8: =IF(C8="", "",_xlfn.XLOOKUP(C8,'Master Price Level'!C:C,'Master Price Level'!D:D)) | F8: {=IFERROR(_xlfn._xlws.FILTER(ST[Customer Code],(ST[Code]=$C8) * (ST[Customer Name]=F$3),"" ),"")} | G8: {=IFERROR(_xlfn.XLOOKUP($C8,Query[Code], _xlfn.XLOOKUP('Promo Form'!F$3,Query[[#Headers],[Code]:[Bing Lee]],Query[[Code]:[Bing Lee]])),"")} | H8: =IFERROR(((G8*(1-F$2))*$CU8)*F$61,"") | I8: =IFERROR(((G8*(1-F$2))*$CU8)*F$60,"") | J8: =IFERROR(IF(H8+I8=0,"",H8+I8),"") | K8: =IFERROR((($CS8/1.1)-(G8-(G8*F$2)))/($CS8/1.1),"") | L8: =IFERROR((($CT8/1.1)+(H8+I8)-(G8-(G8*F$2)))/($CT8/1.1),"") | M8: {=IFERROR(_xlfn._xlws.FILTER(ST[SOH],(ST[Code]=$C8) * (ST[Customer Name]=F$3),"" ),"")} | N8: {=IFERROR( _xlfn.LET( _xlpm.result, INDEX(_xlfn._xlws.FILTER(ST[6wk avg], (ST[Code]=$C8)*(ST[Customer Name]=F$3), ""), 1), IF(_xlpm.result=0, "", _xlpm.result) ), "")} | O8: =IFERROR(IF(CEILING(N8 + (N8 * $O$2), 1) = 0, "", CEILING(N8 + (N8 * $O$2), 1))*$B$3, "") | P8: =IFERROR((O8*H8),"") | Q8: =IFERROR((O8*I8),"") | S8: {=IFERROR(_xlfn._xlws.FILTER(ST[Customer Code],(ST[Code]=$C8) * (ST[Customer Name]=S$3),"" ),"")} | T8: {=IFERROR(_xlfn.XLOOKUP($C8,Query[Code], _xlfn.XLOOKUP('Promo Form'!S$3,Query[[#Headers],[Code]:[Bing Lee]],Query[[Code]:[Bing Lee]])),"")} | U8: =IFERROR(((T8*(1-S$2))*$CU8)*S$61,"") | V8: =IFERROR(((T8*(1-S$2))*$CU8)*S$60,"") | W8: =IFERROR(IF(U8+V8=0,"",U8+V8),"") | X8: =IFERROR((($CS8/1.1)-(T8-(T8*S$2)))/($CS8/1.1),"") | Y8: =IFERROR((($CT8/1.1)+(U8+V8)-(T8-(T8*S$2)))/($CT8/1.1),"") | Z8: {=IFERROR(_xlfn._xlws.FILTER(ST[SOH],(ST[Code]=$C8) * (ST[Customer Name]=S$3),"" ),"")} | AA8: {=IFERROR( _xlfn.LET( _xlpm.result, INDEX(_xlfn._xlws.FILTER(ST[6wk avg], (ST[Code]=$C8)*(ST[Customer Name]=S$3), ""), 1), IF(_xlpm.result=0, "", _xlpm.result) ), "")} | AB8: =IFERROR(IF(CEILING(AA8 + (AA8 * $AB$2), 1) = 0, "", CEILING(AA8 + (AA8 * $AB$2), 1))*$B$3, "") | AC8: =IFERROR((AB8*U8),"") | AD8: =IFERROR((AB8*V8),"") | AF8: {=IFERROR(_xlfn._xlws.FILTER(ST[Customer Code],(ST[Code]=$C8) * (ST[Customer Name]=AF$3),"" ),"")} | AG8: {=IFERROR(_xlfn.XLOOKUP($C8,Query[Code], _xlfn.XLOOKUP('Promo Form'!AF$3,Query[[#Headers],[Code]:[Bing Lee]],Query[[Code]:[Bing Lee]])),"")} | AH8: =IFERROR(((AG8*(1-AF$2))*$CU8)*AF$61,"") | AI8: =IFERROR(((AG8*(1-AF$2))*$CU8)*AF$60,"") | AJ8: =IFERROR(IF(AH8+AI8=0,"",AH8+AI8),"") | AK8: =IFERROR((($CS8/1.1)-(AG8-(AG8*AF$2)))/($CS8/1.1),"") | AL8: =IFERROR((($CT8/1.1)+(AH8+AI8)-(AG8-(AG8*AF$2)))/($CT8/1.1),"") | AM8: {=IFERROR(_xlfn._xlws.FILTER(ST[SOH],(ST[Code]=$C8) * (ST[Customer Name]=AF$3),"" ),"")} | AN8: {=IFERROR( _xlfn.LET( _xlpm.result, INDEX(_xlfn._xlws.FILTER(ST[6wk avg], (ST[Code]=$C8)*(ST[Customer Name]=AF$3), ""), 1), IF(_xlpm.result=0, "", _xlpm.result) ), "")} | AO8: =IFERROR(IF(CEILING(AN8 + (AN8 * $AO$2), 1) = 0, "", CEILING(AN8 + (AN8 * $AO$2), 1))*$B$3, "") | AP8: =IFERROR((AO8*AH8),"") | AQ8: =IFERROR((AO8*AI8),"") | AS8: {=IFERROR(_xlfn._xlws.FILTER(ST[Customer Code],(ST[Code]=$C8) * (ST[Customer Name]=AS$3),"" ),"")} | AT8: {=IFERROR(_xlfn.XLOOKUP($C8,Query[Code], _xlfn.XLOOKUP('Promo Form'!AS$3,Query[[#Headers],[Code]:[Bing Lee]],Query[[Code]:[Bing Lee]])),"")} | AU8: =IFERROR(((AT8*(1-AS$2))*$CU8)*AS$61,"") | AV8: =IFERROR(((AT8*(1-AS$2))*$CU8)*AS$60,"") | AW8: =IFERROR(IF(AU8+AV8=0,"",AU8+AV8),"") | AX8: =IFERROR((($CS8/1.1)-(AT8-(AT8*AS$2)))/($CS8/1.1),"") | AY8: =IFERROR((($CT8/1.1)+(AU8+AV8)-(AT8-(AT8*AS$2)))/($CT8/1.1),"") | AZ8: {=IFERROR(_xlfn._xlws.FILTER(ST[SOH],(ST[Code]=$C8) * (ST[Customer Name]=AS$3),"" ),"")} | BA8: {=IFERROR( _xlfn.LET( _xlpm.result, INDEX(_xlfn._xlws.FILTER(ST[6wk avg], (ST[Code]=$C8)*(ST[Customer Name]=AS$3), ""), 1), IF(_xlpm.result=0, "", _xlpm.result) ), "")} | BB8: =IFERROR(IF(CEILING(BA8 + (BA8 * $BB$2), 1) = 0, "", CEILING(BA8 + (BA8 * $BB$2), 1))*$B$3, "") | BC8: =IFERROR((BB8*AU8),"") | BD8: =IFERROR((BB8*AV8),"") | BF8: {=IFERROR(_xlfn._xlws.FILTER(ST[Customer Code],(ST[Code]=$C8) * (ST[Customer Name]=BF$3),"" ),"")} | BG8: {=IFERROR(_xlfn.XLOOKUP($C8,Query[Code], _xlfn.XLOOKUP('Promo Form'!BF$3,Query[[#Headers],[Code]:[Bing Lee]],Query[[Code]:[Bing Lee]])),"")} | BH8: =IFERROR(((BG8*(1-BF$2))*$CU8)*BF$61,"") | BI8: =IFERROR(((BG8*(1-BF$2))*$CU8)*BF$60,"") | BJ8: =IFERROR(IF(BH8+BI8=0,"",BH8+BI8),"") | BK8: =IFERROR((($CS8/1.1)-(BG8-(BG8*BF$2)))/($CS8/1.1),"") | BL8: =IFERROR((($CT8/1.1)+(BH8+BI8)-(BG8-(BG8*BF$2)))/($CT8/1.1),"") | BM8: {=IFERROR(_xlfn._xlws.FILTER(ST[SOH],(ST[Code]=$C8) * (ST[Customer Name]=BF$3),"" ),"")} | BN8: {=IFERROR( _xlfn.LET( _xlpm.result, INDEX(_xlfn._xlws.FILTER(ST[6wk avg], (ST[Code]=$C8)*(ST[Customer Name]=BF$3), ""), 1), IF(_xlpm.result=0, "", _xlpm.result) ), "")} | BO8: =IFERROR(IF(CEILING(BN8 + (BN8 * $BO$2), 1) = 0, "", CEILING(BN8 + (BN8 * $BO$2), 1))*$B$3, "") | BP8: =IFERROR((BO8*BH8),"") | BQ8: =IFERROR((BO8*BI8),"") | BS8: {=IFERROR(_xlfn._xlws.FILTER(ST[Customer Code],(ST[Code]=$C8) * (ST[Customer Name]=BS$3),"" ),"")} | BT8: {=IFERROR(_xlfn.XLOOKUP($C8,Query[Code], _xlfn.XLOOKUP('Promo Form'!BS$3,Query[[#Headers],[Code]:[Bing Lee]],Query[[Code]:[Bing Lee]])),"")} | BU8: =IFERROR(((BT8*(1-BS$2))*$CU8)*BS$61,"") | BV8: =IFERROR(((BT8*(1-BS$2))*$CU8)*BS$60,"") | BW8: =IFERROR(IF(BU8+BV8=0,"",BU8+BV8),"") | BX8: =IFERROR((($CS8/1.1)-(BT8-(BT8*BS$2)))/($CS8/1.1),"") | BY8: =IFERROR((($CT8/1.1)+(BU8+BV8)-(BT8-(BT8*BS$2)))/($CT8/1.1),"") | BZ8: {=IFERROR(_xlfn._xlws.FILTER(ST[SOH],(ST[Code]=$C8) * (ST[Customer Name]=BS$3),"" ),"")} | CA8: {=IFERROR( _xlfn.LET( _xlpm.result, INDEX(_xlfn._xlws.FILTER(ST[6wk avg], (ST[Code]=$C8)*(ST[Customer Name]=BS$3), ""), 1), IF(_xlpm.result=0, "", _xlpm.result) ), "")} | CB8: =IFERROR(IF(CEILING(CA8 + (CA8 * $CB$2), 1) = 0, "", CEILING(CA8 + (CA8 * $CB$2), 1))*$B$3, "") | CC8: =IFERROR((CB8*BU8),"") | CD8: =IFERROR((CB8*BV8),"") | CF8: {=IFERROR(_xlfn._xlws.FILTER(ST[Customer Code],(ST[Code]=$C8) * (ST[Customer Name]=CF$3),"" ),"")} | CG8: {=IFERROR(_xlfn.XLOOKUP($C8,Query[Code], _xlfn.XLOOKUP('Promo Form'!CF$3,Query[[#Headers],[Code]:[Bing Lee]],Query[[Code]:[Bing Lee]])),"")} | CH8: =IFERROR(((CG8*(1-CF$2))*$CU8)*CF$61,"") | CI8: =IFERROR(((CG8*(1-CF$2))*$CU8)*CF$60,"") | CJ8: =IFERROR(IF(CH8+CI8=0,"",CH8+CI8),"") | CK8: =IFERROR((($CS8/1.1)-(CG8-(CG8*CF$2)))/($CS8/1.1),"") | CL8: =IFERROR((($CT8/1.1)+(CH8+CI8)-(CG8-(CG8*CF$2)))/($CT8/1.1),"") | CM8: {=IFERROR(_xlfn._xlws.FILTER(ST[SOH],(ST[Code]=$C8) * (ST[Customer Name]=CF$3),"" ),"")} | CN8: {=IFERROR( _xlfn.LET( _xlpm.result, INDEX(_xlfn._xlws.FILTER(ST[6wk avg], (ST[Code]=$C8)*(ST[Customer Name]=CF$3), ""), 1), IF(_xlpm.result=0, "", _xlpm.result) ), "")} | CO8: =IFERROR(IF(CEILING(CN8 + (CN8 * $CO$2), 1) = 0, "", CEILING(CN8 + (CN8 * $CO$2), 1))*$B$3, "") | CP8: =IFERROR((CO8*CH8),"") | CQ8: =IFERROR((CO8*CI8),"") | CS8: =IFERROR(_xlfn.XLOOKUP(C8,Query[Code],Query[Base (RRP Inc)]),"") | CT8: =IFERROR(CS8-(CS8*CU8),"") | CU8: =IF(C8="", "",CU7) | CV8: =IFERROR((CS8-CT8),"")
A9: =IF(C9="","",A8) | B9: =IF(C9="","",B8) | D9: =IF(C9="", "",_xlfn.XLOOKUP(C9,'Master Price Level'!C:C,'Master Price Level'!D:D)) | F9: {=IFERROR(_xlfn._xlws.FILTER(ST[Customer Code],(ST[Code]=$C9) * (ST[Customer Name]=F$3),"" ),"")} | G9: {=IFERROR(_xlfn.XLOOKUP($C9,Query[Code], _xlfn.XLOOKUP('Promo Form'!F$3,Query[[#Headers],[Code]:[Bing Lee]],Query[[Code]:[Bing Lee]])),"")} | H9: =IFERROR(((G9*(1-F$2))*$CU9)*F$61,"") | I9: =IFERROR(((G9*(1-F$2))*$CU9)*F$60,"") | J9: =IFERROR(IF(H9+I9=0,"",H9+I9),"") | K9: =IFERROR((($CS9/1.1)-(G9-(G9*F$2)))/($CS9/1.1),"") | L9: =IFERROR((($CT9/1.1)+(H9+I9)-(G9-(G9*F$2)))/($CT9/1.1),"") | M9: {=IFERROR(_xlfn._xlws.FILTER(ST[SOH],(ST[Code]=$C9) * (ST[Customer Name]=F$3),"" ),"")} | N9: {=IFERROR( _xlfn.LET( _xlpm.result, INDEX(_xlfn._xlws.FILTER(ST[6wk avg], (ST[Code]=$C9)*(ST[Customer Name]=F$3), ""), 1), IF(_xlpm.result=0, "", _xlpm.result) ), "")} | O9: =IFERROR(IF(CEILING(N9 + (N9 * $O$2), 1) = 0, "", CEILING(N9 + (N9 * $O$2), 1))*$B$3, "") | P9: =IFERROR((O9*H9),"") | Q9: =IFERROR((O9*I9),"") | S9: {=IFERROR(_xlfn._xlws.FILTER(ST[Customer Code],(ST[Code]=$C9) * (ST[Customer Name]=S$3),"" ),"")} | T9: {=IFERROR(_xlfn.XLOOKUP($C9,Query[Code], _xlfn.XLOOKUP('Promo Form'!S$3,Query[[#Headers],[Code]:[Bing Lee]],Query[[Code]:[Bing Lee]])),"")} | U9: =IFERROR(((T9*(1-S$2))*$CU9)*S$61,"") | V9: =IFERROR(((T9*(1-S$2))*$CU9)*S$60,"") | W9: =IFERROR(IF(U9+V9=0,"",U9+V9),"") | X9: =IFERROR((($CS9/1.1)-(T9-(T9*S$2)))/($CS9/1.1),"") | Y9: =IFERROR((($CT9/1.1)+(U9+V9)-(T9-(T9*S$2)))/($CT9/1.1),"") | Z9: {=IFERROR(_xlfn._xlws.FILTER(ST[SOH],(ST[Code]=$C9) * (ST[Customer Name]=S$3),"" ),"")} | AA9: {=IFERROR( _xlfn.LET( _xlpm.result, INDEX(_xlfn._xlws.FILTER(ST[6wk avg], (ST[Code]=$C9)*(ST[Customer Name]=S$3), ""), 1), IF(_xlpm.result=0, "", _xlpm.result) ), "")} | AB9: =IFERROR(IF(CEILING(AA9 + (AA9 * $AB$2), 1) = 0, "", CEILING(AA9 + (AA9 * $AB$2), 1))*$B$3, "") | AC9: =IFERROR((AB9*U9),"") | AD9: =IFERROR((AB9*V9),"") | AF9: {=IFERROR(_xlfn._xlws.FILTER(ST[Customer Code],(ST[Code]=$C9) * (ST[Customer Name]=AF$3),"" ),"")} | AG9: {=IFERROR(_xlfn.XLOOKUP($C9,Query[Code], _xlfn.XLOOKUP('Promo Form'!AF$3,Query[[#Headers],[Code]:[Bing Lee]],Query[[Code]:[Bing Lee]])),"")} | AH9: =IFERROR(((AG9*(1-AF$2))*$CU9)*AF$61,"") | AI9: =IFERROR(((AG9*(1-AF$2))*$CU9)*AF$60,"") | AJ9: =IFERROR(IF(AH9+AI9=0,"",AH9+AI9),"") | AK9: =IFERROR((($CS9/1.1)-(AG9-(AG9*AF$2)))/($CS9/1.1),"") | AL9: =IFERROR((($CT9/1.1)+(AH9+AI9)-(AG9-(AG9*AF$2)))/($CT9/1.1),"") | AM9: {=IFERROR(_xlfn._xlws.FILTER(ST[SOH],(ST[Code]=$C9) * (ST[Customer Name]=AF$3),"" ),"")} | AN9: {=IFERROR( _xlfn.LET( _xlpm.result, INDEX(_xlfn._xlws.FILTER(ST[6wk avg], (ST[Code]=$C9)*(ST[Customer Name]=AF$3), ""), 1), IF(_xlpm.result=0, "", _xlpm.result) ), "")} | AO9: =IFERROR(IF(CEILING(AN9 + (AN9 * $AO$2), 1) = 0, "", CEILING(AN9 + (AN9 * $AO$2), 1))*$B$3, "") | AP9: =IFERROR((AO9*AH9),"") | AQ9: =IFERROR((AO9*AI9),"") | AS9: {=IFERROR(_xlfn._xlws.FILTER(ST[Customer Code],(ST[Code]=$C9) * (ST[Customer Name]=AS$3),"" ),"")} | AT9: {=IFERROR(_xlfn.XLOOKUP($C9,Query[Code], _xlfn.XLOOKUP('Promo Form'!AS$3,Query[[#Headers],[Code]:[Bing Lee]],Query[[Code]:[Bing Lee]])),"")} | AU9: =IFERROR(((AT9*(1-AS$2))*$CU9)*AS$61,"") | AV9: =IFERROR(((AT9*(1-AS$2))*$CU9)*AS$60,"") | AW9: =IFERROR(IF(AU9+AV9=0,"",AU9+AV9),"") | AX9: =IFERROR((($CS9/1.1)-(AT9-(AT9*AS$2)))/($CS9/1.1),"") | AY9: =IFERROR((($CT9/1.1)+(AU9+AV9)-(AT9-(AT9*AS$2)))/($CT9/1.1),"") | AZ9: {=IFERROR(_xlfn._xlws.FILTER(ST[SOH],(ST[Code]=$C9) * (ST[Customer Name]=AS$3),"" ),"")} | BA9: {=IFERROR( _xlfn.LET( _xlpm.result, INDEX(_xlfn._xlws.FILTER(ST[6wk avg], (ST[Code]=$C9)*(ST[Customer Name]=AS$3), ""), 1), IF(_xlpm.result=0, "", _xlpm.result) ), "")} | BB9: =IFERROR(IF(CEILING(BA9 + (BA9 * $BB$2), 1) = 0, "", CEILING(BA9 + (BA9 * $BB$2), 1))*$B$3, "") | BC9: =IFERROR((BB9*AU9),"") | BD9: =IFERROR((BB9*AV9),"") | BF9: {=IFERROR(_xlfn._xlws.FILTER(ST[Customer Code],(ST[Code]=$C9) * (ST[Customer Name]=BF$3),"" ),"")} | BG9: {=IFERROR(_xlfn.XLOOKUP($C9,Query[Code], _xlfn.XLOOKUP('Promo Form'!BF$3,Query[[#Headers],[Code]:[Bing Lee]],Query[[Code]:[Bing Lee]])),"")} | BH9: =IFERROR(((BG9*(1-BF$2))*$CU9)*BF$61,"") | BI9: =IFERROR(((BG9*(1-BF$2))*$CU9)*BF$60,"") | BJ9: =IFERROR(IF(BH9+BI9=0,"",BH9+BI9),"") | BK9: =IFERROR((($CS9/1.1)-(BG9-(BG9*BF$2)))/($CS9/1.1),"") | BL9: =IFERROR((($CT9/1.1)+(BH9+BI9)-(BG9-(BG9*BF$2)))/($CT9/1.1),"") | BM9: {=IFERROR(_xlfn._xlws.FILTER(ST[SOH],(ST[Code]=$C9) * (ST[Customer Name]=BF$3),"" ),"")} | BN9: {=IFERROR( _xlfn.LET( _xlpm.result, INDEX(_xlfn._xlws.FILTER(ST[6wk avg], (ST[Code]=$C9)*(ST[Customer Name]=BF$3), ""), 1), IF(_xlpm.result=0, "", _xlpm.result) ), "")} | BO9: =IFERROR(IF(CEILING(BN9 + (BN9 * $BO$2), 1) = 0, "", CEILING(BN9 + (BN9 * $BO$2), 1))*$B$3, "") | BP9: =IFERROR((BO9*BH9),"") | BQ9: =IFERROR((BO9*BI9),"") | BS9: {=IFERROR(_xlfn._xlws.FILTER(ST[Customer Code],(ST[Code]=$C9) * (ST[Customer Name]=BS$3),"" ),"")} | BT9: {=IFERROR(_xlfn.XLOOKUP($C9,Query[Code], _xlfn.XLOOKUP('Promo Form'!BS$3,Query[[#Headers],[Code]:[Bing Lee]],Query[[Code]:[Bing Lee]])),"")} | BU9: =IFERROR(((BT9*(1-BS$2))*$CU9)*BS$61,"") | BV9: =IFERROR(((BT9*(1-BS$2))*$CU9)*BS$60,"") | BW9: =IFERROR(IF(BU9+BV9=0,"",BU9+BV9),"") | BX9: =IFERROR((($CS9/1.1)-(BT9-(BT9*BS$2)))/($CS9/1.1),"") | BY9: =IFERROR((($CT9/1.1)+(BU9+BV9)-(BT9-(BT9*BS$2)))/($CT9/1.1),"") | BZ9: {=IFERROR(_xlfn._xlws.FILTER(ST[SOH],(ST[Code]=$C9) * (ST[Customer Name]=BS$3),"" ),"")} | CA9: {=IFERROR( _xlfn.LET( _xlpm.result, INDEX(_xlfn._xlws.FILTER(ST[6wk avg], (ST[Code]=$C9)*(ST[Customer Name]=BS$3), ""), 1), IF(_xlpm.result=0, "", _xlpm.result) ), "")} | CB9: =IFERROR(IF(CEILING(CA9 + (CA9 * $CB$2), 1) = 0, "", CEILING(CA9 + (CA9 * $CB$2), 1))*$B$3, "") | CC9: =IFERROR((CB9*BU9),"") | CD9: =IFERROR((CB9*BV9),"") | CF9: {=IFERROR(_xlfn._xlws.FILTER(ST[Customer Code],(ST[Code]=$C9) * (ST[Customer Name]=CF$3),"" ),"")} | CG9: {=IFERROR(_xlfn.XLOOKUP($C9,Query[Code], _xlfn.XLOOKUP('Promo Form'!CF$3,Query[[#Headers],[Code]:[Bing Lee]],Query[[Code]:[Bing Lee]])),"")} | CH9: =IFERROR(((CG9*(1-CF$2))*$CU9)*CF$61,"") | CI9: =IFERROR(((CG9*(1-CF$2))*$CU9)*CF$60,"") | CJ9: =IFERROR(IF(CH9+CI9=0,"",CH9+CI9),"") | CK9: =IFERROR((($CS9/1.1)-(CG9-(CG9*CF$2)))/($CS9/1.1),"") | CL9: =IFERROR((($CT9/1.1)+(CH9+CI9)-(CG9-(CG9*CF$2)))/($CT9/1.1),"") | CM9: {=IFERROR(_xlfn._xlws.FILTER(ST[SOH],(ST[Code]=$C9) * (ST[Customer Name]=CF$3),"" ),"")} | CN9: {=IFERROR( _xlfn.LET( _xlpm.result, INDEX(_xlfn._xlws.FILTER(ST[6wk avg], (ST[Code]=$C9)*(ST[Customer Name]=CF$3), ""), 1), IF(_xlpm.result=0, "", _xlpm.result) ), "")} | CO9: =IFERROR(IF(CEILING(CN9 + (CN9 * $CO$2), 1) = 0, "", CEILING(CN9 + (CN9 * $CO$2), 1))*$B$3, "") | CP9: =IFERROR((CO9*CH9),"") | CQ9: =IFERROR((CO9*CI9),"") | CS9: =IFERROR(_xlfn.XLOOKUP(C9,Query[Code],Query[Base (RRP Inc)]),"") | CT9: =IFERROR(CS9-(CS9*CU9),"") | CU9: =IF(C9="", "",CU8) | CV9: =IFERROR((CS9-CT9),"")
A10: =IF(C10="","",A9) | B10: =IF(C10="","",B9) | D10: =IF(C10="", "",_xlfn.XLOOKUP(C10,'Master Price Level'!C:C,'Master Price Level'!D:D)) | F10: {=IFERROR(_xlfn._xlws.FILTER(ST[Customer Code],(ST[Code]=$C10) * (ST[Customer Name]=F$3),"" ),"")} | G10: {=IFERROR(_xlfn.XLOOKUP($C10,Query[Code], _xlfn.XLOOKUP('Promo Form'!F$3,Query[[#Headers],[Code]:[Bing Lee]],Query[[Code]:[Bing Lee]])),"")} | H10: =IFERROR(((G10*(1-F$2))*$CU10)*F$61,"") | I10: =IFERROR(((G10*(1-F$2))*$CU10)*F$60,"") | J10: =IFERROR(IF(H10+I10=0,"",H10+I10),"") | K10: =IFERROR((($CS10/1.1)-(G10-(G10*F$2)))/($CS10/1.1),"") | L10: =IFERROR((($CT10/1.1)+(H10+I10)-(G10-(G10*F$2)))/($CT10/1.1),"") | M10: {=IFERROR(_xlfn._xlws.FILTER(ST[SOH],(ST[Code]=$C10) * (ST[Customer Name]=F$3),"" ),"")} | N10: {=IFERROR( _xlfn.LET( _xlpm.result, INDEX(_xlfn._xlws.FILTER(ST[6wk avg], (ST[Code]=$C10)*(ST[Customer Name]=F$3), ""), 1), IF(_xlpm.result=0, "", _xlpm.result) ), "")} | O10: =IFERROR(IF(CEILING(N10 + (N10 * $O$2), 1) = 0, "", CEILING(N10 + (N10 * $O$2), 1))*$B$3, "") | P10: =IFERROR((O10*H10),"") | Q10: =IFERROR((O10*I10),"") | S10: {=IFERROR(_xlfn._xlws.FILTER(ST[Customer Code],(ST[Code]=$C10) * (ST[Customer Name]=S$3),"" ),"")} | T10: {=IFERROR(_xlfn.XLOOKUP($C10,Query[Code], _xlfn.XLOOKUP('Promo Form'!S$3,Query[[#Headers],[Code]:[Bing Lee]],Query[[Code]:[Bing Lee]])),"")} | U10: =IFERROR(((T10*(1-S$2))*$CU10)*S$61,"") | V10: =IFERROR(((T10*(1-S$2))*$CU10)*S$60,"") | W10: =IFERROR(IF(U10+V10=0,"",U10+V10),"") | X10: =IFERROR((($CS10/1.1)-(T10-(T10*S$2)))/($CS10/1.1),"") | Y10: =IFERROR((($CT10/1.1)+(U10+V10)-(T10-(T10*S$2)))/($CT10/1.1),"") | Z10: {=IFERROR(_xlfn._xlws.FILTER(ST[SOH],(ST[Code]=$C10) * (ST[Customer Name]=S$3),"" ),"")} | AA10: {=IFERROR( _xlfn.LET( _xlpm.result, INDEX(_xlfn._xlws.FILTER(ST[6wk avg], (ST[Code]=$C10)*(ST[Customer Name]=S$3), ""), 1), IF(_xlpm.result=0, "", _xlpm.result) ), "")} | AB10: =IFERROR(IF(CEILING(AA10 + (AA10 * $AB$2), 1) = 0, "", CEILING(AA10 + (AA10 * $AB$2), 1))*$B$3, "") | AC10: =IFERROR((AB10*U10),"") | AD10: =IFERROR((AB10*V10),"") | AF10: {=IFERROR(_xlfn._xlws.FILTER(ST[Customer Code],(ST[Code]=$C10) * (ST[Customer Name]=AF$3),"" ),"")} | AG10: {=IFERROR(_xlfn.XLOOKUP($C10,Query[Code], _xlfn.XLOOKUP('Promo Form'!AF$3,Query[[#Headers],[Code]:[Bing Lee]],Query[[Code]:[Bing Lee]])),"")} | AH10: =IFERROR(((AG10*(1-AF$2))*$CU10)*AF$61,"") | AI10: =IFERROR(((AG10*(1-AF$2))*$CU10)*AF$60,"") | AJ10: =IFERROR(IF(AH10+AI10=0,"",AH10+AI10),"") | AK10: =IFERROR((($CS10/1.1)-(AG10-(AG10*AF$2)))/($CS10/1.1),"") | AL10: =IFERROR((($CT10/1.1)+(AH10+AI10)-(AG10-(AG10*AF$2)))/($CT10/1.1),"") | AM10: {=IFERROR(_xlfn._xlws.FILTER(ST[SOH],(ST[Code]=$C10) * (ST[Customer Name]=AF$3),"" ),"")} | AN10: {=IFERROR( _xlfn.LET( _xlpm.result, INDEX(_xlfn._xlws.FILTER(ST[6wk avg], (ST[Code]=$C10)*(ST[Customer Name]=AF$3), ""), 1), IF(_xlpm.result=0, "", _xlpm.result) ), "")} | AO10: =IFERROR(IF(CEILING(AN10 + (AN10 * $AO$2), 1) = 0, "", CEILING(AN10 + (AN10 * $AO$2), 1))*$B$3, "") | AP10: =IFERROR((AO10*AH10),"") | AQ10: =IFERROR((AO10*AI10),"") | AS10: {=IFERROR(_xlfn._xlws.FILTER(ST[Customer Code],(ST[Code]=$C10) * (ST[Customer Name]=AS$3),"" ),"")} | AT10: {=IFERROR(_xlfn.XLOOKUP($C10,Query[Code], _xlfn.XLOOKUP('Promo Form'!AS$3,Query[[#Headers],[Code]:[Bing Lee]],Query[[Code]:[Bing Lee]])),"")} | AU10: =IFERROR(((AT10*(1-AS$2))*$CU10)*AS$61,"") | AV10: =IFERROR(((AT10*(1-AS$2))*$CU10)*AS$60,"") | AW10: =IFERROR(IF(AU10+AV10=0,"",AU10+AV10),"") | AX10: =IFERROR((($CS10/1.1)-(AT10-(AT10*AS$2)))/($CS10/1.1),"") | AY10: =IFERROR((($CT10/1.1)+(AU10+AV10)-(AT10-(AT10*AS$2)))/($CT10/1.1),"") | AZ10: {=IFERROR(_xlfn._xlws.FILTER(ST[SOH],(ST[Code]=$C10) * (ST[Customer Name]=AS$3),"" ),"")} | BA10: {=IFERROR( _xlfn.LET( _xlpm.result, INDEX(_xlfn._xlws.FILTER(ST[6wk avg], (ST[Code]=$C10)*(ST[Customer Name]=AS$3), ""), 1), IF(_xlpm.result=0, "", _xlpm.result) ), "")} | BB10: =IFERROR(IF(CEILING(BA10 + (BA10 * $BB$2), 1) = 0, "", CEILING(BA10 + (BA10 * $BB$2), 1))*$B$3, "") | BC10: =IFERROR((BB10*AU10),"") | BD10: =IFERROR((BB10*AV10),"") | BF10: {=IFERROR(_xlfn._xlws.FILTER(ST[Customer Code],(ST[Code]=$C10) * (ST[Customer Name]=BF$3),"" ),"")} | BG10: {=IFERROR(_xlfn.XLOOKUP($C10,Query[Code], _xlfn.XLOOKUP('Promo Form'!BF$3,Query[[#Headers],[Code]:[Bing Lee]],Query[[Code]:[Bing Lee]])),"")} | BH10: =IFERROR(((BG10*(1-BF$2))*$CU10)*BF$61,"") | BI10: =IFERROR(((BG10*(1-BF$2))*$CU10)*BF$60,"") | BJ10: =IFERROR(IF(BH10+BI10=0,"",BH10+BI10),"") | BK10: =IFERROR((($CS10/1.1)-(BG10-(BG10*BF$2)))/($CS10/1.1),"") | BL10: =IFERROR((($CT10/1.1)+(BH10+BI10)-(BG10-(BG10*BF$2)))/($CT10/1.1),"") | BM10: {=IFERROR(_xlfn._xlws.FILTER(ST[SOH],(ST[Code]=$C10) * (ST[Customer Name]=BF$3),"" ),"")} | BN10: {=IFERROR( _xlfn.LET( _xlpm.result, INDEX(_xlfn._xlws.FILTER(ST[6wk avg], (ST[Code]=$C10)*(ST[Customer Name]=BF$3), ""), 1), IF(_xlpm.result=0, "", _xlpm.result) ), "")} | BO10: =IFERROR(IF(CEILING(BN10 + (BN10 * $BO$2), 1) = 0, "", CEILING(BN10 + (BN10 * $BO$2), 1))*$B$3, "") | BP10: =IFERROR((BO10*BH10),"") | BQ10: =IFERROR((BO10*BI10),"") | BS10: {=IFERROR(_xlfn._xlws.FILTER(ST[Customer Code],(ST[Code]=$C10) * (ST[Customer Name]=BS$3),"" ),"")} | BT10: {=IFERROR(_xlfn.XLOOKUP($C10,Query[Code], _xlfn.XLOOKUP('Promo Form'!BS$3,Query[[#Headers],[Code]:[Bing Lee]],Query[[Code]:[Bing Lee]])),"")} | BU10: =IFERROR(((BT10*(1-BS$2))*$CU10)*BS$61,"") | BV10: =IFERROR(((BT10*(1-BS$2))*$CU10)*BS$60,"") | BW10: =IFERROR(IF(BU10+BV10=0,"",BU10+BV10),"") | BX10: =IFERROR((($CS10/1.1)-(BT10-(BT10*BS$2)))/($CS10/1.1),"") | BY10: =IFERROR((($CT10/1.1)+(BU10+BV10)-(BT10-(BT10*BS$2)))/($CT10/1.1),"") | BZ10: {=IFERROR(_xlfn._xlws.FILTER(ST[SOH],(ST[Code]=$C10) * (ST[Customer Name]=BS$3),"" ),"")} | CA10: {=IFERROR( _xlfn.LET( _xlpm.result, INDEX(_xlfn._xlws.FILTER(ST[6wk avg], (ST[Code]=$C10)*(ST[Customer Name]=BS$3), ""), 1), IF(_xlpm.result=0, "", _xlpm.result) ), "")} | CB10: =IFERROR(IF(CEILING(CA10 + (CA10 * $CB$2), 1) = 0, "", CEILING(CA10 + (CA10 * $CB$2), 1))*$B$3, "") | CC10: =IFERROR((CB10*BU10),"") | CD10: =IFERROR((CB10*BV10),"") | CF10: {=IFERROR(_xlfn._xlws.FILTER(ST[Customer Code],(ST[Code]=$C10) * (ST[Customer Name]=CF$3),"" ),"")} | CG10: {=IFERROR(_xlfn.XLOOKUP($C10,Query[Code], _xlfn.XLOOKUP('Promo Form'!CF$3,Query[[#Headers],[Code]:[Bing Lee]],Query[[Code]:[Bing Lee]])),"")} | CH10: =IFERROR(((CG10*(1-CF$2))*$CU10)*CF$61,"") | CI10: =IFERROR(((CG10*(1-CF$2))*$CU10)*CF$60,"") | CJ10: =IFERROR(IF(CH10+CI10=0,"",CH10+CI10),"") | CK10: =IFERROR((($CS10/1.1)-(CG10-(CG10*CF$2)))/($CS10/1.1),"") | CL10: =IFERROR((($CT10/1.1)+(CH10+CI10)-(CG10-(CG10*CF$2)))/($CT10/1.1),"") | CM10: {=IFERROR(_xlfn._xlws.FILTER(ST[SOH],(ST[Code]=$C10) * (ST[Customer Name]=CF$3),"" ),"")} | CN10: {=IFERROR( _xlfn.LET( _xlpm.result, INDEX(_xlfn._xlws.FILTER(ST[6wk avg], (ST[Code]=$C10)*(ST[Customer Name]=CF$3), ""), 1), IF(_xlpm.result=0, "", _xlpm.result) ), "")} | CO10: =IFERROR(IF(CEILING(CN10 + (CN10 * $CO$2), 1) = 0, "", CEILING(CN10 + (CN10 * $CO$2), 1))*$B$3, "") | CP10: =IFERROR((CO10*CH10),"") | CQ10: =IFERROR((CO10*CI10),"") | CS10: =IFERROR(_xlfn.XLOOKUP(C10,Query[Code],Query[Base (RRP Inc)]),"") | CT10: =IFERROR(CS10-(CS10*CU10),"") | CU10: =IF(C10="", "",CU9) | CV10: =IFERROR((CS10-CT10),"")
A11: =IF(C11="","",A10) | B11: =IF(C11="","",B10) | D11: =IF(C11="", "",_xlfn.XLOOKUP(C11,'Master Price Level'!C:C,'Master Price Level'!D:D)) | F11: {=IFERROR(_xlfn._xlws.FILTER(ST[Customer Code],(ST[Code]=$C11) * (ST[Customer Name]=F$3),"" ),"")} | G11: {=IFERROR(_xlfn.XLOOKUP($C11,Query[Code], _xlfn.XLOOKUP('Promo Form'!F$3,Query[[#Headers],[Code]:[Bing Lee]],Query[[Code]:[Bing Lee]])),"")} | H11: =IFERROR(((G11*(1-F$2))*$CU11)*F$61,"") | I11: =IFERROR(((G11*(1-F$2))*$CU11)*F$60,"") | J11: =IFERROR(IF(H11+I11=0,"",H11+I11),"") | K11: =IFERROR((($CS11/1.1)-(G11-(G11*F$2)))/($CS11/1.1),"") | L11: =IFERROR((($CT11/1.1)+(H11+I11)-(G11-(G11*F$2)))/($CT11/1.1),"") | M11: {=IFERROR(_xlfn._xlws.FILTER(ST[SOH],(ST[Code]=$C11) * (ST[Customer Name]=F$3),"" ),"")} | N11: {=IFERROR( _xlfn.LET( _xlpm.result, INDEX(_xlfn._xlws.FILTER(ST[6wk avg], (ST[Code]=$C11)*(ST[Customer Name]=F$3), ""), 1), IF(_xlpm.result=0, "", _xlpm.result) ), "")} | O11: =IFERROR(IF(CEILING(N11 + (N11 * $O$2), 1) = 0, "", CEILING(N11 + (N11 * $O$2), 1))*$B$3, "") | P11: =IFERROR((O11*H11),"") | Q11: =IFERROR((O11*I11),"") | S11: {=IFERROR(_xlfn._xlws.FILTER(ST[Customer Code],(ST[Code]=$C11) * (ST[Customer Name]=S$3),"" ),"")} | T11: {=IFERROR(_xlfn.XLOOKUP($C11,Query[Code], _xlfn.XLOOKUP('Promo Form'!S$3,Query[[#Headers],[Code]:[Bing Lee]],Query[[Code]:[Bing Lee]])),"")} | U11: =IFERROR(((T11*(1-S$2))*$CU11)*S$61,"") | V11: =IFERROR(((T11*(1-S$2))*$CU11)*S$60,"") | W11: =IFERROR(IF(U11+V11=0,"",U11+V11),"") | X11: =IFERROR((($CS11/1.1)-(T11-(T11*S$2)))/($CS11/1.1),"") | Y11: =IFERROR((($CT11/1.1)+(U11+V11)-(T11-(T11*S$2)))/($CT11/1.1),"") | Z11: {=IFERROR(_xlfn._xlws.FILTER(ST[SOH],(ST[Code]=$C11) * (ST[Customer Name]=S$3),"" ),"")} | AA11: {=IFERROR( _xlfn.LET( _xlpm.result, INDEX(_xlfn._xlws.FILTER(ST[6wk avg], (ST[Code]=$C11)*(ST[Customer Name]=S$3), ""), 1), IF(_xlpm.result=0, "", _xlpm.result) ), "")} | AB11: =IFERROR(IF(CEILING(AA11 + (AA11 * $AB$2), 1) = 0, "", CEILING(AA11 + (AA11 * $AB$2), 1))*$B$3, "") | AC11: =IFERROR((AB11*U11),"") | AD11: =IFERROR((AB11*V11),"") | AF11: {=IFERROR(_xlfn._xlws.FILTER(ST[Customer Code],(ST[Code]=$C11) * (ST[Customer Name]=AF$3),"" ),"")} | AG11: {=IFERROR(_xlfn.XLOOKUP($C11,Query[Code], _xlfn.XLOOKUP('Promo Form'!AF$3,Query[[#Headers],[Code]:[Bing Lee]],Query[[Code]:[Bing Lee]])),"")} | AH11: =IFERROR(((AG11*(1-AF$2))*$CU11)*AF$61,"") | AI11: =IFERROR(((AG11*(1-AF$2))*$CU11)*AF$60,"") | AJ11: =IFERROR(IF(AH11+AI11=0,"",AH11+AI11),"") | AK11: =IFERROR((($CS11/1.1)-(AG11-(AG11*AF$2)))/($CS11/1.1),"") | AL11: =IFERROR((($CT11/1.1)+(AH11+AI11)-(AG11-(AG11*AF$2)))/($CT11/1.1),"") | AM11: {=IFERROR(_xlfn._xlws.FILTER(ST[SOH],(ST[Code]=$C11) * (ST[Customer Name]=AF$3),"" ),"")} | AN11: {=IFERROR( _xlfn.LET( _xlpm.result, INDEX(_xlfn._xlws.FILTER(ST[6wk avg], (ST[Code]=$C11)*(ST[Customer Name]=AF$3), ""), 1), IF(_xlpm.result=0, "", _xlpm.result) ), "")} | AO11: =IFERROR(IF(CEILING(AN11 + (AN11 * $AO$2), 1) = 0, "", CEILING(AN11 + (AN11 * $AO$2), 1))*$B$3, "") | AP11: =IFERROR((AO11*AH11),"") | AQ11: =IFERROR((AO11*AI11),"") | AS11: {=IFERROR(_xlfn._xlws.FILTER(ST[Customer Code],(ST[Code]=$C11) * (ST[Customer Name]=AS$3),"" ),"")} | AT11: {=IFERROR(_xlfn.XLOOKUP($C11,Query[Code], _xlfn.XLOOKUP('Promo Form'!AS$3,Query[[#Headers],[Code]:[Bing Lee]],Query[[Code]:[Bing Lee]])),"")} | AU11: =IFERROR(((AT11*(1-AS$2))*$CU11)*AS$61,"") | AV11: =IFERROR(((AT11*(1-AS$2))*$CU11)*AS$60,"") | AW11: =IFERROR(IF(AU11+AV11=0,"",AU11+AV11),"") | AX11: =IFERROR((($CS11/1.1)-(AT11-(AT11*AS$2)))/($CS11/1.1),"") | AY11: =IFERROR((($CT11/1.1)+(AU11+AV11)-(AT11-(AT11*AS$2)))/($CT11/1.1),"") | AZ11: {=IFERROR(_xlfn._xlws.FILTER(ST[SOH],(ST[Code]=$C11) * (ST[Customer Name]=AS$3),"" ),"")} | BA11: {=IFERROR( _xlfn.LET( _xlpm.result, INDEX(_xlfn._xlws.FILTER(ST[6wk avg], (ST[Code]=$C11)*(ST[Customer Name]=AS$3), ""), 1), IF(_xlpm.result=0, "", _xlpm.result) ), "")} | BB11: =IFERROR(IF(CEILING(BA11 + (BA11 * $BB$2), 1) = 0, "", CEILING(BA11 + (BA11 * $BB$2), 1))*$B$3, "") | BC11: =IFERROR((BB11*AU11),"") | BD11: =IFERROR((BB11*AV11),"") | BF11: {=IFERROR(_xlfn._xlws.FILTER(ST[Customer Code],(ST[Code]=$C11) * (ST[Customer Name]=BF$3),"" ),"")} | BG11: {=IFERROR(_xlfn.XLOOKUP($C11,Query[Code], _xlfn.XLOOKUP('Promo Form'!BF$3,Query[[#Headers],[Code]:[Bing Lee]],Query[[Code]:[Bing Lee]])),"")} | BH11: =IFERROR(((BG11*(1-BF$2))*$CU11)*BF$61,"") | BI11: =IFERROR(((BG11*(1-BF$2))*$CU11)*BF$60,"") | BJ11: =IFERROR(IF(BH11+BI11=0,"",BH11+BI11),"") | BK11: =IFERROR((($CS11/1.1)-(BG11-(BG11*BF$2)))/($CS11/1.1),"") | BL11: =IFERROR((($CT11/1.1)+(BH11+BI11)-(BG11-(BG11*BF$2)))/($CT11/1.1),"") | BM11: {=IFERROR(_xlfn._xlws.FILTER(ST[SOH],(ST[Code]=$C11) * (ST[Customer Name]=BF$3),"" ),"")} | BN11: {=IFERROR( _xlfn.LET( _xlpm.result, INDEX(_xlfn._xlws.FILTER(ST[6wk avg], (ST[Code]=$C11)*(ST[Customer Name]=BF$3), ""), 1), IF(_xlpm.result=0, "", _xlpm.result) ), "")} | BO11: =IFERROR(IF(CEILING(BN11 + (BN11 * $BO$2), 1) = 0, "", CEILING(BN11 + (BN11 * $BO$2), 1))*$B$3, "") | BP11: =IFERROR((BO11*BH11),"") | BQ11: =IFERROR((BO11*BI11),"") | BS11: {=IFERROR(_xlfn._xlws.FILTER(ST[Customer Code],(ST[Code]=$C11) * (ST[Customer Name]=BS$3),"" ),"")} | BT11: {=IFERROR(_xlfn.XLOOKUP($C11,Query[Code], _xlfn.XLOOKUP('Promo Form'!BS$3,Query[[#Headers],[Code]:[Bing Lee]],Query[[Code]:[Bing Lee]])),"")} | BU11: =IFERROR(((BT11*(1-BS$2))*$CU11)*BS$61,"") | BV11: =IFERROR(((BT11*(1-BS$2))*$CU11)*BS$60,"") | BW11: =IFERROR(IF(BU11+BV11=0,"",BU11+BV11),"") | BX11: =IFERROR((($CS11/1.1)-(BT11-(BT11*BS$2)))/($CS11/1.1),"") | BY11: =IFERROR((($CT11/1.1)+(BU11+BV11)-(BT11-(BT11*BS$2)))/($CT11/1.1),"") | BZ11: {=IFERROR(_xlfn._xlws.FILTER(ST[SOH],(ST[Code]=$C11) * (ST[Customer Name]=BS$3),"" ),"")} | CA11: {=IFERROR( _xlfn.LET( _xlpm.result, INDEX(_xlfn._xlws.FILTER(ST[6wk avg], (ST[Code]=$C11)*(ST[Customer Name]=BS$3), ""), 1), IF(_xlpm.result=0, "", _xlpm.result) ), "")} | CB11: =IFERROR(IF(CEILING(CA11 + (CA11 * $CB$2), 1) = 0, "", CEILING(CA11 + (CA11 * $CB$2), 1))*$B$3, "") | CC11: =IFERROR((CB11*BU11),"") | CD11: =IFERROR((CB11*BV11),"") | CF11: {=IFERROR(_xlfn._xlws.FILTER(ST[Customer Code],(ST[Code]=$C11) * (ST[Customer Name]=CF$3),"" ),"")} | CG11: {=IFERROR(_xlfn.XLOOKUP($C11,Query[Code], _xlfn.XLOOKUP('Promo Form'!CF$3,Query[[#Headers],[Code]:[Bing Lee]],Query[[Code]:[Bing Lee]])),"")} | CH11: =IFERROR(((CG11*(1-CF$2))*$CU11)*CF$61,"") | CI11: =IFERROR(((CG11*(1-CF$2))*$CU11)*CF$60,"") | CJ11: =IFERROR(IF(CH11+CI11=0,"",CH11+CI11),"") | CK11: =IFERROR((($CS11/1.1)-(CG11-(CG11*CF$2)))/($CS11/1.1),"") | CL11: =IFERROR((($CT11/1.1)+(CH11+CI11)-(CG11-(CG11*CF$2)))/($CT11/1.1),"") | CM11: {=IFERROR(_xlfn._xlws.FILTER(ST[SOH],(ST[Code]=$C11) * (ST[Customer Name]=CF$3),"" ),"")} | CN11: {=IFERROR( _xlfn.LET( _xlpm.result, INDEX(_xlfn._xlws.FILTER(ST[6wk avg], (ST[Code]=$C11)*(ST[Customer Name]=CF$3), ""), 1), IF(_xlpm.result=0, "", _xlpm.result) ), "")} | CO11: =IFERROR(IF(CEILING(CN11 + (CN11 * $CO$2), 1) = 0, "", CEILING(CN11 + (CN11 * $CO$2), 1))*$B$3, "") | CP11: =IFERROR((CO11*CH11),"") | CQ11: =IFERROR((CO11*CI11),"") | CS11: =IFERROR(_xlfn.XLOOKUP(C11,Query[Code],Query[Base (RRP Inc)]),"") | CT11: =IFERROR(CS11-(CS11*CU11),"") | CU11: =IF(C11="", "",CU10) | CV11: =IFERROR((CS11-CT11),"")
A12: =IF(C12="","",A11) | B12: =IF(C12="","",B11) | D12: =IF(C12="", "",_xlfn.XLOOKUP(C12,'Master Price Level'!C:C,'Master Price Level'!D:D)) | F12: {=IFERROR(_xlfn._xlws.FILTER(ST[Customer Code],(ST[Code]=$C12) * (ST[Customer Name]=F$3),"" ),"")} | G12: {=IFERROR(_xlfn.XLOOKUP($C12,Query[Code], _xlfn.XLOOKUP('Promo Form'!F$3,Query[[#Headers],[Code]:[Bing Lee]],Query[[Code]:[Bing Lee]])),"")} | H12: =IFERROR(((G12*(1-F$2))*$CU12)*F$61,"") | I12: =IFERROR(((G12*(1-F$2))*$CU12)*F$60,"") | J12: =IFERROR(IF(H12+I12=0,"",H12+I12),"") | K12: =IFERROR((($CS12/1.1)-(G12-(G12*F$2)))/($CS12/1.1),"") | L12: =IFERROR((($CT12/1.1)+(H12+I12)-(G12-(G12*F$2)))/($CT12/1.1),"") | M12: {=IFERROR(_xlfn._xlws.FILTER(ST[SOH],(ST[Code]=$C12) * (ST[Customer Name]=F$3),"" ),"")} | N12: {=IFERROR( _xlfn.LET( _xlpm.result, INDEX(_xlfn._xlws.FILTER(ST[6wk avg], (ST[Code]=$C12)*(ST[Customer Name]=F$3), ""), 1), IF(_xlpm.result=0, "", _xlpm.result) ), "")} | O12: =IFERROR(IF(CEILING(N12 + (N12 * $O$2), 1) = 0, "", CEILING(N12 + (N12 * $O$2), 1))*$B$3, "") | P12: =IFERROR((O12*H12),"") | Q12: =IFERROR((O12*I12),"") | S12: {=IFERROR(_xlfn._xlws.FILTER(ST[Customer Code],(ST[Code]=$C12) * (ST[Customer Name]=S$3),"" ),"")} | T12: {=IFERROR(_xlfn.XLOOKUP($C12,Query[Code], _xlfn.XLOOKUP('Promo Form'!S$3,Query[[#Headers],[Code]:[Bing Lee]],Query[[Code]:[Bing Lee]])),"")} | U12: =IFERROR(((T12*(1-S$2))*$CU12)*S$61,"") | V12: =IFERROR(((T12*(1-S$2))*$CU12)*S$60,"") | W12: =IFERROR(IF(U12+V12=0,"",U12+V12),"") | X12: =IFERROR((($CS12/1.1)-(T12-(T12*S$2)))/($CS12/1.1),"") | Y12: =IFERROR((($CT12/1.1)+(U12+V12)-(T12-(T12*S$2)))/($CT12/1.1),"") | Z12: {=IFERROR(_xlfn._xlws.FILTER(ST[SOH],(ST[Code]=$C12) * (ST[Customer Name]=S$3),"" ),"")} | AA12: {=IFERROR( _xlfn.LET( _xlpm.result, INDEX(_xlfn._xlws.FILTER(ST[6wk avg], (ST[Code]=$C12)*(ST[Customer Name]=S$3), ""), 1), IF(_xlpm.result=0, "", _xlpm.result) ), "")} | AB12: =IFERROR(IF(CEILING(AA12 + (AA12 * $AB$2), 1) = 0, "", CEILING(AA12 + (AA12 * $AB$2), 1))*$B$3, "") | AC12: =IFERROR((AB12*U12),"") | AD12: =IFERROR((AB12*V12),"") | AF12: {=IFERROR(_xlfn._xlws.FILTER(ST[Customer Code],(ST[Code]=$C12) * (ST[Customer Name]=AF$3),"" ),"")} | AG12: {=IFERROR(_xlfn.XLOOKUP($C12,Query[Code], _xlfn.XLOOKUP('Promo Form'!AF$3,Query[[#Headers],[Code]:[Bing Lee]],Query[[Code]:[Bing Lee]])),"")} | AH12: =IFERROR(((AG12*(1-AF$2))*$CU12)*AF$61,"") | AI12: =IFERROR(((AG12*(1-AF$2))*$CU12)*AF$60,"") | AJ12: =IFERROR(IF(AH12+AI12=0,"",AH12+AI12),"") | AK12: =IFERROR((($CS12/1.1)-(AG12-(AG12*AF$2)))/($CS12/1.1),"") | AL12: =IFERROR((($CT12/1.1)+(AH12+AI12)-(AG12-(AG12*AF$2)))/($CT12/1.1),"") | AM12: {=IFERROR(_xlfn._xlws.FILTER(ST[SOH],(ST[Code]=$C12) * (ST[Customer Name]=AF$3),"" ),"")} | AN12: {=IFERROR( _xlfn.LET( _xlpm.result, INDEX(_xlfn._xlws.FILTER(ST[6wk avg], (ST[Code]=$C12)*(ST[Customer Name]=AF$3), ""), 1), IF(_xlpm.result=0, "", _xlpm.result) ), "")} | AO12: =IFERROR(IF(CEILING(AN12 + (AN12 * $AO$2), 1) = 0, "", CEILING(AN12 + (AN12 * $AO$2), 1))*$B$3, "") | AP12: =IFERROR((AO12*AH12),"") | AQ12: =IFERROR((AO12*AI12),"") | AS12: {=IFERROR(_xlfn._xlws.FILTER(ST[Customer Code],(ST[Code]=$C12) * (ST[Customer Name]=AS$3),"" ),"")} | AT12: {=IFERROR(_xlfn.XLOOKUP($C12,Query[Code], _xlfn.XLOOKUP('Promo Form'!AS$3,Query[[#Headers],[Code]:[Bing Lee]],Query[[Code]:[Bing Lee]])),"")} | AU12: =IFERROR(((AT12*(1-AS$2))*$CU12)*AS$61,"") | AV12: =IFERROR(((AT12*(1-AS$2))*$CU12)*AS$60,"") | AW12: =IFERROR(IF(AU12+AV12=0,"",AU12+AV12),"") | AX12: =IFERROR((($CS12/1.1)-(AT12-(AT12*AS$2)))/($CS12/1.1),"") | AY12: =IFERROR((($CT12/1.1)+(AU12+AV12)-(AT12-(AT12*AS$2)))/($CT12/1.1),"") | AZ12: {=IFERROR(_xlfn._xlws.FILTER(ST[SOH],(ST[Code]=$C12) * (ST[Customer Name]=AS$3),"" ),"")} | BA12: {=IFERROR( _xlfn.LET( _xlpm.result, INDEX(_xlfn._xlws.FILTER(ST[6wk avg], (ST[Code]=$C12)*(ST[Customer Name]=AS$3), ""), 1), IF(_xlpm.result=0, "", _xlpm.result) ), "")} | BB12: =IFERROR(IF(CEILING(BA12 + (BA12 * $BB$2), 1) = 0, "", CEILING(BA12 + (BA12 * $BB$2), 1))*$B$3, "") | BC12: =IFERROR((BB12*AU12),"") | BD12: =IFERROR((BB12*AV12),"") | BF12: {=IFERROR(_xlfn._xlws.FILTER(ST[Customer Code],(ST[Code]=$C12) * (ST[Customer Name]=BF$3),"" ),"")} | BG12: {=IFERROR(_xlfn.XLOOKUP($C12,Query[Code], _xlfn.XLOOKUP('Promo Form'!BF$3,Query[[#Headers],[Code]:[Bing Lee]],Query[[Code]:[Bing Lee]])),"")} | BH12: =IFERROR(((BG12*(1-BF$2))*$CU12)*BF$61,"") | BI12: =IFERROR(((BG12*(1-BF$2))*$CU12)*BF$60,"") | BJ12: =IFERROR(IF(BH12+BI12=0,"",BH12+BI12),"") | BK12: =IFERROR((($CS12/1.1)-(BG12-(BG12*BF$2)))/($CS12/1.1),"") | BL12: =IFERROR((($CT12/1.1)+(BH12+BI12)-(BG12-(BG12*BF$2)))/($CT12/1.1),"") | BM12: {=IFERROR(_xlfn._xlws.FILTER(ST[SOH],(ST[Code]=$C12) * (ST[Customer Name]=BF$3),"" ),"")} | BN12: {=IFERROR( _xlfn.LET( _xlpm.result, INDEX(_xlfn._xlws.FILTER(ST[6wk avg], (ST[Code]=$C12)*(ST[Customer Name]=BF$3), ""), 1), IF(_xlpm.result=0, "", _xlpm.result) ), "")} | BO12: =IFERROR(IF(CEILING(BN12 + (BN12 * $BO$2), 1) = 0, "", CEILING(BN12 + (BN12 * $BO$2), 1))*$B$3, "") | BP12: =IFERROR((BO12*BH12),"") | BQ12: =IFERROR((BO12*BI12),"") | BS12: {=IFERROR(_xlfn._xlws.FILTER(ST[Customer Code],(ST[Code]=$C12) * (ST[Customer Name]=BS$3),"" ),"")} | BT12: {=IFERROR(_xlfn.XLOOKUP($C12,Query[Code], _xlfn.XLOOKUP('Promo Form'!BS$3,Query[[#Headers],[Code]:[Bing Lee]],Query[[Code]:[Bing Lee]])),"")} | BU12: =IFERROR(((BT12*(1-BS$2))*$CU12)*BS$61,"") | BV12: =IFERROR(((BT12*(1-BS$2))*$CU12)*BS$60,"") | BW12: =IFERROR(IF(BU12+BV12=0,"",BU12+BV12),"") | BX12: =IFERROR((($CS12/1.1)-(BT12-(BT12*BS$2)))/($CS12/1.1),"") | BY12: =IFERROR((($CT12/1.1)+(BU12+BV12)-(BT12-(BT12*BS$2)))/($CT12/1.1),"") | BZ12: {=IFERROR(_xlfn._xlws.FILTER(ST[SOH],(ST[Code]=$C12) * (ST[Customer Name]=BS$3),"" ),"")} | CA12: {=IFERROR( _xlfn.LET( _xlpm.result, INDEX(_xlfn._xlws.FILTER(ST[6wk avg], (ST[Code]=$C12)*(ST[Customer Name]=BS$3), ""), 1), IF(_xlpm.result=0, "", _xlpm.result) ), "")} | CB12: =IFERROR(IF(CEILING(CA12 + (CA12 * $CB$2), 1) = 0, "", CEILING(CA12 + (CA12 * $CB$2), 1))*$B$3, "") | CC12: =IFERROR((CB12*BU12),"") | CD12: =IFERROR((CB12*BV12),"") | CF12: {=IFERROR(_xlfn._xlws.FILTER(ST[Customer Code],(ST[Code]=$C12) * (ST[Customer Name]=CF$3),"" ),"")} | CG12: {=IFERROR(_xlfn.XLOOKUP($C12,Query[Code], _xlfn.XLOOKUP('Promo Form'!CF$3,Query[[#Headers],[Code]:[Bing Lee]],Query[[Code]:[Bing Lee]])),"")} | CH12: =IFERROR(((CG12*(1-CF$2))*$CU12)*CF$61,"") | CI12: =IFERROR(((CG12*(1-CF$2))*$CU12)*CF$60,"") | CJ12: =IFERROR(IF(CH12+CI12=0,"",CH12+CI12),"") | CK12: =IFERROR((($CS12/1.1)-(CG12-(CG12*CF$2)))/($CS12/1.1),"") | CL12: =IFERROR((($CT12/1.1)+(CH12+CI12)-(CG12-(CG12*CF$2)))/($CT12/1.1),"") | CM12: {=IFERROR(_xlfn._xlws.FILTER(ST[SOH],(ST[Code]=$C12) * (ST[Customer Name]=CF$3),"" ),"")} | CN12: {=IFERROR( _xlfn.LET( _xlpm.result, INDEX(_xlfn._xlws.FILTER(ST[6wk avg], (ST[Code]=$C12)*(ST[Customer Name]=CF$3), ""), 1), IF(_xlpm.result=0, "", _xlpm.result) ), "")} | CO12: =IFERROR(IF(CEILING(CN12 + (CN12 * $CO$2), 1) = 0, "", CEILING(CN12 + (CN12 * $CO$2), 1))*$B$3, "") | CP12: =IFERROR((CO12*CH12),"") | CQ12: =IFERROR((CO12*CI12),"") | CS12: =IFERROR(_xlfn.XLOOKUP(C12,Query[Code],Query[Base (RRP Inc)]),"") | CT12: =IFERROR(CS12-(CS12*CU12),"") | CU12: =IF(C12="", "",CU11) | CV12: =IFERROR((CS12-CT12),"")
A13: =IF(C13="","",A12) | B13: =IF(C13="","",B12) | D13: =IF(C13="", "",_xlfn.XLOOKUP(C13,'Master Price Level'!C:C,'Master Price Level'!D:D)) | F13: {=IFERROR(_xlfn._xlws.FILTER(ST[Customer Code],(ST[Code]=$C13) * (ST[Customer Name]=F$3),"" ),"")} | G13: {=IFERROR(_xlfn.XLOOKUP($C13,Query[Code], _xlfn.XLOOKUP('Promo Form'!F$3,Query[[#Headers],[Code]:[Bing Lee]],Query[[Code]:[Bing Lee]])),"")} | H13: =IFERROR(((G13*(1-F$2))*$CU13)*F$61,"") | I13: =IFERROR(((G13*(1-F$2))*$CU13)*F$60,"") | J13: =IFERROR(IF(H13+I13=0,"",H13+I13),"") | K13: =IFERROR((($CS13/1.1)-(G13-(G13*F$2)))/($CS13/1.1),"") | L13: =IFERROR((($CT13/1.1)+(H13+I13)-(G13-(G13*F$2)))/($CT13/1.1),"") | M13: {=IFERROR(_xlfn._xlws.FILTER(ST[SOH],(ST[Code]=$C13) * (ST[Customer Name]=F$3),"" ),"")} | N13: {=IFERROR( _xlfn.LET( _xlpm.result, INDEX(_xlfn._xlws.FILTER(ST[6wk avg], (ST[Code]=$C13)*(ST[Customer Name]=F$3), ""), 1), IF(_xlpm.result=0, "", _xlpm.result) ), "")} | O13: =IFERROR(IF(CEILING(N13 + (N13 * $O$2), 1) = 0, "", CEILING(N13 + (N13 * $O$2), 1))*$B$3, "") | P13: =IFERROR((O13*H13),"") | Q13: =IFERROR((O13*I13),"") | S13: {=IFERROR(_xlfn._xlws.FILTER(ST[Customer Code],(ST[Code]=$C13) * (ST[Customer Name]=S$3),"" ),"")} | T13: {=IFERROR(_xlfn.XLOOKUP($C13,Query[Code], _xlfn.XLOOKUP('Promo Form'!S$3,Query[[#Headers],[Code]:[Bing Lee]],Query[[Code]:[Bing Lee]])),"")} | U13: =IFERROR(((T13*(1-S$2))*$CU13)*S$61,"") | V13: =IFERROR(((T13*(1-S$2))*$CU13)*S$60,"") | W13: =IFERROR(IF(U13+V13=0,"",U13+V13),"") | X13: =IFERROR((($CS13/1.1)-(T13-(T13*S$2)))/($CS13/1.1),"") | Y13: =IFERROR((($CT13/1.1)+(U13+V13)-(T13-(T13*S$2)))/($CT13/1.1),"") | Z13: {=IFERROR(_xlfn._xlws.FILTER(ST[SOH],(ST[Code]=$C13) * (ST[Customer Name]=S$3),"" ),"")} | AA13: {=IFERROR( _xlfn.LET( _xlpm.result, INDEX(_xlfn._xlws.FILTER(ST[6wk avg], (ST[Code]=$C13)*(ST[Customer Name]=S$3), ""), 1), IF(_xlpm.result=0, "", _xlpm.result) ), "")} | AB13: =IFERROR(IF(CEILING(AA13 + (AA13 * $AB$2), 1) = 0, "", CEILING(AA13 + (AA13 * $AB$2), 1))*$B$3, "") | AC13: =IFERROR((AB13*U13),"") | AD13: =IFERROR((AB13*V13),"") | AF13: {=IFERROR(_xlfn._xlws.FILTER(ST[Customer Code],(ST[Code]=$C13) * (ST[Customer Name]=AF$3),"" ),"")} | AG13: {=IFERROR(_xlfn.XLOOKUP($C13,Query[Code], _xlfn.XLOOKUP('Promo Form'!AF$3,Query[[#Headers],[Code]:[Bing Lee]],Query[[Code]:[Bing Lee]])),"")} | AH13: =IFERROR(((AG13*(1-AF$2))*$CU13)*AF$61,"") | AI13: =IFERROR(((AG13*(1-AF$2))*$CU13)*AF$60,"") | AJ13: =IFERROR(IF(AH13+AI13=0,"",AH13+AI13),"") | AK13: =IFERROR((($CS13/1.1)-(AG13-(AG13*AF$2)))/($CS13/1.1),"") | AL13: =IFERROR((($CT13/1.1)+(AH13+AI13)-(AG13-(AG13*AF$2)))/($CT13/1.1),"") | AM13: {=IFERROR(_xlfn._xlws.FILTER(ST[SOH],(ST[Code]=$C13) * (ST[Customer Name]=AF$3),"" ),"")} | AN13: {=IFERROR( _xlfn.LET( _xlpm.result, INDEX(_xlfn._xlws.FILTER(ST[6wk avg], (ST[Code]=$C13)*(ST[Customer Name]=AF$3), ""), 1), IF(_xlpm.result=0, "", _xlpm.result) ), "")} | AO13: =IFERROR(IF(CEILING(AN13 + (AN13 * $AO$2), 1) = 0, "", CEILING(AN13 + (AN13 * $AO$2), 1))*$B$3, "") | AP13: =IFERROR((AO13*AH13),"") | AQ13: =IFERROR((AO13*AI13),"") | AS13: {=IFERROR(_xlfn._xlws.FILTER(ST[Customer Code],(ST[Code]=$C13) * (ST[Customer Name]=AS$3),"" ),"")} | AT13: {=IFERROR(_xlfn.XLOOKUP($C13,Query[Code], _xlfn.XLOOKUP('Promo Form'!AS$3,Query[[#Headers],[Code]:[Bing Lee]],Query[[Code]:[Bing Lee]])),"")} | AU13: =IFERROR(((AT13*(1-AS$2))*$CU13)*AS$61,"") | AV13: =IFERROR(((AT13*(1-AS$2))*$CU13)*AS$60,"") | AW13: =IFERROR(IF(AU13+AV13=0,"",AU13+AV13),"") | AX13: =IFERROR((($CS13/1.1)-(AT13-(AT13*AS$2)))/($CS13/1.1),"") | AY13: =IFERROR((($CT13/1.1)+(AU13+AV13)-(AT13-(AT13*AS$2)))/($CT13/1.1),"") | AZ13: {=IFERROR(_xlfn._xlws.FILTER(ST[SOH],(ST[Code]=$C13) * (ST[Customer Name]=AS$3),"" ),"")} | BA13: {=IFERROR( _xlfn.LET( _xlpm.result, INDEX(_xlfn._xlws.FILTER(ST[6wk avg], (ST[Code]=$C13)*(ST[Customer Name]=AS$3), ""), 1), IF(_xlpm.result=0, "", _xlpm.result) ), "")} | BB13: =IFERROR(IF(CEILING(BA13 + (BA13 * $BB$2), 1) = 0, "", CEILING(BA13 + (BA13 * $BB$2), 1))*$B$3, "") | BC13: =IFERROR((BB13*AU13),"") | BD13: =IFERROR((BB13*AV13),"") | BF13: {=IFERROR(_xlfn._xlws.FILTER(ST[Customer Code],(ST[Code]=$C13) * (ST[Customer Name]=BF$3),"" ),"")} | BG13: {=IFERROR(_xlfn.XLOOKUP($C13,Query[Code], _xlfn.XLOOKUP('Promo Form'!BF$3,Query[[#Headers],[Code]:[Bing Lee]],Query[[Code]:[Bing Lee]])),"")} | BH13: =IFERROR(((BG13*(1-BF$2))*$CU13)*BF$61,"") | BI13: =IFERROR(((BG13*(1-BF$2))*$CU13)*BF$60,"") | BJ13: =IFERROR(IF(BH13+BI13=0,"",BH13+BI13),"") | BK13: =IFERROR((($CS13/1.1)-(BG13-(BG13*BF$2)))/($CS13/1.1),"") | BL13: =IFERROR((($CT13/1.1)+(BH13+BI13)-(BG13-(BG13*BF$2)))/($CT13/1.1),"") | BM13: {=IFERROR(_xlfn._xlws.FILTER(ST[SOH],(ST[Code]=$C13) * (ST[Customer Name]=BF$3),"" ),"")} | BN13: {=IFERROR( _xlfn.LET( _xlpm.result, INDEX(_xlfn._xlws.FILTER(ST[6wk avg], (ST[Code]=$C13)*(ST[Customer Name]=BF$3), ""), 1), IF(_xlpm.result=0, "", _xlpm.result) ), "")} | BO13: =IFERROR(IF(CEILING(BN13 + (BN13 * $BO$2), 1) = 0, "", CEILING(BN13 + (BN13 * $BO$2), 1))*$B$3, "") | BP13: =IFERROR((BO13*BH13),"") | BQ13: =IFERROR((BO13*BI13),"") | BS13: {=IFERROR(_xlfn._xlws.FILTER(ST[Customer Code],(ST[Code]=$C13) * (ST[Customer Name]=BS$3),"" ),"")} | BT13: {=IFERROR(_xlfn.XLOOKUP($C13,Query[Code], _xlfn.XLOOKUP('Promo Form'!BS$3,Query[[#Headers],[Code]:[Bing Lee]],Query[[Code]:[Bing Lee]])),"")} | BU13: =IFERROR(((BT13*(1-BS$2))*$CU13)*BS$61,"") | BV13: =IFERROR(((BT13*(1-BS$2))*$CU13)*BS$60,"") | BW13: =IFERROR(IF(BU13+BV13=0,"",BU13+BV13),"") | BX13: =IFERROR((($CS13/1.1)-(BT13-(BT13*BS$2)))/($CS13/1.1),"") | BY13: =IFERROR((($CT13/1.1)+(BU13+BV13)-(BT13-(BT13*BS$2)))/($CT13/1.1),"") | BZ13: {=IFERROR(_xlfn._xlws.FILTER(ST[SOH],(ST[Code]=$C13) * (ST[Customer Name]=BS$3),"" ),"")} | CA13: {=IFERROR( _xlfn.LET( _xlpm.result, INDEX(_xlfn._xlws.FILTER(ST[6wk avg], (ST[Code]=$C13)*(ST[Customer Name]=BS$3), ""), 1), IF(_xlpm.result=0, "", _xlpm.result) ), "")} | CB13: =IFERROR(IF(CEILING(CA13 + (CA13 * $CB$2), 1) = 0, "", CEILING(CA13 + (CA13 * $CB$2), 1))*$B$3, "") | CC13: =IFERROR((CB13*BU13),"") | CD13: =IFERROR((CB13*BV13),"") | CF13: {=IFERROR(_xlfn._xlws.FILTER(ST[Customer Code],(ST[Code]=$C13) * (ST[Customer Name]=CF$3),"" ),"")} | CG13: {=IFERROR(_xlfn.XLOOKUP($C13,Query[Code], _xlfn.XLOOKUP('Promo Form'!CF$3,Query[[#Headers],[Code]:[Bing Lee]],Query[[Code]:[Bing Lee]])),"")} | CH13: =IFERROR(((CG13*(1-CF$2))*$CU13)*CF$61,"") | CI13: =IFERROR(((CG13*(1-CF$2))*$CU13)*CF$60,"") | CJ13: =IFERROR(IF(CH13+CI13=0,"",CH13+CI13),"") | CK13: =IFERROR((($CS13/1.1)-(CG13-(CG13*CF$2)))/($CS13/1.1),"") | CL13: =IFERROR((($CT13/1.1)+(CH13+CI13)-(CG13-(CG13*CF$2)))/($CT13/1.1),"") | CM13: {=IFERROR(_xlfn._xlws.FILTER(ST[SOH],(ST[Code]=$C13) * (ST[Customer Name]=CF$3),"" ),"")} | CN13: {=IFERROR( _xlfn.LET( _xlpm.result, INDEX(_xlfn._xlws.FILTER(ST[6wk avg], (ST[Code]=$C13)*(ST[Customer Name]=CF$3), ""), 1), IF(_xlpm.result=0, "", _xlpm.result) ), "")} | CO13: =IFERROR(IF(CEILING(CN13 + (CN13 * $CO$2), 1) = 0, "", CEILING(CN13 + (CN13 * $CO$2), 1))*$B$3, "") | CP13: =IFERROR((CO13*CH13),"") | CQ13: =IFERROR((CO13*CI13),"") | CS13: =IFERROR(_xlfn.XLOOKUP(C13,Query[Code],Query[Base (RRP Inc)]),"") | CT13: =IFERROR(CS13-(CS13*CU13),"") | CU13: =IF(C13="", "",CU12) | CV13: =IFERROR((CS13-CT13),"")
A14: =IF(C14="","",A13) | B14: =IF(C14="","",B13) | D14: =IF(C14="", "",_xlfn.XLOOKUP(C14,'Master Price Level'!C:C,'Master Price Level'!D:D)) | F14: {=IFERROR(_xlfn._xlws.FILTER(ST[Customer Code],(ST[Code]=$C14) * (ST[Customer Name]=F$3),"" ),"")} | G14: {=IFERROR(_xlfn.XLOOKUP($C14,Query[Code], _xlfn.XLOOKUP('Promo Form'!F$3,Query[[#Headers],[Code]:[Bing Lee]],Query[[Code]:[Bing Lee]])),"")} | H14: =IFERROR(((G14*(1-F$2))*$CU14)*F$61,"") | I14: =IFERROR(((G14*(1-F$2))*$CU14)*F$60,"") | J14: =IFERROR(IF(H14+I14=0,"",H14+I14),"") | K14: =IFERROR((($CS14/1.1)-(G14-(G14*F$2)))/($CS14/1.1),"") | L14: =IFERROR((($CT14/1.1)+(H14+I14)-(G14-(G14*F$2)))/($CT14/1.1),"") | M14: {=IFERROR(_xlfn._xlws.FILTER(ST[SOH],(ST[Code]=$C14) * (ST[Customer Name]=F$3),"" ),"")} | N14: {=IFERROR( _xlfn.LET( _xlpm.result, INDEX(_xlfn._xlws.FILTER(ST[6wk avg], (ST[Code]=$C14)*(ST[Customer Name]=F$3), ""), 1), IF(_xlpm.result=0, "", _xlpm.result) ), "")} | O14: =IFERROR(IF(CEILING(N14 + (N14 * $O$2), 1) = 0, "", CEILING(N14 + (N14 * $O$2), 1))*$B$3, "") | P14: =IFERROR((O14*H14),"") | Q14: =IFERROR((O14*I14),"") | S14: {=IFERROR(_xlfn._xlws.FILTER(ST[Customer Code],(ST[Code]=$C14) * (ST[Customer Name]=S$3),"" ),"")} | T14: {=IFERROR(_xlfn.XLOOKUP($C14,Query[Code], _xlfn.XLOOKUP('Promo Form'!S$3,Query[[#Headers],[Code]:[Bing Lee]],Query[[Code]:[Bing Lee]])),"")} | U14: =IFERROR(((T14*(1-S$2))*$CU14)*S$61,"") | V14: =IFERROR(((T14*(1-S$2))*$CU14)*S$60,"") | W14: =IFERROR(IF(U14+V14=0,"",U14+V14),"") | X14: =IFERROR((($CS14/1.1)-(T14-(T14*S$2)))/($CS14/1.1),"") | Y14: =IFERROR((($CT14/1.1)+(U14+V14)-(T14-(T14*S$2)))/($CT14/1.1),"") | Z14: {=IFERROR(_xlfn._xlws.FILTER(ST[SOH],(ST[Code]=$C14) * (ST[Customer Name]=S$3),"" ),"")} | AA14: {=IFERROR( _xlfn.LET( _xlpm.result, INDEX(_xlfn._xlws.FILTER(ST[6wk avg], (ST[Code]=$C14)*(ST[Customer Name]=S$3), ""), 1), IF(_xlpm.result=0, "", _xlpm.result) ), "")} | AB14: =IFERROR(IF(CEILING(AA14 + (AA14 * $AB$2), 1) = 0, "", CEILING(AA14 + (AA14 * $AB$2), 1))*$B$3, "") | AC14: =IFERROR((AB14*U14),"") | AD14: =IFERROR((AB14*V14),"") | AF14: {=IFERROR(_xlfn._xlws.FILTER(ST[Customer Code],(ST[Code]=$C14) * (ST[Customer Name]=AF$3),"" ),"")} | AG14: {=IFERROR(_xlfn.XLOOKUP($C14,Query[Code], _xlfn.XLOOKUP('Promo Form'!AF$3,Query[[#Headers],[Code]:[Bing Lee]],Query[[Code]:[Bing Lee]])),"")} | AH14: =IFERROR(((AG14*(1-AF$2))*$CU14)*AF$61,"") | AI14: =IFERROR(((AG14*(1-AF$2))*$CU14)*AF$60,"") | AJ14: =IFERROR(IF(AH14+AI14=0,"",AH14+AI14),"") | AK14: =IFERROR((($CS14/1.1)-(AG14-(AG14*AF$2)))/($CS14/1.1),"") | AL14: =IFERROR((($CT14/1.1)+(AH14+AI14)-(AG14-(AG14*AF$2)))/($CT14/1.1),"") | AM14: {=IFERROR(_xlfn._xlws.FILTER(ST[SOH],(ST[Code]=$C14) * (ST[Customer Name]=AF$3),"" ),"")} | AN14: {=IFERROR( _xlfn.LET( _xlpm.result, INDEX(_xlfn._xlws.FILTER(ST[6wk avg], (ST[Code]=$C14)*(ST[Customer Name]=AF$3), ""), 1), IF(_xlpm.result=0, "", _xlpm.result) ), "")} | AO14: =IFERROR(IF(CEILING(AN14 + (AN14 * $AO$2), 1) = 0, "", CEILING(AN14 + (AN14 * $AO$2), 1))*$B$3, "") | AP14: =IFERROR((AO14*AH14),"") | AQ14: =IFERROR((AO14*AI14),"") | AS14: {=IFERROR(_xlfn._xlws.FILTER(ST[Customer Code],(ST[Code]=$C14) * (ST[Customer Name]=AS$3),"" ),"")} | AT14: {=IFERROR(_xlfn.XLOOKUP($C14,Query[Code], _xlfn.XLOOKUP('Promo Form'!AS$3,Query[[#Headers],[Code]:[Bing Lee]],Query[[Code]:[Bing Lee]])),"")} | AU14: =IFERROR(((AT14*(1-AS$2))*$CU14)*AS$61,"") | AV14: =IFERROR(((AT14*(1-AS$2))*$CU14)*AS$60,"") | AW14: =IFERROR(IF(AU14+AV14=0,"",AU14+AV14),"") | AX14: =IFERROR((($CS14/1.1)-(AT14-(AT14*AS$2)))/($CS14/1.1),"") | AY14: =IFERROR((($CT14/1.1)+(AU14+AV14)-(AT14-(AT14*AS$2)))/($CT14/1.1),"") | AZ14: {=IFERROR(_xlfn._xlws.FILTER(ST[SOH],(ST[Code]=$C14) * (ST[Customer Name]=AS$3),"" ),"")} | BA14: {=IFERROR( _xlfn.LET( _xlpm.result, INDEX(_xlfn._xlws.FILTER(ST[6wk avg], (ST[Code]=$C14)*(ST[Customer Name]=AS$3), ""), 1), IF(_xlpm.result=0, "", _xlpm.result) ), "")} | BB14: =IFERROR(IF(CEILING(BA14 + (BA14 * $BB$2), 1) = 0, "", CEILING(BA14 + (BA14 * $BB$2), 1))*$B$3, "") | BC14: =IFERROR((BB14*AU14),"") | BD14: =IFERROR((BB14*AV14),"") | BF14: {=IFERROR(_xlfn._xlws.FILTER(ST[Customer Code],(ST[Code]=$C14) * (ST[Customer Name]=BF$3),"" ),"")} | BG14: {=IFERROR(_xlfn.XLOOKUP($C14,Query[Code], _xlfn.XLOOKUP('Promo Form'!BF$3,Query[[#Headers],[Code]:[Bing Lee]],Query[[Code]:[Bing Lee]])),"")} | BH14: =IFERROR(((BG14*(1-BF$2))*$CU14)*BF$61,"") | BI14: =IFERROR(((BG14*(1-BF$2))*$CU14)*BF$60,"") | BJ14: =IFERROR(IF(BH14+BI14=0,"",BH14+BI14),"") | BK14: =IFERROR((($CS14/1.1)-(BG14-(BG14*BF$2)))/($CS14/1.1),"") | BL14: =IFERROR((($CT14/1.1)+(BH14+BI14)-(BG14-(BG14*BF$2)))/($CT14/1.1),"") | BM14: {=IFERROR(_xlfn._xlws.FILTER(ST[SOH],(ST[Code]=$C14) * (ST[Customer Name]=BF$3),"" ),"")} | BN14: {=IFERROR( _xlfn.LET( _xlpm.result, INDEX(_xlfn._xlws.FILTER(ST[6wk avg], (ST[Code]=$C14)*(ST[Customer Name]=BF$3), ""), 1), IF(_xlpm.result=0, "", _xlpm.result) ), "")} | BO14: =IFERROR(IF(CEILING(BN14 + (BN14 * $BO$2), 1) = 0, "", CEILING(BN14 + (BN14 * $BO$2), 1))*$B$3, "") | BP14: =IFERROR((BO14*BH14),"") | BQ14: =IFERROR((BO14*BI14),"") | BS14: {=IFERROR(_xlfn._xlws.FILTER(ST[Customer Code],(ST[Code]=$C14) * (ST[Customer Name]=BS$3),"" ),"")} | BT14: {=IFERROR(_xlfn.XLOOKUP($C14,Query[Code], _xlfn.XLOOKUP('Promo Form'!BS$3,Query[[#Headers],[Code]:[Bing Lee]],Query[[Code]:[Bing Lee]])),"")} | BU14: =IFERROR(((BT14*(1-BS$2))*$CU14)*BS$61,"") | BV14: =IFERROR(((BT14*(1-BS$2))*$CU14)*BS$60,"") | BW14: =IFERROR(IF(BU14+BV14=0,"",BU14+BV14),"") | BX14: =IFERROR((($CS14/1.1)-(BT14-(BT14*BS$2)))/($CS14/1.1),"") | BY14: =IFERROR((($CT14/1.1)+(BU14+BV14)-(BT14-(BT14*BS$2)))/($CT14/1.1),"") | BZ14: {=IFERROR(_xlfn._xlws.FILTER(ST[SOH],(ST[Code]=$C14) * (ST[Customer Name]=BS$3),"" ),"")} | CA14: {=IFERROR( _xlfn.LET( _xlpm.result, INDEX(_xlfn._xlws.FILTER(ST[6wk avg], (ST[Code]=$C14)*(ST[Customer Name]=BS$3), ""), 1), IF(_xlpm.result=0, "", _xlpm.result) ), "")} | CB14: =IFERROR(IF(CEILING(CA14 + (CA14 * $CB$2), 1) = 0, "", CEILING(CA14 + (CA14 * $CB$2), 1))*$B$3, "") | CC14: =IFERROR((CB14*BU14),"") | CD14: =IFERROR((CB14*BV14),"") | CF14: {=IFERROR(_xlfn._xlws.FILTER(ST[Customer Code],(ST[Code]=$C14) * (ST[Customer Name]=CF$3),"" ),"")} | CG14: {=IFERROR(_xlfn.XLOOKUP($C14,Query[Code], _xlfn.XLOOKUP('Promo Form'!CF$3,Query[[#Headers],[Code]:[Bing Lee]],Query[[Code]:[Bing Lee]])),"")} | CH14: =IFERROR(((CG14*(1-CF$2))*$CU14)*CF$61,"") | CI14: =IFERROR(((CG14*(1-CF$2))*$CU14)*CF$60,"") | CJ14: =IFERROR(IF(CH14+CI14=0,"",CH14+CI14),"") | CK14: =IFERROR((($CS14/1.1)-(CG14-(CG14*CF$2)))/($CS14/1.1),"") | CL14: =IFERROR((($CT14/1.1)+(CH14+CI14)-(CG14-(CG14*CF$2)))/($CT14/1.1),"") | CM14: {=IFERROR(_xlfn._xlws.FILTER(ST[SOH],(ST[Code]=$C14) * (ST[Customer Name]=CF$3),"" ),"")} | CN14: {=IFERROR( _xlfn.LET( _xlpm.result, INDEX(_xlfn._xlws.FILTER(ST[6wk avg], (ST[Code]=$C14)*(ST[Customer Name]=CF$3), ""), 1), IF(_xlpm.result=0, "", _xlpm.result) ), "")} | CO14: =IFERROR(IF(CEILING(CN14 + (CN14 * $CO$2), 1) = 0, "", CEILING(CN14 + (CN14 * $CO$2), 1))*$B$3, "") | CP14: =IFERROR((CO14*CH14),"") | CQ14: =IFERROR((CO14*CI14),"") | CS14: =IFERROR(_xlfn.XLOOKUP(C14,Query[Code],Query[Base (RRP Inc)]),"") | CT14: =IFERROR(CS14-(CS14*CU14),"") | CU14: =IF(C14="", "",CU13) | CV14: =IFERROR((CS14-CT14),"")
A15: =IF(C15="","",A14) | B15: =IF(C15="","",B14) | D15: =IF(C15="", "",_xlfn.XLOOKUP(C15,'Master Price Level'!C:C,'Master Price Level'!D:D)) | F15: {=IFERROR(_xlfn._xlws.FILTER(ST[Customer Code],(ST[Code]=$C15) * (ST[Customer Name]=F$3),"" ),"")} | G15: {=IFERROR(_xlfn.XLOOKUP($C15,Query[Code], _xlfn.XLOOKUP('Promo Form'!F$3,Query[[#Headers],[Code]:[Bing Lee]],Query[[Code]:[Bing Lee]])),"")} | H15: =IFERROR(((G15*(1-F$2))*$CU15)*F$61,"") | I15: =IFERROR(((G15*(1-F$2))*$CU15)*F$60,"") | J15: =IFERROR(IF(H15+I15=0,"",H15+I15),"") | K15: =IFERROR((($CS15/1.1)-(G15-(G15*F$2)))/($CS15/1.1),"") | L15: =IFERROR((($CT15/1.1)+(H15+I15)-(G15-(G15*F$2)))/($CT15/1.1),"") | M15: {=IFERROR(_xlfn._xlws.FILTER(ST[SOH],(ST[Code]=$C15) * (ST[Customer Name]=F$3),"" ),"")} | N15: {=IFERROR( _xlfn.LET( _xlpm.result, INDEX(_xlfn._xlws.FILTER(ST[6wk avg], (ST[Code]=$C15)*(ST[Customer Name]=F$3), ""), 1), IF(_xlpm.result=0, "", _xlpm.result) ), "")} | O15: =IFERROR(IF(CEILING(N15 + (N15 * $O$2), 1) = 0, "", CEILING(N15 + (N15 * $O$2), 1))*$B$3, "") | P15: =IFERROR((O15*H15),"") | Q15: =IFERROR((O15*I15),"") | S15: {=IFERROR(_xlfn._xlws.FILTER(ST[Customer Code],(ST[Code]=$C15) * (ST[Customer Name]=S$3),"" ),"")} | T15: {=IFERROR(_xlfn.XLOOKUP($C15,Query[Code], _xlfn.XLOOKUP('Promo Form'!S$3,Query[[#Headers],[Code]:[Bing Lee]],Query[[Code]:[Bing Lee]])),"")} | U15: =IFERROR(((T15*(1-S$2))*$CU15)*S$61,"") | V15: =IFERROR(((T15*(1-S$2))*$CU15)*S$60,"") | W15: =IFERROR(IF(U15+V15=0,"",U15+V15),"") | X15: =IFERROR((($CS15/1.1)-(T15-(T15*S$2)))/($CS15/1.1),"") | Y15: =IFERROR((($CT15/1.1)+(U15+V15)-(T15-(T15*S$2)))/($CT15/1.1),"") | Z15: {=IFERROR(_xlfn._xlws.FILTER(ST[SOH],(ST[Code]=$C15) * (ST[Customer Name]=S$3),"" ),"")} | AA15: {=IFERROR( _xlfn.LET( _xlpm.result, INDEX(_xlfn._xlws.FILTER(ST[6wk avg], (ST[Code]=$C15)*(ST[Customer Name]=S$3), ""), 1), IF(_xlpm.result=0, "", _xlpm.result) ), "")} | AB15: =IFERROR(IF(CEILING(AA15 + (AA15 * $AB$2), 1) = 0, "", CEILING(AA15 + (AA15 * $AB$2), 1))*$B$3, "") | AC15: =IFERROR((AB15*U15),"") | AD15: =IFERROR((AB15*V15),"") | AF15: {=IFERROR(_xlfn._xlws.FILTER(ST[Customer Code],(ST[Code]=$C15) * (ST[Customer Name]=AF$3),"" ),"")} | AG15: {=IFERROR(_xlfn.XLOOKUP($C15,Query[Code], _xlfn.XLOOKUP('Promo Form'!AF$3,Query[[#Headers],[Code]:[Bing Lee]],Query[[Code]:[Bing Lee]])),"")} | AH15: =IFERROR(((AG15*(1-AF$2))*$CU15)*AF$61,"") | AI15: =IFERROR(((AG15*(1-AF$2))*$CU15)*AF$60,"") | AJ15: =IFERROR(IF(AH15+AI15=0,"",AH15+AI15),"") | AK15: =IFERROR((($CS15/1.1)-(AG15-(AG15*AF$2)))/($CS15/1.1),"") | AL15: =IFERROR((($CT15/1.1)+(AH15+AI15)-(AG15-(AG15*AF$2)))/($CT15/1.1),"") | AM15: {=IFERROR(_xlfn._xlws.FILTER(ST[SOH],(ST[Code]=$C15) * (ST[Customer Name]=AF$3),"" ),"")} | AN15: {=IFERROR( _xlfn.LET( _xlpm.result, INDEX(_xlfn._xlws.FILTER(ST[6wk avg], (ST[Code]=$C15)*(ST[Customer Name]=AF$3), ""), 1), IF(_xlpm.result=0, "", _xlpm.result) ), "")} | AO15: =IFERROR(IF(CEILING(AN15 + (AN15 * $AO$2), 1) = 0, "", CEILING(AN15 + (AN15 * $AO$2), 1))*$B$3, "") | AP15: =IFERROR((AO15*AH15),"") | AQ15: =IFERROR((AO15*AI15),"") | AS15: {=IFERROR(_xlfn._xlws.FILTER(ST[Customer Code],(ST[Code]=$C15) * (ST[Customer Name]=AS$3),"" ),"")} | AT15: {=IFERROR(_xlfn.XLOOKUP($C15,Query[Code], _xlfn.XLOOKUP('Promo Form'!AS$3,Query[[#Headers],[Code]:[Bing Lee]],Query[[Code]:[Bing Lee]])),"")} | AU15: =IFERROR(((AT15*(1-AS$2))*$CU15)*AS$61,"") | AV15: =IFERROR(((AT15*(1-AS$2))*$CU15)*AS$60,"") | AW15: =IFERROR(IF(AU15+AV15=0,"",AU15+AV15),"") | AX15: =IFERROR((($CS15/1.1)-(AT15-(AT15*AS$2)))/($CS15/1.1),"") | AY15: =IFERROR((($CT15/1.1)+(AU15+AV15)-(AT15-(AT15*AS$2)))/($CT15/1.1),"") | AZ15: {=IFERROR(_xlfn._xlws.FILTER(ST[SOH],(ST[Code]=$C15) * (ST[Customer Name]=AS$3),"" ),"")} | BA15: {=IFERROR( _xlfn.LET( _xlpm.result, INDEX(_xlfn._xlws.FILTER(ST[6wk avg], (ST[Code]=$C15)*(ST[Customer Name]=AS$3), ""), 1), IF(_xlpm.result=0, "", _xlpm.result) ), "")} | BB15: =IFERROR(IF(CEILING(BA15 + (BA15 * $BB$2), 1) = 0, "", CEILING(BA15 + (BA15 * $BB$2), 1))*$B$3, "") | BC15: =IFERROR((BB15*AU15),"") | BD15: =IFERROR((BB15*AV15),"") | BF15: {=IFERROR(_xlfn._xlws.FILTER(ST[Customer Code],(ST[Code]=$C15) * (ST[Customer Name]=BF$3),"" ),"")} | BG15: {=IFERROR(_xlfn.XLOOKUP($C15,Query[Code], _xlfn.XLOOKUP('Promo Form'!BF$3,Query[[#Headers],[Code]:[Bing Lee]],Query[[Code]:[Bing Lee]])),"")} | BH15: =IFERROR(((BG15*(1-BF$2))*$CU15)*BF$61,"") | BI15: =IFERROR(((BG15*(1-BF$2))*$CU15)*BF$60,"") | BJ15: =IFERROR(IF(BH15+BI15=0,"",BH15+BI15),"") | BK15: =IFERROR((($CS15/1.1)-(BG15-(BG15*BF$2)))/($CS15/1.1),"") | BL15: =IFERROR((($CT15/1.1)+(BH15+BI15)-(BG15-(BG15*BF$2)))/($CT15/1.1),"") | BM15: {=IFERROR(_xlfn._xlws.FILTER(ST[SOH],(ST[Code]=$C15) * (ST[Customer Name]=BF$3),"" ),"")} | BN15: {=IFERROR( _xlfn.LET( _xlpm.result, INDEX(_xlfn._xlws.FILTER(ST[6wk avg], (ST[Code]=$C15)*(ST[Customer Name]=BF$3), ""), 1), IF(_xlpm.result=0, "", _xlpm.result) ), "")} | BO15: =IFERROR(IF(CEILING(BN15 + (BN15 * $BO$2), 1) = 0, "", CEILING(BN15 + (BN15 * $BO$2), 1))*$B$3, "") | BP15: =IFERROR((BO15*BH15),"") | BQ15: =IFERROR((BO15*BI15),"") | BS15: {=IFERROR(_xlfn._xlws.FILTER(ST[Customer Code],(ST[Code]=$C15) * (ST[Customer Name]=BS$3),"" ),"")} | BT15: {=IFERROR(_xlfn.XLOOKUP($C15,Query[Code], _xlfn.XLOOKUP('Promo Form'!BS$3,Query[[#Headers],[Code]:[Bing Lee]],Query[[Code]:[Bing Lee]])),"")} | BU15: =IFERROR(((BT15*(1-BS$2))*$CU15)*BS$61,"") | BV15: =IFERROR(((BT15*(1-BS$2))*$CU15)*BS$60,"") | BW15: =IFERROR(IF(BU15+BV15=0,"",BU15+BV15),"") | BX15: =IFERROR((($CS15/1.1)-(BT15-(BT15*BS$2)))/($CS15/1.1),"") | BY15: =IFERROR((($CT15/1.1)+(BU15+BV15)-(BT15-(BT15*BS$2)))/($CT15/1.1),"") | BZ15: {=IFERROR(_xlfn._xlws.FILTER(ST[SOH],(ST[Code]=$C15) * (ST[Customer Name]=BS$3),"" ),"")} | CA15: {=IFERROR( _xlfn.LET( _xlpm.result, INDEX(_xlfn._xlws.FILTER(ST[6wk avg], (ST[Code]=$C15)*(ST[Customer Name]=BS$3), ""), 1), IF(_xlpm.result=0, "", _xlpm.result) ), "")} | CB15: =IFERROR(IF(CEILING(CA15 + (CA15 * $CB$2), 1) = 0, "", CEILING(CA15 + (CA15 * $CB$2), 1))*$B$3, "") | CC15: =IFERROR((CB15*BU15),"") | CD15: =IFERROR((CB15*BV15),"") | CF15: {=IFERROR(_xlfn._xlws.FILTER(ST[Customer Code],(ST[Code]=$C15) * (ST[Customer Name]=CF$3),"" ),"")} | CG15: {=IFERROR(_xlfn.XLOOKUP($C15,Query[Code], _xlfn.XLOOKUP('Promo Form'!CF$3,Query[[#Headers],[Code]:[Bing Lee]],Query[[Code]:[Bing Lee]])),"")} | CH15: =IFERROR(((CG15*(1-CF$2))*$CU15)*CF$61,"") | CI15: =IFERROR(((CG15*(1-CF$2))*$CU15)*CF$60,"") | CJ15: =IFERROR(IF(CH15+CI15=0,"",CH15+CI15),"") | CK15: =IFERROR((($CS15/1.1)-(CG15-(CG15*CF$2)))/($CS15/1.1),"") | CL15: =IFERROR((($CT15/1.1)+(CH15+CI15)-(CG15-(CG15*CF$2)))/($CT15/1.1),"") | CM15: {=IFERROR(_xlfn._xlws.FILTER(ST[SOH],(ST[Code]=$C15) * (ST[Customer Name]=CF$3),"" ),"")} | CN15: {=IFERROR( _xlfn.LET( _xlpm.result, INDEX(_xlfn._xlws.FILTER(ST[6wk avg], (ST[Code]=$C15)*(ST[Customer Name]=CF$3), ""), 1), IF(_xlpm.result=0, "", _xlpm.result) ), "")} | CO15: =IFERROR(IF(CEILING(CN15 + (CN15 * $CO$2), 1) = 0, "", CEILING(CN15 + (CN15 * $CO$2), 1))*$B$3, "") | CP15: =IFERROR((CO15*CH15),"") | CQ15: =IFERROR((CO15*CI15),"") | CS15: =IFERROR(_xlfn.XLOOKUP(C15,Query[Code],Query[Base (RRP Inc)]),"") | CT15: =IFERROR(CS15-(CS15*CU15),"") | CU15: =IF(C15="", "",CU14) | CV15: =IFERROR((CS15-CT15),"")
A16: =IF(C16="","",A15) | B16: =IF(C16="","",B15) | D16: =IF(C16="", "",_xlfn.XLOOKUP(C16,'Master Price Level'!C:C,'Master Price Level'!D:D)) | F16: {=IFERROR(_xlfn._xlws.FILTER(ST[Customer Code],(ST[Code]=$C16) * (ST[Customer Name]=F$3),"" ),"")} | G16: {=IFERROR(_xlfn.XLOOKUP($C16,Query[Code], _xlfn.XLOOKUP('Promo Form'!F$3,Query[[#Headers],[Code]:[Bing Lee]],Query[[Code]:[Bing Lee]])),"")} | H16: =IFERROR(((G16*(1-F$2))*$CU16)*F$61,"") | I16: =IFERROR(((G16*(1-F$2))*$CU16)*F$60,"") | J16: =IFERROR(IF(H16+I16=0,"",H16+I16),"") | K16: =IFERROR((($CS16/1.1)-(G16-(G16*F$2)))/($CS16/1.1),"") | L16: =IFERROR((($CT16/1.1)+(H16+I16)-(G16-(G16*F$2)))/($CT16/1.1),"") | M16: {=IFERROR(_xlfn._xlws.FILTER(ST[SOH],(ST[Code]=$C16) * (ST[Customer Name]=F$3),"" ),"")} | N16: {=IFERROR( _xlfn.LET( _xlpm.result, INDEX(_xlfn._xlws.FILTER(ST[6wk avg], (ST[Code]=$C16)*(ST[Customer Name]=F$3), ""), 1), IF(_xlpm.result=0, "", _xlpm.result) ), "")} | O16: =IFERROR(IF(CEILING(N16 + (N16 * $O$2), 1) = 0, "", CEILING(N16 + (N16 * $O$2), 1))*$B$3, "") | P16: =IFERROR((O16*H16),"") | Q16: =IFERROR((O16*I16),"") | S16: {=IFERROR(_xlfn._xlws.FILTER(ST[Customer Code],(ST[Code]=$C16) * (ST[Customer Name]=S$3),"" ),"")} | T16: {=IFERROR(_xlfn.XLOOKUP($C16,Query[Code], _xlfn.XLOOKUP('Promo Form'!S$3,Query[[#Headers],[Code]:[Bing Lee]],Query[[Code]:[Bing Lee]])),"")} | U16: =IFERROR(((T16*(1-S$2))*$CU16)*S$61,"") | V16: =IFERROR(((T16*(1-S$2))*$CU16)*S$60,"") | W16: =IFERROR(IF(U16+V16=0,"",U16+V16),"") | X16: =IFERROR((($CS16/1.1)-(T16-(T16*S$2)))/($CS16/1.1),"") | Y16: =IFERROR((($CT16/1.1)+(U16+V16)-(T16-(T16*S$2)))/($CT16/1.1),"") | Z16: {=IFERROR(_xlfn._xlws.FILTER(ST[SOH],(ST[Code]=$C16) * (ST[Customer Name]=S$3),"" ),"")} | AA16: {=IFERROR( _xlfn.LET( _xlpm.result, INDEX(_xlfn._xlws.FILTER(ST[6wk avg], (ST[Code]=$C16)*(ST[Customer Name]=S$3), ""), 1), IF(_xlpm.result=0, "", _xlpm.result) ), "")} | AB16: =IFERROR(IF(CEILING(AA16 + (AA16 * $AB$2), 1) = 0, "", CEILING(AA16 + (AA16 * $AB$2), 1))*$B$3, "") | AC16: =IFERROR((AB16*U16),"") | AD16: =IFERROR((AB16*V16),"") | AF16: {=IFERROR(_xlfn._xlws.FILTER(ST[Customer Code],(ST[Code]=$C16) * (ST[Customer Name]=AF$3),"" ),"")} | AG16: {=IFERROR(_xlfn.XLOOKUP($C16,Query[Code], _xlfn.XLOOKUP('Promo Form'!AF$3,Query[[#Headers],[Code]:[Bing Lee]],Query[[Code]:[Bing Lee]])),"")} | AH16: =IFERROR(((AG16*(1-AF$2))*$CU16)*AF$61,"") | AI16: =IFERROR(((AG16*(1-AF$2))*$CU16)*AF$60,"") | AJ16: =IFERROR(IF(AH16+AI16=0,"",AH16+AI16),"") | AK16: =IFERROR((($CS16/1.1)-(AG16-(AG16*AF$2)))/($CS16/1.1),"") | AL16: =IFERROR((($CT16/1.1)+(AH16+AI16)-(AG16-(AG16*AF$2)))/($CT16/1.1),"") | AM16: {=IFERROR(_xlfn._xlws.FILTER(ST[SOH],(ST[Code]=$C16) * (ST[Customer Name]=AF$3),"" ),"")} | AN16: {=IFERROR( _xlfn.LET( _xlpm.result, INDEX(_xlfn._xlws.FILTER(ST[6wk avg], (ST[Code]=$C16)*(ST[Customer Name]=AF$3), ""), 1), IF(_xlpm.result=0, "", _xlpm.result) ), "")} | AO16: =IFERROR(IF(CEILING(AN16 + (AN16 * $AO$2), 1) = 0, "", CEILING(AN16 + (AN16 * $AO$2), 1))*$B$3, "") | AP16: =IFERROR((AO16*AH16),"") | AQ16: =IFERROR((AO16*AI16),"") | AS16: {=IFERROR(_xlfn._xlws.FILTER(ST[Customer Code],(ST[Code]=$C16) * (ST[Customer Name]=AS$3),"" ),"")} | AT16: {=IFERROR(_xlfn.XLOOKUP($C16,Query[Code], _xlfn.XLOOKUP('Promo Form'!AS$3,Query[[#Headers],[Code]:[Bing Lee]],Query[[Code]:[Bing Lee]])),"")} | AU16: =IFERROR(((AT16*(1-AS$2))*$CU16)*AS$61,"") | AV16: =IFERROR(((AT16*(1-AS$2))*$CU16)*AS$60,"") | AW16: =IFERROR(IF(AU16+AV16=0,"",AU16+AV16),"") | AX16: =IFERROR((($CS16/1.1)-(AT16-(AT16*AS$2)))/($CS16/1.1),"") | AY16: =IFERROR((($CT16/1.1)+(AU16+AV16)-(AT16-(AT16*AS$2)))/($CT16/1.1),"") | AZ16: {=IFERROR(_xlfn._xlws.FILTER(ST[SOH],(ST[Code]=$C16) * (ST[Customer Name]=AS$3),"" ),"")} | BA16: {=IFERROR( _xlfn.LET( _xlpm.result, INDEX(_xlfn._xlws.FILTER(ST[6wk avg], (ST[Code]=$C16)*(ST[Customer Name]=AS$3), ""), 1), IF(_xlpm.result=0, "", _xlpm.result) ), "")} | BB16: =IFERROR(IF(CEILING(BA16 + (BA16 * $BB$2), 1) = 0, "", CEILING(BA16 + (BA16 * $BB$2), 1))*$B$3, "") | BC16: =IFERROR((BB16*AU16),"") | BD16: =IFERROR((BB16*AV16),"") | BF16: {=IFERROR(_xlfn._xlws.FILTER(ST[Customer Code],(ST[Code]=$C16) * (ST[Customer Name]=BF$3),"" ),"")} | BG16: {=IFERROR(_xlfn.XLOOKUP($C16,Query[Code], _xlfn.XLOOKUP('Promo Form'!BF$3,Query[[#Headers],[Code]:[Bing Lee]],Query[[Code]:[Bing Lee]])),"")} | BH16: =IFERROR(((BG16*(1-BF$2))*$CU16)*BF$61,"") | BI16: =IFERROR(((BG16*(1-BF$2))*$CU16)*BF$60,"") | BJ16: =IFERROR(IF(BH16+BI16=0,"",BH16+BI16),"") | BK16: =IFERROR((($CS16/1.1)-(BG16-(BG16*BF$2)))/($CS16/1.1),"") | BL16: =IFERROR((($CT16/1.1)+(BH16+BI16)-(BG16-(BG16*BF$2)))/($CT16/1.1),"") | BM16: {=IFERROR(_xlfn._xlws.FILTER(ST[SOH],(ST[Code]=$C16) * (ST[Customer Name]=BF$3),"" ),"")} | BN16: {=IFERROR( _xlfn.LET( _xlpm.result, INDEX(_xlfn._xlws.FILTER(ST[6wk avg], (ST[Code]=$C16)*(ST[Customer Name]=BF$3), ""), 1), IF(_xlpm.result=0, "", _xlpm.result) ), "")} | BO16: =IFERROR(IF(CEILING(BN16 + (BN16 * $BO$2), 1) = 0, "", CEILING(BN16 + (BN16 * $BO$2), 1))*$B$3, "") | BP16: =IFERROR((BO16*BH16),"") | BQ16: =IFERROR((BO16*BI16),"") | BS16: {=IFERROR(_xlfn._xlws.FILTER(ST[Customer Code],(ST[Code]=$C16) * (ST[Customer Name]=BS$3),"" ),"")} | BT16: {=IFERROR(_xlfn.XLOOKUP($C16,Query[Code], _xlfn.XLOOKUP('Promo Form'!BS$3,Query[[#Headers],[Code]:[Bing Lee]],Query[[Code]:[Bing Lee]])),"")} | BU16: =IFERROR(((BT16*(1-BS$2))*$CU16)*BS$61,"") | BV16: =IFERROR(((BT16*(1-BS$2))*$CU16)*BS$60,"") | BW16: =IFERROR(IF(BU16+BV16=0,"",BU16+BV16),"") | BX16: =IFERROR((($CS16/1.1)-(BT16-(BT16*BS$2)))/($CS16/1.1),"") | BY16: =IFERROR((($CT16/1.1)+(BU16+BV16)-(BT16-(BT16*BS$2)))/($CT16/1.1),"") | BZ16: {=IFERROR(_xlfn._xlws.FILTER(ST[SOH],(ST[Code]=$C16) * (ST[Customer Name]=BS$3),"" ),"")} | CA16: {=IFERROR( _xlfn.LET( _xlpm.result, INDEX(_xlfn._xlws.FILTER(ST[6wk avg], (ST[Code]=$C16)*(ST[Customer Name]=BS$3), ""), 1), IF(_xlpm.result=0, "", _xlpm.result) ), "")} | CB16: =IFERROR(IF(CEILING(CA16 + (CA16 * $CB$2), 1) = 0, "", CEILING(CA16 + (CA16 * $CB$2), 1))*$B$3, "") | CC16: =IFERROR((CB16*BU16),"") | CD16: =IFERROR((CB16*BV16),"") | CF16: {=IFERROR(_xlfn._xlws.FILTER(ST[Customer Code],(ST[Code]=$C16) * (ST[Customer Name]=CF$3),"" ),"")} | CG16: {=IFERROR(_xlfn.XLOOKUP($C16,Query[Code], _xlfn.XLOOKUP('Promo Form'!CF$3,Query[[#Headers],[Code]:[Bing Lee]],Query[[Code]:[Bing Lee]])),"")} | CH16: =IFERROR(((CG16*(1-CF$2))*$CU16)*CF$61,"") | CI16: =IFERROR(((CG16*(1-CF$2))*$CU16)*CF$60,"") | CJ16: =IFERROR(IF(CH16+CI16=0,"",CH16+CI16),"") | CK16: =IFERROR((($CS16/1.1)-(CG16-(CG16*CF$2)))/($CS16/1.1),"") | CL16: =IFERROR((($CT16/1.1)+(CH16+CI16)-(CG16-(CG16*CF$2)))/($CT16/1.1),"") | CM16: {=IFERROR(_xlfn._xlws.FILTER(ST[SOH],(ST[Code]=$C16) * (ST[Customer Name]=CF$3),"" ),"")} | CN16: {=IFERROR( _xlfn.LET( _xlpm.result, INDEX(_xlfn._xlws.FILTER(ST[6wk avg], (ST[Code]=$C16)*(ST[Customer Name]=CF$3), ""), 1), IF(_xlpm.result=0, "", _xlpm.result) ), "")} | CO16: =IFERROR(IF(CEILING(CN16 + (CN16 * $CO$2), 1) = 0, "", CEILING(CN16 + (CN16 * $CO$2), 1))*$B$3, "") | CP16: =IFERROR((CO16*CH16),"") | CQ16: =IFERROR((CO16*CI16),"") | CS16: =IFERROR(_xlfn.XLOOKUP(C16,Query[Code],Query[Base (RRP Inc)]),"") | CT16: =IFERROR(CS16-(CS16*CU16),"") | CU16: =IF(C16="", "",CU15) | CV16: =IFERROR((CS16-CT16),"")
A17: =IF(C17="","",A16) | B17: =IF(C17="","",B16) | D17: =IF(C17="", "",_xlfn.XLOOKUP(C17,'Master Price Level'!C:C,'Master Price Level'!D:D)) | F17: {=IFERROR(_xlfn._xlws.FILTER(ST[Customer Code],(ST[Code]=$C17) * (ST[Customer Name]=F$3),"" ),"")} | G17: {=IFERROR(_xlfn.XLOOKUP($C17,Query[Code], _xlfn.XLOOKUP('Promo Form'!F$3,Query[[#Headers],[Code]:[Bing Lee]],Query[[Code]:[Bing Lee]])),"")} | H17: =IFERROR(((G17*(1-F$2))*$CU17)*F$61,"") | I17: =IFERROR(((G17*(1-F$2))*$CU17)*F$60,"") | J17: =IFERROR(IF(H17+I17=0,"",H17+I17),"") | K17: =IFERROR((($CS17/1.1)-(G17-(G17*F$2)))/($CS17/1.1),"") | L17: =IFERROR((($CT17/1.1)+(H17+I17)-(G17-(G17*F$2)))/($CT17/1.1),"") | M17: {=IFERROR(_xlfn._xlws.FILTER(ST[SOH],(ST[Code]=$C17) * (ST[Customer Name]=F$3),"" ),"")} | N17: {=IFERROR( _xlfn.LET( _xlpm.result, INDEX(_xlfn._xlws.FILTER(ST[6wk avg], (ST[Code]=$C17)*(ST[Customer Name]=F$3), ""), 1), IF(_xlpm.result=0, "", _xlpm.result) ), "")} | O17: =IFERROR(IF(CEILING(N17 + (N17 * $O$2), 1) = 0, "", CEILING(N17 + (N17 * $O$2), 1))*$B$3, "") | P17: =IFERROR((O17*H17),"") | Q17: =IFERROR((O17*I17),"") | S17: {=IFERROR(_xlfn._xlws.FILTER(ST[Customer Code],(ST[Code]=$C17) * (ST[Customer Name]=S$3),"" ),"")} | T17: {=IFERROR(_xlfn.XLOOKUP($C17,Query[Code], _xlfn.XLOOKUP('Promo Form'!S$3,Query[[#Headers],[Code]:[Bing Lee]],Query[[Code]:[Bing Lee]])),"")} | U17: =IFERROR(((T17*(1-S$2))*$CU17)*S$61,"") | V17: =IFERROR(((T17*(1-S$2))*$CU17)*S$60,"") | W17: =IFERROR(IF(U17+V17=0,"",U17+V17),"") | X17: =IFERROR((($CS17/1.1)-(T17-(T17*S$2)))/($CS17/1.1),"") | Y17: =IFERROR((($CT17/1.1)+(U17+V17)-(T17-(T17*S$2)))/($CT17/1.1),"") | Z17: {=IFERROR(_xlfn._xlws.FILTER(ST[SOH],(ST[Code]=$C17) * (ST[Customer Name]=S$3),"" ),"")} | AA17: {=IFERROR( _xlfn.LET( _xlpm.result, INDEX(_xlfn._xlws.FILTER(ST[6wk avg], (ST[Code]=$C17)*(ST[Customer Name]=S$3), ""), 1), IF(_xlpm.result=0, "", _xlpm.result) ), "")} | AB17: =IFERROR(IF(CEILING(AA17 + (AA17 * $AB$2), 1) = 0, "", CEILING(AA17 + (AA17 * $AB$2), 1))*$B$3, "") | AC17: =IFERROR((AB17*U17),"") | AD17: =IFERROR((AB17*V17),"") | AF17: {=IFERROR(_xlfn._xlws.FILTER(ST[Customer Code],(ST[Code]=$C17) * (ST[Customer Name]=AF$3),"" ),"")} | AG17: {=IFERROR(_xlfn.XLOOKUP($C17,Query[Code], _xlfn.XLOOKUP('Promo Form'!AF$3,Query[[#Headers],[Code]:[Bing Lee]],Query[[Code]:[Bing Lee]])),"")} | AH17: =IFERROR(((AG17*(1-AF$2))*$CU17)*AF$61,"") | AI17: =IFERROR(((AG17*(1-AF$2))*$CU17)*AF$60,"") | AJ17: =IFERROR(IF(AH17+AI17=0,"",AH17+AI17),"") | AK17: =IFERROR((($CS17/1.1)-(AG17-(AG17*AF$2)))/($CS17/1.1),"") | AL17: =IFERROR((($CT17/1.1)+(AH17+AI17)-(AG17-(AG17*AF$2)))/($CT17/1.1),"") | AM17: {=IFERROR(_xlfn._xlws.FILTER(ST[SOH],(ST[Code]=$C17) * (ST[Customer Name]=AF$3),"" ),"")} | AN17: {=IFERROR( _xlfn.LET( _xlpm.result, INDEX(_xlfn._xlws.FILTER(ST[6wk avg], (ST[Code]=$C17)*(ST[Customer Name]=AF$3), ""), 1), IF(_xlpm.result=0, "", _xlpm.result) ), "")} | AO17: =IFERROR(IF(CEILING(AN17 + (AN17 * $AO$2), 1) = 0, "", CEILING(AN17 + (AN17 * $AO$2), 1))*$B$3, "") | AP17: =IFERROR((AO17*AH17),"") | AQ17: =IFERROR((AO17*AI17),"") | AS17: {=IFERROR(_xlfn._xlws.FILTER(ST[Customer Code],(ST[Code]=$C17) * (ST[Customer Name]=AS$3),"" ),"")} | AT17: {=IFERROR(_xlfn.XLOOKUP($C17,Query[Code], _xlfn.XLOOKUP('Promo Form'!AS$3,Query[[#Headers],[Code]:[Bing Lee]],Query[[Code]:[Bing Lee]])),"")} | AU17: =IFERROR(((AT17*(1-AS$2))*$CU17)*AS$61,"") | AV17: =IFERROR(((AT17*(1-AS$2))*$CU17)*AS$60,"") | AW17: =IFERROR(IF(AU17+AV17=0,"",AU17+AV17),"") | AX17: =IFERROR((($CS17/1.1)-(AT17-(AT17*AS$2)))/($CS17/1.1),"") | AY17: =IFERROR((($CT17/1.1)+(AU17+AV17)-(AT17-(AT17*AS$2)))/($CT17/1.1),"") | AZ17: {=IFERROR(_xlfn._xlws.FILTER(ST[SOH],(ST[Code]=$C17) * (ST[Customer Name]=AS$3),"" ),"")} | BA17: {=IFERROR( _xlfn.LET( _xlpm.result, INDEX(_xlfn._xlws.FILTER(ST[6wk avg], (ST[Code]=$C17)*(ST[Customer Name]=AS$3), ""), 1), IF(_xlpm.result=0, "", _xlpm.result) ), "")} | BB17: =IFERROR(IF(CEILING(BA17 + (BA17 * $BB$2), 1) = 0, "", CEILING(BA17 + (BA17 * $BB$2), 1))*$B$3, "") | BC17: =IFERROR((BB17*AU17),"") | BD17: =IFERROR((BB17*AV17),"") | BF17: {=IFERROR(_xlfn._xlws.FILTER(ST[Customer Code],(ST[Code]=$C17) * (ST[Customer Name]=BF$3),"" ),"")} | BG17: {=IFERROR(_xlfn.XLOOKUP($C17,Query[Code], _xlfn.XLOOKUP('Promo Form'!BF$3,Query[[#Headers],[Code]:[Bing Lee]],Query[[Code]:[Bing Lee]])),"")} | BH17: =IFERROR(((BG17*(1-BF$2))*$CU17)*BF$61,"") | BI17: =IFERROR(((BG17*(1-BF$2))*$CU17)*BF$60,"") | BJ17: =IFERROR(IF(BH17+BI17=0,"",BH17+BI17),"") | BK17: =IFERROR((($CS17/1.1)-(BG17-(BG17*BF$2)))/($CS17/1.1),"") | BL17: =IFERROR((($CT17/1.1)+(BH17+BI17)-(BG17-(BG17*BF$2)))/($CT17/1.1),"") | BM17: {=IFERROR(_xlfn._xlws.FILTER(ST[SOH],(ST[Code]=$C17) * (ST[Customer Name]=BF$3),"" ),"")} | BN17: {=IFERROR( _xlfn.LET( _xlpm.result, INDEX(_xlfn._xlws.FILTER(ST[6wk avg], (ST[Code]=$C17)*(ST[Customer Name]=BF$3), ""), 1), IF(_xlpm.result=0, "", _xlpm.result) ), "")} | BO17: =IFERROR(IF(CEILING(BN17 + (BN17 * $BO$2), 1) = 0, "", CEILING(BN17 + (BN17 * $BO$2), 1))*$B$3, "") | BP17: =IFERROR((BO17*BH17),"") | BQ17: =IFERROR((BO17*BI17),"") | BS17: {=IFERROR(_xlfn._xlws.FILTER(ST[Customer Code],(ST[Code]=$C17) * (ST[Customer Name]=BS$3),"" ),"")} | BT17: {=IFERROR(_xlfn.XLOOKUP($C17,Query[Code], _xlfn.XLOOKUP('Promo Form'!BS$3,Query[[#Headers],[Code]:[Bing Lee]],Query[[Code]:[Bing Lee]])),"")} | BU17: =IFERROR(((BT17*(1-BS$2))*$CU17)*BS$61,"") | BV17: =IFERROR(((BT17*(1-BS$2))*$CU17)*BS$60,"") | BW17: =IFERROR(IF(BU17+BV17=0,"",BU17+BV17),"") | BX17: =IFERROR((($CS17/1.1)-(BT17-(BT17*BS$2)))/($CS17/1.1),"") | BY17: =IFERROR((($CT17/1.1)+(BU17+BV17)-(BT17-(BT17*BS$2)))/($CT17/1.1),"") | BZ17: {=IFERROR(_xlfn._xlws.FILTER(ST[SOH],(ST[Code]=$C17) * (ST[Customer Name]=BS$3),"" ),"")} | CA17: {=IFERROR( _xlfn.LET( _xlpm.result, INDEX(_xlfn._xlws.FILTER(ST[6wk avg], (ST[Code]=$C17)*(ST[Customer Name]=BS$3), ""), 1), IF(_xlpm.result=0, "", _xlpm.result) ), "")} | CB17: =IFERROR(IF(CEILING(CA17 + (CA17 * $CB$2), 1) = 0, "", CEILING(CA17 + (CA17 * $CB$2), 1))*$B$3, "") | CC17: =IFERROR((CB17*BU17),"") | CD17: =IFERROR((CB17*BV17),"") | CF17: {=IFERROR(_xlfn._xlws.FILTER(ST[Customer Code],(ST[Code]=$C17) * (ST[Customer Name]=CF$3),"" ),"")} | CG17: {=IFERROR(_xlfn.XLOOKUP($C17,Query[Code], _xlfn.XLOOKUP('Promo Form'!CF$3,Query[[#Headers],[Code]:[Bing Lee]],Query[[Code]:[Bing Lee]])),"")} | CH17: =IFERROR(((CG17*(1-CF$2))*$CU17)*CF$61,"") | CI17: =IFERROR(((CG17*(1-CF$2))*$CU17)*CF$60,"") | CJ17: =IFERROR(IF(CH17+CI17=0,"",CH17+CI17),"") | CK17: =IFERROR((($CS17/1.1)-(CG17-(CG17*CF$2)))/($CS17/1.1),"") | CL17: =IFERROR((($CT17/1.1)+(CH17+CI17)-(CG17-(CG17*CF$2)))/($CT17/1.1),"") | CM17: {=IFERROR(_xlfn._xlws.FILTER(ST[SOH],(ST[Code]=$C17) * (ST[Customer Name]=CF$3),"" ),"")} | CN17: {=IFERROR( _xlfn.LET( _xlpm.result, INDEX(_xlfn._xlws.FILTER(ST[6wk avg], (ST[Code]=$C17)*(ST[Customer Name]=CF$3), ""), 1), IF(_xlpm.result=0, "", _xlpm.result) ), "")} | CO17: =IFERROR(IF(CEILING(CN17 + (CN17 * $CO$2), 1) = 0, "", CEILING(CN17 + (CN17 * $CO$2), 1))*$B$3, "") | CP17: =IFERROR((CO17*CH17),"") | CQ17: =IFERROR((CO17*CI17),"") | CS17: =IFERROR(_xlfn.XLOOKUP(C17,Query[Code],Query[Base (RRP Inc)]),"") | CT17: =IFERROR(CS17-(CS17*CU17),"") | CU17: =IF(C17="", "",CU16) | CV17: =IFERROR((CS17-CT17),"")
A18: =IF(C18="","",A17) | B18: =IF(C18="","",B17) | D18: =IF(C18="", "",_xlfn.XLOOKUP(C18,'Master Price Level'!C:C,'Master Price Level'!D:D)) | F18: {=IFERROR(_xlfn._xlws.FILTER(ST[Customer Code],(ST[Code]=$C18) * (ST[Customer Name]=F$3),"" ),"")} | G18: {=IFERROR(_xlfn.XLOOKUP($C18,Query[Code], _xlfn.XLOOKUP('Promo Form'!F$3,Query[[#Headers],[Code]:[Bing Lee]],Query[[Code]:[Bing Lee]])),"")} | H18: =IFERROR(((G18*(1-F$2))*$CU18)*F$61,"") | I18: =IFERROR(((G18*(1-F$2))*$CU18)*F$60,"") | J18: =IFERROR(IF(H18+I18=0,"",H18+I18),"") | K18: =IFERROR((($CS18/1.1)-(G18-(G18*F$2)))/($CS18/1.1),"") | L18: =IFERROR((($CT18/1.1)+(H18+I18)-(G18-(G18*F$2)))/($CT18/1.1),"") | M18: {=IFERROR(_xlfn._xlws.FILTER(ST[SOH],(ST[Code]=$C18) * (ST[Customer Name]=F$3),"" ),"")} | N18: {=IFERROR( _xlfn.LET( _xlpm.result, INDEX(_xlfn._xlws.FILTER(ST[6wk avg], (ST[Code]=$C18)*(ST[Customer Name]=F$3), ""), 1), IF(_xlpm.result=0, "", _xlpm.result) ), "")} | O18: =IFERROR(IF(CEILING(N18 + (N18 * $O$2), 1) = 0, "", CEILING(N18 + (N18 * $O$2), 1))*$B$3, "") | P18: =IFERROR((O18*H18),"") | Q18: =IFERROR((O18*I18),"") | S18: {=IFERROR(_xlfn._xlws.FILTER(ST[Customer Code],(ST[Code]=$C18) * (ST[Customer Name]=S$3),"" ),"")} | T18: {=IFERROR(_xlfn.XLOOKUP($C18,Query[Code], _xlfn.XLOOKUP('Promo Form'!S$3,Query[[#Headers],[Code]:[Bing Lee]],Query[[Code]:[Bing Lee]])),"")} | U18: =IFERROR(((T18*(1-S$2))*$CU18)*S$61,"") | V18: =IFERROR(((T18*(1-S$2))*$CU18)*S$60,"") | W18: =IFERROR(IF(U18+V18=0,"",U18+V18),"") | X18: =IFERROR((($CS18/1.1)-(T18-(T18*S$2)))/($CS18/1.1),"") | Y18: =IFERROR((($CT18/1.1)+(U18+V18)-(T18-(T18*S$2)))/($CT18/1.1),"") | Z18: {=IFERROR(_xlfn._xlws.FILTER(ST[SOH],(ST[Code]=$C18) * (ST[Customer Name]=S$3),"" ),"")} | AA18: {=IFERROR( _xlfn.LET( _xlpm.result, INDEX(_xlfn._xlws.FILTER(ST[6wk avg], (ST[Code]=$C18)*(ST[Customer Name]=S$3), ""), 1), IF(_xlpm.result=0, "", _xlpm.result) ), "")} | AB18: =IFERROR(IF(CEILING(AA18 + (AA18 * $AB$2), 1) = 0, "", CEILING(AA18 + (AA18 * $AB$2), 1))*$B$3, "") | AC18: =IFERROR((AB18*U18),"") | AD18: =IFERROR((AB18*V18),"") | AF18: {=IFERROR(_xlfn._xlws.FILTER(ST[Customer Code],(ST[Code]=$C18) * (ST[Customer Name]=AF$3),"" ),"")} | AG18: {=IFERROR(_xlfn.XLOOKUP($C18,Query[Code], _xlfn.XLOOKUP('Promo Form'!AF$3,Query[[#Headers],[Code]:[Bing Lee]],Query[[Code]:[Bing Lee]])),"")} | AH18: =IFERROR(((AG18*(1-AF$2))*$CU18)*AF$61,"") | AI18: =IFERROR(((AG18*(1-AF$2))*$CU18)*AF$60,"") | AJ18: =IFERROR(IF(AH18+AI18=0,"",AH18+AI18),"") | AK18: =IFERROR((($CS18/1.1)-(AG18-(AG18*AF$2)))/($CS18/1.1),"") | AL18: =IFERROR((($CT18/1.1)+(AH18+AI18)-(AG18-(AG18*AF$2)))/($CT18/1.1),"") | AM18: {=IFERROR(_xlfn._xlws.FILTER(ST[SOH],(ST[Code]=$C18) * (ST[Customer Name]=AF$3),"" ),"")} | AN18: {=IFERROR( _xlfn.LET( _xlpm.result, INDEX(_xlfn._xlws.FILTER(ST[6wk avg], (ST[Code]=$C18)*(ST[Customer Name]=AF$3), ""), 1), IF(_xlpm.result=0, "", _xlpm.result) ), "")} | AO18: =IFERROR(IF(CEILING(AN18 + (AN18 * $AO$2), 1) = 0, "", CEILING(AN18 + (AN18 * $AO$2), 1))*$B$3, "") | AP18: =IFERROR((AO18*AH18),"") | AQ18: =IFERROR((AO18*AI18),"") | AS18: {=IFERROR(_xlfn._xlws.FILTER(ST[Customer Code],(ST[Code]=$C18) * (ST[Customer Name]=AS$3),"" ),"")} | AT18: {=IFERROR(_xlfn.XLOOKUP($C18,Query[Code], _xlfn.XLOOKUP('Promo Form'!AS$3,Query[[#Headers],[Code]:[Bing Lee]],Query[[Code]:[Bing Lee]])),"")} | AU18: =IFERROR(((AT18*(1-AS$2))*$CU18)*AS$61,"") | AV18: =IFERROR(((AT18*(1-AS$2))*$CU18)*AS$60,"") | AW18: =IFERROR(IF(AU18+AV18=0,"",AU18+AV18),"") | AX18: =IFERROR((($CS18/1.1)-(AT18-(AT18*AS$2)))/($CS18/1.1),"") | AY18: =IFERROR((($CT18/1.1)+(AU18+AV18)-(AT18-(AT18*AS$2)))/($CT18/1.1),"") | AZ18: {=IFERROR(_xlfn._xlws.FILTER(ST[SOH],(ST[Code]=$C18) * (ST[Customer Name]=AS$3),"" ),"")} | BA18: {=IFERROR( _xlfn.LET( _xlpm.result, INDEX(_xlfn._xlws.FILTER(ST[6wk avg], (ST[Code]=$C18)*(ST[Customer Name]=AS$3), ""), 1), IF(_xlpm.result=0, "", _xlpm.result) ), "")} | BB18: =IFERROR(IF(CEILING(BA18 + (BA18 * $BB$2), 1) = 0, "", CEILING(BA18 + (BA18 * $BB$2), 1))*$B$3, "") | BC18: =IFERROR((BB18*AU18),"") | BD18: =IFERROR((BB18*AV18),"") | BF18: {=IFERROR(_xlfn._xlws.FILTER(ST[Customer Code],(ST[Code]=$C18) * (ST[Customer Name]=BF$3),"" ),"")} | BG18: {=IFERROR(_xlfn.XLOOKUP($C18,Query[Code], _xlfn.XLOOKUP('Promo Form'!BF$3,Query[[#Headers],[Code]:[Bing Lee]],Query[[Code]:[Bing Lee]])),"")} | BH18: =IFERROR(((BG18*(1-BF$2))*$CU18)*BF$61,"") | BI18: =IFERROR(((BG18*(1-BF$2))*$CU18)*BF$60,"") | BJ18: =IFERROR(IF(BH18+BI18=0,"",BH18+BI18),"") | BK18: =IFERROR((($CS18/1.1)-(BG18-(BG18*BF$2)))/($CS18/1.1),"") | BL18: =IFERROR((($CT18/1.1)+(BH18+BI18)-(BG18-(BG18*BF$2)))/($CT18/1.1),"") | BM18: {=IFERROR(_xlfn._xlws.FILTER(ST[SOH],(ST[Code]=$C18) * (ST[Customer Name]=BF$3),"" ),"")} | BN18: {=IFERROR( _xlfn.LET( _xlpm.result, INDEX(_xlfn._xlws.FILTER(ST[6wk avg], (ST[Code]=$C18)*(ST[Customer Name]=BF$3), ""), 1), IF(_xlpm.result=0, "", _xlpm.result) ), "")} | BO18: =IFERROR(IF(CEILING(BN18 + (BN18 * $BO$2), 1) = 0, "", CEILING(BN18 + (BN18 * $BO$2), 1))*$B$3, "") | BP18: =IFERROR((BO18*BH18),"") | BQ18: =IFERROR((BO18*BI18),"") | BS18: {=IFERROR(_xlfn._xlws.FILTER(ST[Customer Code],(ST[Code]=$C18) * (ST[Customer Name]=BS$3),"" ),"")} | BT18: {=IFERROR(_xlfn.XLOOKUP($C18,Query[Code], _xlfn.XLOOKUP('Promo Form'!BS$3,Query[[#Headers],[Code]:[Bing Lee]],Query[[Code]:[Bing Lee]])),"")} | BU18: =IFERROR(((BT18*(1-BS$2))*$CU18)*BS$61,"") | BV18: =IFERROR(((BT18*(1-BS$2))*$CU18)*BS$60,"") | BW18: =IFERROR(IF(BU18+BV18=0,"",BU18+BV18),"") | BX18: =IFERROR((($CS18/1.1)-(BT18-(BT18*BS$2)))/($CS18/1.1),"") | BY18: =IFERROR((($CT18/1.1)+(BU18+BV18)-(BT18-(BT18*BS$2)))/($CT18/1.1),"") | BZ18: {=IFERROR(_xlfn._xlws.FILTER(ST[SOH],(ST[Code]=$C18) * (ST[Customer Name]=BS$3),"" ),"")} | CA18: {=IFERROR( _xlfn.LET( _xlpm.result, INDEX(_xlfn._xlws.FILTER(ST[6wk avg], (ST[Code]=$C18)*(ST[Customer Name]=BS$3), ""), 1), IF(_xlpm.result=0, "", _xlpm.result) ), "")} | CB18: =IFERROR(IF(CEILING(CA18 + (CA18 * $CB$2), 1) = 0, "", CEILING(CA18 + (CA18 * $CB$2), 1))*$B$3, "") | CC18: =IFERROR((CB18*BU18),"") | CD18: =IFERROR((CB18*BV18),"") | CF18: {=IFERROR(_xlfn._xlws.FILTER(ST[Customer Code],(ST[Code]=$C18) * (ST[Customer Name]=CF$3),"" ),"")} | CG18: {=IFERROR(_xlfn.XLOOKUP($C18,Query[Code], _xlfn.XLOOKUP('Promo Form'!CF$3,Query[[#Headers],[Code]:[Bing Lee]],Query[[Code]:[Bing Lee]])),"")} | CH18: =IFERROR(((CG18*(1-CF$2))*$CU18)*CF$61,"") | CI18: =IFERROR(((CG18*(1-CF$2))*$CU18)*CF$60,"") | CJ18: =IFERROR(IF(CH18+CI18=0,"",CH18+CI18),"") | CK18: =IFERROR((($CS18/1.1)-(CG18-(CG18*CF$2)))/($CS18/1.1),"") | CL18: =IFERROR((($CT18/1.1)+(CH18+CI18)-(CG18-(CG18*CF$2)))/($CT18/1.1),"") | CM18: {=IFERROR(_xlfn._xlws.FILTER(ST[SOH],(ST[Code]=$C18) * (ST[Customer Name]=CF$3),"" ),"")} | CN18: {=IFERROR( _xlfn.LET( _xlpm.result, INDEX(_xlfn._xlws.FILTER(ST[6wk avg], (ST[Code]=$C18)*(ST[Customer Name]=CF$3), ""), 1), IF(_xlpm.result=0, "", _xlpm.result) ), "")} | CO18: =IFERROR(IF(CEILING(CN18 + (CN18 * $CO$2), 1) = 0, "", CEILING(CN18 + (CN18 * $CO$2), 1))*$B$3, "") | CP18: =IFERROR((CO18*CH18),"") | CQ18: =IFERROR((CO18*CI18),"") | CS18: =IFERROR(_xlfn.XLOOKUP(C18,Query[Code],Query[Base (RRP Inc)]),"") | CT18: =IFERROR(CS18-(CS18*CU18),"") | CU18: =IF(C18="", "",CU17) | CV18: =IFERROR((CS18-CT18),"")
... A49: =IF(C49="","",A48) | B49: =IF(C49="","",B48) | D49: =IF(C49="", "",_xlfn.XLOOKUP(C49,'Master Price Level'!C:C,'Master Price Level'!D:D)) | F49: {=IFERROR(_xlfn._xlws.FILTER(ST[Customer Code],(ST[Code]=$C49) * (ST[Customer Name]=F$3),"" ),"")} | G49: {=IFERROR(_xlfn.XLOOKUP($C49,Query[Code], _xlfn.XLOOKUP('Promo Form'!F$3,Query[[#Headers],[Code]:[Bing Lee]],Query[[Code]:[Bing Lee]])),"")} | H49: =IFERROR(((G49*(1-F$2))*$CU49)*F$61,"") | I49: =IFERROR(((G49*(1-F$2))*$CU49)*F$60,"") | J49: =IFERROR(IF(H49+I49=0,"",H49+I49),"") | K49: =IFERROR((($CS49/1.1)-(G49-(G49*F$2)))/($CS49/1.1),"") | L49: =IFERROR((($CT49/1.1)+(H49+I49)-(G49-(G49*F$2)))/($CT49/1.1),"") | M49: {=IFERROR(_xlfn._xlws.FILTER(ST[SOH],(ST[Code]=$C49) * (ST[Customer Name]=F$3),"" ),"")} | N49: {=IFERROR( _xlfn.LET( _xlpm.result, INDEX(_xlfn._xlws.FILTER(ST[6wk avg], (ST[Code]=$C49)*(ST[Customer Name]=F$3), ""), 1), IF(_xlpm.result=0, "", _xlpm.result) ), "")} | O49: =IFERROR(IF(CEILING(N49 + (N49 * $O$2), 1) = 0, "", CEILING(N49 + (N49 * $O$2), 1))*$B$3, "") | P49: =IFERROR((O49*H49),"") | Q49: =IFERROR((O49*I49),"") | S49: {=IFERROR(_xlfn._xlws.FILTER(ST[Customer Code],(ST[Code]=$C49) * (ST[Customer Name]=S$3),"" ),"")} | T49: {=IFERROR(_xlfn.XLOOKUP($C49,Query[Code], _xlfn.XLOOKUP('Promo Form'!S$3,Query[[#Headers],[Code]:[Bing Lee]],Query[[Code]:[Bing Lee]])),"")} | U49: =IFERROR(((T49*(1-S$2))*$CU49)*S$61,"") | V49: =IFERROR(((T49*(1-S$2))*$CU49)*S$60,"") | W49: =IFERROR(IF(U49+V49=0,"",U49+V49),"") | X49: =IFERROR((($CS49/1.1)-(T49-(T49*S$2)))/($CS49/1.1),"") | Y49: =IFERROR((($CT49/1.1)+(U49+V49)-(T49-(T49*S$2)))/($CT49/1.1),"") | Z49: {=IFERROR(_xlfn._xlws.FILTER(ST[SOH],(ST[Code]=$C49) * (ST[Customer Name]=S$3),"" ),"")} | AA49: {=IFERROR( _xlfn.LET( _xlpm.result, INDEX(_xlfn._xlws.FILTER(ST[6wk avg], (ST[Code]=$C49)*(ST[Customer Name]=S$3), ""), 1), IF(_xlpm.result=0, "", _xlpm.result) ), "")} | AB49: =IFERROR(IF(CEILING(AA49 + (AA49 * $AB$2), 1) = 0, "", CEILING(AA49 + (AA49 * $AB$2), 1))*$B$3, "") | AC49: =IFERROR((AB49*U49),"") | AD49: =IFERROR((AB49*V49),"") | AF49: {=IFERROR(_xlfn._xlws.FILTER(ST[Customer Code],(ST[Code]=$C49) * (ST[Customer Name]=AF$3),"" ),"")} | AG49: {=IFERROR(_xlfn.XLOOKUP($C49,Query[Code], _xlfn.XLOOKUP('Promo Form'!AF$3,Query[[#Headers],[Code]:[Bing Lee]],Query[[Code]:[Bing Lee]])),"")} | AH49: =IFERROR(((AG49*(1-AF$2))*$CU49)*AF$61,"") | AI49: =IFERROR(((AG49*(1-AF$2))*$CU49)*AF$60,"") | AJ49: =IFERROR(IF(AH49+AI49=0,"",AH49+AI49),"") | AK49: =IFERROR((($CS49/1.1)-(AG49-(AG49*AF$2)))/($CS49/1.1),"") | AL49: =IFERROR((($CT49/1.1)+(AH49+AI49)-(AG49-(AG49*AF$2)))/($CT49/1.1),"") | AM49: {=IFERROR(_xlfn._xlws.FILTER(ST[SOH],(ST[Code]=$C49) * (ST[Customer Name]=AF$3),"" ),"")} | AN49: {=IFERROR( _xlfn.LET( _xlpm.result, INDEX(_xlfn._xlws.FILTER(ST[6wk avg], (ST[Code]=$C49)*(ST[Customer Name]=AF$3), ""), 1), IF(_xlpm.result=0, "", _xlpm.result) ), "")} | AO49: =IFERROR(IF(CEILING(AN49 + (AN49 * $AO$2), 1) = 0, "", CEILING(AN49 + (AN49 * $AO$2), 1))*$B$3, "") | AP49: =IFERROR((AO49*AH49),"") | AQ49: =IFERROR((AO49*AI49),"") | AS49: {=IFERROR(_xlfn._xlws.FILTER(ST[Customer Code],(ST[Code]=$C49) * (ST[Customer Name]=AS$3),"" ),"")} | AT49: {=IFERROR(_xlfn.XLOOKUP($C49,Query[Code], _xlfn.XLOOKUP('Promo Form'!AS$3,Query[[#Headers],[Code]:[Bing Lee]],Query[[Code]:[Bing Lee]])),"")} | AU49: =IFERROR(((AT49*(1-AS$2))*$CU49)*AS$61,"") | AV49: =IFERROR(((AT49*(1-AS$2))*$CU49)*AS$60,"") | AW49: =IFERROR(IF(AU49+AV49=0,"",AU49+AV49),"") | AX49: =IFERROR((($CS49/1.1)-(AT49-(AT49*AS$2)))/($CS49/1.1),"") | AY49: =IFERROR((($CT49/1.1)+(AU49+AV49)-(AT49-(AT49*AS$2)))/($CT49/1.1),"") | AZ49: {=IFERROR(_xlfn._xlws.FILTER(ST[SOH],(ST[Code]=$C49) * (ST[Customer Name]=AS$3),"" ),"")} | BA49: {=IFERROR( _xlfn.LET( _xlpm.result, INDEX(_xlfn._xlws.FILTER(ST[6wk avg], (ST[Code]=$C49)*(ST[Customer Name]=AS$3), ""), 1), IF(_xlpm.result=0, "", _xlpm.result) ), "")} | BB49: =IFERROR(IF(CEILING(BA49 + (BA49 * $BB$2), 1) = 0, "", CEILING(BA49 + (BA49 * $BB$2), 1))*$B$3, "") | BC49: =IFERROR((BB49*AU49),"") | BD49: =IFERROR((BB49*AV49),"") | BF49: {=IFERROR(_xlfn._xlws.FILTER(ST[Customer Code],(ST[Code]=$C49) * (ST[Customer Name]=BF$3),"" ),"")} | BG49: {=IFERROR(_xlfn.XLOOKUP($C49,Query[Code], _xlfn.XLOOKUP('Promo Form'!BF$3,Query[[#Headers],[Code]:[Bing Lee]],Query[[Code]:[Bing Lee]])),"")} | BH49: =IFERROR(((BG49*(1-BF$2))*$CU49)*BF$61,"") | BI49: =IFERROR(((BG49*(1-BF$2))*$CU49)*BF$60,"") | BJ49: =IFERROR(IF(BH49+BI49=0,"",BH49+BI49),"") | BK49: =IFERROR((($CS49/1.1)-(BG49-(BG49*BF$2)))/($CS49/1.1),"") | BL49: =IFERROR((($CT49/1.1)+(BH49+BI49)-(BG49-(BG49*BF$2)))/($CT49/1.1),"") | BM49: {=IFERROR(_xlfn._xlws.FILTER(ST[SOH],(ST[Code]=$C49) * (ST[Customer Name]=BF$3),"" ),"")} | BN49: {=IFERROR( _xlfn.LET( _xlpm.result, INDEX(_xlfn._xlws.FILTER(ST[6wk avg], (ST[Code]=$C49)*(ST[Customer Name]=BF$3), ""), 1), IF(_xlpm.result=0, "", _xlpm.result) ), "")} | BO49: =IFERROR(IF(CEILING(BN49 + (BN49 * $BO$2), 1) = 0, "", CEILING(BN49 + (BN49 * $BO$2), 1))*$B$3, "") | BP49: =IFERROR((BO49*BH49),"") | BQ49: =IFERROR((BO49*BI49),"") | BS49: {=IFERROR(_xlfn._xlws.FILTER(ST[Customer Code],(ST[Code]=$C49) * (ST[Customer Name]=BS$3),"" ),"")} | BT49: {=IFERROR(_xlfn.XLOOKUP($C49,Query[Code], _xlfn.XLOOKUP('Promo Form'!BS$3,Query[[#Headers],[Code]:[Bing Lee]],Query[[Code]:[Bing Lee]])),"")} | BU49: =IFERROR(((BT49*(1-BS$2))*$CU49)*BS$61,"") | BV49: =IFERROR(((BT49*(1-BS$2))*$CU49)*BS$60,"") | BW49: =IFERROR(IF(BU49+BV49=0,"",BU49+BV49),"") | BX49: =IFERROR((($CS49/1.1)-(BT49-(BT49*BS$2)))/($CS49/1.1),"") | BY49: =IFERROR((($CT49/1.1)+(BU49+BV49)-(BT49-(BT49*BS$2)))/($CT49/1.1),"") | BZ49: {=IFERROR(_xlfn._xlws.FILTER(ST[SOH],(ST[Code]=$C49) * (ST[Customer Name]=BS$3),"" ),"")} | CA49: {=IFERROR( _xlfn.LET( _xlpm.result, INDEX(_xlfn._xlws.FILTER(ST[6wk avg], (ST[Code]=$C49)*(ST[Customer Name]=BS$3), ""), 1), IF(_xlpm.result=0, "", _xlpm.result) ), "")} | CB49: =IFERROR(IF(CEILING(CA49 + (CA49 * $CB$2), 1) = 0, "", CEILING(CA49 + (CA49 * $CB$2), 1))*$B$3, "") | CC49: =IFERROR((CB49*BU49),"") | CD49: =IFERROR((CB49*BV49),"") | CF49: {=IFERROR(_xlfn._xlws.FILTER(ST[Customer Code],(ST[Code]=$C49) * (ST[Customer Name]=CF$3),"" ),"")} | CG49: {=IFERROR(_xlfn.XLOOKUP($C49,Query[Code], _xlfn.XLOOKUP('Promo Form'!CF$3,Query[[#Headers],[Code]:[Bing Lee]],Query[[Code]:[Bing Lee]])),"")} | CH49: =IFERROR(((CG49*(1-CF$2))*$CU49)*CF$61,"") | CI49: =IFERROR(((CG49*(1-CF$2))*$CU49)*CF$60,"") | CJ49: =IFERROR(IF(CH49+CI49=0,"",CH49+CI49),"") | CK49: =IFERROR((($CS49/1.1)-(CG49-(CG49*CF$2)))/($CS49/1.1),"") | CL49: =IFERROR((($CT49/1.1)+(CH49+CI49)-(CG49-(CG49*CF$2)))/($CT49/1.1),"") | CM49: {=IFERROR(_xlfn._xlws.FILTER(ST[SOH],(ST[Code]=$C49) * (ST[Customer Name]=CF$3),"" ),"")} | CN49: {=IFERROR( _xlfn.LET( _xlpm.result, INDEX(_xlfn._xlws.FILTER(ST[6wk avg], (ST[Code]=$C49)*(ST[Customer Name]=CF$3), ""), 1), IF(_xlpm.result=0, "", _xlpm.result) ), "")} | CO49: =IFERROR(IF(CEILING(CN49 + (CN49 * $CO$2), 1) = 0, "", CEILING(CN49 + (CN49 * $CO$2), 1))*$B$3, "") | CP49: =IFERROR((CO49*CH49),"") | CQ49: =IFERROR((CO49*CI49),"") | CS49: =IFERROR(_xlfn.XLOOKUP(C49,Query[Code],Query[Base (RRP Inc)]),"") | CT49: =IFERROR(CS49-(CS49*CU49),"") | CU49: =IF(C49="", "",CU48) | CV49: =IFERROR((CS49-CT49),"")
A50: Last Day for Customer claims to be submitted | D50: =B5+14 -> 45836 | L50: =IFERROR((($FD50/1.1)+(H50+I50)-(G50-(G50*F$2)))/($FD50/1.1),"") | O50: =IFERROR((($FD50/1.1)+(I50+J50)-(H50-(H50*G$2)))/($FD50/1.1),"") | Y50: =IFERROR((($FD50/1.1)+(U50+V50)-(T50-(T50*S$2)))/($FD50/1.1),"") | AB50: =IFERROR((($FD50/1.1)+(V50+W50)-(U50-(U50*T$2)))/($FD50/1.1),"") | AL50: =IFERROR((($FD50/1.1)+(AH50+AI50)-(AG50-(AG50*AF$2)))/($FD50/1.1),"") | AO50: =IFERROR((($FD50/1.1)+(AI50+AJ50)-(AH50-(AH50*AG$2)))/($FD50/1.1),"") | AY50: =IFERROR((($FD50/1.1)+(AU50+AV50)-(AT50-(AT50*AS$2)))/($FD50/1.1),"") | BB50: =IFERROR((($FD50/1.1)+(AV50+AW50)-(AU50-(AU50*AT$2)))/($FD50/1.1),"") | BL50: =IFERROR((($FD50/1.1)+(BH50+BI50)-(BG50-(BG50*BF$2)))/($FD50/1.1),"") | BO50: =IFERROR((($FD50/1.1)+(BI50+BJ50)-(BH50-(BH50*BG$2)))/($FD50/1.1),"") | BY50: =IFERROR((($FD50/1.1)+(BU50+BV50)-(BT50-(BT50*BS$2)))/($FD50/1.1),"") | CB50: =IFERROR((($FD50/1.1)+(BV50+BW50)-(BU50-(BU50*BT$2)))/($FD50/1.1),"") | CL50: =IFERROR((($FD50/1.1)+(CH50+CI50)-(CG50-(CG50*CF$2)))/($FD50/1.1),"") | CO50: =IFERROR((($FD50/1.1)+(CI50+CJ50)-(CH50-(CH50*CG$2)))/($FD50/1.1),"")
F51: TRUE | O51: Total | P51: Supplier | Q51: Macgear | S51: FALSE | AB51: Total | AC51: Supplier | AD51: Macgear | AF51: FALSE | AO51: Total | AP51: Supplier | AQ51: Macgear | AS51: FALSE | BB51: Total | BC51: Supplier | BD51: Macgear | BF51: FALSE | BO51: Total | BP51: Supplier | BQ51: Macgear | BS51: FALSE | CB51: Total | CC51: Supplier | CD51: Macgear | CF51: FALSE | CO51: Total | CP51: Supplier | CQ51: Macgear
A52: TOTAL Macgear Claim AUD Ex | D52: =SUM(Q52,AD52,AQ52,BD52,BQ52,CD52,CQ52) -> 0 | F52: =IF(F51,"ACTIVE","INACTIVE") -> ACTIVE | P52: =SUM(P5:P49) -> 0 | Q52: =SUM(Q5:Q49) -> 0 | S52: =IF(S51,"ACTIVE","INACTIVE") -> INACTIVE | AC52: =SUM(AC5:AC49) -> 0 | AD52: =SUM(AD5:AD49) -> 0 | AF52: =IF(AF51,"ACTIVE","INACTIVE") -> INACTIVE | AP52: =SUM(AP5:AP49) -> 0 | AQ52: =SUM(AQ5:AQ49) -> 0 | AS52: =IF(AS51,"ACTIVE","INACTIVE") -> INACTIVE | BC52: =SUM(BC5:BC49) -> 0 | BD52: =SUM(BD5:BD49) -> 0 | BF52: =IF(BF51,"ACTIVE","INACTIVE") -> INACTIVE | BP52: =SUM(BP5:BP49) -> 0 | BQ52: =SUM(BQ5:BQ49) -> 0 | BS52: =IF(BS51,"ACTIVE","INACTIVE") -> INACTIVE | CC52: =SUM(CC5:CC49) -> 0 | CD52: =SUM(CD5:CD49) -> 0 | CF52: =IF(CF51,"ACTIVE","INACTIVE") -> INACTIVE | CP52: =SUM(CP5:CP49) -> 0 | CQ52: =SUM(CQ5:CQ49) -> 0
A53: TOTAL Brand Claim AUD Ex | D53: =SUM(P52,AC52,AP52,BC52,BP52,CC52,CP52) -> 0
A54: TOTAL CLAIM to USD ex | D54: =D53*D55 -> 0
A55: Vendor Claim | B55: Not Sent | C55: AUD to USD Rate | D55: 0.65
A56: Claim Date | C56: #VALUE! | D56: {=_FV(C56,"Price")} -> 0.7042 | E56: {=_FV(C56,"Exchange")} -> #VALUE!
A57: Vendor Claim $ | E57: {=_FV(C57,"Change (%)",TRUE)} -> #VALUE!
A58: Claims and Funding | F58: Ratio | G58: Company | S58: Ratio | T58: Company | AF58: Ratio | AG58: Company | AS58: Ratio | AT58: Company | BF58: Ratio | BG58: Company | BS58: Ratio | BT58: Company | CF58: Ratio | CG58: Company
A59: This shows the split of funding between the Retailer, Macgear and Brand | D59: Retailer | F59: 0.333 | G59: Retailer | S59: 0.333 | T59: Retailer | AF59: 0.333 | AG59: Retailer | AS59: 0.333 | AT59: Retailer | BF59: 0.333 | BG59: Retailer | BS59: 0.333 | BT59: Retailer | CF59: 0.333 | CG59: Retailer
D60: MacGear | F60: 0.333 | G60: MacGear | S60: 0.333 | T60: MacGear | AF60: 0.333 | AG60: MacGear | AS60: 0.333 | AT60: MacGear | BF60: 0.333 | BG60: MacGear | BS60: 0.333 | BT60: MacGear | CF60: 0.333 | CG60: MacGear
D61: Brand | F61: 0.333 | G61: Supplier | S61: 0.333 | T61: Supplier | AF61: 0.333 | AG61: Supplier | AS61: 0.333 | AT61: Supplier | BF61: 0.333 | BG61: Supplier | BS61: 0.333 | BT61: Supplier | CF61: 0.333 | CG61: Supplier
F62: =SUM(F59:F61) -> 0.999 | G62: Total (should = 1) | S62: =SUM(S59:S61) -> 0.999 | T62: Total (should = 1) | AF62: =SUM(AF59:AF61) -> 0.999 | AG62: Total (should = 1) | AS62: =SUM(AS59:AS61) -> 0.999 | AT62: Total (should = 1) | BF62: =SUM(BF59:BF61) -> 0.999 | BG62: Total (should = 1) | BS62: =SUM(BS59:BS61) -> 0.999 | BT62: Total (should = 1) | CF62: =SUM(CF59:CF61) -> 0.999 | CG62: Total (should = 1)
H63: Notes: | U63: Notes: | AH63: Notes: | AU63: Notes: | BH63: Notes: | BU63: Notes: | CH63: Notes:
F64: Claim Details | S64: Claim Details | AF64: Claim Details | AS64: Claim Details | BF64: Claim Details | BS64: Claim Details | CF64: Claim Details
A65: Date of claim | D65: Date | G65: Date | T65: Date | AG65: Date | AT65: Date | BG65: Date | BT65: Date | CG65: Date
A66: Amount Claimed by Customer | D66: Customer Claim Amount | G66: Cust Claim $ | T66: Cust Claim $ | AG66: Cust Claim $ | AT66: Cust Claim $ | BG66: Cust Claim $ | BT66: Cust Claim $ | CG66: Cust Claim $
A67: Check Value | D67: Check Value | F67: =P52+Q52 -> 0 | G67: Check Value | S67: =AC52+AD52 -> 0 | T67: Check Value | AF67: =AP52+AQ52 -> 0 | AG67: Check Value | AS67: =BC52+BD52 -> 0 | AT67: Check Value | BF67: =BP52+BQ52 -> 0 | BG67: Check Value | BS67: =CC52+CD52 -> 0 | BT67: Check Value | CF67: =CP52+CQ52 -> 0 | CG67: Check Value
A68: Status of customers claim | D68: Status | F68: Not Received | G68: Status | S68: Not Received | T68: Status | AF68: Not Received | AG68: Status | AS68: Not Received | AT68: Status | BF68: Not Received | BG68: Status | BS68: Not Received | BT68: Status | CF68: Not Received | CG68: Status

Sheet Sales Copy
A1: AUSTRALIAN Claim Number | C1: ='Promo Form'!C1 -> 0 | D1: Name of Promotion
A2: Brand | C2: ='Promo Form'!C2 -> 0 | D2: ='Promo Form'!D2 -> 0
A3: Promo Date(s) | C3: Code | D3: Product Description | G3: ='Promo Form'!F3 -> AU - Officeworks | O3: ='Promo Form'!S3 -> JB HIFI | W3: ='Promo Form'!AF3 -> AU - Amazon | AE3: ='Promo Form'!AS3 -> AU - The Good Guys | AM3: ='Promo Form'!BF3 -> Bing Lee | AU3: ='Promo Form'!BS3 -> Harvey Norman | BC3: ='Promo Form'!CF3 -> Harvey Norman
A4: From | B4: To | F4: Customer Code | G4: Retailer Buy ex | H4: Total Support | I4: End to End Standard Margin | J4: End to End Promo Margin | K4: 6wk Avg | L4: Expected Sales / Actual Sales | N4: Customer Code | O4: Retailer Buy ex | P4: Total Support | Q4: End to End Standard Margin | R4: End to End Promo Margin | S4: 6wk Avg | T4: Expected Sales / Actual Sales | V4: Customer Code | W4: Retailer Buy ex | X4: Total Support | Y4: End to End Standard Margin | Z4: End to End Promo Margin | AA4: 6wk Avg | AB4: Expected Sales / Actual Sales | AD4: Customer Code | AE4: Retailer Buy ex | AF4: Total Support | AG4: End to End Standard Margin | AH4: End to End Promo Margin | AI4: 6wk Avg | AJ4: Expected Sales / Actual Sales | AL4: Customer Code | AM4: Retailer Buy ex | AN4: Total Support | AO4: End to End Standard Margin | AP4: End to End Promo Margin | AQ4: 6wk Avg | AR4: Expected Sales / Actual Sales | AT4: Customer Code | AU4: Retailer Buy ex | AV4: Total Support | AW4: End to End Standard Margin | AX4: End to End Promo Margin | AY4: 6wk Avg | AZ4: Expected Sales / Actual Sales | BB4: Customer Code | BC4: Retailer Buy ex | BD4: Total Support | BE4: End to End Standard Margin | BF4: End to End Promo Margin | BG4: 6wk Avg | BH4: Expected Sales / Actual Sales | BJ4: RRP Inc | BK4: Recommended Sale Inc | BL4: Recommended % Off | BM4: Recommended $ Off | BN4: Comments
A5: ='Promo Form'!A5 -> 45809 | B5: ='Promo Form'!B5 -> 45822 | C5: ='Promo Form'!C5 -> A1902T11 | D5: ='Promo Form'!D5 -> ANKER 100W Charging Base for ANKER Prime Power Bank | F5: ='Promo Form'!F5 | G5: ='Promo Form'!G5 -> 84.98 | H5: ='Promo Form'!J5 -> 9.7912256 | I5: ='Promo Form'!K5 -> 0.52422201 | J5: ='Promo Form'!L5 -> 0.48449454 | K5: ='Promo Form'!N5 | L5: ='Promo Form'!O5 | N5: ='Promo Form'!S5 | O5: ='Promo Form'!T5 -> 0 | P5: ='Promo Form'!W5 | Q5: ='Promo Form'!X5 -> 1 | R5: ='Promo Form'!Y5 -> 1 | S5: ='Promo Form'!AA5 | T5: ='Promo Form'!AB5 | V5: ='Promo Form'!AF5 | W5: ='Promo Form'!AG5 -> 0 | X5: ='Promo Form'!AJ5 | Y5: ='Promo Form'!AK5 -> 1 | Z5: ='Promo Form'!AL5 -> 1 | AA5: ='Promo Form'!AN5 | AB5: ='Promo Form'!AO5 | AD5: ='Promo Form'!AS5 | AE5: ='Promo Form'!AT5 -> 0 | AF5: ='Promo Form'!AW5 | AG5: ='Promo Form'!AX5 -> 1 | AH5: ='Promo Form'!AY5 -> 1 | AI5: ='Promo Form'!BA5 | AJ5: ='Promo Form'!BB5 | AL5: ='Promo Form'!BF5 | AM5: ='Promo Form'!BG5 -> 0 | AN5: ='Promo Form'!BJ5 | AO5: ='Promo Form'!BK5 -> 1 | AP5: ='Promo Form'!BL5 -> 1 | AQ5: ='Promo Form'!BN5 | AR5: ='Promo Form'!BO5 | AT5: ='Promo Form'!BS5 | AU5: ='Promo Form'!BT5 -> 92.7 | AV5: ='Promo Form'!BW5 -> 10.248541 | AW5: ='Promo Form'!BX5 -> 0.502 | AX5: ='Promo Form'!BY5 -> 0.460417 | AY5: ='Promo Form'!CA5 | AZ5: ='Promo Form'!CB5 | BB5: ='Promo Form'!CF5 | BC5: ='Promo Form'!CG5 -> 92.7 | BD5: ='Promo Form'!CJ5 -> 10.248541 | BE5: ='Promo Form'!CK5 -> 0.502 | BF5: ='Promo Form'!CL5 -> 0.460417 | BG5: ='Promo Form'!CN5 | BH5: ='Promo Form'!CO5 | BJ5: ='Promo Form'!CS5 -> 169.95 | BK5: ='Promo Form'!CT5 -> 135.96 | BL5: ='Promo Form'!CU5 -> 0.2 | BM5: ='Promo Form'!CV5 -> 33.99 | BN5: ='Promo Form'!CW5 -> 0
A6: ='Promo Form'!A6 | B6: ='Promo Form'!B6 | C6: ='Promo Form'!C6 -> 0 | D6: ='Promo Form'!D6 | F6: ='Promo Form'!F6 | G6: ='Promo Form'!G6 | H6: ='Promo Form'!J6 | I6: ='Promo Form'!K6 | J6: ='Promo Form'!L6 | K6: ='Promo Form'!N6 | L6: ='Promo Form'!O6 | N6: ='Promo Form'!S6 | O6: ='Promo Form'!T6 | P6: ='Promo Form'!W6 | Q6: ='Promo Form'!X6 | R6: ='Promo Form'!Y6 | S6: ='Promo Form'!AA6 | T6: ='Promo Form'!AB6 | V6: ='Promo Form'!AF6 | W6: ='Promo Form'!AG6 | X6: ='Promo Form'!AJ6 | Y6: ='Promo Form'!AK6 | Z6: ='Promo Form'!AL6 | AA6: ='Promo Form'!AN6 | AB6: ='Promo Form'!AO6 | AD6: ='Promo Form'!AS6 | AE6: ='Promo Form'!AT6 | AF6: ='Promo Form'!AW6 | AG6: ='Promo Form'!AX6 | AH6: ='Promo Form'!AY6 | AI6: ='Promo Form'!BA6 | AJ6: ='Promo Form'!BB6 | AL6: ='Promo Form'!BF6 | AM6: ='Promo Form'!BG6 | AN6: ='Promo Form'!BJ6 | AO6: ='Promo Form'!BK6 | AP6: ='Promo Form'!BL6 | AQ6: ='Promo Form'!BN6 | AR6: ='Promo Form'!BO6 | AT6: ='Promo Form'!BS6 | AU6: ='Promo Form'!BT6 | AV6: ='Promo Form'!BW6 | AW6: ='Promo Form'!BX6 | AX6: ='Promo Form'!BY6 | AY6: ='Promo Form'!CA6 | AZ6: ='Promo Form'!CB6 | BB6: ='Promo Form'!CF6 | BC6: ='Promo Form'!CG6 | BD6: ='Promo Form'!CJ6 | BE6: ='Promo Form'!CK6 | BF6: ='Promo Form'!CL6 | BG6: ='Promo Form'!CN6 | BH6: ='Promo Form'!CO6 | BJ6: ='Promo Form'!CS6 | BK6: ='Promo Form'!CT6 | BL6: ='Promo Form'!CU6 | BM6: ='Promo Form'!CV6 | BN6: ='Promo Form'!CW6 -> 0
A7: ='Promo Form'!A7 | B7: ='Promo Form'!B7 | C7: ='Promo Form'!C7 -> 0 | D7: ='Promo Form'!D7 | F7: ='Promo Form'!F7 | G7: ='Promo Form'!G7 | H7: ='Promo Form'!J7 | I7: ='Promo Form'!K7 | J7: ='Promo Form'!L7 | K7: ='Promo Form'!N7 | L7: ='Promo Form'!O7 | N7: ='Promo Form'!S7 | O7: ='Promo Form'!T7 | P7: ='Promo Form'!W7 | Q7: ='Promo Form'!X7 | R7: ='Promo Form'!Y7 | S7: ='Promo Form'!AA7 | T7: ='Promo Form'!AB7 | V7: ='Promo Form'!AF7 | W7: ='Promo Form'!AG7 | X7: ='Promo Form'!AJ7 | Y7: ='Promo Form'!AK7 | Z7: ='Promo Form'!AL7 | AA7: ='Promo Form'!AN7 | AB7: ='Promo Form'!AO7 | AD7: ='Promo Form'!AS7 | AE7: ='Promo Form'!AT7 | AF7: ='Promo Form'!AW7 | AG7: ='Promo Form'!AX7 | AH7: ='Promo Form'!AY7 | AI7: ='Promo Form'!BA7 | AJ7: ='Promo Form'!BB7 | AL7: ='Promo Form'!BF7 | AM7: ='Promo Form'!BG7 | AN7: ='Promo Form'!BJ7 | AO7: ='Promo Form'!BK7 | AP7: ='Promo Form'!BL7 | AQ7: ='Promo Form'!BN7 | AR7: ='Promo Form'!BO7 | AT7: ='Promo Form'!BS7 | AU7: ='Promo Form'!BT7 | AV7: ='Promo Form'!BW7 | AW7: ='Promo Form'!BX7 | AX7: ='Promo Form'!BY7 | AY7: ='Promo Form'!CA7 | AZ7: ='Promo Form'!CB7 | BB7: ='Promo Form'!CF7 | BC7: ='Promo Form'!CG7 | BD7: ='Promo Form'!CJ7 | BE7: ='Promo Form'!CK7 | BF7: ='Promo Form'!CL7 | BG7: ='Promo Form'!CN7 | BH7: ='Promo Form'!CO7 | BJ7: ='Promo Form'!CS7 | BK7: ='Promo Form'!CT7 | BL7: ='Promo Form'!CU7 | BM7: ='Promo Form'!CV7 | BN7: ='Promo Form'!CW7 -> 0
A8: ='Promo Form'!A8 | B8: ='Promo Form'!B8 | C8: ='Promo Form'!C8 -> 0 | D8: ='Promo Form'!D8 | F8: ='Promo Form'!F8 | G8: ='Promo Form'!G8 | H8: ='Promo Form'!J8 | I8: ='Promo Form'!K8 | J8: ='Promo Form'!L8 | K8: ='Promo Form'!N8 | L8: ='Promo Form'!O8 | N8: ='Promo Form'!S8 | O8: ='Promo Form'!T8 | P8: ='Promo Form'!W8 | Q8: ='Promo Form'!X8 | R8: ='Promo Form'!Y8 | S8: ='Promo Form'!AA8 | T8: ='Promo Form'!AB8 | V8: ='Promo Form'!AF8 | W8: ='Promo Form'!AG8 | X8: ='Promo Form'!AJ8 | Y8: ='Promo Form'!AK8 | Z8: ='Promo Form'!AL8 | AA8: ='Promo Form'!AN8 | AB8: ='Promo Form'!AO8 | AD8: ='Promo Form'!AS8 | AE8: ='Promo Form'!AT8 | AF8: ='Promo Form'!AW8 | AG8: ='Promo Form'!AX8 | AH8: ='Promo Form'!AY8 | AI8: ='Promo Form'!BA8 | AJ8: ='Promo Form'!BB8 | AL8: ='Promo Form'!BF8 | AM8: ='Promo Form'!BG8 | AN8: ='Promo Form'!BJ8 | AO8: ='Promo Form'!BK8 | AP8: ='Promo Form'!BL8 | AQ8: ='Promo Form'!BN8 | AR8: ='Promo Form'!BO8 | AT8: ='Promo Form'!BS8 | AU8: ='Promo Form'!BT8 | AV8: ='Promo Form'!BW8 | AW8: ='Promo Form'!BX8 | AX8: ='Promo Form'!BY8 | AY8: ='Promo Form'!CA8 | AZ8: ='Promo Form'!CB8 | BB8: ='Promo Form'!CF8 | BC8: ='Promo Form'!CG8 | BD8: ='Promo Form'!CJ8 | BE8: ='Promo Form'!CK8 | BF8: ='Promo Form'!CL8 | BG8: ='Promo Form'!CN8 | BH8: ='Promo Form'!CO8 | BJ8: ='Promo Form'!CS8 | BK8: ='Promo Form'!CT8 | BL8: ='Promo Form'!CU8 | BM8: ='Promo Form'!CV8 | BN8: ='Promo Form'!CW8 -> 0
A9: ='Promo Form'!A9 | B9: ='Promo Form'!B9 | C9: ='Promo Form'!C9 -> 0 | D9: ='Promo Form'!D9 | F9: ='Promo Form'!F9 | G9: ='Promo Form'!G9 | H9: ='Promo Form'!J9 | I9: ='Promo Form'!K9 | J9: ='Promo Form'!L9 | K9: ='Promo Form'!N9 | L9: ='Promo Form'!O9 | N9: ='Promo Form'!S9 | O9: ='Promo Form'!T9 | P9: ='Promo Form'!W9 | Q9: ='Promo Form'!X9 | R9: ='Promo Form'!Y9 | S9: ='Promo Form'!AA9 | T9: ='Promo Form'!AB9 | V9: ='Promo Form'!AF9 | W9: ='Promo Form'!AG9 | X9: ='Promo Form'!AJ9 | Y9: ='Promo Form'!AK9 | Z9: ='Promo Form'!AL9 | AA9: ='Promo Form'!AN9 | AB9: ='Promo Form'!AO9 | AD9: ='Promo Form'!AS9 | AE9: ='Promo Form'!AT9 | AF9: ='Promo Form'!AW9 | AG9: ='Promo Form'!AX9 | AH9: ='Promo Form'!AY9 | AI9: ='Promo Form'!BA9 | AJ9: ='Promo Form'!BB9 | AL9: ='Promo Form'!BF9 | AM9: ='Promo Form'!BG9 | AN9: ='Promo Form'!BJ9 | AO9: ='Promo Form'!BK9 | AP9: ='Promo Form'!BL9 | AQ9: ='Promo Form'!BN9 | AR9: ='Promo Form'!BO9 | AT9: ='Promo Form'!BS9 | AU9: ='Promo Form'!BT9 | AV9: ='Promo Form'!BW9 | AW9: ='Promo Form'!BX9 | AX9: ='Promo Form'!BY9 | AY9: ='Promo Form'!CA9 | AZ9: ='Promo Form'!CB9 | BB9: ='Promo Form'!CF9 | BC9: ='Promo Form'!CG9 | BD9: ='Promo Form'!CJ9 | BE9: ='Promo Form'!CK9 | BF9: ='Promo Form'!CL9 | BG9: ='Promo Form'!CN9 | BH9: ='Promo Form'!CO9 | BJ9: ='Promo Form'!CS9 | BK9: ='Promo Form'!CT9 | BL9: ='Promo Form'!CU9 | BM9: ='Promo Form'!CV9 | BN9: ='Promo Form'!CW9 -> 0
A10: ='Promo Form'!A10 | B10: ='Promo Form'!B10 | C10: ='Promo Form'!C10 -> 0 | D10: ='Promo Form'!D10 | F10: ='Promo Form'!F10 | G10: ='Promo Form'!G10 | H10: ='Promo Form'!J10 | I10: ='Promo Form'!K10 | J10: ='Promo Form'!L10 | K10: ='Promo Form'!N10 | L10: ='Promo Form'!O10 | N10: ='Promo Form'!S10 | O10: ='Promo Form'!T10 | P10: ='Promo Form'!W10 | Q10: ='Promo Form'!X10 | R10: ='Promo Form'!Y10 | S10: ='Promo Form'!AA10 | T10: ='Promo Form'!AB10 | V10: ='Promo Form'!AF10 | W10: ='Promo Form'!AG10 | X10: ='Promo Form'!AJ10 | Y10: ='Promo Form'!AK10 | Z10: ='Promo Form'!AL10 | AA10: ='Promo Form'!AN10 | AB10: ='Promo Form'!AO10 | AD10: ='Promo Form'!AS10 | AE10: ='Promo Form'!AT10 | AF10: ='Promo Form'!AW10 | AG10: ='Promo Form'!AX10 | AH10: ='Promo Form'!AY10 | AI10: ='Promo Form'!BA10 | AJ10: ='Promo Form'!BB10 | AL10: ='Promo Form'!BF10 | AM10: ='Promo Form'!BG10 | AN10: ='Promo Form'!BJ10 | AO10: ='Promo Form'!BK10 | AP10: ='Promo Form'!BL10 | AQ10: ='Promo Form'!BN10 | AR10: ='Promo Form'!BO10 | AT10: ='Promo Form'!BS10 | AU10: ='Promo Form'!BT10 | AV10: ='Promo Form'!BW10 | AW10: ='Promo Form'!BX10 | AX10: ='Promo Form'!BY10 | AY10: ='Promo Form'!CA10 | AZ10: ='Promo Form'!CB10 | BB10: ='Promo Form'!CF10 | BC10: ='Promo Form'!CG10 | BD10: ='Promo Form'!CJ10 | BE10: ='Promo Form'!CK10 | BF10: ='Promo Form'!CL10 | BG10: ='Promo Form'!CN10 | BH10: ='Promo Form'!CO10 | BJ10: ='Promo Form'!CS10 | BK10: ='Promo Form'!CT10 | BL10: ='Promo Form'!CU10 | BM10: ='Promo Form'!CV10 | BN10: ='Promo Form'!CW10 -> 0
A11: ='Promo Form'!A11 | B11: ='Promo Form'!B11 | C11: ='Promo Form'!C11 -> 0 | D11: ='Promo Form'!D11 | F11: ='Promo Form'!F11 | G11: ='Promo Form'!G11 | H11: ='Promo Form'!J11 | I11: ='Promo Form'!K11 | J11: ='Promo Form'!L11 | K11: ='Promo Form'!N11 | L11: ='Promo Form'!O11 | N11: ='Promo Form'!S11 | O11: ='Promo Form'!T11 | P11: ='Promo Form'!W11 | Q11: ='Promo Form'!X11 | R11: ='Promo Form'!Y11 | S11: ='Promo Form'!AA11 | T11: ='Promo Form'!AB11 | V11: ='Promo Form'!AF11 | W11: ='Promo Form'!AG11 | X11: ='Promo Form'!AJ11 | Y11: ='Promo Form'!AK11 | Z11: ='Promo Form'!AL11 | AA11: ='Promo Form'!AN11 | AB11: ='Promo Form'!AO11 | AD11: ='Promo Form'!AS11 | AE11: ='Promo Form'!AT11 | AF11: ='Promo Form'!AW11 | AG11: ='Promo Form'!AX11 | AH11: ='Promo Form'!AY11 | AI11: ='Promo Form'!BA11 | AJ11: ='Promo Form'!BB11 | AL11: ='Promo Form'!BF11 | AM11: ='Promo Form'!BG11 | AN11: ='Promo Form'!BJ11 | AO11: ='Promo Form'!BK11 | AP11: ='Promo Form'!BL11 | AQ11: ='Promo Form'!BN11 | AR11: ='Promo Form'!BO11 | AT11: ='Promo Form'!BS11 | AU11: ='Promo Form'!BT11 | AV11: ='Promo Form'!BW11 | AW11: ='Promo Form'!BX11 | AX11: ='Promo Form'!BY11 | AY11: ='Promo Form'!CA11 | AZ11: ='Promo Form'!CB11 | BB11: ='Promo Form'!CF11 | BC11: ='Promo Form'!CG11 | BD11: ='Promo Form'!CJ11 | BE11: ='Promo Form'!CK11 | BF11: ='Promo Form'!CL11 | BG11: ='Promo Form'!CN11 | BH11: ='Promo Form'!CO11 | BJ11: ='Promo Form'!CS11 | BK11: ='Promo Form'!CT11 | BL11: ='Promo Form'!CU11 | BM11: ='Promo Form'!CV11 | BN11: ='Promo Form'!CW11 -> 0
A12: ='Promo Form'!A12 | B12: ='Promo Form'!B12 | C12: ='Promo Form'!C12 -> 0 | D12: ='Promo Form'!D12 | F12: ='Promo Form'!F12 | G12: ='Promo Form'!G12 | H12: ='Promo Form'!J12 | I12: ='Promo Form'!K12 | J12: ='Promo Form'!L12 | K12: ='Promo Form'!N12 | L12: ='Promo Form'!O12 | N12: ='Promo Form'!S12 | O12: ='Promo Form'!T12 | P12: ='Promo Form'!W12 | Q12: ='Promo Form'!X12 | R12: ='Promo Form'!Y12 | S12: ='Promo Form'!AA12 | T12: ='Promo Form'!AB12 | V12: ='Promo Form'!AF12 | W12: ='Promo Form'!AG12 | X12: ='Promo Form'!AJ12 | Y12: ='Promo Form'!AK12 | Z12: ='Promo Form'!AL12 | AA12: ='Promo Form'!AN12 | AB12: ='Promo Form'!AO12 | AD12: ='Promo Form'!AS12 | AE12: ='Promo Form'!AT12 | AF12: ='Promo Form'!AW12 | AG12: ='Promo Form'!AX12 | AH12: ='Promo Form'!AY12 | AI12: ='Promo Form'!BA12 | AJ12: ='Promo Form'!BB12 | AL12: ='Promo Form'!BF12 | AM12: ='Promo Form'!BG12 | AN12: ='Promo Form'!BJ12 | AO12: ='Promo Form'!BK12 | AP12: ='Promo Form'!BL12 | AQ12: ='Promo Form'!BN12 | AR12: ='Promo Form'!BO12 | AT12: ='Promo Form'!BS12 | AU12: ='Promo Form'!BT12 | AV12: ='Promo Form'!BW12 | AW12: ='Promo Form'!BX12 | AX12: ='Promo Form'!BY12 | AY12: ='Promo Form'!CA12 | AZ12: ='Promo Form'!CB12 | BB12: ='Promo Form'!CF12 | BC12: ='Promo Form'!CG12 | BD12: ='Promo Form'!CJ12 | BE12: ='Promo Form'!CK12 | BF12: ='Promo Form'!CL12 | BG12: ='Promo Form'!CN12 | BH12: ='Promo Form'!CO12 | BJ12: ='Promo Form'!CS12 | BK12: ='Promo Form'!CT12 | BL12: ='Promo Form'!CU12 | BM12: ='Promo Form'!CV12 | BN12: ='Promo Form'!CW12 -> 0
A13: ='Promo Form'!A13 | B13: ='Promo Form'!B13 | C13: ='Promo Form'!C13 -> 0 | D13: ='Promo Form'!D13 | F13: ='Promo Form'!F13 | G13: ='Promo Form'!G13 | H13: ='Promo Form'!J13 | I13: ='Promo Form'!K13 | J13: ='Promo Form'!L13 | K13: ='Promo Form'!N13 | L13: ='Promo Form'!O13 | N13: ='Promo Form'!S13 | O13: ='Promo Form'!T13 | P13: ='Promo Form'!W13 | Q13: ='Promo Form'!X13 | R13: ='Promo Form'!Y13 | S13: ='Promo Form'!AA13 | T13: ='Promo Form'!AB13 | V13: ='Promo Form'!AF13 | W13: ='Promo Form'!AG13 | X13: ='Promo Form'!AJ13 | Y13: ='Promo Form'!AK13 | Z13: ='Promo Form'!AL13 | AA13: ='Promo Form'!AN13 | AB13: ='Promo Form'!AO13 | AD13: ='Promo Form'!AS13 | AE13: ='Promo Form'!AT13 | AF13: ='Promo Form'!AW13 | AG13: ='Promo Form'!AX13 | AH13: ='Promo Form'!AY13 | AI13: ='Promo Form'!BA13 | AJ13: ='Promo Form'!BB13 | AL13: ='Promo Form'!BF13 | AM13: ='Promo Form'!BG13 | AN13: ='Promo Form'!BJ13 | AO13: ='Promo Form'!BK13 | AP13: ='Promo Form'!BL13 | AQ13: ='Promo Form'!BN13 | AR13: ='Promo Form'!BO13 | AT13: ='Promo Form'!BS13 | AU13: ='Promo Form'!BT13 | AV13: ='Promo Form'!BW13 | AW13: ='Promo Form'!BX13 | AX13: ='Promo Form'!BY13 | AY13: ='Promo Form'!CA13 | AZ13: ='Promo Form'!CB13 | BB13: ='Promo Form'!CF13 | BC13: ='Promo Form'!CG13 | BD13: ='Promo Form'!CJ13 | BE13: ='Promo Form'!CK13 | BF13: ='Promo Form'!CL13 | BG13: ='Promo Form'!CN13 | BH13: ='Promo Form'!CO13 | BJ13: ='Promo Form'!CS13 | BK13: ='Promo Form'!CT13 | BL13: ='Promo Form'!CU13 | BM13: ='Promo Form'!CV13 | BN13: ='Promo Form'!CW13 -> 0
A14: ='Promo Form'!A14 | B14: ='Promo Form'!B14 | C14: ='Promo Form'!C14 -> 0 | D14: ='Promo Form'!D14 | F14: ='Promo Form'!F14 | G14: ='Promo Form'!G14 | H14: ='Promo Form'!J14 | I14: ='Promo Form'!K14 | J14: ='Promo Form'!L14 | K14: ='Promo Form'!N14 | L14: ='Promo Form'!O14 | N14: ='Promo Form'!S14 | O14: ='Promo Form'!T14 | P14: ='Promo Form'!W14 | Q14: ='Promo Form'!X14 | R14: ='Promo Form'!Y14 | S14: ='Promo Form'!AA14 | T14: ='Promo Form'!AB14 | V14: ='Promo Form'!AF14 | W14: ='Promo Form'!AG14 | X14: ='Promo Form'!AJ14 | Y14: ='Promo Form'!AK14 | Z14: ='Promo Form'!AL14 | AA14: ='Promo Form'!AN14 | AB14: ='Promo Form'!AO14 | AD14: ='Promo Form'!AS14 | AE14: ='Promo Form'!AT14 | AF14: ='Promo Form'!AW14 | AG14: ='Promo Form'!AX14 | AH14: ='Promo Form'!AY14 | AI14: ='Promo Form'!BA14 | AJ14: ='Promo Form'!BB14 | AL14: ='Promo Form'!BF14 | AM14: ='Promo Form'!BG14 | AN14: ='Promo Form'!BJ14 | AO14: ='Promo Form'!BK14 | AP14: ='Promo Form'!BL14 | AQ14: ='Promo Form'!BN14 | AR14: ='Promo Form'!BO14 | AT14: ='Promo Form'!BS14 | AU14: ='Promo Form'!BT14 | AV14: ='Promo Form'!BW14 | AW14: ='Promo Form'!BX14 | AX14: ='Promo Form'!BY14 | AY14: ='Promo Form'!CA14 | AZ14: ='Promo Form'!CB14 | BB14: ='Promo Form'!CF14 | BC14: ='Promo Form'!CG14 | BD14: ='Promo Form'!CJ14 | BE14: ='Promo Form'!CK14 | BF14: ='Promo Form'!CL14 | BG14: ='Promo Form'!CN14 | BH14: ='Promo Form'!CO14 | BJ14: ='Promo Form'!CS14 | BK14: ='Promo Form'!CT14 | BL14: ='Promo Form'!CU14 | BM14: ='Promo Form'!CV14 | BN14: ='Promo Form'!CW14 -> 0
A15: ='Promo Form'!A15 | B15: ='Promo Form'!B15 | C15: ='Promo Form'!C15 -> 0 | D15: ='Promo Form'!D15 | F15: ='Promo Form'!F15 | G15: ='Promo Form'!G15 | H15: ='Promo Form'!J15 | I15: ='Promo Form'!K15 | J15: ='Promo Form'!L15 | K15: ='Promo Form'!N15 | L15: ='Promo Form'!O15 | N15: ='Promo Form'!S15 | O15: ='Promo Form'!T15 | P15: ='Promo Form'!W15 | Q15: ='Promo Form'!X15 | R15: ='Promo Form'!Y15 | S15: ='Promo Form'!AA15 | T15: ='Promo Form'!AB15 | V15: ='Promo Form'!AF15 | W15: ='Promo Form'!AG15 | X15: ='Promo Form'!AJ15 | Y15: ='Promo Form'!AK15 | Z15: ='Promo Form'!AL15 | AA15: ='Promo Form'!AN15 | AB15: ='Promo Form'!AO15 | AD15: ='Promo Form'!AS15 | AE15: ='Promo Form'!AT15 | AF15: ='Promo Form'!AW15 | AG15: ='Promo Form'!AX15 | AH15: ='Promo Form'!AY15 | AI15: ='Promo Form'!BA15 | AJ15: ='Promo Form'!BB15 | AL15: ='Promo Form'!BF15 | AM15: ='Promo Form'!BG15 | AN15: ='Promo Form'!BJ15 | AO15: ='Promo Form'!BK15 | AP15: ='Promo Form'!BL15 | AQ15: ='Promo Form'!BN15 | AR15: ='Promo Form'!BO15 | AT15: ='Promo Form'!BS15 | AU15: ='Promo Form'!BT15 | AV15: ='Promo Form'!BW15 | AW15: ='Promo Form'!BX15 | AX15: ='Promo Form'!BY15 | AY15: ='Promo Form'!CA15 | AZ15: ='Promo Form'!CB15 | BB15: ='Promo Form'!CF15 | BC15: ='Promo Form'!CG15 | BD15: ='Promo Form'!CJ15 | BE15: ='Promo Form'!CK15 | BF15: ='Promo Form'!CL15 | BG15: ='Promo Form'!CN15 | BH15: ='Promo Form'!CO15 | BJ15: ='Promo Form'!CS15 | BK15: ='Promo Form'!CT15 | BL15: ='Promo Form'!CU15 | BM15: ='Promo Form'!CV15 | BN15: ='Promo Form'!CW15 -> 0
A16: ='Promo Form'!A16 | B16: ='Promo Form'!B16 | C16: ='Promo Form'!C16 -> 0 | D16: ='Promo Form'!D16 | F16: ='Promo Form'!F16 | G16: ='Promo Form'!G16 | H16: ='Promo Form'!J16 | I16: ='Promo Form'!K16 | J16: ='Promo Form'!L16 | K16: ='Promo Form'!N16 | L16: ='Promo Form'!O16 | N16: ='Promo Form'!S16 | O16: ='Promo Form'!T16 | P16: ='Promo Form'!W16 | Q16: ='Promo Form'!X16 | R16: ='Promo Form'!Y16 | S16: ='Promo Form'!AA16 | T16: ='Promo Form'!AB16 | V16: ='Promo Form'!AF16 | W16: ='Promo Form'!AG16 | X16: ='Promo Form'!AJ16 | Y16: ='Promo Form'!AK16 | Z16: ='Promo Form'!AL16 | AA16: ='Promo Form'!AN16 | AB16: ='Promo Form'!AO16 | AD16: ='Promo Form'!AS16 | AE16: ='Promo Form'!AT16 | AF16: ='Promo Form'!AW16 | AG16: ='Promo Form'!AX16 | AH16: ='Promo Form'!AY16 | AI16: ='Promo Form'!BA16 | AJ16: ='Promo Form'!BB16 | AL16: ='Promo Form'!BF16 | AM16: ='Promo Form'!BG16 | AN16: ='Promo Form'!BJ16 | AO16: ='Promo Form'!BK16 | AP16: ='Promo Form'!BL16 | AQ16: ='Promo Form'!BN16 | AR16: ='Promo Form'!BO16 | AT16: ='Promo Form'!BS16 | AU16: ='Promo Form'!BT16 | AV16: ='Promo Form'!BW16 | AW16: ='Promo Form'!BX16 | AX16: ='Promo Form'!BY16 | AY16: ='Promo Form'!CA16 | AZ16: ='Promo Form'!CB16 | BB16: ='Promo Form'!CF16 | BC16: ='Promo Form'!CG16 | BD16: ='Promo Form'!CJ16 | BE16: ='Promo Form'!CK16 | BF16: ='Promo Form'!CL16 | BG16: ='Promo Form'!CN16 | BH16: ='Promo Form'!CO16 | BJ16: ='Promo Form'!CS16 | BK16: ='Promo Form'!CT16 | BL16: ='Promo Form'!CU16 | BM16: ='Promo Form'!CV16 | BN16: ='Promo Form'!CW16 -> 0
... A49: ='Promo Form'!A49 | B49: ='Promo Form'!B49 | C49: ='Promo Form'!C49 -> 0 | D49: ='Promo Form'!D49 | F49: ='Promo Form'!F49 | G49: ='Promo Form'!G49 | H49: ='Promo Form'!J49 | I49: ='Promo Form'!K49 | J49: ='Promo Form'!L49 | K49: ='Promo Form'!N49 | L49: ='Promo Form'!O49 | N49: ='Promo Form'!S49 | O49: ='Promo Form'!T49 | P49: ='Promo Form'!W49 | Q49: ='Promo Form'!X49 | R49: ='Promo Form'!Y49 | S49: ='Promo Form'!AA49 | T49: ='Promo Form'!AB49 | V49: ='Promo Form'!AF49 | W49: ='Promo Form'!AG49 | X49: ='Promo Form'!AJ49 | Y49: ='Promo Form'!AK49 | Z49: ='Promo Form'!AL49 | AA49: ='Promo Form'!AN49 | AB49: ='Promo Form'!AO49 | AD49: ='Promo Form'!AS49 | AE49: ='Promo Form'!AT49 | AF49: ='Promo Form'!AW49 | AG49: ='Promo Form'!AX49 | AH49: ='Promo Form'!AY49 | AI49: ='Promo Form'!BA49 | AJ49: ='Promo Form'!BB49 | AL49: ='Promo Form'!BF49 | AM49: ='Promo Form'!BG49 | AN49: ='Promo Form'!BJ49 | AO49: ='Promo Form'!BK49 | AP49: ='Promo Form'!BL49 | AQ49: ='Promo Form'!BN49 | AR49: ='Promo Form'!BO49 | AT49: ='Promo Form'!BS49 | AU49: ='Promo Form'!BT49 | AV49: ='Promo Form'!BW49 | AW49: ='Promo Form'!BX49 | AX49: ='Promo Form'!BY49 | AY49: ='Promo Form'!CA49 | AZ49: ='Promo Form'!CB49 | BB49: ='Promo Form'!CF49 | BC49: ='Promo Form'!CG49 | BD49: ='Promo Form'!CJ49 | BE49: ='Promo Form'!CK49 | BF49: ='Promo Form'!CL49 | BG49: ='Promo Form'!CN49 | BH49: ='Promo Form'!CO49 | BJ49: ='Promo Form'!CS49 | BK49: ='Promo Form'!CT49 | BL49: ='Promo Form'!CU49 | BM49: ='Promo Form'!CV49 | BN49: ='Promo Form'!CW49 -> 0
A50: Last Day for Customer claims to be submitted | D50: ='Promo Form'!D50 -> 45836 | J50: =IFERROR((($FR50/1.1)+(#REF!+#REF!)-(G50-(G50*F$2)))/($FR50/1.1),"") | L50: =IFERROR((($FR50/1.1)+(#REF!+H50)-(#REF!-(#REF!*G$2)))/($FR50/1.1),"") | R50: =IFERROR((($FR50/1.1)+(#REF!+#REF!)-(O50-(O50*N$2)))/($FR50/1.1),"") | T50: =IFERROR((($FR50/1.1)+(#REF!+P50)-(#REF!-(#REF!*O$2)))/($FR50/1.1),"") | Z50: =IFERROR((($FR50/1.1)+(#REF!+#REF!)-(W50-(W50*V$2)))/($FR50/1.1),"") | AB50: =IFERROR((($FR50/1.1)+(#REF!+X50)-(#REF!-(#REF!*W$2)))/($FR50/1.1),"") | AH50: =IFERROR((($FR50/1.1)+(#REF!+#REF!)-(AE50-(AE50*AD$2)))/($FR50/1.1),"") | AJ50: =IFERROR((($FR50/1.1)+(#REF!+AF50)-(#REF!-(#REF!*AE$2)))/($FR50/1.1),"") | AP50: =IFERROR((($FR50/1.1)+(#REF!+#REF!)-(AM50-(AM50*AL$2)))/($FR50/1.1),"") | AR50: =IFERROR((($FR50/1.1)+(#REF!+AN50)-(#REF!-(#REF!*AM$2)))/($FR50/1.1),"") | AX50: =IFERROR((($FR50/1.1)+(#REF!+#REF!)-(AU50-(AU50*AT$2)))/($FR50/1.1),"") | AZ50: =IFERROR((($FR50/1.1)+(#REF!+AV50)-(#REF!-(#REF!*AU$2)))/($FR50/1.1),"") | BF50: =IFERROR((($FR50/1.1)+(#REF!+#REF!)-(BC50-(BC50*BB$2)))/($FR50/1.1),"") | BH50: =IFERROR((($FR50/1.1)+(#REF!+BD50)-(#REF!-(#REF!*BC$2)))/($FR50/1.1),"")
F51: NOTES | N51: NOTES | V51: NOTES | AD51: NOTES | AL51: NOTES | AT51: NOTES | BB51: NOTES
F52: ='Promo Form'!H64 -> 0 | N52: ='Promo Form'!U64 -> 0 | V52: ='Promo Form'!AH64 -> 0 | AD52: ='Promo Form'!AU64 -> 0 | AL52: ='Promo Form'!BH64 -> 0 | AT52: ='Promo Form'!BU64 -> 0 | BB52: ='Promo Form'!CH64 -> 0

Sheet Vendor Copy
A1: AUSTRALIAN Claim Number | C1: ='Promo Form'!C1 -> 0 | D1: Name of Promotion
A2: Brand | C2: ='Promo Form'!C2 -> 0 | D2: ='Promo Form'!D2 -> 0
A3: Promo Date(s) | C3: Code | D3: Product Description | F3: ='Promo Form'!F3 -> AU - Officeworks | J3: ='Promo Form'!S3 -> JB HIFI | N3: ='Promo Form'!AF3 -> AU - Amazon | R3: ='Promo Form'!AS3 -> AU - The Good Guys | V3: ='Promo Form'!BF3 -> Bing Lee | Z3: ='Promo Form'!BS3 -> Harvey Norman | AD3: ='Promo Form'!CF3 -> Harvey Norman
A4: From | B4: To | F4: Supplier Support | G4: Expected Sales / Actual Sales | H4: Supplier Claim Amount | J4: Supplier Support | K4: Expected Sales / Actual Sales | L4: Supplier Claim Amount | N4: Supplier Support | O4: Expected Sales / Actual Sales | P4: Supplier Claim Amount | R4: Supplier Support | S4: Expected Sales / Actual Sales | T4: Supplier Claim Amount | V4: Supplier Support | W4: Expected Sales / Actual Sales | X4: Supplier Claim Amount | Z4: Supplier Support | AA4: Expected Sales / Actual Sales | AB4: Supplier Claim Amount | AD4: Supplier Support | AE4: Expected Sales / Actual Sales | AF4: Supplier Claim Amount | AH4: RRP Inc | AI4: Recommended Sale Inc | AJ4: Recommended % Off | AK4: Recommended $ Off | AL4: Comments
A5: ='Promo Form'!A5 -> 45809 | B5: ='Promo Form'!B5 -> 45822 | C5: ='Promo Form'!C5 -> A1902T11 | D5: ='Promo Form'!D5 -> ANKER 100W Charging Base for ANKER Prime Power Bank | F5: ='Promo Form'!H5 -> 4.8956128 | G5: ='Promo Form'!O5 | H5: ='Promo Form'!P5 | J5: ='Promo Form'!U5 -> 0 | K5: ='Promo Form'!AB5 | L5: ='Promo Form'!AC5 | N5: ='Promo Form'!AH5 -> 0 | O5: ='Promo Form'!AO5 | P5: ='Promo Form'!AP5 | R5: ='Promo Form'!AU5 -> 0 | S5: ='Promo Form'!BB5 | T5: ='Promo Form'!BC5 | V5: ='Promo Form'!BH5 -> 0 | W5: ='Promo Form'!BO5 | X5: ='Promo Form'!BP5 | Z5: ='Promo Form'!BU5 -> 5.1242706 | AA5: ='Promo Form'!CB5 | AB5: ='Promo Form'!CC5 | AD5: ='Promo Form'!CH5 -> 5.1242706 | AE5: ='Promo Form'!CO5 | AF5: ='Promo Form'!CP5 | AH5: ='Promo Form'!CS5 -> 169.95 | AI5: ='Promo Form'!CT5 -> 135.96 | AJ5: ='Promo Form'!CU5 -> 0.2 | AK5: ='Promo Form'!CV5 -> 33.99 | AL5: ='Promo Form'!CW5 -> 0
A6: ='Promo Form'!A6 | B6: ='Promo Form'!B6 | C6: ='Promo Form'!C6 -> 0 | D6: ='Promo Form'!D6 | F6: ='Promo Form'!H6 | G6: ='Promo Form'!O6 | H6: ='Promo Form'!P6 | J6: ='Promo Form'!U6 | K6: ='Promo Form'!AB6 | L6: ='Promo Form'!AC6 | N6: ='Promo Form'!AH6 | O6: ='Promo Form'!AO6 | P6: ='Promo Form'!AP6 | R6: ='Promo Form'!AU6 | S6: ='Promo Form'!BB6 | T6: ='Promo Form'!BC6 | V6: ='Promo Form'!BH6 | W6: ='Promo Form'!BO6 | X6: ='Promo Form'!BP6 | Z6: ='Promo Form'!BU6 | AA6: ='Promo Form'!CB6 | AB6: ='Promo Form'!CC6 | AD6: ='Promo Form'!CH6 | AE6: ='Promo Form'!CO6 | AF6: ='Promo Form'!CP6 | AH6: ='Promo Form'!CS6 | AI6: ='Promo Form'!CT6 | AJ6: ='Promo Form'!CU6 | AK6: ='Promo Form'!CV6 | AL6: ='Promo Form'!CW6 -> 0
A7: ='Promo Form'!A7 | B7: ='Promo Form'!B7 | C7: ='Promo Form'!C7 -> 0 | D7: ='Promo Form'!D7 | F7: ='Promo Form'!H7 | G7: ='Promo Form'!O7 | H7: ='Promo Form'!P7 | J7: ='Promo Form'!U7 | K7: ='Promo Form'!AB7 | L7: ='Promo Form'!AC7 | N7: ='Promo Form'!AH7 | O7: ='Promo Form'!AO7 | P7: ='Promo Form'!AP7 | R7: ='Promo Form'!AU7 | S7: ='Promo Form'!BB7 | T7: ='Promo Form'!BC7 | V7: ='Promo Form'!BH7 | W7: ='Promo Form'!BO7 | X7: ='Promo Form'!BP7 | Z7: ='Promo Form'!BU7 | AA7: ='Promo Form'!CB7 | AB7: ='Promo Form'!CC7 | AD7: ='Promo Form'!CH7 | AE7: ='Promo Form'!CO7 | AF7: ='Promo Form'!CP7 | AH7: ='Promo Form'!CS7 | AI7: ='Promo Form'!CT7 | AJ7: ='Promo Form'!CU7 | AK7: ='Promo Form'!CV7 | AL7: ='Promo Form'!CW7 -> 0
A8: ='Promo Form'!A8 | B8: ='Promo Form'!B8 | C8: ='Promo Form'!C8 -> 0 | D8: ='Promo Form'!D8 | F8: ='Promo Form'!H8 | G8: ='Promo Form'!O8 | H8: ='Promo Form'!P8 | J8: ='Promo Form'!U8 | K8: ='Promo Form'!AB8 | L8: ='Promo Form'!AC8 | N8: ='Promo Form'!AH8 | O8: ='Promo Form'!AO8 | P8: ='Promo Form'!AP8 | R8: ='Promo Form'!AU8 | S8: ='Promo Form'!BB8 | T8: ='Promo Form'!BC8 | V8: ='Promo Form'!BH8 | W8: ='Promo Form'!BO8 | X8: ='Promo Form'!BP8 | Z8: ='Promo Form'!BU8 | AA8: ='Promo Form'!CB8 | AB8: ='Promo Form'!CC8 | AD8: ='Promo Form'!CH8 | AE8: ='Promo Form'!CO8 | AF8: ='Promo Form'!CP8 | AH8: ='Promo Form'!CS8 | AI8: ='Promo Form'!CT8 | AJ8: ='Promo Form'!CU8 | AK8: ='Promo Form'!CV8 | AL8: ='Promo Form'!CW8 -> 0
A9: ='Promo Form'!A9 | B9: ='Promo Form'!B9 | C9: ='Promo Form'!C9 -> 0 | D9: ='Promo Form'!D9 | F9: ='Promo Form'!H9 | G9: ='Promo Form'!O9 | H9: ='Promo Form'!P9 | J9: ='Promo Form'!U9 | K9: ='Promo Form'!AB9 | L9: ='Promo Form'!AC9 | N9: ='Promo Form'!AH9 | O9: ='Promo Form'!AO9 | P9: ='Promo Form'!AP9 | R9: ='Promo Form'!AU9 | S9: ='Promo Form'!BB9 | T9: ='Promo Form'!BC9 | V9: ='Promo Form'!BH9 | W9: ='Promo Form'!BO9 | X9: ='Promo Form'!BP9 | Z9: ='Promo Form'!BU9 | AA9: ='Promo Form'!CB9 | AB9: ='Promo Form'!CC9 | AD9: ='Promo Form'!CH9 | AE9: ='Promo Form'!CO9 | AF9: ='Promo Form'!CP9 | AH9: ='Promo Form'!CS9 | AI9: ='Promo Form'!CT9 | AJ9: ='Promo Form'!CU9 | AK9: ='Promo Form'!CV9 | AL9: ='Promo Form'!CW9 -> 0
A10: ='Promo Form'!A10 | B10: ='Promo Form'!B10 | C10: ='Promo Form'!C10 -> 0 | D10: ='Promo Form'!D10 | F10: ='Promo Form'!H10 | G10: ='Promo Form'!O10 | H10: ='Promo Form'!P10 | J10: ='Promo Form'!U10 | K10: ='Promo Form'!AB10 | L10: ='Promo Form'!AC10 | N10: ='Promo Form'!AH10 | O10: ='Promo Form'!AO10 | P10: ='Promo Form'!AP10 | R10: ='Promo Form'!AU10 | S10: ='Promo Form'!BB10 | T10: ='Promo Form'!BC10 | V10: ='Promo Form'!BH10 | W10: ='Promo Form'!BO10 | X10: ='Promo Form'!BP10 | Z10: ='Promo Form'!BU10 | AA10: ='Promo Form'!CB10 | AB10: ='Promo Form'!CC10 | AD10: ='Promo Form'!CH10 | AE10: ='Promo Form'!CO10 | AF10: ='Promo Form'!CP10 | AH10: ='Promo Form'!CS10 | AI10: ='Promo Form'!CT10 | AJ10: ='Promo Form'!CU10 | AK10: ='Promo Form'!CV10 | AL10: ='Promo Form'!CW10 -> 0
A11: ='Promo Form'!A11 | B11: ='Promo Form'!B11 | C11: ='Promo Form'!C11 -> 0 | D11: ='Promo Form'!D11 | F11: ='Promo Form'!H11 | G11: ='Promo Form'!O11 | H11: ='Promo Form'!P11 | J11: ='Promo Form'!U11 | K11: ='Promo Form'!AB11 | L11: ='Promo Form'!AC11 | N11: ='Promo Form'!AH11 | O11: ='Promo Form'!AO11 | P11: ='Promo Form'!AP11 | R11: ='Promo Form'!AU11 | S11: ='Promo Form'!BB11 | T11: ='Promo Form'!BC11 | V11: ='Promo Form'!BH11 | W11: ='Promo Form'!BO11 | X11: ='Promo Form'!BP11 | Z11: ='Promo Form'!BU11 | AA11: ='Promo Form'!CB11 | AB11: ='Promo Form'!CC11 | AD11: ='Promo Form'!CH11 | AE11: ='Promo Form'!CO11 | AF11: ='Promo Form'!CP11 | AH11: ='Promo Form'!CS11 | AI11: ='Promo Form'!CT11 | AJ11: ='Promo Form'!CU11 | AK11: ='Promo Form'!CV11 | AL11: ='Promo Form'!CW11 -> 0
A12: ='Promo Form'!A12 | B12: ='Promo Form'!B12 | C12: ='Promo Form'!C12 -> 0 | D12: ='Promo Form'!D12 | F12: ='Promo Form'!H12 | G12: ='Promo Form'!O12 | H12: ='Promo Form'!P12 | J12: ='Promo Form'!U12 | K12: ='Promo Form'!AB12 | L12: ='Promo Form'!AC12 | N12: ='Promo Form'!AH12 | O12: ='Promo Form'!AO12 | P12: ='Promo Form'!AP12 | R12: ='Promo Form'!AU12 | S12: ='Promo Form'!BB12 | T12: ='Promo Form'!BC12 | V12: ='Promo Form'!BH12 | W12: ='Promo Form'!BO12 | X12: ='Promo Form'!BP12 | Z12: ='Promo Form'!BU12 | AA12: ='Promo Form'!CB12 | AB12: ='Promo Form'!CC12 | AD12: ='Promo Form'!CH12 | AE12: ='Promo Form'!CO12 | AF12: ='Promo Form'!CP12 | AH12: ='Promo Form'!CS12 | AI12: ='Promo Form'!CT12 | AJ12: ='Promo Form'!CU12 | AK12: ='Promo Form'!CV12 | AL12: ='Promo Form'!CW12 -> 0
A13: ='Promo Form'!A13 | B13: ='Promo Form'!B13 | C13: ='Promo Form'!C13 -> 0 | D13: ='Promo Form'!D13 | F13: ='Promo Form'!H13 | G13: ='Promo Form'!O13 | H13: ='Promo Form'!P13 | J13: ='Promo Form'!U13 | K13: ='Promo Form'!AB13 | L13: ='Promo Form'!AC13 | N13: ='Promo Form'!AH13 | O13: ='Promo Form'!AO13 | P13: ='Promo Form'!AP13 | R13: ='Promo Form'!AU13 | S13: ='Promo Form'!BB13 | T13: ='Promo Form'!BC13 | V13: ='Promo Form'!BH13 | W13: ='Promo Form'!BO13 | X13: ='Promo Form'!BP13 | Z13: ='Promo Form'!BU13 | AA13: ='Promo Form'!CB13 | AB13: ='Promo Form'!CC13 | AD13: ='Promo Form'!CH13 | AE13: ='Promo Form'!CO13 | AF13: ='Promo Form'!CP13 | AH13: ='Promo Form'!CS13 | AI13: ='Promo Form'!CT13 | AJ13: ='Promo Form'!CU13 | AK13: ='Promo Form'!CV13 | AL13: ='Promo Form'!CW13 -> 0
A14: ='Promo Form'!A14 | B14: ='Promo Form'!B14 | C14: ='Promo Form'!C14 -> 0 | D14: ='Promo Form'!D14 | F14: ='Promo Form'!H14 | G14: ='Promo Form'!O14 | H14: ='Promo Form'!P14 | J14: ='Promo Form'!U14 | K14: ='Promo Form'!AB14 | L14: ='Promo Form'!AC14 | N14: ='Promo Form'!AH14 | O14: ='Promo Form'!AO14 | P14: ='Promo Form'!AP14 | R14: ='Promo Form'!AU14 | S14: ='Promo Form'!BB14 | T14: ='Promo Form'!BC14 | V14: ='Promo Form'!BH14 | W14: ='Promo Form'!BO14 | X14: ='Promo Form'!BP14 | Z14: ='Promo Form'!BU14 | AA14: ='Promo Form'!CB14 | AB14: ='Promo Form'!CC14 | AD14: ='Promo Form'!CH14 | AE14: ='Promo Form'!CO14 | AF14: ='Promo Form'!CP14 | AH14: ='Promo Form'!CS14 | AI14: ='Promo Form'!CT14 | AJ14: ='Promo Form'!CU14 | AK14: ='Promo Form'!CV14 | AL14: ='Promo Form'!CW14 -> 0
A15: ='Promo Form'!A15 | B15: ='Promo Form'!B15 | C15: ='Promo Form'!C15 -> 0 | D15: ='Promo Form'!D15 | F15: ='Promo Form'!H15 | G15: ='Promo Form'!O15 | H15: ='Promo Form'!P15 | J15: ='Promo Form'!U15 | K15: ='Promo Form'!AB15 | L15: ='Promo Form'!AC15 | N15: ='Promo Form'!AH15 | O15: ='Promo Form'!AO15 | P15: ='Promo Form'!AP15 | R15: ='Promo Form'!AU15 | S15: ='Promo Form'!BB15 | T15: ='Promo Form'!BC15 | V15: ='Promo Form'!BH15 | W15: ='Promo Form'!BO15 | X15: ='Promo Form'!BP15 | Z15: ='Promo Form'!BU15 | AA15: ='Promo Form'!CB15 | AB15: ='Promo Form'!CC15 | AD15: ='Promo Form'!CH15 | AE15: ='Promo Form'!CO15 | AF15: ='Promo Form'!CP15 | AH15: ='Promo Form'!CS15 | AI15: ='Promo Form'!CT15 | AJ15: ='Promo Form'!CU15 | AK15: ='Promo Form'!CV15 | AL15: ='Promo Form'!CW15 -> 0
A16: ='Promo Form'!A16 | B16: ='Promo Form'!B16 | C16: ='Promo Form'!C16 -> 0 | D16: ='Promo Form'!D16 | F16: ='Promo Form'!H16 | G16: ='Promo Form'!O16 | H16: ='Promo Form'!P16 | J16: ='Promo Form'!U16 | K16: ='Promo Form'!AB16 | L16: ='Promo Form'!AC16 | N16: ='Promo Form'!AH16 | O16: ='Promo Form'!AO16 | P16: ='Promo Form'!AP16 | R16: ='Promo Form'!AU16 | S16: ='Promo Form'!BB16 | T16: ='Promo Form'!BC16 | V16: ='Promo Form'!BH16 | W16: ='Promo Form'!BO16 | X16: ='Promo Form'!BP16 | Z16: ='Promo Form'!BU16 | AA16: ='Promo Form'!CB16 | AB16: ='Promo Form'!CC16 | AD16: ='Promo Form'!CH16 | AE16: ='Promo Form'!CO16 | AF16: ='Promo Form'!CP16 | AH16: ='Promo Form'!CS16 | AI16: ='Promo Form'!CT16 | AJ16: ='Promo Form'!CU16 | AK16: ='Promo Form'!CV16 | AL16: ='Promo Form'!CW16 -> 0
... A49: ='Promo Form'!A49 | B49: ='Promo Form'!B49 | C49: ='Promo Form'!C49 -> 0 | D49: ='Promo Form'!D49 | F49: ='Promo Form'!H49 | G49: ='Promo Form'!O49 | H49: ='Promo Form'!P49 | J49: ='Promo Form'!U49 | K49: ='Promo Form'!AB49 | L49: ='Promo Form'!AC49 | N49: ='Promo Form'!AH49 | O49: ='Promo Form'!AO49 | P49: ='Promo Form'!AP49 | R49: ='Promo Form'!AU49 | S49: ='Promo Form'!BB49 | T49: ='Promo Form'!BC49 | V49: ='Promo Form'!BH49 | W49: ='Promo Form'!BO49 | X49: ='Promo Form'!BP49 | Z49: ='Promo Form'!BU49 | AA49: ='Promo Form'!CB49 | AB49: ='Promo Form'!CC49 | AD49: ='Promo Form'!CH49 | AE49: ='Promo Form'!CO49 | AF49: ='Promo Form'!CP49 | AH49: ='Promo Form'!CS49 | AI49: ='Promo Form'!CT49 | AJ49: ='Promo Form'!CU49 | AK49: ='Promo Form'!CV49 | AL49: ='Promo Form'!CW49 -> 0
A50: Last Day for Customer claims to be submitted | G50: Total | H50: Supplier | K50: Total | L50: Supplier | O50: Total | P50: Supplier | S50: Total | T50: Supplier | W50: Total | X50: Supplier | AA50: Total | AB50: Supplier | AE50: Total | AF50: Supplier
H51: ='Promo Form'!P52 -> 0 | L51: ='Promo Form'!AC52 -> 0 | P51: ='Promo Form'!AP52 -> 0 | T51: ='Promo Form'!BC52 -> 0 | X51: ='Promo Form'!BP52 -> 0 | AB51: ='Promo Form'!CC52 -> 0 | AF51: ='Promo Form'!CP52 -> 0
A52: TOTAL Brand Claim AUD Ex | D52: ='Promo Form'!D53 -> 0
A53: TOTAL CLAIM to USD ex | D53: ='Promo Form'!D54 -> 0
C54: AUD to USD Rate | D54: ='Promo Form'!D55 -> 0.65
B57: VENDOR NOTE | D57: ** Please note, Expected Sales and claim totals are a projection based on estimated sales within promo Period. Total claim will vary depending on success of promotion.

Sheet Data Validation
B2: Rebate
A3: Spare | B3: 0
A4: JB HIFI | B4: 0.19
A5: AU - Officeworks | B5: 0.135
A6: Harvey Norman | B6: 0.17
A7: AU - Amazon | B7: 0.125
A8: Dealer 1 | B8: 0
A9: Dealer 2 | B9: 0
A10: AU - Bunnings | B10: 0.15
A11: AU - The Good Guys | B11: 0.15
A12: Bing Lee | B12: 0.2
A13: Education

Sheet Master Price Level
A1: Source.Name | B1: Brand | C1: Code | D1: Description | E1: AU Status | F1: Base (RRP Inc) | G1: Clearance - MacGear + Brand Sites | H1: Dealer 1 | I1: Dealer 2 | J1: Dealer 3 | K1: Education | L1: JB HIFI | M1: Harvey Norman | N1: Costco | O1: AU - Amazon | P1: LS travel | Q1: AU - Officeworks | R1: AU - The Good Guys | S1: AU - WH Smith | T1: AU - Big W | U1: AU - Bunnings | V1: NZ AU - AirPoints / Aciem | W1: NZ AU - Smart Loyalty | X1: NZ AU - Fly Buys | Y1: NZ AU - Qantas | Z1: NZ AU - RRP - Home Of Brands | AA1: NZ AU - RRP - List Price | AB1: Clearance - Home Of Brands | AC1: Bing Lee
A2: Master Price Level AU.csv | B2: - None - | C2: KNAAPBCN_SAMPLE | D2: KNAAP BCN Fatbike E-Bike (Black) | E2: Inactive | F2: 169.99 | Z2: 169.99
A3: Master Price Level AU.csv | B3: - None - | C3: MKTG-12 | D3: MARKETING 4x small Sphero panels, 1x indi panel, 1x, BOLT+ panel, 1x RVR+ panel, 1x Blueprint panel | E3: Inactive | F3: 169.99 | Z3: 169.99
A4: Master Price Level AU.csv | B4: - None - | C4: MKTG-27 | D4: MARKETING Banner - Bonelk | E4: Inactive | F4: 169.99 | Z4: 169.99
A5: Master Price Level AU.csv | B5: - None - | C5: MKTG-26 | D5: MARKETING Banner - Satechi | E5: Inactive | F5: 169.99 | Z5: 169.99
A6: Master Price Level AU.csv | B6: - None - | C6: MKTG-38 | D6: MARKETING Bollard Signage (Upgrade Program) and Plastic Channel Tracks for Sphero Table signs | E6: Inactive | F6: 169.99 | Z6: 169.99
A7: Master Price Level AU.csv | B7: - None - | C7: MKTG-06 | D7: MARKETING Bolt Powerpack - Customer Demo Unit | E7: Inactive | F7: 169.99 | Z7: 169.99
A8: Master Price Level AU.csv | B8: - None - | C8: MKTG-40 | D8: MARKETING BOLT+ Power Pack | E8: Inactive | F8: 169.99 | Z8: 169.99
A9: Master Price Level AU.csv | B9: - None - | C9: MKTG-17 | D9: MARKETING Coreflute Sheets - 4 full sheets/2 cut panels | E9: Inactive | F9: 169.99 | Z9: 169.99
A10: Master Price Level AU.csv | B10: - None - | C10: MKTG-20 | D10: MARKETING EduTech Action Box | E10: Inactive | F10: 169.99 | Z10: 169.99
A11: Master Price Level AU.csv | B11: - None - | C11: MKTG-16 | D11: MARKETING Expo Trestle Table 1.2m | E11: Inactive | F11: 169.99 | Z11: 169.99
A12: Master Price Level AU.csv | B12: - None - | C12: MKTG-07 | D12: MARKETING Golf and City Sphero Mats - Customer Demo Unit | E12: Inactive | F12: 169.99 | Z12: 169.99
A13: Master Price Level AU.csv | B13: - None - | C13: MKTG-15 | D13: MARKETING IKEA Peg Board Hardware | E13: Inactive | F13: 169.99 | Z13: 169.99
... A24: Master Price Level AU.csv | B24: - None - | C24: MKTG-31 | D24: MARKETING JB Hi-Fi Action Box 5 | E24: Inactive | F24: 169.99 | Z24: 169.99
A25: Master Price Level AU.csv | B25: - None - | C25: MKTG-32 | D25: MARKETING JB Hi-Fi Action Box 6 | E25: Inactive | F25: 169.99
A26: Master Price Level AU.csv | B26: - None - | C26: MKTG-04 | D26: MARKETING Large Plinths x2 | E26: Inactive | F26: 169.99 | Z26: 169.99
A27: Master Price Level AU.csv | B27: - None - | C27: MKTG-33 | D27: MARKETING Light Box (1m x 2.5m) #1 - Back panel for Sphero logo Left | E27: Inactive | F27: 169.99 | Z27: 169.99
A28: Master Price Level AU.csv | B28: - None - | C28: MKTG-34 | D28: MARKETING Light Box (1m x 2.5m) #2 - Back panel for Sphero logo Right | E28: Inactive | F28: 169.99 | Z28: 169.99
A29: Master Price Level AU.csv | B29: - None - | C29: MKTG-35 | D29: MARKETING Light Box (2m x 2.5m) #3 - Back panel for RVR+ and Blueprint | E29: Inactive | F29: 169.99 | Z29: 169.99
A30: Master Price Level AU.csv | B30: - None - | C30: MKTG-36 | D30: MARKETING Light Box (2m x 2.5m) #4 - Back panel for indi and BOLT | E30: Inactive | F30: 169.99 | Z30: 169.99
A31: Master Price Level AU.csv | B31: - None - | C31: MKTG-45 | D31: MARKETING Misc | E31: Inactive | F31: 169.99 | Z31: 169.99
A32: Master Price Level AU.csv | B32: - None - | C32: MKTG-37 | D32: MARKETING Old Table Boards (RVR+ (Old x1), BOLT+ (damaged corner x1), Sphero (Old x2), BOLT (OG) (Old x2), indi (Old x2)) | E32: Inactive | F32: 169.99 | Z32: 169.99
A33: Master Price Level AU.csv | B33: - None - | C33: MKTG-08 | D33: MARKETING Pegs for JB Hi-Fi Conference | E33: Inactive | F33: 169.99 | Z33: 169.99
A34: Master Price Level AU.csv | B34: - None - | C34: MKTG-46 | D34: MARKETING Perspex Display Stands | E34: Inactive | F34: 169.99 | Z34: 169.99
A35: Master Price Level AU.csv | B35: - None - | C35: MKTG-05 | D35: MARKETING Peter Abt Props | E35: Inactive | F35: 169.99 | Z35: 169.99
A36: Master Price Level AU.csv | B36: - None - | C36: MKTG-42 | D36: MARKETING Printed collateral + CSF Books | E36: Inactive | F36: 169.99 | Z36: 169.99
A37: Master Price Level AU.csv | B37: - None - | C37: MKTG-43 | D37: MARKETING RVR+ (x1), BOLT+ (x3) | E37: Inactive | F37: 169.99 | Z37: 169.99
... A77: Master Price Level AU.csv | B77: - None - | C77: SEDLEY-15 | D77: SEDLEY POSSESSIONS | E77: Inactive | F77: 169.99 | Z77: 169.99
A78: Master Price Level AU.csv | B78: ADONIT | C78: ADAIVB | D78: ADONIT AI Vocal | E78: Inactive | F78: 149.99 | G78: 29.99 | H78: 88.63 | I78: 95.45 | J78: 123.95 | K78: 88.63 | L78: 102.27 | O78: 109.08 | Q78: 102.27 | Y78: 115.9 | Z78: 149.99
A79: Master Price Level AU.csv | B79: ADONIT | C79: ADJD4B | D79: ADONIT Dash 4 (Black) | E79: Active | F79: 119.99 | H79: 65.45 | I79: 76.36 | J79: 98.17 | K79: 76.36 | L79: 70.9 | M79: 70.9 | O79: 87.27 | P79: 65.45 | Q79: 76.36 | R79: 81.81 | Y79: 92.72 | Z79: 119.99
A80: Master Price Level AU.csv | B80: ADONIT | C80: ADJD4S | D80: ADONIT Dash 4 (Silver) | E80: Active | F80: 119.99 | H80: 65.45 | I80: 76.36 | J80: 98.17 | K80: 76.36 | L80: 70.9 | M80: 70.9 | O80: 87.27 | P80: 65.45 | Q80: 76.36 | R80: 81.81 | Y80: 92.72 | Z80: 119.99
A81: Master Price Level AU.csv | B81: ADONIT | C81: ADIB | D81: ADONIT Ink Stylus (Black) | E81: Inactive | F81: 109.99 | G81: 59.99 | H81: 59.99 | I81: 69.99 | J81: 89.99 | K81: 59.99 | L81: 64.99 | M81: 64.99 | O81: 59.09 | P81: 54.54 | Q81: 69.99 | R81: 74.99 | Y81: 84.99 | Z81: 109.99
A82: Master Price Level AU.csv | B82: ADONIT | C82: ADCIPB110 | D82: ADONIT iPad Case 11" 1st, 2nd, 3rd Gen | E82: Inactive | F82: 59.99 | G82: 29.99 | H82: 32.72 | I82: 38.18 | J82: 49.58 | K82: 32.72 | L82: 38.18 | M82: 40.9 | O82: 39.99 | Q82: 38.18 | Y82: 46.36 | Z82: 59.99
A83: Master Price Level AU.csv | B83: ADONIT | C83: ADCIPB129 | D83: ADONIT iPad Case 12.9" 3rd, 4th, 5th Gen | E83: Inactive | F83: 64.99 | G83: 29.99 | H83: 35.45 | I83: 41.36 | J83: 53.71 | K83: 35.45 | L83: 41.36 | M83: 44.31 | O83: 47.27 | Q83: 41.36 | Y83: 50.22 | Z83: 64.99
A84: Master Price Level AU.csv | B84: ADONIT | C84: ADJD3B | D84: ADONIT Jot Dash 3 (Black) | E84: Inactive | F84: 109.99 | G84: 79.99 | H84: 59.99 | I84: 69.99 | J84: 89.99 | K84: 59.99 | L84: 58 | M84: 64.99 | O84: 59.09 | P84: 54.54 | Q84: 57 | R84: 75.76
A85: Master Price Level AU.csv | B85: ADONIT | C85: ADJD3BR | D85: ADONIT Jot Dash 3 (Bronze) | E85: Inactive | F85: 109.99 | G85: 79.99 | H85: 59.99 | I85: 69.99 | J85: 89.99 | K85: 59.99 | L85: 58 | M85: 64.99 | O85: 59.09 | P85: 54.54 | Q85: 57 | R85: 75.76 | Y85: 84.99 | Z85: 109.99
A86: Master Price Level AU.csv | B86: ADONIT | C86: ARDCH | D86: ADONIT Jot Dash USB Charger | E86: Inactive | F86: 29.99 | G86: 29.99 | H86: 19.08 | I86: 19.08 | J86: 24.54 | K86: 19.08 | L86: 21.81 | M86: 15.9 | O86: 18.17 | Q86: 21.27 | R86: 20.38 | Y86: 23.17 | Z86: 29.99
A87: Master Price Level AU.csv | B87: ADONIT | C87: ADMB | D87: ADONIT Mark (Black) | E87: Active | F87: 29.99 | G87: 29.99 | H87: 16.36 | I87: 19.08 | J87: 24.54 | K87: 16.36 | L87: 16.36 | M87: 16.36 | O87: 16.54 | P87: 13.63 | Q87: 16.36 | R87: 20.45 | Y87: 23.17 | Z87: 29.99
A88: Master Price Level AU.csv | B88: ADONIT | C88: ADMS | D88: ADONIT Mark (Silver) | E88: Active | F88: 29.99 | G88: 29.99 | H88: 16.36 | I88: 19.08 | J88: 24.54 | K88: 16.36 | L88: 16.36 | M88: 16.36 | O88: 16.54 | P88: 13.63 | Q88: 16.36 | R88: 20.45 | Y88: 23.17 | Z88: 29.99
A89: Master Price Level AU.csv | B89: ADONIT | C89: ADM4RB | D89: ADONIT Mini 4 (Blue) | E89: Active | F89: 39.99 | H89: 21.81 | I89: 25.45 | J89: 32.74 | K89: 25.45 | L89: 23.63 | M89: 23.63 | O89: 27.63 | P89: 18.18 | Q89: 21.81 | R89: 27.27 | Y89: 33.22 | Z89: 42.99
A90: Master Price Level AU.csv | B90: ADONIT | C90: ADM4DG | D90: ADONIT Mini 4 (Grey) | E90: Active | F90: 39.99 | H90: 21.81 | I90: 25.45 | J90: 32.74 | K90: 25.45 | L90: 23.63 | M90: 23.63 | O90: 27.63 | P90: 18.18 | Q90: 21.81 | R90: 27.27 | Y90: 33.22 | Z90: 42.99
A91: Master Price Level AU.csv | B91: ADONIT | C91: ADNEOG | D91: ADONIT NEO (Space Grey) | E91: Active | F91: 79.99 | H91: 43.63 | I91: 50.9 | J91: 66.11 | K91: 43.63 | L91: 47.27 | M91: 50.9 | O91: 58.17 | Q91: 50.9 | R91: 54.54
A92: Master Price Level AU.csv | B92: ADONIT | C92: ADNEOIB | D92: ADONIT NEO Ink Stylus (Black) | E92: Active | F92: 89.99 | H92: 49.09 | I92: 57.27 | J92: 73.37 | K92: 49.09 | L92: 53.18 | M92: 57.27 | O92: 65.45 | Q92: 57.27 | R92: 61.36
A93: Master Price Level AU.csv | B93: ADONIT | C93: ADNEOLBA | D93: ADONIT NEO Lite (Black) | E93: Inactive | F93: 59.99 | H93: 32.72 | I93: 38.18 | J93: 49.57 | K93: 32.72 | L93: 35.45 | M93: 35.45 | O93: 43.63 | P93: 30 | Q93: 34.09 | R93: 40.9
A94: Master Price Level AU.csv | B94: ADONIT | C94: ADNEOLS | D94: ADONIT NEO Lite (Silver) | E94: Inactive | F94: 59.99 | H94: 32.72 | I94: 38.18 | J94: 49.57 | K94: 32.72 | L94: 35.45 | M94: 35.45 | O94: 43.63 | P94: 30 | Q94: 34.09 | R94: 40.9
A95: Master Price Level AU.csv | B95: ADONIT | C95: ADNEOPG | D95: ADONIT NEO Pro (Space Grey) | E95: Inactive | F95: 99.99 | H95: 54.54 | I95: 63.63 | J95: 82.63 | K95: 54.54 | L95: 59.09 | M95: 63.63 | O95: 72.72 | Q95: 63.63 | R95: 68.18
A96: Master Price Level AU.csv | B96: ADONIT | C96: ADNB | D96: ADONIT Note (Black) | E96: Inactive | F96: 79.99 | H96: 43.63 | I96: 50.9 | J96: 65.44 | K96: 50.9 | L96: 47.27 | M96: 50.9 | O96: 58.17 | P96: 40 | Q96: 50.9 | R96: 47.27 | Y96: 61.81 | Z96: 79.99
A97: Master Price Level AU.csv | B97: ADONIT | C97: ADNSB | D97: ADONIT Note Plus (Black) | E97: Inactive | F97: 119.99 | G97: 89.99 | H97: 70.9 | I97: 76.36 | J97: 99.16 | K97: 70.9 | L97: 76.36 | M97: 87.27 | O97: 87.27 | Q97: 76.36 | R97: 70.9 | Y97: 92.72 | Z97: 119.99
A98: Master Price Level AU.csv | B98: ADONIT | C98: ADNT | D98: ADONIT Note Replacement Tips (3 Pack) | E98: Inactive | F98: 22.99 | G98: 22.99 | H98: 13.59 | I98: 14.63 | J98: 18.81 | K98: 13.59 | L98: 14.63 | M98: 15.68 | O98: 16.72 | Q98: 14.63 | R98: 18.17 | Y98: 17.77 | Z98: 22.99
A99: Master Price Level AU.csv | B99: ADONIT | C99: ADFIP109 | D99: ADONIT Paperfeel iPad Film 10.9" | E99: Inactive | F99: 54.99 | G99: 9.99 | H99: 29.99 | I99: 34.99 | J99: 45.45 | K99: 29.99 | L99: 34.99 | M99: 37.49 | O99: 39.99 | Q99: 34.99 | Y99: 42.49 | Z99: 54.99
A100: Master Price Level AU.csv | B100: ADONIT | C100: ADFIP110 | D100: ADONIT Paperfeel iPad Film 11" 1st, 2nd, 3rd Gen | E100: Inactive | F100: 54.99 | G100: 9.99 | H100: 29.99 | I100: 34.99 | J100: 45.45 | K100: 29.99 | L100: 34.99 | M100: 37.49 | O100: 39.99 | Q100: 34.99 | Y100: 42.49 | Z100: 54.99
A101: Master Price Level AU.csv | B101: ADONIT | C101: ADFIP129 | D101: ADONIT Paperfeel iPad Film 12.9" 3rd, 4th, 5th Gen | E101: Inactive | F101: 54.99 | G101: 9.99 | H101: 29.99 | I101: 34.99 | J101: 45.45 | K101: 29.99 | L101: 34.99 | M101: 37.49 | O101: 39.99 | Q101: 34.99 | Y101: 42.49 | Z101: 54.99
A102: Master Price Level AU.csv | B102: ADONIT | C102: ADP4B | D102: ADONIT Pro 4 (Black) | E102: Active | F102: 59.99 | H102: 32.72 | I102: 38.18 | J102: 49.11 | K102: 38.18 | L102: 35.45 | M102: 35.45 | O102: 45.81 | P102: 27.27 | Q102: 34.09 | R102: 40.9 | Y102: 48.67 | Z102: 62.99
A103: Master Price Level AU.csv | B103: ADONIT | C103: ADP4S | D103: ADONIT Pro 4 (Silver) | E103: Active | F103: 59.99 | H103: 32.72 | I103: 38.18 | J103: 49.11 | K103: 38.18 | L103: 35.45 | M103: 35.45 | O103: 45.81 | P103: 27.27 | Q103: 34.09 | R103: 40.9 | Y103: 48.67 | Z103: 62.99
A104: Master Price Level AU.csv | B104: ADONIT | C104: ADRDK | D104: ADONIT Replacement Disc Tip Mini 4 / Pro 3 / Pro 4 - 2 pack | E104: Active | F104: 27.99 | G104: 27.99 | H104: 15.27 | I104: 17.81 | J104: 22.9 | K104: 15.27 | L104: 15.27 | M104: 15.27 | O104: 18.17 | Q104: 15.27 | R104: 19.08 | Y104: 21.63 | Z104: 27.99
A105: Master Price Level AU.csv | B105: ADONIT | C105: ADMNR | D105: ADONIT Replacement Nib for AI-Vocal and Dash 4 (3 pack) | E105: Active | F105: 24.99 | H105: 15.9 | I105: 15.9 | J105: 20.45 | K105: 15.9 | L105: 15.9 | M105: 18.17 | O105: 18.17 | Q105: 15.9 | R105: 17.04 | Y105: 19.31 | Z105: 24.99
A106: Master Price Level AU.csv | B106: ADONIT | C106: ARD4CH | D106: ADONIT Replacement USB Charger for Dash 4 | E106: Active | F106: 29.99 | H106: 19.08 | I106: 19.08 | J106: 24.54 | K106: 19.08 | L106: 19.08 | M106: 21.81 | O106: 21.81 | Q106: 19.08 | R106: 20.45 | Y106: 23.17 | Z106: 29.99
A107: Master Price Level AU.csv | B107: ADONIT | C107: ADSE2B | D107: ADONIT SE 2 - Black | E107: Active | F107: 59.99 | H107: 32.72 | I107: 38.18 | K107: 32.72 | L107: 35.45 | M107: 35.45 | O107: 43.63 | P107: 27.27 | Q107: 38.18
A108: Master Price Level AU.csv | B108: ADONIT | C108: ADSE2PK | D108: ADONIT SE 2 - Pink | E108: Inactive | F108: 59.99 | H108: 32.72 | I108: 38.18 | L108: 35.45 | M108: 35.45 | O108: 43.63 | Q108: 38.18
A109: Master Price Level AU.csv | B109: ADONIT | C109: ADSE2W | D109: ADONIT SE 2 - White | E109: Active | F109: 59.99 | H109: 32.72 | I109: 38.18 | K109: 32.72 | L109: 35.45 | M109: 32.72 | O109: 43.63 | P109: 27.27 | Q109: 38.18
A110: Master Price Level AU.csv | B110: AIRTHINGS | C110: AT-960 | D110: AIRTHINGS View Plus | E110: EOL | F110: 399.99 | G110: 148 | H110: 272.72 | I110: 290.9 | J110: 327.26 | K110: 272.72 | L110: 305.27 | M110: 327.26 | O110: 290.9 | Q110: 290.9 | R110: 290.9 | S110: 254.54 | U110: 272.72
A111: Master Price Level AU.csv | B111: AIRTHINGS | C111: AT-980 | D111: AIRTHINGS View Pollution | E111: EOL | F111: 329.99 | G111: 48 | H111: 224.99 | I111: 239.99 | J111: 269.99 | K111: 224.99 | L111: 251.84 | M111: 269.99 | O111: 239.99 | Q111: 239.99 | R111: 239.99 | S111: 209.99 | U111: 239.99
A112: Master Price Level AU.csv | B112: AIRTHINGS | C112: AT-292 | D112: AIRTHINGS Wave Mini | E112: EOL | F112: 129.99 | G112: 38 | H112: 88.63 | I112: 94.54 | J112: 106.36 | K112: 88.63 | L112: 99.21 | M112: 106.36 | O112: 94.54 | Q112: 94.54 | R112: 94.54 | S112: 82.72 | U112: 88.63
A113: Master Price Level AU.csv | B113: AIRTHINGS | C113: AT-2910 | D113: AIRTHINGS Wave Plus | E113: EOL | F113: 329.99 | G113: 148 | H113: 224.99 | I113: 239.99 | J113: 269.99 | K113: 224.99 | L113: 251.84 | M113: 269.99 | O113: 239.99 | Q113: 239.99 | R113: 239.99 | S113: 209.99 | U113: 239.99
A114: Master Price Level AU.csv | B114: ANKER | C114: A1902T11 | D114: ANKER 100W Charging Base for ANKER Prime Power Bank | E114: Active | F114: 169.95 | M114: 92.7 | Q114: 84.98
A115: Master Price Level AU.csv | B115: ANKER | C115: A1388H11 | D115: ANKER 10K 22.5W Power Bank (Black) | E115: Active | F115: 59.95 | Q115: 29.98
A116: Master Price Level AU.csv | B116: ANKER | C116: A1384H11 | D116: ANKER 20K 30 W Power Bank (Black) | E116: Active | F116: 79.95 | Q116: 39.98
A117: Master Price Level AU.csv | B117: ANKER | C117: A2643T11 | D117: ANKER 313 Ace 2 45W Wall Charger | E117: Active | F117: 39.95 | Q117: 19.98
A118: Master Price Level AU.csv | B118: ANKER | C118: A8356H11 | D118: ANKER 332 5-in-1 USB-C Hub with 4K HDMI | E118: Active | F118: 69.95 | Q118: 34.98
A119: Master Price Level AU.csv | B119: ANKER | C119: A121BT41 | D119: ANKER Charger 100W with display (Silver) | E119: Active | F119: 119.95 | L119: 44.83
A120: Master Price Level AU.csv | B120: ANKER | C120: A2698T11 | D120: ANKER Charger 30W (Black) | E120: Active | F120: 34.95 | L120: 13.06
A121: Master Price Level AU.csv | B121: ANKER | C121: A2698T21 | D121: ANKER Charger 30W (White) | E121: Active | F121: 34.95 | L121: 13.06
A122: Master Price Level AU.csv | B122: ANKER | C122: B2148T11 | D122: ANKER GaNPrime 120W 3-Port Wall Charger with USB-C to USB-C Cable | E122: Active | F122: 159.95 | M122: 87.25 | Q122: 79.98
A123: Master Price Level AU.csv | B123: ANKER | C123: B2668T11 | D123: ANKER GaNPrime 65W 3-Port Wall Charger with USB-C to USB-C Cable | E123: Active | F123: 99.95 | M123: 54.52 | Q123: 49.98
A124: Master Price Level AU.csv | B124: ANKER | C124: A1654H11 | D124: ANKER MagGo 10K Magnetic Power Bank with Qi2 (Black) | E124: Active | F124: 149.95 | M124: 81.79
A125: Master Price Level AU.csv | B125: ANKER | C125: A1259H11 | D125: ANKER Nano 10K 30W Power Bank with Built-In USB-C Cable (Black) | E125: Active | F125: 99.95 | M125: 54.52
A126: Master Price Level AU.csv | B126: ANKER | C126: A2663T11 | D126: ANKER Nano II 65W | E126: Active | F126: 89.95 | M126: 49.06 | Q126: 44.98
A127: Master Price Level AU.csv | B127: ANKER | C127: A110DH11 | D127: ANKER Power Bank 10K, 22.5W, Built-In USB-C Cable (Black) | E127: Active | F127: 54.95 | L127: 20.54
A128: Master Price Level AU.csv | B128: ANKER | C128: A110EH11 | D128: ANKER Power Bank 20K, 22.5W, Built-In USB-C Cable (Black) | E128: Active | F128: 79.95 | L128: 29.88
A129: Master Price Level AU.csv | B129: ANKER | C129: A1681H12 | D129: ANKER Power Bank 20K,45W,Built-In Dual USB-C Cables (Black) | E129: Active | F129: 99.95 | L129: 37.35
A130: Master Price Level AU.csv | B130: ANKER | C130: A1681H32 | D130: ANKER Power Bank 20K,45W,Built-In Dual USB-C Cables (Blue) | E130: Active | F130: 99.95 | L130: 37.35
A131: Master Price Level AU.csv | B131: ANKER | C131: A1695H11 | D131: ANKER Power Bank 25K, 165W, Built-In and Retractable Cables (Black) | E131: Active | F131: 199.95 | L131: 74.73
A132: Master Price Level AU.csv | B132: ANKER | C132: A1695H41 | D132: ANKER Power Bank 25K, 165W, Built-In and Retractable Cables (Silver) | E132: Active | F132: 199.95 | L132: 74.73
A133: Master Price Level AU.csv | B133: ANKER | C133: A1335011 | D133: ANKER Prime 12K 130W Power Bank (Black) | E133: Active | F133: 169.95 | M133: 92.7 | Q133: 84.98
A134: Master Price Level AU.csv | B134: ANKER | C134: A1336011 | D134: ANKER Prime 20K 200W Power Bank (Black) | E134: Active | F134: 229.95 | M134: 125.43 | Q134: 114.98
A135: Master Price Level AU.csv | B135: ANKER | C135: A2345T41 | D135: ANKER Prime 250W GaN Desktop Charger | E135: Active | F135: 299.95 | Q135: 149.98
A136: Master Price Level AU.csv | B136: ANKER | C136: A1340011 | D136: ANKER Prime 27K 250W PD 3.1 Power Bank (Black? | E136: Active | F136: 299.95 | M136: 163.61 | Q136: 149.98
A137: Master Price Level AU.csv | B137: ANKI | C137: 000-00060 | D137: ANKI Cozmo Carry Case | E137: EOL | F137: 54.99 | G137: 19.99 | H137: 16.36 | I137: 16.36 | J137: 44.99 | K137: 16.36 | L137: 37.49 | M137: 48.18 | O137: 45.99 | Q137: 51.27 | R137: 51.27 | Y137: 42.49 | Z137: 54.99
A138: Master Price Level AU.csv | B138: ANKI | C138: 000-00078 | D138: ANKI Vector Space by Anki | E138: EOL | F138: 54.99 | G138: 14.99 | H138: 12.26 | I138: 12.26 | J138: 44.99 | K138: 12.26 | L138: 37.49 | M138: 54.47 | O138: 45.99 | Q138: 54.47 | R138: 54.47 | Y138: 42.49 | Z138: 54.99
A139: Master Price Level AU.csv | B139: ANKI | C139: POP_HN_COZMO | D139: COZMO Cardboard Display Unit | E139: EOL | F139: 1 | H139: 0.01 | M139: 0.01
A140: Master Price Level AU.csv | B140: BACKBONE | C140: BB-02-B-X | D140: Backbone One - Mobile Gaming Controller for Lightning (Xbox Edition) (Gen 1) | E140: Inactive | F140: 179.99 | H140: 130.9 | I140: 139.08 | J140: 155.45 | K140: 130.9 | L140: 151.5 | M140: 155.45 | O140: 147.26 | P140: 120.9 | Q140: 147.26 | R140: 147.26 | S140: 120.9 | Y140: 146.81 | Z140: 179.99
A141: Master Price Level AU.csv | B141: BENQ | C141: TK700STi | D141: BENQ 4K HDR Projector TK700STi | E141: Inactive | F141: 2599 | H141: 90 | V141: 2191.91 | W141: 2191.91 | X141: 2191.91 | Y141: 2191.91 | Z141: 2679
A142: Master Price Level AU.csv | B142: BENQ | C142: 9H.W49WT.WS7 | D142: BENQ ScreenBar Halo LED Monitor Light | E142: Inactive | F142: 249 | H142: 226.4 | V142: 203.73 | W142: 203.73 | X142: 203.73 | Y142: 203.73 | Z142: 249
A143: Master Price Level AU.csv | B143: BENQ | C143: 9H.W43WT.WQ1 | D143: BENQ ScreenBar Plus LED Monitor Light | E143: Active | F143: 209 | H143: 190 | V143: 171 | W143: 171 | X143: 171 | Y143: 171 | Z143: 209
A144: Master Price Level AU.csv | B144: BENQ | C144: 5J.W3P14.002 | D144: BENQ WiT Clamp | E144: Inactive | F144: 39 | H144: 35.5 | Y144: 31.91 | Z144: 39
A145: Master Price Level AU.csv | B145: BENQ | C145: 5J.W4414.011 | D145: BENQ WiT Floor Stand Extension | E145: Inactive | F145: 139 | H145: 126.4 | Y145: 113.73 | Z145: 139
A146: Master Price Level AU.csv | B146: BODUM | C146: 1801-16BD | D146: BODUM Assam Tea Press with Stainless Steel Filter 1L (Silver) | E146: Inactive | F146: 99.95 | G146: 99.95 | V146: 77.23 | W146: 72.69 | X146: 72.69 | Y146: 59.06 | Z146: 99.95
A147: Master Price Level AU.csv | B147: BODUM | C147: 1812-01BD | D147: BODUM Assam Tea Press with Stainless Steel Filter 500ml (Black) | E147: Inactive | F147: 59.95 | G147: 59.95 | V147: 46.33 | W147: 43.6 | X147: 43.6 | Y147: 35.43 | Z147: 59.95
A148: Master Price Level AU.csv | B148: BODUM | C148: 1807-16_BD | D148: BODUM Assam Tea Press with Stainless Steel Filter 500ml (Silver) | E148: Inactive | F148: 74.95 | G148: 74.95 | V148: 57.92 | W148: 54.51 | X148: 54.51 | Y148: 44.29 | Z148: 74.95
A149: Master Price Level AU.csv | B149: BODUM | C149: 10709-913AUS-3_BD | D149: BODUM Bistro 2 Slice Toaster 940W (Off-White) | E149: Inactive | G149: 94.95 | V149: 77.23 | W149: 77.23 | X149: 77.23 | Y149: 77.23 | Z149: 94.95
...

Sheet ST
A1: Code | B1: Description | C1: Brand | D1: Customer Name | E1: Customer Code | F1: 6wk avg | G1: SOH
A2: 000-00033 | B2: ANKI OVERDRIVE Expansion Car - Thermo | C2: ANKI | D2: AU - Amazon | E2: B00V6951LM
A3: 000-00037 | B3: ANKI OVERDRIVE Expansion Track - Collision Kit | C3: ANKI | D3: AU - Amazon | E3: B00V695HM0
A4: 000-00046 | B4: Anki OVERDRIVE Starter Kit | C4: ANKI | D4: AU - Amazon | E4: B0157Z3I7Y
A5: 000-00050 | B5: Anki OVERDRIVE Supertruck - X-52 Vehicle | C5: ANKI | D5: AU - Amazon | E5: B01FM8ZGPI
A6: 000-00060 | B6: ANKI Cozmo Carry Case | C6: ANKI | D6: AU - Amazon | E6: B073HTKFGV
A7: 000-00060 | B7: ANKI Cozmo Carry Case | C7: ANKI | D7: Harvey Norman
A8: 000-00067 | B8: ANKI Cozmo | C8: ANKI | D8: AU - Amazon | E8: B0747LZTM8
A9: 000-00068 | B9: ANKI OVERDRIVE Fast & Furious Starter Kit | C9: ANKI | D9: AU - Amazon | E9: B0747M487C
A10: 000-00078 | B10: ANKI Vector Space by Anki | C10: ANKI | D10: AU - Amazon | E10: B07G3QSX8G
A11: 000-00079 | B11: Anki Vector by Anki | C11: ANKI | D11: AU - Amazon | E11: B078T42JCM
A12: 010101AF000549 | B12: MOVA i10 Cordless Stick Vacuum | C12: MOVA | D12: AU - Amazon | E12: B0FN7GMLJP
A13: 010201AA000437 | B13: MOVA Z50 Ultra Wet and Dry Robotic Vacuum | C13: MOVA | D13: Harvey Norman | E13: Z50ULTRA | F13: -8 | G13: 15
A14: 010201AA000437 | B14: MOVA Z50 Ultra Wet and Dry Robotic Vacuum | C14: MOVA | D14: JB HIFI | E14: 811510 | F14: -4.3333333 | G14: 83
A15: 010201AA000488 | B15: MOVA V50 Ultra Wet and Dry Robotic Vacuum | C15: MOVA | D15: AU - Amazon | E15: B0FK4X713X | F15: 3.6666667 | G15: 0
A16: 010201AA000488 | B16: MOVA V50 Ultra Wet and Dry Robotic Vacuum | C16: MOVA | D16: Harvey Norman | E16: V50ULTRA | F16: 77.5 | G16: 23
A17: 010201AA000488 | B17: MOVA V50 Ultra Wet and Dry Robotic Vacuum | C17: MOVA | D17: JB HIFI | E17: 815708 | F17: 22.833333 | G17: 48
A18: 010201AA000795 | B18: MOVA Z60 Ultra Roller Wet and Dry Robotic Vacuum | C18: MOVA | D18: Harvey Norman | E18: Z60ULTRA | F18: 44.5 | G18: 1547
A19: 010201AA000795 | B19: MOVA Z60 Ultra Roller Wet and Dry Robotic Vacuum | C19: MOVA | D19: JB HIFI | E19: 842257 | F19: 24.833333 | G19: 485
A20: 010201AA000795 | B20: MOVA Z60 Ultra Roller Wet and Dry Robotic Vacuum | C20: MOVA | D20: AU - The Good Guys | F20: 8 | G20: 437
A21: 010201AA000984 | B21: MOVA S70 Roller Wet and Dry Vacuum | C21: MOVA | D21: Harvey Norman | E21: S70ROLLER | F21: 19.166667 | G21: 992
A22: 010201AA001014 | B22: MOVA S70 Pro Roller Wet and Dry Vacuum | C22: MOVA | D22: JB HIFI | E22: 890509 | F22: 1.1666667 | G22: 378
A23: 010201AA001014 | B23: MOVA S70 Pro Roller Wet and Dry Vacuum | C23: MOVA | D23: AU - The Good Guys | F23: 2.8333333 | G23: 571
A24: 010201AA001019 | B24: MOVA S70 Ultra Roller Wet and Dry Vacuum | C24: MOVA | D24: Harvey Norman | E24: S70ULTRAROLLER | F24: 14.166667 | G24: 528
A25: 010201AA001070 | B25: MOVA P70 Pro Ultra Wet and Dry Vacuum | C25: MOVA | D25: JB HIFI | E25: 890510 | F25: 1.8333333 | G25: 546
A26: 010204AA000643 | B26: MOVA P50 Pro Ultra Wet and Dry Robotic Vacuum | C26: MOVA | D26: JB HIFI | E26: 811511 | F26: 57.166667 | G26: 123
A27: 010204AA000727 | B27: MOVA P50 Ultra Wet and Dry Robotic Vacuum | C27: MOVA | D27: Harvey Norman | E27: P50ULTRA | F27: 1.1666667 | G27: -1
A28: 010204AA000891 | B28: MOVA E40 Ultra Robotic Vacuum | C28: MOVA | D28: AU - Amazon | E28: B0F9P8MW8P | F28: 0.66666667 | G28: 20
A29: 010204AA000891 | B29: MOVA E40 Ultra Robotic Vacuum | C29: MOVA | D29: AU - The Good Guys | F29: 44.333333 | G29: 447
A30: 010204AA001081 | B30: MOVA Mobius 60 Wet and Dry Robotic Vacuum | C30: MOVA | D30: Harvey Norman | E30: MOBIUS60 | F30: 10.333333 | G30: 164
A31: 010401AA000273 | B31: MOVA Shine 10 Hair Dryer - Silver | C31: MOVA | D31: AU - Amazon | E31: B0F7XSRBNV
A32: 010401AA000323 | B32: MOVA Shine 20 Hair Dryer - Gold | C32: MOVA | D32: Harvey Norman | E32: SHINE20GOLD | F32: 4.6666667 | G32: 384
A33: 010401AB000273 | B33: MOVA Shine 10 Hair Dryer - Gold | C33: MOVA | D33: AU - Amazon | E33: B0F12LH7TN | F33: 0.66666667 | G33: 5
A34: 010401AC000279 | B34: MOVA Flip 10 Hair Styler | C34: MOVA | D34: AU - Amazon | E34: B0FCFMHMXF | F34: 12.833333 | G34: 18
A35: 010403AE000024 | B35: MOVA Master 10 Hair Styler - Silver | C35: MOVA | D35: Harvey Norman | E35: MASTER10SILVER | F35: 6.5 | G35: 412
A36: 010403AN000024 | B36: MOVA Master 10 Hair Styler - Pink | C36: MOVA | D36: Harvey Norman | E36: MASTER10PINK | F36: 8.8333333 | G36: 175
A37: 010901AA000024 | B37: MOVA Robotic Lawn Mower 1000 | C37: MOVA | D37: AU - Amazon | E37: B0FN3XK7BY
A38: 010901AA000024 | B38: MOVA Robotic Lawn Mower 1000 | C38: MOVA | D38: Harvey Norman | E38: MRLM1000 | F38: 4.8333333 | G38: 226
A39: 010901AA000024 | B39: MOVA Robotic Lawn Mower 1000 | C39: MOVA | D39: JB HIFI | E39: 847872 | F39: 1 | G39: 3
A40: 010901AA000026 | B40: MOVA Robotic Lawn Mower 600 | C40: MOVA | D40: AU - Amazon | E40: B0FN3VZJLP
A41: 010901AA000026 | B41: MOVA Robotic Lawn Mower 600 | C41: MOVA | D41: Harvey Norman | E41: MRLM600 | F41: 1.5 | G41: 1
A42: 010901AA000026 | B42: MOVA Robotic Lawn Mower 600 | C42: MOVA | D42: JB HIFI | E42: 847873
A43: 010902AA000016 | B43: MOVA Diver A10 Robotic Pool Cleaner | C43: MOVA | D43: Harvey Norman | E43: DIVERA10 | F43: 3.1666667 | G43: 342
A44: 011102AA000032 | B44: MOVA M50 Ultra Wet and Dry Vacuum | C44: MOVA | D44: Harvey Norman | E44: M50ULTRA | F44: 7.3333333 | G44: 161
A45: 011106AA000047 | B45: MOVA X4 Pro Wet and Dry Vacuum | C45: MOVA | D45: AU - Amazon | E45: B0FVLC5HY8 | F45: 1.6666667 | G45: 9
A46: 011106AA000047 | B46: MOVA X4 Pro Wet and Dry Vacuum | C46: MOVA | D46: Harvey Norman | E46: X4PRO | F46: 23 | G46: 216
A47: 011106AA000047 | B47: MOVA X4 Pro Wet and Dry Vacuum | C47: MOVA | D47: JB HIFI | E47: 811512 | F47: 10.166667 | G47: 134
A48: 100039 | B48: BOLD Smart Cylinder Lock - SX-33 | C48: BOLD | D48: AU - Amazon | E48: B08HLXVP7Q
A49: 100196 | B49: BOLD Connect Control Hub | C49: BOLD | D49: AU - Amazon | E49: B08TQGMBM8
A50: 100343 | B50: BOLD Smart Cylinder Lock - SX-43 | C50: BOLD | D50: AU - Amazon | E50: B094W16KG6
A51: 100357 | B51: BOLD Smart Cylinder Lock - SX-35 | C51: BOLD | D51: AU - Amazon | E51: B094W5JCPP
A52: 100360 | B52: BOLD Smart Cylinder Lock - SX-45 | C52: BOLD | D52: AU - Amazon | E52: B094W4B4ZH
A53: 100398 | B53: BOLD Smart Cylinder Lock SX-33 + Bold Connect Control Hub | C53: BOLD | D53: AU - Amazon | E53: B08TR1C7CS
A54: 100405 | B54: NUKI Fob | C54: NUKI | D54: AU - Amazon | E54: B0791H69HP
A55: 100405 | B55: NUKI Fob | C55: NUKI | D55: Harvey Norman
A56: 101-1005P04 | B56: MOBILEPIXELS Duex Lite Grey - 12.5" | C56: MOBILE PIXELS | D56: JB HIFI | E56: 626749
A57: 101-1005P04 | B57: MOBILEPIXELS Duex Lite Grey - 12.5" | C57: MOBILE PIXELS | D57: AU - Officeworks | E57: MPDUEXLITG
A58: 101-1005P04 | B58: MOBILEPIXELS Duex Lite Grey - 12.5" | C58: MOBILE PIXELS | D58: Scorptec
A59: 101-1005P05 | B59: MOBILEPIXELS Duex Lite Navy - 12.5" | C59: MOBILE PIXELS | D59: JB HIFI | E59: 626753
A60: 101-1005P05 | B60: MOBILEPIXELS Duex Lite Navy - 12.5" | C60: MOBILE PIXELS | D60: Mwave | E60: AC61442
A61: 101-1005P05 | B61: MOBILEPIXELS Duex Lite Navy - 12.5" | C61: MOBILE PIXELS | D61: AU - Officeworks | E61: MPDUEXLITN
A62: 101-1005P05 | B62: MOBILEPIXELS Duex Lite Navy - 12.5" | C62: MOBILE PIXELS | D62: Scorptec
A63: 101-1006P01 | B63: MOBILEPIXELS Duex Plus - 13.3" | C63: MOBILE PIXELS | D63: JB HIFI | E63: 626757
A64: 101-1006P01 | B64: MOBILEPIXELS Duex Plus - 13.3" | C64: MOBILE PIXELS | D64: AU - Officeworks | E64: MPDUEXPLUS
A65: 101-1006P01 | B65: MOBILEPIXELS Duex Plus - 13.3" | C65: MOBILE PIXELS | D65: Scorptec
A66: 101-1007P01 | B66: MOBILEPIXELS Duex Max Blue - 14.1" | C66: MOBILE PIXELS | D66: JB HIFI | E66: 626761
A67: 101-1007P01 | B67: MOBILEPIXELS Duex Max Blue - 14.1" | C67: MOBILE PIXELS | D67: Mwave | E67: AC61443
A68: 101-1007P01 | B68: MOBILEPIXELS Duex Max Blue - 14.1" | C68: MOBILE PIXELS | D68: AU - Officeworks | E68: MPDUEXMAXB
A69: 101-1007P01 | B69: MOBILEPIXELS Duex Max Blue - 14.1" | C69: MOBILE PIXELS | D69: Scorptec
A70: 101-1007P04 | B70: MOBILEPIXELS Duex Max (Grey) - 14.1" | C70: MOBILE PIXELS | D70: JB HIFI | E70: 626765
A71: 101-1007P04 | B71: MOBILEPIXELS Duex Max (Grey) - 14.1" | C71: MOBILE PIXELS | D71: AU - Officeworks | E71: MPDUEXMAXG
A72: 101-1007P04 | B72: MOBILEPIXELS Duex Max (Grey) - 14.1" | C72: MOBILE PIXELS | D72: Scorptec
A73: 101-1008P01 | B73: MOBILEPIXELS Glance Pro - 15.6" | C73: MOBILE PIXELS | D73: JB HIFI | E73: 626769
A74: 101-1008P01 | B74: MOBILEPIXELS Glance Pro - 15.6" | C74: MOBILE PIXELS | D74: Mwave | E74: AC61445
A75: 101-1008P01 | B75: MOBILEPIXELS Glance Pro - 15.6" | C75: MOBILE PIXELS | D75: AU - Officeworks | E75: MPGLANCEPR
A76: 101-1008P01 | B76: MOBILEPIXELS Glance Pro - 15.6" | C76: MOBILE PIXELS | D76: WH Smith Australia
A77: 101-1009P01 | B77: MOBILEPIXELS Glance - 16" | C77: MOBILE PIXELS | D77: AU - Officeworks | E77: MP1009P01
A78: 101-1009P01 | B78: MOBILEPIXELS Glance - 16" | C78: MOBILE PIXELS | D78: Scorptec
A79: 101-1012P01 | B79: MOBILEPIXELS Glance Plus - 15.6" | C79: MOBILE PIXELS | D79: AU - Amazon | E79: B0C5MRVJCQ
A80: 101-1012P01 | B80: MOBILEPIXELS Glance Plus - 15.6" | C80: MOBILE PIXELS | D80: Mwave | E80: AC70958
A81: 101-1012P01 | B81: MOBILEPIXELS Glance Plus - 15.6" | C81: MOBILE PIXELS | D81: AU - Officeworks | E81: MP1012P01
A82: 101-1012P01 | B82: MOBILEPIXELS Glance Plus - 15.6" | C82: MOBILE PIXELS | D82: Scorptec
A83: 104179 | B83: TADO Smart AC Control V3+ | C83: TADO | D83: AU - Amazon | E83: B08GG6SXQB
A84: 104179 | B84: TADO Smart AC Control V3+ | C84: TADO | D84: JB HIFI | E84: 485150
A85: 104179 | B85: TADO Smart AC Control V3+ | C85: TADO | D85: AU - Officeworks | E85: MCTADOV3
A86: 106-1001P01 | B86: MOBILEPIXELS Black Magnets | C86: MOBILE PIXELS | D86: AU - Officeworks | E86: MBPIXBLK
A87: 106-1002P01 | B87: MOBILEPIXELS Silver Magnets | C87: MOBILE PIXELS | D87: AU - Officeworks | E87: MBPIXSLV
A88: 116-1001P03 | B88: Mobile Pixels Geminos T (FHD) Dual 24" Stacked Monitor | C88: MOBILE PIXELS | D88: Harvey Norman Online
A89: 116-1001P03 | B89: Mobile Pixels Geminos T (FHD) Dual 24" Stacked Monitor | C89: MOBILE PIXELS | D89: Mwave | E89: AC82708
A90: 116-1001P03 | B90: Mobile Pixels Geminos T (FHD) Dual 24" Stacked Monitor | C90: MOBILE PIXELS | D90: AU - Officeworks | E90: MPGEMINOST
A91: 116-1001P03 | B91: Mobile Pixels Geminos T (FHD) Dual 24" Stacked Monitor | C91: MOBILE PIXELS | D91: Scorptec
A92: 20010100001198 | B92: MOVA Dust Bag for E40 E50 P50 P70 S70 V50 Z60 and Mobius Series | C92: MOVA | D92: AU - Amazon | E92: B0FFH3ZX19 | F92: 0.83333333 | G92: 4
A93: 20010100001198 | B93: MOVA Dust Bag for E40 E50 P50 P70 S70 V50 Z60 and Mobius Series | C93: MOVA | D93: Harvey Norman | E93: MDBAGV50 | F93: 37.833333 | G93: 676
A94: 20010100001198 | B94: MOVA Dust Bag for E40 E50 P50 P70 S70 V50 Z60 and Mobius Series | C94: MOVA | D94: JB HIFI | E94: 815284 | F94: 17.666667 | G94: 366
A95: 20010100001198 | B95: MOVA Dust Bag for E40 E50 P50 P70 S70 V50 Z60 and Mobius Series | C95: MOVA | D95: AU - The Good Guys | F95: 3.6666667 | G95: 395
A96: 20010100001259 | B96: MOVA Dust Box Filter x2 for E40 E50 P50 P70 Series | C96: MOVA | D96: Harvey Norman | E96: MDBF2PKP50U | F96: 0.5 | G96: 7
A97: 20010100001259 | B97: MOVA Dust Box Filter x2 for E40 E50 P50 P70 Series | C97: MOVA | D97: AU - The Good Guys | F97: 0 | G97: 0
A98: 20010100001273 | B98: MOVA Mop Pad x4 for E40 E50 P V Series | C98: MOVA | D98: Harvey Norman | E98: MMOPPAD1PKV50 | F98: 5.1666667 | G98: 391
A99: 20010100001273 | B99: MOVA Mop Pad x4 for E40 E50 P V Series | C99: MOVA | D99: JB HIFI | E99: 815285 | F99: 0 | G99: 2
A100: 20010100001273 | B100: MOVA Mop Pad x4 for E40 E50 P V Series | C100: MOVA | D100: AU - The Good Guys | F100: 0 | G100: 0
...

Sheet Sell_Through
A1: Name | B1: Customer Code | C1: Display Name | D1: Brand | E1: AU Status | F1: Base Price | G1: Customer Name | H1: % vs SOH | I1: Status | J1: DC | K1: Bus. Online | L1: Retail | M1: WOS | N1: 6wk avg | O1: Retail Value | P1: SOH
A2: TS-2259 | B2: 632130 | C2: TWELVE SOUTH AirFly SE | D2: TWELVE SOUTH | E2: Active | F2: 59.99 | G2: JB Hifi | H2: 0.10210392 | I2: CURRENT | M2: 9.4079174 | N2: 484.16667 | O2: 28915 | P2: 4555
A3: ELK-80061-R | B3: 667276 | C3: BONELK USB-A to USB-C 3.0 Adapter - (Black) | D3: BONELK | E3: Active | F3: 15.99 | G3: JB Hifi | H3: 0.14341391 | I3: CURRENT | M3: 6.5208452 | N3: 291.83333 | O3: 4765 | P3: 1903
A4: ST-TAUCM | B4: 586300 | C4: SATECHI Aluminium USB-A to USB-C Adapter (Space Grey) | D4: SATECHI | E4: Active | F4: 17.99 | G4: JB Hifi | H4: 0.036031702 | I4: CURRENT | M4: 31.543353 | N4: 230.66667 | O4: 4839 | P4: 7276
A5: ELK-80062-R | B5: 667280 | C5: BONELK USB-C to USB-A 3.0 Adapter - (Black) | D5: BONELK | E5: Active | F5: 14.99 | G5: JB Hifi | H5: 0.21372549 | I5: CURRENT | M5: 4.1402214 | N5: 225.83333 | O5: 3433 | P5: 935
A6: ELK-80061-R | B6: ELK80061R | C6: BONELK USB-A to USB-C 3.0 Adapter - (Black) | D6: BONELK | E6: Active | F6: 15.99 | G6: AU - Officeworks | H6: 0.11336634 | J6: 1 | K6: 61 | L6: 1958 | M6: 9.6612642 | N6: 205.66667 | O6: 3454 | P6: 1987
A7: ELK-80079-R | B7: ELK80079R | C7: BONELK USB-C to USB-A 3.0 Adapter (Space Grey) | D7: BONELK | E7: Active | F7: 14.99 | G7: AU - Officeworks | H7: 0.20139501 | J7: 27 | K7: 40 | L7: 1068 | M7: 6.2977099 | N7: 218.33333 | O7: 3208 | P7: 1375
A8: ELK-80077-R | B8: ELK80077R | C8: BONELK USB-A to USB-C 3.0 Adapter (Space Grey) | D8: BONELK | E8: Active | F8: 15.99 | G8: AU - Officeworks | H8: 0.2009476 | J8: 21 | K8: 38 | L8: 1137 | M8: 4.8865979 | N8: 226.33333 | O8: 3326 | P8: 1106
A9: ELK-80019-R | B9: MELK80019R | C9: BONELK Long-Life USB-C to USB-A Adapter - 15cm (Space Grey) | D9: BONELK | E9: Active | F9: 19.99 | G9: AU - Officeworks | H9: 0.13857323 | J9: 19 | K9: 38 | L9: 999 | M9: 5.9895197 | N9: 190.83333 | O9: 3898 | P9: 1143
A10: ELK-80062-R | B10: ELK80062R | C10: BONELK USB-C to USB-A 3.0 Adapter - (Black) | D10: BONELK | E10: Active | F10: 14.99 | G10: AU - Officeworks | H10: 0.080778641 | J10: 13 | K10: 179 | L10: 2124 | M10: 14.996948 | N10: 163.83333 | O10: 2593 | P10: 2457
A11: ELK-80065-R | B11: 667278 | C11: BONELK USB-C to MicroSD/SD Adapter - (Black) | D11: BONELK | E11: Active | F11: 29.99 | G11: JB Hifi | H11: 0.25518462 | I11: CURRENT | M11: 3.3910806 | N11: 194.33333 | O11: 4439 | P11: 659
A12: ELK-05037-R | B12: ELK05037R | C12: BONELK Long-Life Easy Grip USB-A to USB-C Cable, 60W (2m) (Black) | D12: BONELK | E12: Active | F12: 22.99 | G12: AU - Officeworks | H12: 0.21020347 | J12: 16 | K12: 18 | L12: 523 | M12: 6.467433 | N12: 130.5 | O12: 3104 | P12: 844
A13: ELK-61007-R | B13: BK61007CB | C13: BONELK Slim Wireless Keyboard and Mouse Combo, KM-322 (Salmon) | D13: BONELK | E13: Active | F13: 39.99 | G13: AU - Officeworks | H13: 0.16307107 | J13: 42 | K13: 33 | L13: 713 | M13: 7.7021277 | N13: 117.5 | O13: 5199 | P13: 905
A14: TS-2010 | B14: 647952 | C14: TWELVE SOUTH AirFly Pro (Black) | D14: TWELVE SOUTH | E14: Active | F14: 89.99 | G14: JB Hifi | H14: 0.083937198 | I14: CURRENT | M14: 10.942731 | N14: 151.33333 | O14: 11519 | P14: 1656
A15: ELK-80075-R | B15: ELK80075R | C15: BONELK Long-Life USB-C to 3.5mm AUX Audio Adapter (Black) | D15: BONELK | E15: Active | F15: 14.99 | G15: AU - Officeworks | H15: 0.23854337 | J15: 24 | K15: 37 | L15: 550 | M15: 5.8921694 | N15: 129.83333 | O15: 1814 | P15: 765
A16: TW-1911 | B16: 403495 | C16: TWELVE SOUTH AirFly Pro (White) | D16: TWELVE SOUTH | E16: Active | F16: 89.99 | G16: JB Hifi | H16: 0.07930565 | I16: CURRENT | M16: 10.505364 | N16: 139.83333 | O16: 10799 | P16: 1469
A17: ELK-05010-R | B17: MELK05010R | C17: BONELK USB-C to HDMI Long Life Cable 1.5m (Black) | D17: BONELK | E17: Active | F17: 49.99 | G17: AU - Officeworks | H17: 0.11139833 | J17: 7 | K17: 112 | L17: 558 | M17: 9.7278912 | N17: 73.5 | O17: 5849 | P17: 715
A18: ELK-05033-R | B18: ELK05033R | C18: BONELK Long-Life Easy Grip USB-A to USB-C Cable, 60W 1.2m (Black) | D18: BONELK | E18: Active | F18: 17.99 | G18: AU - Officeworks | H18: 0.18969516 | J18: 16 | K18: 20 | L18: 467 | M18: 5.9918033 | N18: 122 | O18: 2069 | P18: 731
A19: ELK-80065-R | B19: ELK80065R | C19: BONELK USB-C to MicroSD/SD Adapter - (Black) | D19: BONELK | E19: Active | F19: 29.99 | G19: AU - Officeworks | H19: 0.11765897 | J19: 12 | K19: 22 | L19: 789 | M19: 8.8925081 | N19: 102.33333 | O19: 3299 | P19: 910
A20: ELK-05120-R | B20: 796020 | C20: BONELK Long-Life USB-C to HDMI Cable 1.5m (Black) | D20: BONELK | E20: Active | F20: 49.99 | G20: JB Hifi | H20: 0.088363955 | M20: 6.2459016 | N20: 122 | O20: 5199 | P20: 762
A21: PL2A-10-24 | B21: 750327 | C21: PAPERLIKE Screen Protector v2.1 for iPad Air 11" (M2, 2024) (2 Pack) | D21: PAPERLIKE | E21: Active | F21: 59.99 | G21: JB Hifi | H21: 0.10170658 | M21: 10.893553 | N21: 111.16667 | O21: 6119 | P21: 1211
A22: ELK-80072-R | B22: 749536 | C22: BONELK USB-C to MicroSD/SD Adapter - (White) | D22: BONELK | E22: Active | F22: 29.99 | G22: JB Hifi | H22: 0.17466411 | M22: 5.0257235 | N22: 103.66667 | O22: 3059 | P22: 521
A23: ELK-80036-R | B23: ELK80036R | C23: BONELK Long-Life USB-A to 4 Port USB 3.0 Slim Hub (Black) | D23: BONELK | E23: Active | F23: 39.99 | G23: AU - Officeworks | H23: 0.11906038 | J23: 20 | K23: 114 | L23: 799 | M23: 12.286169 | N23: 104.83333 | O23: 4079 | P23: 1288
A24: ELK-61012-R | B24: ELK61012R | C24: BONELK Slim Wireless Keyboard and Mouse Combo, KM-314 - Black | D24: BONELK | E24: Active | F24: 29.99 | G24: AU - Officeworks | H24: 0.12096774 | J24: 43 | K24: 66 | L24: 542 | M24: 8.8136273 | N24: 83.166667 | O24: 2999 | P24: 733
A25: PL2A-10-22 | B25: 618875 | C25: PAPERLIKE Screen Protector v2.1 for iPad 10.9" 10th Gen (2 Pack) | D25: PAPERLIKE | E25: Active | F25: 59.99 | G25: JB Hifi | H25: 0.1830254 | I25: CURRENT | M25: 4.9204545 | N25: 88 | O25: 5699 | P25: 433
A26: ELK-80036-R | B26: 514935 | C26: BONELK Long-Life USB-A to 4 Port USB 3.0 Slim Hub (Black) | D26: BONELK | E26: Active | F26: 39.99 | G26: JB Hifi | H26: 0.19303995 | I26: CURRENT | M26: 5.6408451 | N26: 94.666667 | O26: 3599 | P26: 534
A27: ELK-62018-R | B27: BK62018MCB | C27: BONELK Bluetooth/Wireless RGB 4D Mouse, 1200DPI, USB-C, M-270 (Black) | D27: BONELK | E27: Active | F27: 39.99 | G27: AU - Officeworks | H27: 0.056279743 | J27: 72 | K27: 116 | L27: 1423 | M27: 22.552239 | N27: 67 | O27: 3599 | P27: 1511
A28: ELK-80070-R | B28: 749534 | C28: BONELK USB-A to USB-C 3.0 Adapter - (White) | D28: BONELK | E28: Active | F28: 15.99 | G28: JB Hifi | H28: 0.1620935 | M28: 5.6121673 | N28: 87.666667 | O28: 1407 | P28: 492
A29: ELK-80044-R | B29: 593243 | C29: BONELK Long-Life 3in1 Multiport Hub - Black | D29: BONELK | E29: Active | F29: 59.99 | G29: JB Hifi | H29: 0.12075372 | I29: CURRENT | M29: 8.4484305 | N29: 74.333333 | O29: 5279 | P29: 628
A30: ELK-05013-R | B30: ELK05013R | C30: BONELK Display Port to Display Port Long Life Cable 3m (Black) | D30: BONELK | E30: Active | F30: 29.99 | G30: AU - Officeworks | H30: 0.10084839 | J30: 7 | K30: 27 | L30: 575 | M30: 10.151589 | N30: 68.166667 | O30: 2549 | P30: 692
A31: ST-MBAM2CL | B31: MGSTMBAMCL | C31: SATECHI Eco Hardshell Case for MacBook Air M2 & M3 (Clear) | D31: SATECHI | E31: Active | F31: 79.99 | G31: AU - Officeworks | H31: 0.068813131 | J31: 15 | K31: 33 | L31: 348 | M31: 6.9099526 | N31: 70.333333 | O31: 6719 | P31: 486
A32: ELK-80071-R | B32: 749535 | C32: BONELK USB-C to USB-A 3.0 Adapter - (White) | D32: BONELK | E32: Active | F32: 14.99 | G32: JB Hifi | H32: 0.15960452 | M32: 5.7717391 | N32: 92 | O32: 1244 | P32: 531
A33: ELK-80019-R | B33: 586311 | C33: BONELK Long-Life USB-C to USB-A Adapter - 15cm (Space Grey) | D33: BONELK | E33: Active | F33: 19.99 | G33: JB Hifi | H33: 0.17739274 | I33: CURRENT | M33: 6.0198675 | N33: 100.66667 | O33: 1639 | P33: 606
A34: ELK-61013-R | B34: ELK61013R | C34: BONELK Slim Wireless Keyboard and Mouse Combo, KM-314 - White | D34: BONELK | E34: Active | F34: 29.99 | G34: AU - Officeworks | H34: 0.14158879 | J34: 33 | K34: 37 | L34: 465 | M34: 8.2411348 | N34: 70.5 | O34: 2429 | P34: 581
A35: ELK-05030-R | B35: ELK05030R | C35: BONELK Long-Life Easy Grip USB-C to USB-C Cable, 100W 1.2m (Black) | D35: BONELK | E35: Active | F35: 19.99 | G35: AU - Officeworks | H35: 0.09803207 | J35: 9 | K35: 29 | L35: 648 | M35: 10.322418 | N35: 66.166667 | O35: 1619 | P35: 683
A36: ELK-80020-R | B36: 495308 | C36: BONELK Long-Life 3in1 Multiport Hub - Space Grey | D36: BONELK | E36: Active | F36: 59.99 | G36: JB Hifi | H36: 0.13642367 | I36: CURRENT | M36: 7.2667946 | N36: 86.833333 | O36: 4739 | P36: 631
A37: ELK-80076-R | B37: ELK80076R | C37: BONELK Long-Life USB-C to 3.5mm AUX Audio Adapter (White) | D37: BONELK | E37: Active | F37: 14.99 | G37: AU - Officeworks | H37: 0.13603791 | J37: 8 | K37: 74 | L37: 639 | M37: 10.551282 | N37: 78 | O37: 1184 | P37: 823
A38: ELK-05012-R | B38: ELK05012R | C38: BONELK Display Port to Display Port Long Life Cable 1.5m (Black) | D38: BONELK | E38: Active | F38: 24.99 | G38: AU - Officeworks | H38: 0.098564955 | J38: 25 | K38: 17 | L38: 620 | M38: 10.665072 | N38: 69.666667 | O38: 1924 | P38: 743
A39: ELK-70408-R | B39: MGELK70408 | C39: BONELK Elevate Laptop Stand (Black) | D39: BONELK | E39: Active | F39: 99.99 | G39: AU - Officeworks | H39: 0.10999618 | J39: 5 | K39: 97 | L39: 770 | M39: 12.380952 | N39: 84 | O39: 7599 | P39: 1040
A40: ELK-05034-R | B40: ELK05034R | C40: BONELK Long-Life Easy Grip USB-A to USB-C Cable, 60W 2m (White) | D40: BONELK | E40: Active | F40: 22.99 | G40: AU - Officeworks | H40: 0.10354423 | J40: 5 | K40: 39 | L40: 525 | M40: 8.6541176 | N40: 70.833333 | O40: 1747 | P40: 613
A41: TS-2259 | B41: B0BQZBMXD4 | C41: TWELVE SOUTH AirFly SE | D41: TWELVE SOUTH | E41: Active | F41: 59.99 | G41: AU - Amazon | H41: 0.50617284 | M41: 1.5804878 | N41: 68.333333 | O41: 4439 | P41: 108
A42: ELK-05035-R | B42: ELK05035R | C42: BONELK Long-Life Easy Grip USB-C to USB-C Right Angle Cable, 100W 2m - (Black) | D42: BONELK | E42: Active | F42: 27.99 | G42: AU - Officeworks | H42: 0.091822095 | J42: 17 | K42: 23 | L42: 657 | M42: 10.437956 | N42: 68.5 | O42: 2071 | P42: 715
A43: ELK-05032-R | B43: ELK05032R | C43: BONELK Long-Life Easy Grip USB-A to USB-C Cable, 60W 1.2m (White) | D43: BONELK | E43: Active | F43: 17.99 | G43: AU - Officeworks | H43: 0.13062652 | J43: 1 | K43: 23 | L43: 524 | M43: 8.2643923 | N43: 78.166667 | O43: 1313 | P43: 646
A44: ELK-05122-R | B44: 796022 | C44: BONELK Long-Life Display Port to Display Port Cable 1.5m (Black) | D44: BONELK | E44: Active | F44: 24.99 | G44: JB Hifi | H44: 0.060626703 | M44: 9.2521008 | N44: 79.333333 | O44: 1774 | P44: 734
A45: PL2A-10-22 | B45: PAPSCRN022 | C45: PAPERLIKE Screen Protector v2.1 for iPad 10.9" 10th Gen (2 Pack) | D45: PAPERLIKE | E45: Active | F45: 59.99 | G45: AU - Officeworks | H45: 0.19663167 | J45: 12 | K45: 19 | L45: 350 | M45: 4.229765 | N45: 63.833333 | O45: 4259 | P45: 270
A46: ELK-05036-R | B46: ELK05036R | C46: BONELK Long-Life Easy Grip USB-C to USB-C Right Angle Cable, 100W 3m - (Black) | D46: BONELK | E46: Active | F46: 32.99 | G46: AU - Officeworks | H46: 0.10030166 | J46: 9 | K46: 44 | L46: 610 | M46: 10.019002 | N46: 70.166667 | O46: 2342 | P46: 703
A47: ELK-61003-R | B47: BK61003KB | C47: BONELK Slim Bluetooth/RF Keyboard and Mouse Combo, KM-447 (Space Grey) | D47: BONELK | E47: Active | F47: 99.99 | G47: AU - Officeworks | H47: 0.1236352 | J47: 31 | K47: 21 | L47: 467 | M47: 9.8923513 | N47: 58.833333 | O47: 7099 | P47: 582
A48: ELK-80063-R | B48: 667284 | C48: BONELK USB-C to 4K HDMI Adapter - (Black) | D48: BONELK | E48: Active | F48: 39.99 | G48: JB Hifi | H48: 0.14212329 | I48: CURRENT | M48: 6.3021583 | N48: 69.5 | O48: 2799 | P48: 438
A49: ELK-61006-R | B49: BK61006KB | C49: BONELK Slim Wireless Keyboard and Mouse Combo, KM-322 (Teal) | D49: BONELK | E49: Active | F49: 39.99 | G49: AU - Officeworks | H49: 0.13065245 | J49: 28 | K49: 23 | L49: 465 | M49: 9.4684932 | N49: 60.833333 | O49: 2759 | P49: 576
A50: ELK-21727-R | B50: ELK21727R | C50: BONELK Long-Life 65W PD GaN Desktop Charger, in-built USB-C Cable 1.5m (Black) | D50: BONELK | E50: Active | F50: 79.99 | G50: AU - Officeworks | H50: 0.079962547 | J50: 15 | K50: 21 | L50: 409 | M50: 9.0956522 | N50: 57.5 | O50: 5519 | P50: 523
A51: ELK-04516-R | B51: ELK04516R | C51: BONELK Long-Life Easy Grip USB-C to USB-C Cable, 100W (3m) (Black) | D51: BONELK | E51: Active | F51: 32.99 | G51: AU - Officeworks | H51: 0.12395633 | J51: 10 | K51: 40 | L51: 469 | M51: 8.7797468 | N51: 65.833333 | O51: 2276 | P51: 578
A52: ELK-61004-R | B52: BK61004KB | C52: BONELK Slim Wireless Keyboard and Mouse Combo, KM-322 (Black) | D52: BONELK | E52: Active | F52: 39.99 | G52: AU - Officeworks | H52: 0.14762404 | J52: 17 | K52: 31 | L52: 429 | M52: 7.5930521 | N52: 67.166667 | O52: 2679 | P52: 510
A53: ELK-54001-R | B53: BON54001R | C53: BONELK Universal Tablet Case 9" - 11" (Black) | D53: BONELK | E53: Active | F53: 49.99 | G53: AU - Officeworks | H53: 0.082580645 | J53: 9 | K53: 28 | L53: 738 | M53: 11.684964 | N53: 69.833333 | O53: 3249 | P53: 816
A54: ELK-80078-R | B54: ELK80078R | C54: BONELK USB-C to MicroSD/SD Adapter (Space Grey) | D54: BONELK | E54: Active | F54: 29.99 | G54: AU - Officeworks | H54: 0.096550179 | J54: 11 | K54: 28 | L54: 705 | M54: 13.944134 | N54: 59.666667 | O54: 1949 | P54: 832
A55: ELK-80059-R | B55: 667272 | C55: BONELK Long-Life USB-C 4 in 1 Multiport Slim Hub (Black) | D55: BONELK | E55: Active | F55: 49.99 | G55: JB Hifi | H55: 0.12173784 | I55: CURRENT | M55: 9.0160428 | N55: 62.333333 | O55: 3099 | P55: 562
