Workbook

Sheet Promo Form
A1: New Zealand Claim Number | D1: Name of Promotion. | F1: Rebate | G1: 6 | R1: Rebate | S1: 6 | AD1: Rebate | AE1: 6 | AP1: Rebate | AQ1: 6 | BB1: Rebate | BC1: 6 | BN1: Rebate | BO1: 6 | BZ1: Rebate | CA1: 6
A2: Brand | F2: 0.24 | M2: Growth | N2: 0.2 | R2: =_xlfn.XLOOKUP(R$3,'Data Validation'!$A:$A,'Data Validation'!$B:$B) -> 0.203 | T2: JB HIFI | Y2: Growth | Z2: 0.2 | AD2: =_xlfn.XLOOKUP(AD$3,'Data Validation'!$A:$A,'Data Validation'!$B:$B) -> 0.17 | AK2: Growth | AL2: 0.2 | AP2: =_xlfn.XLOOKUP(AP$3,'Data Validation'!$A:$A,'Data Validation'!$B:$B) -> 0.05 | AW2: Growth | AX2: 0.2 | BB2: =_xlfn.XLOOKUP(BB$3,'Data Validation'!$A:$A,'Data Validation'!$B:$B) -> 0 | BI2: Growth | BJ2: 0.2 | BN2: =_xlfn.XLOOKUP(BN$3,'Data Validation'!$A:$A,'Data Validation'!$B:$B) -> 0 | BU2: Growth | BV2: 0.2 | BZ2: =_xlfn.XLOOKUP(BZ$3,'Data Validation'!$A:$A,'Data Validation'!$B:$B) -> 0 | CG2: Growth | CH2: 0.2
A3: Promo Date(s) | B3: =(B5-A5)/7 -> 2 | C3: Code | D3: Product Description | F3: Harvey Norman | G3: <-- Select | J3: =F3 -> Harvey Norman | R3: JB HIFI | S3: <-- Select | V3: =R3 -> JB HIFI | AD3: Harvey Norman | AE3: <-- Select | AH3: =AD3 -> Harvey Norman | AP3: PB Tech | AQ3: <-- Select | AT3: =AP3 -> PB Tech | BB3: Spare | BC3: <-- Select | BF3: =BB3 -> Spare | BN3: Spare | BO3: <-- Select | BR3: =BN3 -> Spare | BZ3: Spare | CA3: <-- Select | CD3: =BZ3 -> Spare
A4: From | B4: To | F4: Customer Code | G4: Retailer Buy ex | H4: Supplier Support | I4: MG Support | J4: Total Support | K4: End to End Standard Margin | L4: End to End Promo Margin | M4: 6wk Avg | N4: Expected Sales / Actual Sales | O4: Supplier Claim Amount | P4: MacGear Claim Amount | R4: Customer Code | S4: Retailer Buy ex | T4: Supplier Support | U4: MG Support | V4: Total Support | W4: End to End Standard Margin | X4: End to End Promo Margin | Y4: 6wk Avg | Z4: Expected Sales / Actual Sales | AA4: Supplier Claim Amount | AB4: MacGear Claim Amount | AD4: Customer Code | AE4: Retailer Buy ex | AF4: Supplier Support | AG4: MG Support | AH4: Total Support | AI4: End to End Standard Margin | AJ4: End to End Promo Margin | AK4: 6wk Avg | AL4: Expected Sales / Actual Sales | AM4: Supplier Claim Amount | AN4: MacGear Claim Amount | AP4: Customer Code | AQ4: Retailer Buy ex | AR4: Supplier Support | AS4: MG Support | AT4: Total Support | AU4: End to End Standard Margin | AV4: End to End Promo Margin | AW4: 6wk Avg | AX4: Expected Sales / Actual Sales | AY4: Supplier Claim Amount | AZ4: MacGear Claim Amount | BB4: Customer Code | BC4: Retailer Buy ex | BD4: Supplier Support | BE4: MG Support | BF4: Total Support | BG4: End to End Standard Margin | BH4: End to End Promo Margin | BI4: 6wk Avg | BJ4: Expected Sales / Actual Sales | BK4: Supplier Claim Amount | BL4: MacGear Claim Amount | BN4: Customer Code | BO4: Retailer Buy ex | BP4: Supplier Support | BQ4: MG Support | BR4: Total Support | BS4: End to End Standard Margin | BT4: End to End Promo Margin | BU4: 6wk Avg | BV4: Expected Sales / Actual Sales | BW4: Supplier Claim Amount | BX4: MacGear Claim Amount | BZ4: Customer Code | CA4: Retailer Buy ex | CB4: Supplier Support | CC4: MG Support | CD4: Total Support | CE4: End to End Standard Margin | CF4: End to End Promo Margin | CG4: 6wk Avg | CH4: Expected Sales / Actual Sales | CI4: Supplier Claim Amount | CJ4: MacGear Claim Amount | CL4: RRP Inc | CM4: Recommended Sale Inc | CN4: Recommended % Off | CO4: Recommended $ Off | CP4: Comments
A5: 45658 | B5: 45672 | C5: ADM4DG | D5: =IF(C5="", "",_xlfn.XLOOKUP(C5,'Master Price Level NZ'!B:B,'Master Price Level NZ'!C:C)) -> ADONIT Mini 4 (Grey) | G5: {=IFERROR(_xlfn.XLOOKUP($C5,Master_Price_Level_NZ[Code],INDEX(Master_Price_Level_NZ[], , MATCH('Promo Form'!F$3, Master_Price_Level_NZ[#Headers], 0))),"")} -> 24.34 | H5: =IFERROR(((G5)*$CN5)*F$39,"") -> 1.217 | I5: =IFERROR(((G5)*$CN5)*F$38,"") -> 1.217 | J5: =IFERROR(IF(H5+I5=0,"",H5+I5),"") -> 2.434 | K5: =IFERROR((($CL5/1.15)-(G5-(G5*F$2)))/($CL5/1.15),"") -> 0.46803801 | L5: =IFERROR((($CM5/1.15)+(H5+I5)-(G5-(G5*F$2)))/($CM5/1.15),"") -> 0.42254126 | M5: {=IFERROR( _xlfn.LET( _xlpm.result, INDEX(_xlfn._xlws.FILTER(ST[6wk avg], (ST[Code]=$C5)*(ST[Customer Name]=F$3), ""), 1), IF(_xlpm.result=0, "", _xlpm.result) ), "")} -> 7.5 | N5: =IFERROR(IF(CEILING(M5 + (M5 * $N$2), 1) = 0, "", CEILING(M5 + (M5 * $N$2), 1))*$B$3, "") -> 18 | O5: =IFERROR((N5*H5),"") -> 21.906 | P5: =IFERROR((N5*I5),"") -> 21.906 | R5: {=IFERROR(_xlfn._xlws.FILTER(#REF!,(#REF!=$C5) * (#REF!=R$3),"" ),"")} | S5: {=IFERROR(_xlfn.XLOOKUP($C5,Master_Price_Level_NZ[Code],INDEX(Master_Price_Level_NZ[], , MATCH('Promo Form'!R$3, Master_Price_Level_NZ[#Headers], 0))),"")} -> 24.34 | T5: =IFERROR(((S5)*$CN5)*R$39,"") -> 1.217 | U5: =IFERROR(((S5)*$CN5)*R$38,"") -> 1.217 | V5: =IFERROR(IF(T5+U5=0,"",T5+U5),"") -> 2.434 | W5: =IFERROR((($CL5/1.15)-(S5-(S5*R$2)))/($CL5/1.15),"") -> 0.44213986 | X5: =IFERROR((($CM5/1.15)+(T5+U5)-(S5-(S5*R$2)))/($CM5/1.15),"") -> 0.39016857 | Y5: {=IFERROR( _xlfn.LET( _xlpm.result, INDEX(_xlfn._xlws.FILTER(ST[6wk avg], (ST[Code]=$C5)*(ST[Customer Name]=R$3), ""), 1), IF(_xlpm.result=0, "", _xlpm.result) ), "")} | Z5: =IFERROR(IF(CEILING(Y5 + (Y5 * $Z$2), 1) = 0, "", CEILING(Y5 + (Y5 * $Z$2), 1))*$B$3, "") | AA5: =IFERROR((Z5*T5),"") | AB5: =IFERROR((Z5*U5),"") | AD5: {=IFERROR(_xlfn._xlws.FILTER(#REF!,(#REF!=$C5) * (#REF!=AD$3),"" ),"")} | AE5: {=IFERROR(_xlfn.XLOOKUP($C5,Master_Price_Level_NZ[Code],INDEX(Master_Price_Level_NZ[], , MATCH('Promo Form'!AD$3, Master_Price_Level_NZ[#Headers], 0))),"")} -> 24.34 | AF5: =IFERROR(((AE5)*$CN5)*AD$39,"") -> 1.217 | AG5: =IFERROR(((AE5)*$CN5)*AD$38,"") -> 1.217 | AH5: =IFERROR(IF(AF5+AG5=0,"",AF5+AG5),"") -> 2.434 | AI5: =IFERROR((($CL5/1.15)-(AE5-(AE5*AD$2)))/($CL5/1.15),"") -> 0.41904151 | AJ5: =IFERROR((($CM5/1.15)+(AF5+AG5)-(AE5-(AE5*AD$2)))/($CM5/1.15),"") -> 0.36129564 | AK5: {=IFERROR( _xlfn.LET( _xlpm.result, INDEX(_xlfn._xlws.FILTER(ST[6wk avg], (ST[Code]=$C5)*(ST[Customer Name]=AD$3), ""), 1), IF(_xlpm.result=0, "", _xlpm.result) ), "")} -> 7.5 | AL5: =IFERROR(IF(CEILING(AK5 + (AK5 * $AL$2), 1) = 0, "", CEILING(AK5 + (AK5 * $AL$2), 1))*$B$3, "") -> 18 | AM5: =IFERROR((AL5*AF5),"") -> 21.906 | AN5: =IFERROR((AL5*AG5),"") -> 21.906 | AP5: {=IFERROR(_xlfn._xlws.FILTER(#REF!,(#REF!=$C5) * (#REF!=AP$3),"" ),"")} | AQ5: {=IFERROR(_xlfn.XLOOKUP($C5,Master_Price_Level_NZ[Code],INDEX(Master_Price_Level_NZ[], , MATCH('Promo Form'!AP$3, Master_Price_Level_NZ[#Headers], 0))),"")} -> 20.86 | AR5: =IFERROR(((AQ5)*$CN5)*AP$39,"") -> 1.043 | AS5: =IFERROR(((AQ5)*$CN5)*AP$38,"") -> 1.043 | AT5: =IFERROR(IF(AR5+AS5=0,"",AR5+AS5),"") -> 2.086 | AU5: =IFERROR((($CL5/1.15)-(AQ5-(AQ5*AP$2)))/($CL5/1.15),"") -> 0.43011878 | AV5: =IFERROR((($CM5/1.15)+(AR5+AS5)-(AQ5-(AQ5*AP$2)))/($CM5/1.15),"") -> 0.36263285 | AW5: {=IFERROR( _xlfn.LET( _xlpm.result, INDEX(_xlfn._xlws.FILTER(ST[6wk avg], (ST[Code]=$C5)*(ST[Customer Name]=AP$3), ""), 1), IF(_xlpm.result=0, "", _xlpm.result) ), "")} -> 18.5 | AX5: =IFERROR(IF(CEILING(AW5 + (AW5 * $AX$2), 1) = 0, "", CEILING(AW5 + (AW5 * $AX$2), 1))*$B$3, "") -> 46 | AY5: =IFERROR((AX5*AR5),"") -> 47.978 | AZ5: =IFERROR((AX5*AS5),"") -> 47.978 | BB5: {=IFERROR(_xlfn._xlws.FILTER(#REF!,(#REF!=$C5) * (#REF!=BB$3),"" ),"")} | BC5: {=IFERROR(_xlfn.XLOOKUP($C5,Master_Price_Level_NZ[Code],INDEX(Master_Price_Level_NZ[], , MATCH('Promo Form'!BB$3, Master_Price_Level_NZ[#Headers], 0))),"")} | BD5: =IFERROR(((BC5)*$CN5)*BB$39,"") | BE5: =IFERROR(((BC5)*$CN5)*BB$38,"") | BF5: =IFERROR(IF(BD5+BE5=0,"",BD5+BE5),"") | BG5: =IFERROR((($CL5/1.15)-(BC5-(BC5*BB$2)))/($CL5/1.15),"") | BH5: =IFERROR((($CM5/1.15)+(BD5+BE5)-(BC5-(BC5*BB$2)))/($CM5/1.15),"") | BI5: {=IFERROR( _xlfn.LET( _xlpm.result, INDEX(_xlfn._xlws.FILTER(ST[6wk avg], (ST[Code]=$C5)*(ST[Customer Name]=BB$3), ""), 1), IF(_xlpm.result=0, "", _xlpm.result) ), "")} | BJ5: =IFERROR(IF(CEILING(BI5 + (BI5 * $BJ$2), 1) = 0, "", CEILING(BI5 + (BI5 * $BJ$2), 1))*$B$3, "") | BK5: =IFERROR((BJ5*BD5),"") | BL5: =IFERROR((BJ5*BE5),"") | BN5: {=IFERROR(_xlfn._xlws.FILTER(#REF!,(#REF!=$C5) * (#REF!=BN$3),"" ),"")} | BO5: {=IFERROR(_xlfn.XLOOKUP($C5,Master_Price_Level_NZ[Code],INDEX(Master_Price_Level_NZ[], , MATCH('Promo Form'!BN$3, Master_Price_Level_NZ[#Headers], 0))),"")} | BP5: =IFERROR(((BO5)*$CN5)*BN$39,"") | BQ5: =IFERROR(((BO5)*$CN5)*BN$38,"") | BR5: =IFERROR(IF(BP5+BQ5=0,"",BP5+BQ5),"") | BS5: =IFERROR((($CL5/1.15)-(BO5-(BO5*BN$2)))/($CL5/1.15),"") | BT5: =IFERROR((($CM5/1.15)+(BP5+BQ5)-(BO5-(BO5*BN$2)))/($CM5/1.15),"") | BU5: {=IFERROR( _xlfn.LET( _xlpm.result, INDEX(_xlfn._xlws.FILTER(ST[6wk avg], (ST[Code]=$C5)*(ST[Customer Name]=BN$3), ""), 1), IF(_xlpm.result=0, "", _xlpm.result) ), "")} | BV5: =IFERROR(IF(CEILING(BU5 + (BU5 * $BV$2), 1) = 0, "", CEILING(BU5 + (BU5 * $BV$2), 1))*$B$3, "") | BW5: =IFERROR((BV5*BP5),"") | BX5: =IFERROR((BV5*BQ5),"") | BZ5: {=IFERROR(_xlfn._xlws.FILTER(#REF!,(#REF!=$C5) * (#REF!=BZ$3),"" ),"")} | CA5: {=IFERROR(_xlfn.XLOOKUP($C5,Master_Price_Level_NZ[Code],INDEX(Master_Price_Level_NZ[], , MATCH('Promo Form'!BZ$3, Master_Price_Level_NZ[#Headers], 0))),"")} | CB5: =IFERROR(((CA5)*$CN5)*BZ$39,"") | CC5: =IFERROR(((CA5)*$CN5)*BZ$38,"") | CD5: =IFERROR(IF(CB5+CC5=0,"",CB5+CC5),"") | CE5: =IFERROR((($CL5/1.15)-(CA5-(CA5*BZ$2)))/($CL5/1.15),"") | CF5: =IFERROR((($CM5/1.1)+(CB5+CC5)-(CA5-(CA5*BZ$2)))/($CM5/1.1),"") | CG5: {=IFERROR( _xlfn.LET( _xlpm.result, INDEX(_xlfn._xlws.FILTER(ST[6wk avg], (ST[Code]=$C5)*(ST[Customer Name]=BZ$3), ""), 1), IF(_xlpm.result=0, "", _xlpm.result) ), "")} | CH5: =IFERROR(IF(CEILING(CG5 + (CG5 * $CH$2), 1) = 0, "", CEILING(CG5 + (CG5 * $CH$2), 1))*$B$3, "") | CI5: =IFERROR((CH5*CB5),"") | CJ5: =IFERROR((CH5*CC5),"") | CL5: =IFERROR(_xlfn.XLOOKUP(C5,Master_Price_Level_NZ[Code],Master_Price_Level_NZ[Base (RRP Inc)]),"") -> 39.99 | CM5: =IFERROR(CL5-(CL5*CN5),"") -> 31.992 | CN5: 0.2 | CO5: =IFERROR((CL5-CM5),"") -> 7.998
A6: =IF(C6="","",A5) | B6: =IF(C6="","",B5) | D6: =IF(C6="", "",_xlfn.XLOOKUP(C6,'Master Price Level NZ'!B:B,'Master Price Level NZ'!C:C)) | G6: {=IFERROR(_xlfn.XLOOKUP($C6,Master_Price_Level_NZ[Code],INDEX(Master_Price_Level_NZ[], , MATCH('Promo Form'!F$3, Master_Price_Level_NZ[#Headers], 0))),"")} | H6: =IFERROR(((G6)*$CN6)*F$39,"") | I6: =IFERROR(((G6)*$CN6)*F$38,"") | J6: =IFERROR(IF(H6+I6=0,"",H6+I6),"") | K6: =IFERROR((($CL6/1.15)-(G6-(G6*F$2)))/($CL6/1.15),"") | L6: =IFERROR((($CM6/1.15)+(H6+I6)-(G6-(G6*F$2)))/($CM6/1.15),"") | M6: {=IFERROR( _xlfn.LET( _xlpm.result, INDEX(_xlfn._xlws.FILTER(ST[6wk avg], (ST[Code]=$C6)*(ST[Customer Name]=F$3), ""), 1), IF(_xlpm.result=0, "", _xlpm.result) ), "")} | N6: =IFERROR(IF(CEILING(M6 + (M6 * $N$2), 1) = 0, "", CEILING(M6 + (M6 * $N$2), 1))*$B$3, "") | O6: =IFERROR((N6*H6),"") | P6: =IFERROR((N6*I6),"") | R6: {=IFERROR(_xlfn._xlws.FILTER(#REF!,(#REF!=$C6) * (#REF!=R$3),"" ),"")} | S6: {=IFERROR(_xlfn.XLOOKUP($C6,Master_Price_Level_NZ[Code],INDEX(Master_Price_Level_NZ[], , MATCH('Promo Form'!R$3, Master_Price_Level_NZ[#Headers], 0))),"")} | T6: =IFERROR(((S6)*$CN6)*R$39,"") | U6: =IFERROR(((S6)*$CN6)*R$38,"") | V6: =IFERROR(IF(T6+U6=0,"",T6+U6),"") | W6: =IFERROR((($CL6/1.15)-(S6-(S6*R$2)))/($CL6/1.15),"") | X6: =IFERROR((($CM6/1.15)+(T6+U6)-(S6-(S6*R$2)))/($CM6/1.15),"") | Y6: {=IFERROR( _xlfn.LET( _xlpm.result, INDEX(_xlfn._xlws.FILTER(ST[6wk avg], (ST[Code]=$C6)*(ST[Customer Name]=R$3), ""), 1), IF(_xlpm.result=0, "", _xlpm.result) ), "")} | Z6: =IFERROR(IF(CEILING(Y6 + (Y6 * $Z$2), 1) = 0, "", CEILING(Y6 + (Y6 * $Z$2), 1))*$B$3, "") | AA6: =IFERROR((Z6*T6),"") | AB6: =IFERROR((Z6*U6),"") | AD6: {=IFERROR(_xlfn._xlws.FILTER(#REF!,(#REF!=$C6) * (#REF!=AD$3),"" ),"")} | AE6: {=IFERROR(_xlfn.XLOOKUP($C6,Master_Price_Level_NZ[Code],INDEX(Master_Price_Level_NZ[], , MATCH('Promo Form'!AD$3, Master_Price_Level_NZ[#Headers], 0))),"")} | AF6: =IFERROR(((AE6)*$CN6)*AD$39,"") | AG6: =IFERROR(((AE6)*$CN6)*AD$38,"") | AH6: =IFERROR(IF(AF6+AG6=0,"",AF6+AG6),"") | AI6: =IFERROR((($CL6/1.15)-(AE6-(AE6*AD$2)))/($CL6/1.15),"") | AJ6: =IFERROR((($CM6/1.15)+(AF6+AG6)-(AE6-(AE6*AD$2)))/($CM6/1.15),"") | AK6: {=IFERROR( _xlfn.LET( _xlpm.result, INDEX(_xlfn._xlws.FILTER(ST[6wk avg], (ST[Code]=$C6)*(ST[Customer Name]=AD$3), ""), 1), IF(_xlpm.result=0, "", _xlpm.result) ), "")} | AL6: =IFERROR(IF(CEILING(AK6 + (AK6 * $AL$2), 1) = 0, "", CEILING(AK6 + (AK6 * $AL$2), 1))*$B$3, "") | AM6: =IFERROR((AL6*AF6),"") | AN6: =IFERROR((AL6*AG6),"") | AP6: {=IFERROR(_xlfn._xlws.FILTER(#REF!,(#REF!=$C6) * (#REF!=AP$3),"" ),"")} | AQ6: {=IFERROR(_xlfn.XLOOKUP($C6,Master_Price_Level_NZ[Code],INDEX(Master_Price_Level_NZ[], , MATCH('Promo Form'!AP$3, Master_Price_Level_NZ[#Headers], 0))),"")} | AR6: =IFERROR(((AQ6)*$CN6)*AP$39,"") | AS6: =IFERROR(((AQ6)*$CN6)*AP$38,"") | AT6: =IFERROR(IF(AR6+AS6=0,"",AR6+AS6),"") | AU6: =IFERROR((($CL6/1.15)-(AQ6-(AQ6*AP$2)))/($CL6/1.15),"") | AV6: =IFERROR((($CM6/1.15)+(AR6+AS6)-(AQ6-(AQ6*AP$2)))/($CM6/1.15),"") | AW6: {=IFERROR( _xlfn.LET( _xlpm.result, INDEX(_xlfn._xlws.FILTER(ST[6wk avg], (ST[Code]=$C6)*(ST[Customer Name]=AP$3), ""), 1), IF(_xlpm.result=0, "", _xlpm.result) ), "")} | AX6: =IFERROR(IF(CEILING(AW6 + (AW6 * $AX$2), 1) = 0, "", CEILING(AW6 + (AW6 * $AX$2), 1))*$B$3, "") | AY6: =IFERROR((AX6*AR6),"") | AZ6: =IFERROR((AX6*AS6),"") | BB6: {=IFERROR(_xlfn._xlws.FILTER(#REF!,(#REF!=$C6) * (#REF!=BB$3),"" ),"")} | BC6: {=IFERROR(_xlfn.XLOOKUP($C6,Master_Price_Level_NZ[Code],INDEX(Master_Price_Level_NZ[], , MATCH('Promo Form'!BB$3, Master_Price_Level_NZ[#Headers], 0))),"")} | BD6: =IFERROR(((BC6)*$CN6)*BB$39,"") | BE6: =IFERROR(((BC6)*$CN6)*BB$38,"") | BF6: =IFERROR(IF(BD6+BE6=0,"",BD6+BE6),"") | BG6: =IFERROR((($CL6/1.15)-(BC6-(BC6*BB$2)))/($CL6/1.15),"") | BH6: =IFERROR((($CM6/1.15)+(BD6+BE6)-(BC6-(BC6*BB$2)))/($CM6/1.15),"") | BI6: {=IFERROR( _xlfn.LET( _xlpm.result, INDEX(_xlfn._xlws.FILTER(ST[6wk avg], (ST[Code]=$C6)*(ST[Customer Name]=BB$3), ""), 1), IF(_xlpm.result=0, "", _xlpm.result) ), "")} | BJ6: =IFERROR(IF(CEILING(BI6 + (BI6 * $BJ$2), 1) = 0, "", CEILING(BI6 + (BI6 * $BJ$2), 1))*$B$3, "") | BK6: =IFERROR((BJ6*BD6),"") | BL6: =IFERROR((BJ6*BE6),"") | BN6: {=IFERROR(_xlfn._xlws.FILTER(#REF!,(#REF!=$C6) * (#REF!=BN$3),"" ),"")} | BO6: {=IFERROR(_xlfn.XLOOKUP($C6,Master_Price_Level_NZ[Code],INDEX(Master_Price_Level_NZ[], , MATCH('Promo Form'!BN$3, Master_Price_Level_NZ[#Headers], 0))),"")} | BP6: =IFERROR(((BO6)*$CN6)*BN$39,"") | BQ6: =IFERROR(((BO6)*$CN6)*BN$38,"") | BR6: =IFERROR(IF(BP6+BQ6=0,"",BP6+BQ6),"") | BS6: =IFERROR((($CL6/1.15)-(BO6-(BO6*BN$2)))/($CL6/1.15),"") | BT6: =IFERROR((($CM6/1.15)+(BP6+BQ6)-(BO6-(BO6*BN$2)))/($CM6/1.15),"") | BU6: {=IFERROR( _xlfn.LET( _xlpm.result, INDEX(_xlfn._xlws.FILTER(ST[6wk avg], (ST[Code]=$C6)*(ST[Customer Name]=BN$3), ""), 1), IF(_xlpm.result=0, "", _xlpm.result) ), "")} | BV6: =IFERROR(IF(CEILING(BU6 + (BU6 * $BV$2), 1) = 0, "", CEILING(BU6 + (BU6 * $BV$2), 1))*$B$3, "") | BW6: =IFERROR((BV6*BP6),"") | BX6: =IFERROR((BV6*BQ6),"") | BZ6: {=IFERROR(_xlfn._xlws.FILTER(#REF!,(#REF!=$C6) * (#REF!=BZ$3),"" ),"")} | CA6: {=IFERROR(_xlfn.XLOOKUP($C6,Master_Price_Level_NZ[Code],INDEX(Master_Price_Level_NZ[], , MATCH('Promo Form'!BZ$3, Master_Price_Level_NZ[#Headers], 0))),"")} | CB6: =IFERROR(((CA6)*$CN6)*BZ$39,"") | CC6: =IFERROR(((CA6)*$CN6)*BZ$38,"") | CD6: =IFERROR(IF(CB6+CC6=0,"",CB6+CC6),"") | CE6: =IFERROR((($CL6/1.15)-(CA6-(CA6*BZ$2)))/($CL6/1.15),"") | CF6: =IFERROR((($CM6/1.1)+(CB6+CC6)-(CA6-(CA6*BZ$2)))/($CM6/1.1),"") | CG6: {=IFERROR( _xlfn.LET( _xlpm.result, INDEX(_xlfn._xlws.FILTER(ST[6wk avg], (ST[Code]=$C6)*(ST[Customer Name]=BZ$3), ""), 1), IF(_xlpm.result=0, "", _xlpm.result) ), "")} | CH6: =IFERROR(IF(CEILING(CG6 + (CG6 * $CH$2), 1) = 0, "", CEILING(CG6 + (CG6 * $CH$2), 1))*$B$3, "") | CI6: =IFERROR((CH6*CB6),"") | CJ6: =IFERROR((CH6*CC6),"") | CL6: =IFERROR(_xlfn.XLOOKUP(C6,Master_Price_Level_NZ[Code],Master_Price_Level_NZ[Base (RRP Inc)]),"") | CM6: =IFERROR(CL6-(CL6*CN6),"") | CN6: =IF(C6="", "",CN5) | CO6: =IFERROR((CL6-CM6),"")
A7: =IF(C7="","",A6) | B7: =IF(C7="","",B6) | D7: =IF(C7="", "",_xlfn.XLOOKUP(C7,'Master Price Level NZ'!B:B,'Master Price Level NZ'!C:C)) | G7: {=IFERROR(_xlfn.XLOOKUP($C7,Master_Price_Level_NZ[Code],INDEX(Master_Price_Level_NZ[], , MATCH('Promo Form'!F$3, Master_Price_Level_NZ[#Headers], 0))),"")} | H7: =IFERROR(((G7*(1-F$2))*$CN7)*F$39,"") | I7: =IFERROR(((G7*(1-F$2))*$CN7)*F$38,"") | J7: =IFERROR(IF(H7+I7=0,"",H7+I7),"") | K7: =IFERROR((($CL7/1.15)-(G7-(G7*F$2)))/($CL7/1.15),"") | L7: =IFERROR((($CM7/1.15)+(H7+I7)-(G7-(G7*F$2)))/($CM7/1.15),"") | M7: {=IF($C7="","",IFERROR(_xlfn._xlws.FILTER(ST[6wk avg],(ST[Code]=$C7)*(ST[Customer Name]=F$3),""),""))} | N7: =IFERROR(IF(CEILING(M7 + (M7 * $N$2), 1) = 0, "", CEILING(M7 + (M7 * $N$2), 1))*$B$3, "") | O7: =IFERROR((N7*H7),"") | P7: =IFERROR((N7*I7),"") | R7: {=IFERROR(_xlfn._xlws.FILTER(#REF!,(#REF!=$C7) * (#REF!=R$3),"" ),"")} | S7: {=IFERROR(_xlfn.XLOOKUP($C7,Master_Price_Level_NZ[Code],INDEX(Master_Price_Level_NZ[], , MATCH('Promo Form'!R$3, Master_Price_Level_NZ[#Headers], 0))),"")} | T7: =IFERROR(((S7*(1-R$2))*$CN7)*R$39,"") | U7: =IFERROR(((S7*(1-R$2))*$CN7)*R$38,"") | V7: =IFERROR(IF(T7+U7=0,"",T7+U7),"") | W7: =IFERROR((($CL7/1.15)-(S7-(S7*R$2)))/($CL7/1.15),"") | X7: =IFERROR((($CM7/1.15)+(T7+U7)-(S7-(S7*R$2)))/($CM7/1.15),"") | Y7: {=IFERROR( _xlfn.LET( _xlpm.result, INDEX(_xlfn._xlws.FILTER(ST[6wk avg], (ST[Code]=$C7)*(ST[Customer Name]=R$3), ""), 1), IF(_xlpm.result=0, "", _xlpm.result) ), "")} | Z7: =IFERROR(IF(CEILING(Y7 + (Y7 * $N$2), 1) = 0, "", CEILING(Y7 + (Y7 * $N$2), 1))*$B$3, "") | AA7: =IFERROR((Z7*T7),"") | AB7: =IFERROR((Z7*U7),"") | AD7: {=IFERROR(_xlfn._xlws.FILTER(#REF!,(#REF!=$C7) * (#REF!=AD$3),"" ),"")} | AE7: {=IFERROR(_xlfn.XLOOKUP($C7,Master_Price_Level_NZ[Code],INDEX(Master_Price_Level_NZ[], , MATCH('Promo Form'!AD$3, Master_Price_Level_NZ[#Headers], 0))),"")} | AF7: =IFERROR(((AE7*(1-AD$2))*$CN7)*AD$39,"") | AG7: =IFERROR(((AE7*(1-AD$2))*$CN7)*AD$38,"") | AH7: =IFERROR(IF(AF7+AG7=0,"",AF7+AG7),"") | AI7: =IFERROR((($CL7/1.15)-(AE7-(AE7*AD$2)))/($CL7/1.15),"") | AJ7: =IFERROR((($CM7/1.15)+(AF7+AG7)-(AE7-(AE7*AD$2)))/($CM7/1.15),"") | AK7: {=IFERROR( _xlfn.LET( _xlpm.result, INDEX(_xlfn._xlws.FILTER(ST[6wk avg], (ST[Code]=$C7)*(ST[Customer Name]=AD$3), ""), 1), IF(_xlpm.result=0, "", _xlpm.result) ), "")} | AL7: =IFERROR(IF(CEILING(AK7 + (AK7 * $N$2), 1) = 0, "", CEILING(AK7 + (AK7 * $N$2), 1))*$B$3, "") | AM7: =IFERROR((AL7*AF7),"") | AN7: =IFERROR((AL7*AG7),"") | AP7: {=IFERROR(_xlfn._xlws.FILTER(#REF!,(#REF!=$C7) * (#REF!=AP$3),"" ),"")} | AQ7: {=IFERROR(_xlfn.XLOOKUP($C7,Master_Price_Level_NZ[Code],INDEX(Master_Price_Level_NZ[], , MATCH('Promo Form'!AP$3, Master_Price_Level_NZ[#Headers], 0))),"")} | AR7: =IFERROR(((AQ7*(1-AP$2))*$CN7)*AP$39,"") | AS7: =IFERROR(((AQ7*(1-AP$2))*$CN7)*AP$38,"") | AT7: =IFERROR(IF(AR7+AS7=0,"",AR7+AS7),"") | AU7: =IFERROR((($CL7/1.15)-(AQ7-(AQ7*AP$2)))/($CL7/1.15),"") | AV7: =IFERROR((($CM7/1.15)+(AR7+AS7)-(AQ7-(AQ7*AP$2)))/($CM7/1.15),"") | AW7: {=IFERROR( _xlfn.LET( _xlpm.result, INDEX(_xlfn._xlws.FILTER(ST[6wk avg], (ST[Code]=$C7)*(ST[Customer Name]=AP$3), ""), 1), IF(_xlpm.result=0, "", _xlpm.result) ), "")} | AX7: =IFERROR(IF(CEILING(AW7 + (AW7 * $N$2), 1) = 0, "", CEILING(AW7 + (AW7 * $N$2), 1))*$B$3, "") | AY7: =IFERROR((AX7*AR7),"") | AZ7: =IFERROR((AX7*AS7),"") | BB7: {=IFERROR(_xlfn._xlws.FILTER(#REF!,(#REF!=$C7) * (#REF!=BB$3),"" ),"")} | BC7: {=IFERROR(_xlfn.XLOOKUP($C7,Master_Price_Level_NZ[Code],INDEX(Master_Price_Level_NZ[], , MATCH('Promo Form'!BB$3, Master_Price_Level_NZ[#Headers], 0))),"")} | BD7: =IFERROR(((BC7*(1-BB$2))*$CN7)*BB$39,"") | BE7: =IFERROR(((BC7*(1-BB$2))*$CN7)*BB$38,"") | BF7: =IFERROR(IF(BD7+BE7=0,"",BD7+BE7),"") | BG7: =IFERROR((($CL7/1.15)-(BC7-(BC7*BB$2)))/($CL7/1.15),"") | BH7: =IFERROR((($CM7/1.15)+(BD7+BE7)-(BC7-(BC7*BB$2)))/($CM7/1.15),"") | BI7: {=IFERROR( _xlfn.LET( _xlpm.result, INDEX(_xlfn._xlws.FILTER(ST[6wk avg], (ST[Code]=$C7)*(ST[Customer Name]=BB$3), ""), 1), IF(_xlpm.result=0, "", _xlpm.result) ), "")} | BJ7: =IFERROR(IF(CEILING(BI7 + (BI7 * $N$2), 1) = 0, "", CEILING(BI7 + (BI7 * $N$2), 1))*$B$3, "") | BK7: =IFERROR((BJ7*BD7),"") | BL7: =IFERROR((BJ7*BE7),"") | BN7: {=IFERROR(_xlfn._xlws.FILTER(#REF!,(#REF!=$C7) * (#REF!=BN$3),"" ),"")} | BO7: {=IFERROR(_xlfn.XLOOKUP($C7,Master_Price_Level_NZ[Code],INDEX(Master_Price_Level_NZ[], , MATCH('Promo Form'!BN$3, Master_Price_Level_NZ[#Headers], 0))),"")} | BP7: =IFERROR(((BO7*(1-BN$2))*$CN7)*BN$39,"") | BQ7: =IFERROR(((BO7*(1-BN$2))*$CN7)*BN$38,"") | BR7: =IFERROR(IF(BP7+BQ7=0,"",BP7+BQ7),"") | BS7: =IFERROR((($CL7/1.15)-(BO7-(BO7*BN$2)))/($CL7/1.15),"") | BT7: =IFERROR((($CM7/1.15)+(BP7+BQ7)-(BO7-(BO7*BN$2)))/($CM7/1.15),"") | BU7: {=IFERROR( _xlfn.LET( _xlpm.result, INDEX(_xlfn._xlws.FILTER(ST[6wk avg], (ST[Code]=$C7)*(ST[Customer Name]=BN$3), ""), 1), IF(_xlpm.result=0, "", _xlpm.result) ), "")} | BV7: =IFERROR(IF(CEILING(BU7 + (BU7 * $N$2), 1) = 0, "", CEILING(BU7 + (BU7 * $N$2), 1))*$B$3, "") | BW7: =IFERROR((BV7*BP7),"") | BX7: =IFERROR((BV7*BQ7),"") | BZ7: {=IFERROR(_xlfn._xlws.FILTER(#REF!,(#REF!=$C7) * (#REF!=BZ$3),"" ),"")} | CA7: {=IFERROR(_xlfn.XLOOKUP($C7,Master_Price_Level_NZ[Code],INDEX(Master_Price_Level_NZ[], , MATCH('Promo Form'!BZ$3, Master_Price_Level_NZ[#Headers], 0))),"")} | CB7: =IFERROR(((CA7*(1-BZ$2))*$CN7)*BZ$39,"") | CC7: =IFERROR(((CA7*(1-BZ$2))*$CN7)*BZ$38,"") | CD7: =IFERROR(IF(CB7+CC7=0,"",CB7+CC7),"") | CE7: =IFERROR((($CL7/1.15)-(CA7-(CA7*BZ$2)))/($CL7/1.15),"") | CF7: =IFERROR((($CM7/1.15)+(CB7+CC7)-(CA7-(CA7*BZ$2)))/($CM7/1.15),"") | CG7: {=IFERROR( _xlfn.LET( _xlpm.result, INDEX(_xlfn._xlws.FILTER(ST[6wk avg], (ST[Code]=$C7)*(ST[Customer Name]=BZ$3), ""), 1), IF(_xlpm.result=0, "", _xlpm.result) ), "")} | CH7: =IFERROR(IF(CEILING(CG7 + (CG7 * $N$2), 1) = 0, "", CEILING(CG7 + (CG7 * $N$2), 1))*$B$3, "") | CI7: =IFERROR((CH7*CB7),"") | CJ7: =IFERROR((CH7*CC7),"") | CL7: =IFERROR(_xlfn.XLOOKUP(C7,Master_Price_Level_NZ[Code],Master_Price_Level_NZ[Base (RRP Inc)]),"") | CM7: =IFERROR(CL7-(CL7*CN7),"") | CN7: =IF(C7="", "",CN6) | CO7: =IFERROR((CL7-CM7),"")
A8: =IF(C8="","",A7) | B8: =IF(C8="","",B7) | D8: =IF(C8="", "",_xlfn.XLOOKUP(C8,'Master Price Level NZ'!B:B,'Master Price Level NZ'!C:C)) | G8: {=IFERROR(_xlfn.XLOOKUP($C8,Master_Price_Level_NZ[Code],INDEX(Master_Price_Level_NZ[], , MATCH('Promo Form'!F$3, Master_Price_Level_NZ[#Headers], 0))),"")} | H8: =IFERROR(((G8*(1-F$2))*$CN8)*F$39,"") | I8: =IFERROR(((G8*(1-F$2))*$CN8)*F$38,"") | J8: =IFERROR(IF(H8+I8=0,"",H8+I8),"") | K8: =IFERROR((($CL8/1.15)-(G8-(G8*F$2)))/($CL8/1.15),"") | L8: =IFERROR((($CM8/1.15)+(H8+I8)-(G8-(G8*F$2)))/($CM8/1.15),"") | M8: {=IF($C8="","",IFERROR(_xlfn._xlws.FILTER(ST[6wk avg],(ST[Code]=$C8)*(ST[Customer Name]=F$3),""),""))} | N8: =IFERROR(IF(CEILING(M8 + (M8 * $N$2), 1) = 0, "", CEILING(M8 + (M8 * $N$2), 1))*$B$3, "") | O8: =IFERROR((N8*H8),"") | P8: =IFERROR((N8*I8),"") | R8: {=IFERROR(_xlfn._xlws.FILTER(#REF!,(#REF!=$C8) * (#REF!=R$3),"" ),"")} | S8: {=IFERROR(_xlfn.XLOOKUP($C8,Master_Price_Level_NZ[Code],INDEX(Master_Price_Level_NZ[], , MATCH('Promo Form'!R$3, Master_Price_Level_NZ[#Headers], 0))),"")} | T8: =IFERROR(((S8*(1-R$2))*$CN8)*R$39,"") | U8: =IFERROR(((S8*(1-R$2))*$CN8)*R$38,"") | V8: =IFERROR(IF(T8+U8=0,"",T8+U8),"") | W8: =IFERROR((($CL8/1.15)-(S8-(S8*R$2)))/($CL8/1.15),"") | X8: =IFERROR((($CM8/1.15)+(T8+U8)-(S8-(S8*R$2)))/($CM8/1.15),"") | Y8: {=IFERROR( _xlfn.LET( _xlpm.result, INDEX(_xlfn._xlws.FILTER(ST[6wk avg], (ST[Code]=$C8)*(ST[Customer Name]=R$3), ""), 1), IF(_xlpm.result=0, "", _xlpm.result) ), "")} | Z8: =IFERROR(IF(CEILING(Y8 + (Y8 * $N$2), 1) = 0, "", CEILING(Y8 + (Y8 * $N$2), 1))*$B$3, "") | AA8: =IFERROR((Z8*T8),"") | AB8: =IFERROR((Z8*U8),"") | AD8: {=IFERROR(_xlfn._xlws.FILTER(#REF!,(#REF!=$C8) * (#REF!=AD$3),"" ),"")} | AE8: {=IFERROR(_xlfn.XLOOKUP($C8,Master_Price_Level_NZ[Code],INDEX(Master_Price_Level_NZ[], , MATCH('Promo Form'!AD$3, Master_Price_Level_NZ[#Headers], 0))),"")} | AF8: =IFERROR(((AE8*(1-AD$2))*$CN8)*AD$39,"") | AG8: =IFERROR(((AE8*(1-AD$2))*$CN8)*AD$38,"") | AH8: =IFERROR(IF(AF8+AG8=0,"",AF8+AG8),"") | AI8: =IFERROR((($CL8/1.15)-(AE8-(AE8*AD$2)))/($CL8/1.15),"") | AJ8: =IFERROR((($CM8/1.15)+(AF8+AG8)-(AE8-(AE8*AD$2)))/($CM8/1.15),"") | AK8: {=IFERROR( _xlfn.LET( _xlpm.result, INDEX(_xlfn._xlws.FILTER(ST[6wk avg], (ST[Code]=$C8)*(ST[Customer Name]=AD$3), ""), 1), IF(_xlpm.result=0, "", _xlpm.result) ), "")} | AL8: =IFERROR(IF(CEILING(AK8 + (AK8 * $N$2), 1) = 0, "", CEILING(AK8 + (AK8 * $N$2), 1))*$B$3, "") | AM8: =IFERROR((AL8*AF8),"") | AN8: =IFERROR((AL8*AG8),"") | AP8: {=IFERROR(_xlfn._xlws.FILTER(#REF!,(#REF!=$C8) * (#REF!=AP$3),"" ),"")} | AQ8: {=IFERROR(_xlfn.XLOOKUP($C8,Master_Price_Level_NZ[Code],INDEX(Master_Price_Level_NZ[], , MATCH('Promo Form'!AP$3, Master_Price_Level_NZ[#Headers], 0))),"")} | AR8: =IFERROR(((AQ8*(1-AP$2))*$CN8)*AP$39,"") | AS8: =IFERROR(((AQ8*(1-AP$2))*$CN8)*AP$38,"") | AT8: =IFERROR(IF(AR8+AS8=0,"",AR8+AS8),"") | AU8: =IFERROR((($CL8/1.15)-(AQ8-(AQ8*AP$2)))/($CL8/1.15),"") | AV8: =IFERROR((($CM8/1.15)+(AR8+AS8)-(AQ8-(AQ8*AP$2)))/($CM8/1.15),"") | AW8: {=IFERROR( _xlfn.LET( _xlpm.result, INDEX(_xlfn._xlws.FILTER(ST[6wk avg], (ST[Code]=$C8)*(ST[Customer Name]=AP$3), ""), 1), IF(_xlpm.result=0, "", _xlpm.result) ), "")} | AX8: =IFERROR(IF(CEILING(AW8 + (AW8 * $N$2), 1) = 0, "", CEILING(AW8 + (AW8 * $N$2), 1))*$B$3, "") | AY8: =IFERROR((AX8*AR8),"") | AZ8: =IFERROR((AX8*AS8),"") | BB8: {=IFERROR(_xlfn._xlws.FILTER(#REF!,(#REF!=$C8) * (#REF!=BB$3),"" ),"")} | BC8: {=IFERROR(_xlfn.XLOOKUP($C8,Master_Price_Level_NZ[Code],INDEX(Master_Price_Level_NZ[], , MATCH('Promo Form'!BB$3, Master_Price_Level_NZ[#Headers], 0))),"")} | BD8: =IFERROR(((BC8*(1-BB$2))*$CN8)*BB$39,"") | BE8: =IFERROR(((BC8*(1-BB$2))*$CN8)*BB$38,"") | BF8: =IFERROR(IF(BD8+BE8=0,"",BD8+BE8),"") | BG8: =IFERROR((($CL8/1.15)-(BC8-(BC8*BB$2)))/($CL8/1.15),"") | BH8: =IFERROR((($CM8/1.15)+(BD8+BE8)-(BC8-(BC8*BB$2)))/($CM8/1.15),"") | BI8: {=IFERROR( _xlfn.LET( _xlpm.result, INDEX(_xlfn._xlws.FILTER(ST[6wk avg], (ST[Code]=$C8)*(ST[Customer Name]=BB$3), ""), 1), IF(_xlpm.result=0, "", _xlpm.result) ), "")} | BJ8: =IFERROR(IF(CEILING(BI8 + (BI8 * $N$2), 1) = 0, "", CEILING(BI8 + (BI8 * $N$2), 1))*$B$3, "") | BK8: =IFERROR((BJ8*BD8),"") | BL8: =IFERROR((BJ8*BE8),"") | BN8: {=IFERROR(_xlfn._xlws.FILTER(#REF!,(#REF!=$C8) * (#REF!=BN$3),"" ),"")} | BO8: {=IFERROR(_xlfn.XLOOKUP($C8,Master_Price_Level_NZ[Code],INDEX(Master_Price_Level_NZ[], , MATCH('Promo Form'!BN$3, Master_Price_Level_NZ[#Headers], 0))),"")} | BP8: =IFERROR(((BO8*(1-BN$2))*$CN8)*BN$39,"") | BQ8: =IFERROR(((BO8*(1-BN$2))*$CN8)*BN$38,"") | BR8: =IFERROR(IF(BP8+BQ8=0,"",BP8+BQ8),"") | BS8: =IFERROR((($CL8/1.15)-(BO8-(BO8*BN$2)))/($CL8/1.15),"") | BT8: =IFERROR((($CM8/1.15)+(BP8+BQ8)-(BO8-(BO8*BN$2)))/($CM8/1.15),"") | BU8: {=IFERROR( _xlfn.LET( _xlpm.result, INDEX(_xlfn._xlws.FILTER(ST[6wk avg], (ST[Code]=$C8)*(ST[Customer Name]=BN$3), ""), 1), IF(_xlpm.result=0, "", _xlpm.result) ), "")} | BV8: =IFERROR(IF(CEILING(BU8 + (BU8 * $N$2), 1) = 0, "", CEILING(BU8 + (BU8 * $N$2), 1))*$B$3, "") | BW8: =IFERROR((BV8*BP8),"") | BX8: =IFERROR((BV8*BQ8),"") | BZ8: {=IFERROR(_xlfn._xlws.FILTER(#REF!,(#REF!=$C8) * (#REF!=BZ$3),"" ),"")} | CA8: {=IFERROR(_xlfn.XLOOKUP($C8,Master_Price_Level_NZ[Code],INDEX(Master_Price_Level_NZ[], , MATCH('Promo Form'!BZ$3, Master_Price_Level_NZ[#Headers], 0))),"")} | CB8: =IFERROR(((CA8*(1-BZ$2))*$CN8)*BZ$39,"") | CC8: =IFERROR(((CA8*(1-BZ$2))*$CN8)*BZ$38,"") | CD8: =IFERROR(IF(CB8+CC8=0,"",CB8+CC8),"") | CE8: =IFERROR((($CL8/1.15)-(CA8-(CA8*BZ$2)))/($CL8/1.15),"") | CF8: =IFERROR((($CM8/1.15)+(CB8+CC8)-(CA8-(CA8*BZ$2)))/($CM8/1.15),"") | CG8: {=IFERROR( _xlfn.LET( _xlpm.result, INDEX(_xlfn._xlws.FILTER(ST[6wk avg], (ST[Code]=$C8)*(ST[Customer Name]=BZ$3), ""), 1), IF(_xlpm.result=0, "", _xlpm.result) ), "")} | CH8: =IFERROR(IF(CEILING(CG8 + (CG8 * $N$2), 1) = 0, "", CEILING(CG8 + (CG8 * $N$2), 1))*$B$3, "") | CI8: =IFERROR((CH8*CB8),"") | CJ8: =IFERROR((CH8*CC8),"") | CL8: =IFERROR(_xlfn.XLOOKUP(C8,Master_Price_Level_NZ[Code],Master_Price_Level_NZ[Base (RRP Inc)]),"") | CM8: =IFERROR(CL8-(CL8*CN8),"") | CN8: =IF(C8="", "",CN7) | CO8: =IFERROR((CL8-CM8),"")
A9: =IF(C9="","",A8) | B9: =IF(C9="","",B8) | D9: =IF(C9="", "",_xlfn.XLOOKUP(C9,'Master Price Level NZ'!B:B,'Master Price Level NZ'!C:C)) | G9: {=IFERROR(_xlfn.XLOOKUP($C9,Master_Price_Level_NZ[Code],INDEX(Master_Price_Level_NZ[], , MATCH('Promo Form'!F$3, Master_Price_Level_NZ[#Headers], 0))),"")} | H9: =IFERROR(((G9*(1-F$2))*$CN9)*F$39,"") | I9: =IFERROR(((G9*(1-F$2))*$CN9)*F$38,"") | J9: =IFERROR(IF(H9+I9=0,"",H9+I9),"") | K9: =IFERROR((($CL9/1.15)-(G9-(G9*F$2)))/($CL9/1.15),"") | L9: =IFERROR((($CM9/1.15)+(H9+I9)-(G9-(G9*F$2)))/($CM9/1.15),"") | M9: {=IF($C9="","",IFERROR(_xlfn._xlws.FILTER(ST[6wk avg],(ST[Code]=$C9)*(ST[Customer Name]=F$3),""),""))} | N9: =IFERROR(IF(CEILING(M9 + (M9 * $N$2), 1) = 0, "", CEILING(M9 + (M9 * $N$2), 1))*$B$3, "") | O9: =IFERROR((N9*H9),"") | P9: =IFERROR((N9*I9),"") | R9: {=IFERROR(_xlfn._xlws.FILTER(#REF!,(#REF!=$C9) * (#REF!=R$3),"" ),"")} | S9: {=IFERROR(_xlfn.XLOOKUP($C9,Master_Price_Level_NZ[Code],INDEX(Master_Price_Level_NZ[], , MATCH('Promo Form'!R$3, Master_Price_Level_NZ[#Headers], 0))),"")} | T9: =IFERROR(((S9*(1-R$2))*$CN9)*R$39,"") | U9: =IFERROR(((S9*(1-R$2))*$CN9)*R$38,"") | V9: =IFERROR(IF(T9+U9=0,"",T9+U9),"") | W9: =IFERROR((($CL9/1.15)-(S9-(S9*R$2)))/($CL9/1.15),"") | X9: =IFERROR((($CM9/1.15)+(T9+U9)-(S9-(S9*R$2)))/($CM9/1.15),"") | Y9: {=IFERROR( _xlfn.LET( _xlpm.result, INDEX(_xlfn._xlws.FILTER(ST[6wk avg], (ST[Code]=$C9)*(ST[Customer Name]=R$3), ""), 1), IF(_xlpm.result=0, "", _xlpm.result) ), "")} | Z9: =IFERROR(IF(CEILING(Y9 + (Y9 * $N$2), 1) = 0, "", CEILING(Y9 + (Y9 * $N$2), 1))*$B$3, "") | AA9: =IFERROR((Z9*T9),"") | AB9: =IFERROR((Z9*U9),"") | AD9: {=IFERROR(_xlfn._xlws.FILTER(#REF!,(#REF!=$C9) * (#REF!=AD$3),"" ),"")} | AE9: {=IFERROR(_xlfn.XLOOKUP($C9,Master_Price_Level_NZ[Code],INDEX(Master_Price_Level_NZ[], , MATCH('Promo Form'!AD$3, Master_Price_Level_NZ[#Headers], 0))),"")} | AF9: =IFERROR(((AE9*(1-AD$2))*$CN9)*AD$39,"") | AG9: =IFERROR(((AE9*(1-AD$2))*$CN9)*AD$38,"") | AH9: =IFERROR(IF(AF9+AG9=0,"",AF9+AG9),"") | AI9: =IFERROR((($CL9/1.15)-(AE9-(AE9*AD$2)))/($CL9/1.15),"") | AJ9: =IFERROR((($CM9/1.15)+(AF9+AG9)-(AE9-(AE9*AD$2)))/($CM9/1.15),"") | AK9: {=IFERROR( _xlfn.LET( _xlpm.result, INDEX(_xlfn._xlws.FILTER(ST[6wk avg], (ST[Code]=$C9)*(ST[Customer Name]=AD$3), ""), 1), IF(_xlpm.result=0, "", _xlpm.result) ), "")} | AL9: =IFERROR(IF(CEILING(AK9 + (AK9 * $N$2), 1) = 0, "", CEILING(AK9 + (AK9 * $N$2), 1))*$B$3, "") | AM9: =IFERROR((AL9*AF9),"") | AN9: =IFERROR((AL9*AG9),"") | AP9: {=IFERROR(_xlfn._xlws.FILTER(#REF!,(#REF!=$C9) * (#REF!=AP$3),"" ),"")} | AQ9: {=IFERROR(_xlfn.XLOOKUP($C9,Master_Price_Level_NZ[Code],INDEX(Master_Price_Level_NZ[], , MATCH('Promo Form'!AP$3, Master_Price_Level_NZ[#Headers], 0))),"")} | AR9: =IFERROR(((AQ9*(1-AP$2))*$CN9)*AP$39,"") | AS9: =IFERROR(((AQ9*(1-AP$2))*$CN9)*AP$38,"") | AT9: =IFERROR(IF(AR9+AS9=0,"",AR9+AS9),"") | AU9: =IFERROR((($CL9/1.15)-(AQ9-(AQ9*AP$2)))/($CL9/1.15),"") | AV9: =IFERROR((($CM9/1.15)+(AR9+AS9)-(AQ9-(AQ9*AP$2)))/($CM9/1.15),"") | AW9: {=IFERROR( _xlfn.LET( _xlpm.result, INDEX(_xlfn._xlws.FILTER(ST[6wk avg], (ST[Code]=$C9)*(ST[Customer Name]=AP$3), ""), 1), IF(_xlpm.result=0, "", _xlpm.result) ), "")} | AX9: =IFERROR(IF(CEILING(AW9 + (AW9 * $N$2), 1) = 0, "", CEILING(AW9 + (AW9 * $N$2), 1))*$B$3, "") | AY9: =IFERROR((AX9*AR9),"") | AZ9: =IFERROR((AX9*AS9),"") | BB9: {=IFERROR(_xlfn._xlws.FILTER(#REF!,(#REF!=$C9) * (#REF!=BB$3),"" ),"")} | BC9: {=IFERROR(_xlfn.XLOOKUP($C9,Master_Price_Level_NZ[Code],INDEX(Master_Price_Level_NZ[], , MATCH('Promo Form'!BB$3, Master_Price_Level_NZ[#Headers], 0))),"")} | BD9: =IFERROR(((BC9*(1-BB$2))*$CN9)*BB$39,"") | BE9: =IFERROR(((BC9*(1-BB$2))*$CN9)*BB$38,"") | BF9: =IFERROR(IF(BD9+BE9=0,"",BD9+BE9),"") | BG9: =IFERROR((($CL9/1.15)-(BC9-(BC9*BB$2)))/($CL9/1.15),"") | BH9: =IFERROR((($CM9/1.15)+(BD9+BE9)-(BC9-(BC9*BB$2)))/($CM9/1.15),"") | BI9: {=IFERROR( _xlfn.LET( _xlpm.result, INDEX(_xlfn._xlws.FILTER(ST[6wk avg], (ST[Code]=$C9)*(ST[Customer Name]=BB$3), ""), 1), IF(_xlpm.result=0, "", _xlpm.result) ), "")} | BJ9: =IFERROR(IF(CEILING(BI9 + (BI9 * $N$2), 1) = 0, "", CEILING(BI9 + (BI9 * $N$2), 1))*$B$3, "") | BK9: =IFERROR((BJ9*BD9),"") | BL9: =IFERROR((BJ9*BE9),"") | BN9: {=IFERROR(_xlfn._xlws.FILTER(#REF!,(#REF!=$C9) * (#REF!=BN$3),"" ),"")} | BO9: {=IFERROR(_xlfn.XLOOKUP($C9,Master_Price_Level_NZ[Code],INDEX(Master_Price_Level_NZ[], , MATCH('Promo Form'!BN$3, Master_Price_Level_NZ[#Headers], 0))),"")} | BP9: =IFERROR(((BO9*(1-BN$2))*$CN9)*BN$39,"") | BQ9: =IFERROR(((BO9*(1-BN$2))*$CN9)*BN$38,"") | BR9: =IFERROR(IF(BP9+BQ9=0,"",BP9+BQ9),"") | BS9: =IFERROR((($CL9/1.15)-(BO9-(BO9*BN$2)))/($CL9/1.15),"") | BT9: =IFERROR((($CM9/1.15)+(BP9+BQ9)-(BO9-(BO9*BN$2)))/($CM9/1.15),"") | BU9: {=IFERROR( _xlfn.LET( _xlpm.result, INDEX(_xlfn._xlws.FILTER(ST[6wk avg], (ST[Code]=$C9)*(ST[Customer Name]=BN$3), ""), 1), IF(_xlpm.result=0, "", _xlpm.result) ), "")} | BV9: =IFERROR(IF(CEILING(BU9 + (BU9 * $N$2), 1) = 0, "", CEILING(BU9 + (BU9 * $N$2), 1))*$B$3, "") | BW9: =IFERROR((BV9*BP9),"") | BX9: =IFERROR((BV9*BQ9),"") | BZ9: {=IFERROR(_xlfn._xlws.FILTER(#REF!,(#REF!=$C9) * (#REF!=BZ$3),"" ),"")} | CA9: {=IFERROR(_xlfn.XLOOKUP($C9,Master_Price_Level_NZ[Code],INDEX(Master_Price_Level_NZ[], , MATCH('Promo Form'!BZ$3, Master_Price_Level_NZ[#Headers], 0))),"")} | CB9: =IFERROR(((CA9*(1-BZ$2))*$CN9)*BZ$39,"") | CC9: =IFERROR(((CA9*(1-BZ$2))*$CN9)*BZ$38,"") | CD9: =IFERROR(IF(CB9+CC9=0,"",CB9+CC9),"") | CE9: =IFERROR((($CL9/1.15)-(CA9-(CA9*BZ$2)))/($CL9/1.15),"") | CF9: =IFERROR((($CM9/1.15)+(CB9+CC9)-(CA9-(CA9*BZ$2)))/($CM9/1.15),"") | CG9: {=IFERROR( _xlfn.LET( _xlpm.result, INDEX(_xlfn._xlws.FILTER(ST[6wk avg], (ST[Code]=$C9)*(ST[Customer Name]=BZ$3), ""), 1), IF(_xlpm.result=0, "", _xlpm.result) ), "")} | CH9: =IFERROR(IF(CEILING(CG9 + (CG9 * $N$2), 1) = 0, "", CEILING(CG9 + (CG9 * $N$2), 1))*$B$3, "") | CI9: =IFERROR((CH9*CB9),"") | CJ9: =IFERROR((CH9*CC9),"") | CL9: =IFERROR(_xlfn.XLOOKUP(C9,Master_Price_Level_NZ[Code],Master_Price_Level_NZ[Base (RRP Inc)]),"") | CM9: =IFERROR(CL9-(CL9*CN9),"") | CN9: =IF(C9="", "",CN8) | CO9: =IFERROR((CL9-CM9),"")
A10: =IF(C10="","",A9) | B10: =IF(C10="","",B9) | D10: =IF(C10="", "",_xlfn.XLOOKUP(C10,'Master Price Level NZ'!B:B,'Master Price Level NZ'!C:C)) | G10: {=IFERROR(_xlfn.XLOOKUP($C10,Master_Price_Level_NZ[Code],INDEX(Master_Price_Level_NZ[], , MATCH('Promo Form'!F$3, Master_Price_Level_NZ[#Headers], 0))),"")} | H10: =IFERROR(((G10*(1-F$2))*$CN10)*F$39,"") | I10: =IFERROR(((G10*(1-F$2))*$CN10)*F$38,"") | J10: =IFERROR(IF(H10+I10=0,"",H10+I10),"") | K10: =IFERROR((($CL10/1.15)-(G10-(G10*F$2)))/($CL10/1.15),"") | L10: =IFERROR((($CM10/1.15)+(H10+I10)-(G10-(G10*F$2)))/($CM10/1.15),"") | M10: {=IF($C10="","",IFERROR(_xlfn._xlws.FILTER(ST[6wk avg],(ST[Code]=$C10)*(ST[Customer Name]=F$3),""),""))} | N10: =IFERROR(IF(CEILING(M10 + (M10 * $N$2), 1) = 0, "", CEILING(M10 + (M10 * $N$2), 1))*$B$3, "") | O10: =IFERROR((N10*H10),"") | P10: =IFERROR((N10*I10),"") | R10: {=IFERROR(_xlfn._xlws.FILTER(#REF!,(#REF!=$C10) * (#REF!=R$3),"" ),"")} | S10: {=IFERROR(_xlfn.XLOOKUP($C10,Master_Price_Level_NZ[Code],INDEX(Master_Price_Level_NZ[], , MATCH('Promo Form'!R$3, Master_Price_Level_NZ[#Headers], 0))),"")} | T10: =IFERROR(((S10*(1-R$2))*$CN10)*R$39,"") | U10: =IFERROR(((S10*(1-R$2))*$CN10)*R$38,"") | V10: =IFERROR(IF(T10+U10=0,"",T10+U10),"") | W10: =IFERROR((($CL10/1.15)-(S10-(S10*R$2)))/($CL10/1.15),"") | X10: =IFERROR((($CM10/1.15)+(T10+U10)-(S10-(S10*R$2)))/($CM10/1.15),"") | Y10: {=IFERROR( _xlfn.LET( _xlpm.result, INDEX(_xlfn._xlws.FILTER(ST[6wk avg], (ST[Code]=$C10)*(ST[Customer Name]=R$3), ""), 1), IF(_xlpm.result=0, "", _xlpm.result) ), "")} | Z10: =IFERROR(IF(CEILING(Y10 + (Y10 * $N$2), 1) = 0, "", CEILING(Y10 + (Y10 * $N$2), 1))*$B$3, "") | AA10: =IFERROR((Z10*T10),"") | AB10: =IFERROR((Z10*U10),"") | AD10: {=IFERROR(_xlfn._xlws.FILTER(#REF!,(#REF!=$C10) * (#REF!=AD$3),"" ),"")} | AE10: {=IFERROR(_xlfn.XLOOKUP($C10,Master_Price_Level_NZ[Code],INDEX(Master_Price_Level_NZ[], , MATCH('Promo Form'!AD$3, Master_Price_Level_NZ[#Headers], 0))),"")} | AF10: =IFERROR(((AE10*(1-AD$2))*$CN10)*AD$39,"") | AG10: =IFERROR(((AE10*(1-AD$2))*$CN10)*AD$38,"") | AH10: =IFERROR(IF(AF10+AG10=0,"",AF10+AG10),"") | AI10: =IFERROR((($CL10/1.15)-(AE10-(AE10*AD$2)))/($CL10/1.15),"") | AJ10: =IFERROR((($CM10/1.15)+(AF10+AG10)-(AE10-(AE10*AD$2)))/($CM10/1.15),"") | AK10: {=IFERROR( _xlfn.LET( _xlpm.result, INDEX(_xlfn._xlws.FILTER(ST[6wk avg], (ST[Code]=$C10)*(ST[Customer Name]=AD$3), ""), 1), IF(_xlpm.result=0, "", _xlpm.result) ), "")} | AL10: =IFERROR(IF(CEILING(AK10 + (AK10 * $N$2), 1) = 0, "", CEILING(AK10 + (AK10 * $N$2), 1))*$B$3, "") | AM10: =IFERROR((AL10*AF10),"") | AN10: =IFERROR((AL10*AG10),"") | AP10: {=IFERROR(_xlfn._xlws.FILTER(#REF!,(#REF!=$C10) * (#REF!=AP$3),"" ),"")} | AQ10: {=IFERROR(_xlfn.XLOOKUP($C10,Master_Price_Level_NZ[Code],INDEX(Master_Price_Level_NZ[], , MATCH('Promo Form'!AP$3, Master_Price_Level_NZ[#Headers], 0))),"")} | AR10: =IFERROR(((AQ10*(1-AP$2))*$CN10)*AP$39,"") | AS10: =IFERROR(((AQ10*(1-AP$2))*$CN10)*AP$38,"") | AT10: =IFERROR(IF(AR10+AS10=0,"",AR10+AS10),"") | AU10: =IFERROR((($CL10/1.15)-(AQ10-(AQ10*AP$2)))/($CL10/1.15),"") | AV10: =IFERROR((($CM10/1.15)+(AR10+AS10)-(AQ10-(AQ10*AP$2)))/($CM10/1.15),"") | AW10: {=IFERROR( _xlfn.LET( _xlpm.result, INDEX(_xlfn._xlws.FILTER(ST[6wk avg], (ST[Code]=$C10)*(ST[Customer Name]=AP$3), ""), 1), IF(_xlpm.result=0, "", _xlpm.result) ), "")} | AX10: =IFERROR(IF(CEILING(AW10 + (AW10 * $N$2), 1) = 0, "", CEILING(AW10 + (AW10 * $N$2), 1))*$B$3, "") | AY10: =IFERROR((AX10*AR10),"") | AZ10: =IFERROR((AX10*AS10),"") | BB10: {=IFERROR(_xlfn._xlws.FILTER(#REF!,(#REF!=$C10) * (#REF!=BB$3),"" ),"")} | BC10: {=IFERROR(_xlfn.XLOOKUP($C10,Master_Price_Level_NZ[Code],INDEX(Master_Price_Level_NZ[], , MATCH('Promo Form'!BB$3, Master_Price_Level_NZ[#Headers], 0))),"")} | BD10: =IFERROR(((BC10*(1-BB$2))*$CN10)*BB$39,"") | BE10: =IFERROR(((BC10*(1-BB$2))*$CN10)*BB$38,"") | BF10: =IFERROR(IF(BD10+BE10=0,"",BD10+BE10),"") | BG10: =IFERROR((($CL10/1.15)-(BC10-(BC10*BB$2)))/($CL10/1.15),"") | BH10: =IFERROR((($CM10/1.15)+(BD10+BE10)-(BC10-(BC10*BB$2)))/($CM10/1.15),"") | BI10: {=IFERROR( _xlfn.LET( _xlpm.result, INDEX(_xlfn._xlws.FILTER(ST[6wk avg], (ST[Code]=$C10)*(ST[Customer Name]=BB$3), ""), 1), IF(_xlpm.result=0, "", _xlpm.result) ), "")} | BJ10: =IFERROR(IF(CEILING(BI10 + (BI10 * $N$2), 1) = 0, "", CEILING(BI10 + (BI10 * $N$2), 1))*$B$3, "") | BK10: =IFERROR((BJ10*BD10),"") | BL10: =IFERROR((BJ10*BE10),"") | BN10: {=IFERROR(_xlfn._xlws.FILTER(#REF!,(#REF!=$C10) * (#REF!=BN$3),"" ),"")} | BO10: {=IFERROR(_xlfn.XLOOKUP($C10,Master_Price_Level_NZ[Code],INDEX(Master_Price_Level_NZ[], , MATCH('Promo Form'!BN$3, Master_Price_Level_NZ[#Headers], 0))),"")} | BP10: =IFERROR(((BO10*(1-BN$2))*$CN10)*BN$39,"") | BQ10: =IFERROR(((BO10*(1-BN$2))*$CN10)*BN$38,"") | BR10: =IFERROR(IF(BP10+BQ10=0,"",BP10+BQ10),"") | BS10: =IFERROR((($CL10/1.15)-(BO10-(BO10*BN$2)))/($CL10/1.15),"") | BT10: =IFERROR((($CM10/1.15)+(BP10+BQ10)-(BO10-(BO10*BN$2)))/($CM10/1.15),"") | BU10: {=IFERROR( _xlfn.LET( _xlpm.result, INDEX(_xlfn._xlws.FILTER(ST[6wk avg], (ST[Code]=$C10)*(ST[Customer Name]=BN$3), ""), 1), IF(_xlpm.result=0, "", _xlpm.result) ), "")} | BV10: =IFERROR(IF(CEILING(BU10 + (BU10 * $N$2), 1) = 0, "", CEILING(BU10 + (BU10 * $N$2), 1))*$B$3, "") | BW10: =IFERROR((BV10*BP10),"") | BX10: =IFERROR((BV10*BQ10),"") | BZ10: {=IFERROR(_xlfn._xlws.FILTER(#REF!,(#REF!=$C10) * (#REF!=BZ$3),"" ),"")} | CA10: {=IFERROR(_xlfn.XLOOKUP($C10,Master_Price_Level_NZ[Code],INDEX(Master_Price_Level_NZ[], , MATCH('Promo Form'!BZ$3, Master_Price_Level_NZ[#Headers], 0))),"")} | CB10: =IFERROR(((CA10*(1-BZ$2))*$CN10)*BZ$39,"") | CC10: =IFERROR(((CA10*(1-BZ$2))*$CN10)*BZ$38,"") | CD10: =IFERROR(IF(CB10+CC10=0,"",CB10+CC10),"") | CE10: =IFERROR((($CL10/1.15)-(CA10-(CA10*BZ$2)))/($CL10/1.15),"") | CF10: =IFERROR((($CM10/1.15)+(CB10+CC10)-(CA10-(CA10*BZ$2)))/($CM10/1.15),"") | CG10: {=IFERROR( _xlfn.LET( _xlpm.result, INDEX(_xlfn._xlws.FILTER(ST[6wk avg], (ST[Code]=$C10)*(ST[Customer Name]=BZ$3), ""), 1), IF(_xlpm.result=0, "", _xlpm.result) ), "")} | CH10: =IFERROR(IF(CEILING(CG10 + (CG10 * $N$2), 1) = 0, "", CEILING(CG10 + (CG10 * $N$2), 1))*$B$3, "") | CI10: =IFERROR((CH10*CB10),"") | CJ10: =IFERROR((CH10*CC10),"") | CL10: =IFERROR(_xlfn.XLOOKUP(C10,Master_Price_Level_NZ[Code],Master_Price_Level_NZ[Base (RRP Inc)]),"") | CM10: =IFERROR(CL10-(CL10*CN10),"") | CN10: =IF(C10="", "",CN9) | CO10: =IFERROR((CL10-CM10),"")
A11: =IF(C11="","",A10) | B11: =IF(C11="","",B10) | D11: =IF(C11="", "",_xlfn.XLOOKUP(C11,'Master Price Level NZ'!B:B,'Master Price Level NZ'!C:C)) | G11: {=IFERROR(_xlfn.XLOOKUP($C11,Master_Price_Level_NZ[Code],INDEX(Master_Price_Level_NZ[], , MATCH('Promo Form'!F$3, Master_Price_Level_NZ[#Headers], 0))),"")} | H11: =IFERROR(((G11*(1-F$2))*$CN11)*F$39,"") | I11: =IFERROR(((G11*(1-F$2))*$CN11)*F$38,"") | J11: =IFERROR(IF(H11+I11=0,"",H11+I11),"") | K11: =IFERROR((($CL11/1.15)-(G11-(G11*F$2)))/($CL11/1.15),"") | L11: =IFERROR((($CM11/1.15)+(H11+I11)-(G11-(G11*F$2)))/($CM11/1.15),"") | M11: {=IF($C11="","",IFERROR(_xlfn._xlws.FILTER(ST[6wk avg],(ST[Code]=$C11)*(ST[Customer Name]=F$3),""),""))} | N11: =IFERROR(IF(CEILING(M11 + (M11 * $N$2), 1) = 0, "", CEILING(M11 + (M11 * $N$2), 1))*$B$3, "") | O11: =IFERROR((N11*H11),"") | P11: =IFERROR((N11*I11),"") | R11: {=IFERROR(_xlfn._xlws.FILTER(#REF!,(#REF!=$C11) * (#REF!=R$3),"" ),"")} | S11: {=IFERROR(_xlfn.XLOOKUP($C11,Master_Price_Level_NZ[Code],INDEX(Master_Price_Level_NZ[], , MATCH('Promo Form'!R$3, Master_Price_Level_NZ[#Headers], 0))),"")} | T11: =IFERROR(((S11*(1-R$2))*$CN11)*R$39,"") | U11: =IFERROR(((S11*(1-R$2))*$CN11)*R$38,"") | V11: =IFERROR(IF(T11+U11=0,"",T11+U11),"") | W11: =IFERROR((($CL11/1.15)-(S11-(S11*R$2)))/($CL11/1.15),"") | X11: =IFERROR((($CM11/1.15)+(T11+U11)-(S11-(S11*R$2)))/($CM11/1.15),"") | Y11: {=IFERROR( _xlfn.LET( _xlpm.result, INDEX(_xlfn._xlws.FILTER(ST[6wk avg], (ST[Code]=$C11)*(ST[Customer Name]=R$3), ""), 1), IF(_xlpm.result=0, "", _xlpm.result) ), "")} | Z11: =IFERROR(IF(CEILING(Y11 + (Y11 * $N$2), 1) = 0, "", CEILING(Y11 + (Y11 * $N$2), 1))*$B$3, "") | AA11: =IFERROR((Z11*T11),"") | AB11: =IFERROR((Z11*U11),"") | AD11: {=IFERROR(_xlfn._xlws.FILTER(#REF!,(#REF!=$C11) * (#REF!=AD$3),"" ),"")} | AE11: {=IFERROR(_xlfn.XLOOKUP($C11,Master_Price_Level_NZ[Code],INDEX(Master_Price_Level_NZ[], , MATCH('Promo Form'!AD$3, Master_Price_Level_NZ[#Headers], 0))),"")} | AF11: =IFERROR(((AE11*(1-AD$2))*$CN11)*AD$39,"") | AG11: =IFERROR(((AE11*(1-AD$2))*$CN11)*AD$38,"") | AH11: =IFERROR(IF(AF11+AG11=0,"",AF11+AG11),"") | AI11: =IFERROR((($CL11/1.15)-(AE11-(AE11*AD$2)))/($CL11/1.15),"") | AJ11: =IFERROR((($CM11/1.15)+(AF11+AG11)-(AE11-(AE11*AD$2)))/($CM11/1.15),"") | AK11: {=IFERROR( _xlfn.LET( _xlpm.result, INDEX(_xlfn._xlws.FILTER(ST[6wk avg], (ST[Code]=$C11)*(ST[Customer Name]=AD$3), ""), 1), IF(_xlpm.result=0, "", _xlpm.result) ), "")} | AL11: =IFERROR(IF(CEILING(AK11 + (AK11 * $N$2), 1) = 0, "", CEILING(AK11 + (AK11 * $N$2), 1))*$B$3, "") | AM11: =IFERROR((AL11*AF11),"") | AN11: =IFERROR((AL11*AG11),"") | AP11: {=IFERROR(_xlfn._xlws.FILTER(#REF!,(#REF!=$C11) * (#REF!=AP$3),"" ),"")} | AQ11: {=IFERROR(_xlfn.XLOOKUP($C11,Master_Price_Level_NZ[Code],INDEX(Master_Price_Level_NZ[], , MATCH('Promo Form'!AP$3, Master_Price_Level_NZ[#Headers], 0))),"")} | AR11: =IFERROR(((AQ11*(1-AP$2))*$CN11)*AP$39,"") | AS11: =IFERROR(((AQ11*(1-AP$2))*$CN11)*AP$38,"") | AT11: =IFERROR(IF(AR11+AS11=0,"",AR11+AS11),"") | AU11: =IFERROR((($CL11/1.15)-(AQ11-(AQ11*AP$2)))/($CL11/1.15),"") | AV11: =IFERROR((($CM11/1.15)+(AR11+AS11)-(AQ11-(AQ11*AP$2)))/($CM11/1.15),"") | AW11: {=IFERROR( _xlfn.LET( _xlpm.result, INDEX(_xlfn._xlws.FILTER(ST[6wk avg], (ST[Code]=$C11)*(ST[Customer Name]=AP$3), ""), 1), IF(_xlpm.result=0, "", _xlpm.result) ), "")} | AX11: =IFERROR(IF(CEILING(AW11 + (AW11 * $N$2), 1) = 0, "", CEILING(AW11 + (AW11 * $N$2), 1))*$B$3, "") | AY11: =IFERROR((AX11*AR11),"") | AZ11: =IFERROR((AX11*AS11),"") | BB11: {=IFERROR(_xlfn._xlws.FILTER(#REF!,(#REF!=$C11) * (#REF!=BB$3),"" ),"")} | BC11: {=IFERROR(_xlfn.XLOOKUP($C11,Master_Price_Level_NZ[Code],INDEX(Master_Price_Level_NZ[], , MATCH('Promo Form'!BB$3, Master_Price_Level_NZ[#Headers], 0))),"")} | BD11: =IFERROR(((BC11*(1-BB$2))*$CN11)*BB$39,"") | BE11: =IFERROR(((BC11*(1-BB$2))*$CN11)*BB$38,"") | BF11: =IFERROR(IF(BD11+BE11=0,"",BD11+BE11),"") | BG11: =IFERROR((($CL11/1.15)-(BC11-(BC11*BB$2)))/($CL11/1.15),"") | BH11: =IFERROR((($CM11/1.15)+(BD11+BE11)-(BC11-(BC11*BB$2)))/($CM11/1.15),"") | BI11: {=IFERROR( _xlfn.LET( _xlpm.result, INDEX(_xlfn._xlws.FILTER(ST[6wk avg], (ST[Code]=$C11)*(ST[Customer Name]=BB$3), ""), 1), IF(_xlpm.result=0, "", _xlpm.result) ), "")} | BJ11: =IFERROR(IF(CEILING(BI11 + (BI11 * $N$2), 1) = 0, "", CEILING(BI11 + (BI11 * $N$2), 1))*$B$3, "") | BK11: =IFERROR((BJ11*BD11),"") | BL11: =IFERROR((BJ11*BE11),"") | BN11: {=IFERROR(_xlfn._xlws.FILTER(#REF!,(#REF!=$C11) * (#REF!=BN$3),"" ),"")} | BO11: {=IFERROR(_xlfn.XLOOKUP($C11,Master_Price_Level_NZ[Code],INDEX(Master_Price_Level_NZ[], , MATCH('Promo Form'!BN$3, Master_Price_Level_NZ[#Headers], 0))),"")} | BP11: =IFERROR(((BO11*(1-BN$2))*$CN11)*BN$39,"") | BQ11: =IFERROR(((BO11*(1-BN$2))*$CN11)*BN$38,"") | BR11: =IFERROR(IF(BP11+BQ11=0,"",BP11+BQ11),"") | BS11: =IFERROR((($CL11/1.15)-(BO11-(BO11*BN$2)))/($CL11/1.15),"") | BT11: =IFERROR((($CM11/1.15)+(BP11+BQ11)-(BO11-(BO11*BN$2)))/($CM11/1.15),"") | BU11: {=IFERROR( _xlfn.LET( _xlpm.result, INDEX(_xlfn._xlws.FILTER(ST[6wk avg], (ST[Code]=$C11)*(ST[Customer Name]=BN$3), ""), 1), IF(_xlpm.result=0, "", _xlpm.result) ), "")} | BV11: =IFERROR(IF(CEILING(BU11 + (BU11 * $N$2), 1) = 0, "", CEILING(BU11 + (BU11 * $N$2), 1))*$B$3, "") | BW11: =IFERROR((BV11*BP11),"") | BX11: =IFERROR((BV11*BQ11),"") | BZ11: {=IFERROR(_xlfn._xlws.FILTER(#REF!,(#REF!=$C11) * (#REF!=BZ$3),"" ),"")} | CA11: {=IFERROR(_xlfn.XLOOKUP($C11,Master_Price_Level_NZ[Code],INDEX(Master_Price_Level_NZ[], , MATCH('Promo Form'!BZ$3, Master_Price_Level_NZ[#Headers], 0))),"")} | CB11: =IFERROR(((CA11*(1-BZ$2))*$CN11)*BZ$39,"") | CC11: =IFERROR(((CA11*(1-BZ$2))*$CN11)*BZ$38,"") | CD11: =IFERROR(IF(CB11+CC11=0,"",CB11+CC11),"") | CE11: =IFERROR((($CL11/1.15)-(CA11-(CA11*BZ$2)))/($CL11/1.15),"") | CF11: =IFERROR((($CM11/1.15)+(CB11+CC11)-(CA11-(CA11*BZ$2)))/($CM11/1.15),"") | CG11: {=IFERROR( _xlfn.LET( _xlpm.result, INDEX(_xlfn._xlws.FILTER(ST[6wk avg], (ST[Code]=$C11)*(ST[Customer Name]=BZ$3), ""), 1), IF(_xlpm.result=0, "", _xlpm.result) ), "")} | CH11: =IFERROR(IF(CEILING(CG11 + (CG11 * $N$2), 1) = 0, "", CEILING(CG11 + (CG11 * $N$2), 1))*$B$3, "") | CI11: =IFERROR((CH11*CB11),"") | CJ11: =IFERROR((CH11*CC11),"") | CL11: =IFERROR(_xlfn.XLOOKUP(C11,Master_Price_Level_NZ[Code],Master_Price_Level_NZ[Base (RRP Inc)]),"") | CM11: =IFERROR(CL11-(CL11*CN11),"") | CN11: =IF(C11="", "",CN10) | CO11: =IFERROR((CL11-CM11),"")
A12: =IF(C12="","",A11) | B12: =IF(C12="","",B11) | D12: =IF(C12="", "",_xlfn.XLOOKUP(C12,'Master Price Level NZ'!B:B,'Master Price Level NZ'!C:C)) | G12: {=IFERROR(_xlfn.XLOOKUP($C12,Master_Price_Level_NZ[Code],INDEX(Master_Price_Level_NZ[], , MATCH('Promo Form'!F$3, Master_Price_Level_NZ[#Headers], 0))),"")} | H12: =IFERROR(((G12*(1-F$2))*$CN12)*F$39,"") | I12: =IFERROR(((G12*(1-F$2))*$CN12)*F$38,"") | J12: =IFERROR(IF(H12+I12=0,"",H12+I12),"") | K12: =IFERROR((($CL12/1.15)-(G12-(G12*F$2)))/($CL12/1.15),"") | L12: =IFERROR((($CM12/1.15)+(H12+I12)-(G12-(G12*F$2)))/($CM12/1.15),"") | M12: {=IF($C12="","",IFERROR(_xlfn._xlws.FILTER(ST[6wk avg],(ST[Code]=$C12)*(ST[Customer Name]=F$3),""),""))} | N12: =IFERROR(IF(CEILING(M12 + (M12 * $N$2), 1) = 0, "", CEILING(M12 + (M12 * $N$2), 1))*$B$3, "") | O12: =IFERROR((N12*H12),"") | P12: =IFERROR((N12*I12),"") | R12: {=IFERROR(_xlfn._xlws.FILTER(#REF!,(#REF!=$C12) * (#REF!=R$3),"" ),"")} | S12: {=IFERROR(_xlfn.XLOOKUP($C12,Master_Price_Level_NZ[Code],INDEX(Master_Price_Level_NZ[], , MATCH('Promo Form'!R$3, Master_Price_Level_NZ[#Headers], 0))),"")} | T12: =IFERROR(((S12*(1-R$2))*$CN12)*R$39,"") | U12: =IFERROR(((S12*(1-R$2))*$CN12)*R$38,"") | V12: =IFERROR(IF(T12+U12=0,"",T12+U12),"") | W12: =IFERROR((($CL12/1.15)-(S12-(S12*R$2)))/($CL12/1.15),"") | X12: =IFERROR((($CM12/1.15)+(T12+U12)-(S12-(S12*R$2)))/($CM12/1.15),"") | Y12: {=IFERROR( _xlfn.LET( _xlpm.result, INDEX(_xlfn._xlws.FILTER(ST[6wk avg], (ST[Code]=$C12)*(ST[Customer Name]=R$3), ""), 1), IF(_xlpm.result=0, "", _xlpm.result) ), "")} | Z12: =IFERROR(IF(CEILING(Y12 + (Y12 * $N$2), 1) = 0, "", CEILING(Y12 + (Y12 * $N$2), 1))*$B$3, "") | AA12: =IFERROR((Z12*T12),"") | AB12: =IFERROR((Z12*U12),"") | AD12: {=IFERROR(_xlfn._xlws.FILTER(#REF!,(#REF!=$C12) * (#REF!=AD$3),"" ),"")} | AE12: {=IFERROR(_xlfn.XLOOKUP($C12,Master_Price_Level_NZ[Code],INDEX(Master_Price_Level_NZ[], , MATCH('Promo Form'!AD$3, Master_Price_Level_NZ[#Headers], 0))),"")} | AF12: =IFERROR(((AE12*(1-AD$2))*$CN12)*AD$39,"") | AG12: =IFERROR(((AE12*(1-AD$2))*$CN12)*AD$38,"") | AH12: =IFERROR(IF(AF12+AG12=0,"",AF12+AG12),"") | AI12: =IFERROR((($CL12/1.15)-(AE12-(AE12*AD$2)))/($CL12/1.15),"") | AJ12: =IFERROR((($CM12/1.15)+(AF12+AG12)-(AE12-(AE12*AD$2)))/($CM12/1.15),"") | AK12: {=IFERROR( _xlfn.LET( _xlpm.result, INDEX(_xlfn._xlws.FILTER(ST[6wk avg], (ST[Code]=$C12)*(ST[Customer Name]=AD$3), ""), 1), IF(_xlpm.result=0, "", _xlpm.result) ), "")} | AL12: =IFERROR(IF(CEILING(AK12 + (AK12 * $N$2), 1) = 0, "", CEILING(AK12 + (AK12 * $N$2), 1))*$B$3, "") | AM12: =IFERROR((AL12*AF12),"") | AN12: =IFERROR((AL12*AG12),"") | AP12: {=IFERROR(_xlfn._xlws.FILTER(#REF!,(#REF!=$C12) * (#REF!=AP$3),"" ),"")} | AQ12: {=IFERROR(_xlfn.XLOOKUP($C12,Master_Price_Level_NZ[Code],INDEX(Master_Price_Level_NZ[], , MATCH('Promo Form'!AP$3, Master_Price_Level_NZ[#Headers], 0))),"")} | AR12: =IFERROR(((AQ12*(1-AP$2))*$CN12)*AP$39,"") | AS12: =IFERROR(((AQ12*(1-AP$2))*$CN12)*AP$38,"") | AT12: =IFERROR(IF(AR12+AS12=0,"",AR12+AS12),"") | AU12: =IFERROR((($CL12/1.15)-(AQ12-(AQ12*AP$2)))/($CL12/1.15),"") | AV12: =IFERROR((($CM12/1.15)+(AR12+AS12)-(AQ12-(AQ12*AP$2)))/($CM12/1.15),"") | AW12: {=IFERROR( _xlfn.LET( _xlpm.result, INDEX(_xlfn._xlws.FILTER(ST[6wk avg], (ST[Code]=$C12)*(ST[Customer Name]=AP$3), ""), 1), IF(_xlpm.result=0, "", _xlpm.result) ), "")} | AX12: =IFERROR(IF(CEILING(AW12 + (AW12 * $N$2), 1) = 0, "", CEILING(AW12 + (AW12 * $N$2), 1))*$B$3, "") | AY12: =IFERROR((AX12*AR12),"") | AZ12: =IFERROR((AX12*AS12),"") | BB12: {=IFERROR(_xlfn._xlws.FILTER(#REF!,(#REF!=$C12) * (#REF!=BB$3),"" ),"")} | BC12: {=IFERROR(_xlfn.XLOOKUP($C12,Master_Price_Level_NZ[Code],INDEX(Master_Price_Level_NZ[], , MATCH('Promo Form'!BB$3, Master_Price_Level_NZ[#Headers], 0))),"")} | BD12: =IFERROR(((BC12*(1-BB$2))*$CN12)*BB$39,"") | BE12: =IFERROR(((BC12*(1-BB$2))*$CN12)*BB$38,"") | BF12: =IFERROR(IF(BD12+BE12=0,"",BD12+BE12),"") | BG12: =IFERROR((($CL12/1.15)-(BC12-(BC12*BB$2)))/($CL12/1.15),"") | BH12: =IFERROR((($CM12/1.15)+(BD12+BE12)-(BC12-(BC12*BB$2)))/($CM12/1.15),"") | BI12: {=IFERROR( _xlfn.LET( _xlpm.result, INDEX(_xlfn._xlws.FILTER(ST[6wk avg], (ST[Code]=$C12)*(ST[Customer Name]=BB$3), ""), 1), IF(_xlpm.result=0, "", _xlpm.result) ), "")} | BJ12: =IFERROR(IF(CEILING(BI12 + (BI12 * $N$2), 1) = 0, "", CEILING(BI12 + (BI12 * $N$2), 1))*$B$3, "") | BK12: =IFERROR((BJ12*BD12),"") | BL12: =IFERROR((BJ12*BE12),"") | BN12: {=IFERROR(_xlfn._xlws.FILTER(#REF!,(#REF!=$C12) * (#REF!=BN$3),"" ),"")} | BO12: {=IFERROR(_xlfn.XLOOKUP($C12,Master_Price_Level_NZ[Code],INDEX(Master_Price_Level_NZ[], , MATCH('Promo Form'!BN$3, Master_Price_Level_NZ[#Headers], 0))),"")} | BP12: =IFERROR(((BO12*(1-BN$2))*$CN12)*BN$39,"") | BQ12: =IFERROR(((BO12*(1-BN$2))*$CN12)*BN$38,"") | BR12: =IFERROR(IF(BP12+BQ12=0,"",BP12+BQ12),"") | BS12: =IFERROR((($CL12/1.15)-(BO12-(BO12*BN$2)))/($CL12/1.15),"") | BT12: =IFERROR((($CM12/1.15)+(BP12+BQ12)-(BO12-(BO12*BN$2)))/($CM12/1.15),"") | BU12: {=IFERROR( _xlfn.LET( _xlpm.result, INDEX(_xlfn._xlws.FILTER(ST[6wk avg], (ST[Code]=$C12)*(ST[Customer Name]=BN$3), ""), 1), IF(_xlpm.result=0, "", _xlpm.result) ), "")} | BV12: =IFERROR(IF(CEILING(BU12 + (BU12 * $N$2), 1) = 0, "", CEILING(BU12 + (BU12 * $N$2), 1))*$B$3, "") | BW12: =IFERROR((BV12*BP12),"") | BX12: =IFERROR((BV12*BQ12),"") | BZ12: {=IFERROR(_xlfn._xlws.FILTER(#REF!,(#REF!=$C12) * (#REF!=BZ$3),"" ),"")} | CA12: {=IFERROR(_xlfn.XLOOKUP($C12,Master_Price_Level_NZ[Code],INDEX(Master_Price_Level_NZ[], , MATCH('Promo Form'!BZ$3, Master_Price_Level_NZ[#Headers], 0))),"")} | CB12: =IFERROR(((CA12*(1-BZ$2))*$CN12)*BZ$39,"") | CC12: =IFERROR(((CA12*(1-BZ$2))*$CN12)*BZ$38,"") | CD12: =IFERROR(IF(CB12+CC12=0,"",CB12+CC12),"") | CE12: =IFERROR((($CL12/1.15)-(CA12-(CA12*BZ$2)))/($CL12/1.15),"") | CF12: =IFERROR((($CM12/1.15)+(CB12+CC12)-(CA12-(CA12*BZ$2)))/($CM12/1.15),"") | CG12: {=IFERROR( _xlfn.LET( _xlpm.result, INDEX(_xlfn._xlws.FILTER(ST[6wk avg], (ST[Code]=$C12)*(ST[Customer Name]=BZ$3), ""), 1), IF(_xlpm.result=0, "", _xlpm.result) ), "")} | CH12: =IFERROR(IF(CEILING(CG12 + (CG12 * $N$2), 1) = 0, "", CEILING(CG12 + (CG12 * $N$2), 1))*$B$3, "") | CI12: =IFERROR((CH12*CB12),"") | CJ12: =IFERROR((CH12*CC12),"") | CL12: =IFERROR(_xlfn.XLOOKUP(C12,Master_Price_Level_NZ[Code],Master_Price_Level_NZ[Base (RRP Inc)]),"") | CM12: =IFERROR(CL12-(CL12*CN12),"") | CN12: =IF(C12="", "",CN11) | CO12: =IFERROR((CL12-CM12),"")
A13: =IF(C13="","",A12) | B13: =IF(C13="","",B12) | D13: =IF(C13="", "",_xlfn.XLOOKUP(C13,'Master Price Level NZ'!B:B,'Master Price Level NZ'!C:C)) | G13: {=IFERROR(_xlfn.XLOOKUP($C13,Master_Price_Level_NZ[Code],INDEX(Master_Price_Level_NZ[], , MATCH('Promo Form'!F$3, Master_Price_Level_NZ[#Headers], 0))),"")} | H13: =IFERROR(((G13*(1-F$2))*$CN13)*F$39,"") | I13: =IFERROR(((G13*(1-F$2))*$CN13)*F$38,"") | J13: =IFERROR(IF(H13+I13=0,"",H13+I13),"") | K13: =IFERROR((($CL13/1.15)-(G13-(G13*F$2)))/($CL13/1.15),"") | L13: =IFERROR((($CM13/1.15)+(H13+I13)-(G13-(G13*F$2)))/($CM13/1.15),"") | M13: {=IF($C13="","",IFERROR(_xlfn._xlws.FILTER(ST[6wk avg],(ST[Code]=$C13)*(ST[Customer Name]=F$3),""),""))} | N13: =IFERROR(IF(CEILING(M13 + (M13 * $N$2), 1) = 0, "", CEILING(M13 + (M13 * $N$2), 1))*$B$3, "") | O13: =IFERROR((N13*H13),"") | P13: =IFERROR((N13*I13),"") | R13: {=IFERROR(_xlfn._xlws.FILTER(#REF!,(#REF!=$C13) * (#REF!=R$3),"" ),"")} | S13: {=IFERROR(_xlfn.XLOOKUP($C13,Master_Price_Level_NZ[Code],INDEX(Master_Price_Level_NZ[], , MATCH('Promo Form'!R$3, Master_Price_Level_NZ[#Headers], 0))),"")} | T13: =IFERROR(((S13*(1-R$2))*$CN13)*R$39,"") | U13: =IFERROR(((S13*(1-R$2))*$CN13)*R$38,"") | V13: =IFERROR(IF(T13+U13=0,"",T13+U13),"") | W13: =IFERROR((($CL13/1.15)-(S13-(S13*R$2)))/($CL13/1.15),"") | X13: =IFERROR((($CM13/1.15)+(T13+U13)-(S13-(S13*R$2)))/($CM13/1.15),"") | Y13: {=IFERROR( _xlfn.LET( _xlpm.result, INDEX(_xlfn._xlws.FILTER(ST[6wk avg], (ST[Code]=$C13)*(ST[Customer Name]=R$3), ""), 1), IF(_xlpm.result=0, "", _xlpm.result) ), "")} | Z13: =IFERROR(IF(CEILING(Y13 + (Y13 * $N$2), 1) = 0, "", CEILING(Y13 + (Y13 * $N$2), 1))*$B$3, "") | AA13: =IFERROR((Z13*T13),"") | AB13: =IFERROR((Z13*U13),"") | AD13: {=IFERROR(_xlfn._xlws.FILTER(#REF!,(#REF!=$C13) * (#REF!=AD$3),"" ),"")} | AE13: {=IFERROR(_xlfn.XLOOKUP($C13,Master_Price_Level_NZ[Code],INDEX(Master_Price_Level_NZ[], , MATCH('Promo Form'!AD$3, Master_Price_Level_NZ[#Headers], 0))),"")} | AF13: =IFERROR(((AE13*(1-AD$2))*$CN13)*AD$39,"") | AG13: =IFERROR(((AE13*(1-AD$2))*$CN13)*AD$38,"") | AH13: =IFERROR(IF(AF13+AG13=0,"",AF13+AG13),"") | AI13: =IFERROR((($CL13/1.15)-(AE13-(AE13*AD$2)))/($CL13/1.15),"") | AJ13: =IFERROR((($CM13/1.15)+(AF13+AG13)-(AE13-(AE13*AD$2)))/($CM13/1.15),"") | AK13: {=IFERROR( _xlfn.LET( _xlpm.result, INDEX(_xlfn._xlws.FILTER(ST[6wk avg], (ST[Code]=$C13)*(ST[Customer Name]=AD$3), ""), 1), IF(_xlpm.result=0, "", _xlpm.result) ), "")} | AL13: =IFERROR(IF(CEILING(AK13 + (AK13 * $N$2), 1) = 0, "", CEILING(AK13 + (AK13 * $N$2), 1))*$B$3, "") | AM13: =IFERROR((AL13*AF13),"") | AN13: =IFERROR((AL13*AG13),"") | AP13: {=IFERROR(_xlfn._xlws.FILTER(#REF!,(#REF!=$C13) * (#REF!=AP$3),"" ),"")} | AQ13: {=IFERROR(_xlfn.XLOOKUP($C13,Master_Price_Level_NZ[Code],INDEX(Master_Price_Level_NZ[], , MATCH('Promo Form'!AP$3, Master_Price_Level_NZ[#Headers], 0))),"")} | AR13: =IFERROR(((AQ13*(1-AP$2))*$CN13)*AP$39,"") | AS13: =IFERROR(((AQ13*(1-AP$2))*$CN13)*AP$38,"") | AT13: =IFERROR(IF(AR13+AS13=0,"",AR13+AS13),"") | AU13: =IFERROR((($CL13/1.15)-(AQ13-(AQ13*AP$2)))/($CL13/1.15),"") | AV13: =IFERROR((($CM13/1.15)+(AR13+AS13)-(AQ13-(AQ13*AP$2)))/($CM13/1.15),"") | AW13: {=IFERROR( _xlfn.LET( _xlpm.result, INDEX(_xlfn._xlws.FILTER(ST[6wk avg], (ST[Code]=$C13)*(ST[Customer Name]=AP$3), ""), 1), IF(_xlpm.result=0, "", _xlpm.result) ), "")} | AX13: =IFERROR(IF(CEILING(AW13 + (AW13 * $N$2), 1) = 0, "", CEILING(AW13 + (AW13 * $N$2), 1))*$B$3, "") | AY13: =IFERROR((AX13*AR13),"") | AZ13: =IFERROR((AX13*AS13),"") | BB13: {=IFERROR(_xlfn._xlws.FILTER(#REF!,(#REF!=$C13) * (#REF!=BB$3),"" ),"")} | BC13: {=IFERROR(_xlfn.XLOOKUP($C13,Master_Price_Level_NZ[Code],INDEX(Master_Price_Level_NZ[], , MATCH('Promo Form'!BB$3, Master_Price_Level_NZ[#Headers], 0))),"")} | BD13: =IFERROR(((BC13*(1-BB$2))*$CN13)*BB$39,"") | BE13: =IFERROR(((BC13*(1-BB$2))*$CN13)*BB$38,"") | BF13: =IFERROR(IF(BD13+BE13=0,"",BD13+BE13),"") | BG13: =IFERROR((($CL13/1.15)-(BC13-(BC13*BB$2)))/($CL13/1.15),"") | BH13: =IFERROR((($CM13/1.15)+(BD13+BE13)-(BC13-(BC13*BB$2)))/($CM13/1.15),"") | BI13: {=IFERROR( _xlfn.LET( _xlpm.result, INDEX(_xlfn._xlws.FILTER(ST[6wk avg], (ST[Code]=$C13)*(ST[Customer Name]=BB$3), ""), 1), IF(_xlpm.result=0, "", _xlpm.result) ), "")} | BJ13: =IFERROR(IF(CEILING(BI13 + (BI13 * $N$2), 1) = 0, "", CEILING(BI13 + (BI13 * $N$2), 1))*$B$3, "") | BK13: =IFERROR((BJ13*BD13),"") | BL13: =IFERROR((BJ13*BE13),"") | BN13: {=IFERROR(_xlfn._xlws.FILTER(#REF!,(#REF!=$C13) * (#REF!=BN$3),"" ),"")} | BO13: {=IFERROR(_xlfn.XLOOKUP($C13,Master_Price_Level_NZ[Code],INDEX(Master_Price_Level_NZ[], , MATCH('Promo Form'!BN$3, Master_Price_Level_NZ[#Headers], 0))),"")} | BP13: =IFERROR(((BO13*(1-BN$2))*$CN13)*BN$39,"") | BQ13: =IFERROR(((BO13*(1-BN$2))*$CN13)*BN$38,"") | BR13: =IFERROR(IF(BP13+BQ13=0,"",BP13+BQ13),"") | BS13: =IFERROR((($CL13/1.15)-(BO13-(BO13*BN$2)))/($CL13/1.15),"") | BT13: =IFERROR((($CM13/1.15)+(BP13+BQ13)-(BO13-(BO13*BN$2)))/($CM13/1.15),"") | BU13: {=IFERROR( _xlfn.LET( _xlpm.result, INDEX(_xlfn._xlws.FILTER(ST[6wk avg], (ST[Code]=$C13)*(ST[Customer Name]=BN$3), ""), 1), IF(_xlpm.result=0, "", _xlpm.result) ), "")} | BV13: =IFERROR(IF(CEILING(BU13 + (BU13 * $N$2), 1) = 0, "", CEILING(BU13 + (BU13 * $N$2), 1))*$B$3, "") | BW13: =IFERROR((BV13*BP13),"") | BX13: =IFERROR((BV13*BQ13),"") | BZ13: {=IFERROR(_xlfn._xlws.FILTER(#REF!,(#REF!=$C13) * (#REF!=BZ$3),"" ),"")} | CA13: {=IFERROR(_xlfn.XLOOKUP($C13,Master_Price_Level_NZ[Code],INDEX(Master_Price_Level_NZ[], , MATCH('Promo Form'!BZ$3, Master_Price_Level_NZ[#Headers], 0))),"")} | CB13: =IFERROR(((CA13*(1-BZ$2))*$CN13)*BZ$39,"") | CC13: =IFERROR(((CA13*(1-BZ$2))*$CN13)*BZ$38,"") | CD13: =IFERROR(IF(CB13+CC13=0,"",CB13+CC13),"") | CE13: =IFERROR((($CL13/1.15)-(CA13-(CA13*BZ$2)))/($CL13/1.15),"") | CF13: =IFERROR((($CM13/1.15)+(CB13+CC13)-(CA13-(CA13*BZ$2)))/($CM13/1.15),"") | CG13: {=IFERROR( _xlfn.LET( _xlpm.result, INDEX(_xlfn._xlws.FILTER(ST[6wk avg], (ST[Code]=$C13)*(ST[Customer Name]=BZ$3), ""), 1), IF(_xlpm.result=0, "", _xlpm.result) ), "")} | CH13: =IFERROR(IF(CEILING(CG13 + (CG13 * $N$2), 1) = 0, "", CEILING(CG13 + (CG13 * $N$2), 1))*$B$3, "") | CI13: =IFERROR((CH13*CB13),"") | CJ13: =IFERROR((CH13*CC13),"") | CL13: =IFERROR(_xlfn.XLOOKUP(C13,Master_Price_Level_NZ[Code],Master_Price_Level_NZ[Base (RRP Inc)]),"") | CM13: =IFERROR(CL13-(CL13*CN13),"") | CN13: =IF(C13="", "",CN12) | CO13: =IFERROR((CL13-CM13),"")
A14: =IF(C14="","",A13) | B14: =IF(C14="","",B13) | D14: =IF(C14="", "",_xlfn.XLOOKUP(C14,'Master Price Level NZ'!B:B,'Master Price Level NZ'!C:C)) | G14: {=IFERROR(_xlfn.XLOOKUP($C14,Master_Price_Level_NZ[Code],INDEX(Master_Price_Level_NZ[], , MATCH('Promo Form'!F$3, Master_Price_Level_NZ[#Headers], 0))),"")} | H14: =IFERROR(((G14*(1-F$2))*$CN14)*F$39,"") | I14: =IFERROR(((G14*(1-F$2))*$CN14)*F$38,"") | J14: =IFERROR(IF(H14+I14=0,"",H14+I14),"") | K14: =IFERROR((($CL14/1.15)-(G14-(G14*F$2)))/($CL14/1.15),"") | L14: =IFERROR((($CM14/1.15)+(H14+I14)-(G14-(G14*F$2)))/($CM14/1.15),"") | M14: {=IF($C14="","",IFERROR(_xlfn._xlws.FILTER(ST[6wk avg],(ST[Code]=$C14)*(ST[Customer Name]=F$3),""),""))} | N14: =IFERROR(IF(CEILING(M14 + (M14 * $N$2), 1) = 0, "", CEILING(M14 + (M14 * $N$2), 1))*$B$3, "") | O14: =IFERROR((N14*H14),"") | P14: =IFERROR((N14*I14),"") | R14: {=IFERROR(_xlfn._xlws.FILTER(#REF!,(#REF!=$C14) * (#REF!=R$3),"" ),"")} | S14: {=IFERROR(_xlfn.XLOOKUP($C14,Master_Price_Level_NZ[Code],INDEX(Master_Price_Level_NZ[], , MATCH('Promo Form'!R$3, Master_Price_Level_NZ[#Headers], 0))),"")} | T14: =IFERROR(((S14*(1-R$2))*$CN14)*R$39,"") | U14: =IFERROR(((S14*(1-R$2))*$CN14)*R$38,"") | V14: =IFERROR(IF(T14+U14=0,"",T14+U14),"") | W14: =IFERROR((($CL14/1.15)-(S14-(S14*R$2)))/($CL14/1.15),"") | X14: =IFERROR((($CM14/1.15)+(T14+U14)-(S14-(S14*R$2)))/($CM14/1.15),"") | Y14: {=IFERROR( _xlfn.LET( _xlpm.result, INDEX(_xlfn._xlws.FILTER(ST[6wk avg], (ST[Code]=$C14)*(ST[Customer Name]=R$3), ""), 1), IF(_xlpm.result=0, "", _xlpm.result) ), "")} | Z14: =IFERROR(IF(CEILING(Y14 + (Y14 * $N$2), 1) = 0, "", CEILING(Y14 + (Y14 * $N$2), 1))*$B$3, "") | AA14: =IFERROR((Z14*T14),"") | AB14: =IFERROR((Z14*U14),"") | AD14: {=IFERROR(_xlfn._xlws.FILTER(#REF!,(#REF!=$C14) * (#REF!=AD$3),"" ),"")} | AE14: {=IFERROR(_xlfn.XLOOKUP($C14,Master_Price_Level_NZ[Code],INDEX(Master_Price_Level_NZ[], , MATCH('Promo Form'!AD$3, Master_Price_Level_NZ[#Headers], 0))),"")} | AF14: =IFERROR(((AE14*(1-AD$2))*$CN14)*AD$39,"") | AG14: =IFERROR(((AE14*(1-AD$2))*$CN14)*AD$38,"") | AH14: =IFERROR(IF(AF14+AG14=0,"",AF14+AG14),"") | AI14: =IFERROR((($CL14/1.15)-(AE14-(AE14*AD$2)))/($CL14/1.15),"") | AJ14: =IFERROR((($CM14/1.15)+(AF14+AG14)-(AE14-(AE14*AD$2)))/($CM14/1.15),"") | AK14: {=IFERROR( _xlfn.LET( _xlpm.result, INDEX(_xlfn._xlws.FILTER(ST[6wk avg], (ST[Code]=$C14)*(ST[Customer Name]=AD$3), ""), 1), IF(_xlpm.result=0, "", _xlpm.result) ), "")} | AL14: =IFERROR(IF(CEILING(AK14 + (AK14 * $N$2), 1) = 0, "", CEILING(AK14 + (AK14 * $N$2), 1))*$B$3, "") | AM14: =IFERROR((AL14*AF14),"") | AN14: =IFERROR((AL14*AG14),"") | AP14: {=IFERROR(_xlfn._xlws.FILTER(#REF!,(#REF!=$C14) * (#REF!=AP$3),"" ),"")} | AQ14: {=IFERROR(_xlfn.XLOOKUP($C14,Master_Price_Level_NZ[Code],INDEX(Master_Price_Level_NZ[], , MATCH('Promo Form'!AP$3, Master_Price_Level_NZ[#Headers], 0))),"")} | AR14: =IFERROR(((AQ14*(1-AP$2))*$CN14)*AP$39,"") | AS14: =IFERROR(((AQ14*(1-AP$2))*$CN14)*AP$38,"") | AT14: =IFERROR(IF(AR14+AS14=0,"",AR14+AS14),"") | AU14: =IFERROR((($CL14/1.15)-(AQ14-(AQ14*AP$2)))/($CL14/1.15),"") | AV14: =IFERROR((($CM14/1.15)+(AR14+AS14)-(AQ14-(AQ14*AP$2)))/($CM14/1.15),"") | AW14: {=IFERROR( _xlfn.LET( _xlpm.result, INDEX(_xlfn._xlws.FILTER(ST[6wk avg], (ST[Code]=$C14)*(ST[Customer Name]=AP$3), ""), 1), IF(_xlpm.result=0, "", _xlpm.result) ), "")} | AX14: =IFERROR(IF(CEILING(AW14 + (AW14 * $N$2), 1) = 0, "", CEILING(AW14 + (AW14 * $N$2), 1))*$B$3, "") | AY14: =IFERROR((AX14*AR14),"") | AZ14: =IFERROR((AX14*AS14),"") | BB14: {=IFERROR(_xlfn._xlws.FILTER(#REF!,(#REF!=$C14) * (#REF!=BB$3),"" ),"")} | BC14: {=IFERROR(_xlfn.XLOOKUP($C14,Master_Price_Level_NZ[Code],INDEX(Master_Price_Level_NZ[], , MATCH('Promo Form'!BB$3, Master_Price_Level_NZ[#Headers], 0))),"")} | BD14: =IFERROR(((BC14*(1-BB$2))*$CN14)*BB$39,"") | BE14: =IFERROR(((BC14*(1-BB$2))*$CN14)*BB$38,"") | BF14: =IFERROR(IF(BD14+BE14=0,"",BD14+BE14),"") | BG14: =IFERROR((($CL14/1.15)-(BC14-(BC14*BB$2)))/($CL14/1.15),"") | BH14: =IFERROR((($CM14/1.15)+(BD14+BE14)-(BC14-(BC14*BB$2)))/($CM14/1.15),"") | BI14: {=IFERROR( _xlfn.LET( _xlpm.result, INDEX(_xlfn._xlws.FILTER(ST[6wk avg], (ST[Code]=$C14)*(ST[Customer Name]=BB$3), ""), 1), IF(_xlpm.result=0, "", _xlpm.result) ), "")} | BJ14: =IFERROR(IF(CEILING(BI14 + (BI14 * $N$2), 1) = 0, "", CEILING(BI14 + (BI14 * $N$2), 1))*$B$3, "") | BK14: =IFERROR((BJ14*BD14),"") | BL14: =IFERROR((BJ14*BE14),"") | BN14: {=IFERROR(_xlfn._xlws.FILTER(#REF!,(#REF!=$C14) * (#REF!=BN$3),"" ),"")} | BO14: {=IFERROR(_xlfn.XLOOKUP($C14,Master_Price_Level_NZ[Code],INDEX(Master_Price_Level_NZ[], , MATCH('Promo Form'!BN$3, Master_Price_Level_NZ[#Headers], 0))),"")} | BP14: =IFERROR(((BO14*(1-BN$2))*$CN14)*BN$39,"") | BQ14: =IFERROR(((BO14*(1-BN$2))*$CN14)*BN$38,"") | BR14: =IFERROR(IF(BP14+BQ14=0,"",BP14+BQ14),"") | BS14: =IFERROR((($CL14/1.15)-(BO14-(BO14*BN$2)))/($CL14/1.15),"") | BT14: =IFERROR((($CM14/1.15)+(BP14+BQ14)-(BO14-(BO14*BN$2)))/($CM14/1.15),"") | BU14: {=IFERROR( _xlfn.LET( _xlpm.result, INDEX(_xlfn._xlws.FILTER(ST[6wk avg], (ST[Code]=$C14)*(ST[Customer Name]=BN$3), ""), 1), IF(_xlpm.result=0, "", _xlpm.result) ), "")} | BV14: =IFERROR(IF(CEILING(BU14 + (BU14 * $N$2), 1) = 0, "", CEILING(BU14 + (BU14 * $N$2), 1))*$B$3, "") | BW14: =IFERROR((BV14*BP14),"") | BX14: =IFERROR((BV14*BQ14),"") | BZ14: {=IFERROR(_xlfn._xlws.FILTER(#REF!,(#REF!=$C14) * (#REF!=BZ$3),"" ),"")} | CA14: {=IFERROR(_xlfn.XLOOKUP($C14,Master_Price_Level_NZ[Code],INDEX(Master_Price_Level_NZ[], , MATCH('Promo Form'!BZ$3, Master_Price_Level_NZ[#Headers], 0))),"")} | CB14: =IFERROR(((CA14*(1-BZ$2))*$CN14)*BZ$39,"") | CC14: =IFERROR(((CA14*(1-BZ$2))*$CN14)*BZ$38,"") | CD14: =IFERROR(IF(CB14+CC14=0,"",CB14+CC14),"") | CE14: =IFERROR((($CL14/1.15)-(CA14-(CA14*BZ$2)))/($CL14/1.15),"") | CF14: =IFERROR((($CM14/1.15)+(CB14+CC14)-(CA14-(CA14*BZ$2)))/($CM14/1.15),"") | CG14: {=IFERROR( _xlfn.LET( _xlpm.result, INDEX(_xlfn._xlws.FILTER(ST[6wk avg], (ST[Code]=$C14)*(ST[Customer Name]=BZ$3), ""), 1), IF(_xlpm.result=0, "", _xlpm.result) ), "")} | CH14: =IFERROR(IF(CEILING(CG14 + (CG14 * $N$2), 1) = 0, "", CEILING(CG14 + (CG14 * $N$2), 1))*$B$3, "") | CI14: =IFERROR((CH14*CB14),"") | CJ14: =IFERROR((CH14*CC14),"") | CL14: =IFERROR(_xlfn.XLOOKUP(C14,Master_Price_Level_NZ[Code],Master_Price_Level_NZ[Base (RRP Inc)]),"") | CM14: =IFERROR(CL14-(CL14*CN14),"") | CN14: =IF(C14="", "",CN13) | CO14: =IFERROR((CL14-CM14),"")
A15: =IF(C15="","",A14) | B15: =IF(C15="","",B14) | D15: =IF(C15="", "",_xlfn.XLOOKUP(C15,'Master Price Level NZ'!B:B,'Master Price Level NZ'!C:C)) | G15: {=IFERROR(_xlfn.XLOOKUP($C15,Master_Price_Level_NZ[Code],INDEX(Master_Price_Level_NZ[], , MATCH('Promo Form'!F$3, Master_Price_Level_NZ[#Headers], 0))),"")} | H15: =IFERROR(((G15*(1-F$2))*$CN15)*F$39,"") | I15: =IFERROR(((G15*(1-F$2))*$CN15)*F$38,"") | J15: =IFERROR(IF(H15+I15=0,"",H15+I15),"") | K15: =IFERROR((($CL15/1.15)-(G15-(G15*F$2)))/($CL15/1.15),"") | L15: =IFERROR((($CM15/1.15)+(H15+I15)-(G15-(G15*F$2)))/($CM15/1.15),"") | M15: {=IF($C15="","",IFERROR(_xlfn._xlws.FILTER(ST[6wk avg],(ST[Code]=$C15)*(ST[Customer Name]=F$3),""),""))} | N15: =IFERROR(IF(CEILING(M15 + (M15 * $N$2), 1) = 0, "", CEILING(M15 + (M15 * $N$2), 1))*$B$3, "") | O15: =IFERROR((N15*H15),"") | P15: =IFERROR((N15*I15),"") | R15: {=IFERROR(_xlfn._xlws.FILTER(#REF!,(#REF!=$C15) * (#REF!=R$3),"" ),"")} | S15: {=IFERROR(_xlfn.XLOOKUP($C15,Master_Price_Level_NZ[Code],INDEX(Master_Price_Level_NZ[], , MATCH('Promo Form'!R$3, Master_Price_Level_NZ[#Headers], 0))),"")} | T15: =IFERROR(((S15*(1-R$2))*$CN15)*R$39,"") | U15: =IFERROR(((S15*(1-R$2))*$CN15)*R$38,"") | V15: =IFERROR(IF(T15+U15=0,"",T15+U15),"") | W15: =IFERROR((($CL15/1.15)-(S15-(S15*R$2)))/($CL15/1.15),"") | X15: =IFERROR((($CM15/1.15)+(T15+U15)-(S15-(S15*R$2)))/($CM15/1.15),"") | Y15: {=IFERROR( _xlfn.LET( _xlpm.result, INDEX(_xlfn._xlws.FILTER(ST[6wk avg], (ST[Code]=$C15)*(ST[Customer Name]=R$3), ""), 1), IF(_xlpm.result=0, "", _xlpm.result) ), "")} | Z15: =IFERROR(IF(CEILING(Y15 + (Y15 * $N$2), 1) = 0, "", CEILING(Y15 + (Y15 * $N$2), 1))*$B$3, "") | AA15: =IFERROR((Z15*T15),"") | AB15: =IFERROR((Z15*U15),"") | AD15: {=IFERROR(_xlfn._xlws.FILTER(#REF!,(#REF!=$C15) * (#REF!=AD$3),"" ),"")} | AE15: {=IFERROR(_xlfn.XLOOKUP($C15,Master_Price_Level_NZ[Code],INDEX(Master_Price_Level_NZ[], , MATCH('Promo Form'!AD$3, Master_Price_Level_NZ[#Headers], 0))),"")} | AF15: =IFERROR(((AE15*(1-AD$2))*$CN15)*AD$39,"") | AG15: =IFERROR(((AE15*(1-AD$2))*$CN15)*AD$38,"") | AH15: =IFERROR(IF(AF15+AG15=0,"",AF15+AG15),"") | AI15: =IFERROR((($CL15/1.15)-(AE15-(AE15*AD$2)))/($CL15/1.15),"") | AJ15: =IFERROR((($CM15/1.15)+(AF15+AG15)-(AE15-(AE15*AD$2)))/($CM15/1.15),"") | AK15: {=IFERROR( _xlfn.LET( _xlpm.result, INDEX(_xlfn._xlws.FILTER(ST[6wk avg], (ST[Code]=$C15)*(ST[Customer Name]=AD$3), ""), 1), IF(_xlpm.result=0, "", _xlpm.result) ), "")} | AL15: =IFERROR(IF(CEILING(AK15 + (AK15 * $N$2), 1) = 0, "", CEILING(AK15 + (AK15 * $N$2), 1))*$B$3, "") | AM15: =IFERROR((AL15*AF15),"") | AN15: =IFERROR((AL15*AG15),"") | AP15: {=IFERROR(_xlfn._xlws.FILTER(#REF!,(#REF!=$C15) * (#REF!=AP$3),"" ),"")} | AQ15: {=IFERROR(_xlfn.XLOOKUP($C15,Master_Price_Level_NZ[Code],INDEX(Master_Price_Level_NZ[], , MATCH('Promo Form'!AP$3, Master_Price_Level_NZ[#Headers], 0))),"")} | AR15: =IFERROR(((AQ15*(1-AP$2))*$CN15)*AP$39,"") | AS15: =IFERROR(((AQ15*(1-AP$2))*$CN15)*AP$38,"") | AT15: =IFERROR(IF(AR15+AS15=0,"",AR15+AS15),"") | AU15: =IFERROR((($CL15/1.15)-(AQ15-(AQ15*AP$2)))/($CL15/1.15),"") | AV15: =IFERROR((($CM15/1.15)+(AR15+AS15)-(AQ15-(AQ15*AP$2)))/($CM15/1.15),"") | AW15: {=IFERROR( _xlfn.LET( _xlpm.result, INDEX(_xlfn._xlws.FILTER(ST[6wk avg], (ST[Code]=$C15)*(ST[Customer Name]=AP$3), ""), 1), IF(_xlpm.result=0, "", _xlpm.result) ), "")} | AX15: =IFERROR(IF(CEILING(AW15 + (AW15 * $N$2), 1) = 0, "", CEILING(AW15 + (AW15 * $N$2), 1))*$B$3, "") | AY15: =IFERROR((AX15*AR15),"") | AZ15: =IFERROR((AX15*AS15),"") | BB15: {=IFERROR(_xlfn._xlws.FILTER(#REF!,(#REF!=$C15) * (#REF!=BB$3),"" ),"")} | BC15: {=IFERROR(_xlfn.XLOOKUP($C15,Master_Price_Level_NZ[Code],INDEX(Master_Price_Level_NZ[], , MATCH('Promo Form'!BB$3, Master_Price_Level_NZ[#Headers], 0))),"")} | BD15: =IFERROR(((BC15*(1-BB$2))*$CN15)*BB$39,"") | BE15: =IFERROR(((BC15*(1-BB$2))*$CN15)*BB$38,"") | BF15: =IFERROR(IF(BD15+BE15=0,"",BD15+BE15),"") | BG15: =IFERROR((($CL15/1.15)-(BC15-(BC15*BB$2)))/($CL15/1.15),"") | BH15: =IFERROR((($CM15/1.15)+(BD15+BE15)-(BC15-(BC15*BB$2)))/($CM15/1.15),"") | BI15: {=IFERROR( _xlfn.LET( _xlpm.result, INDEX(_xlfn._xlws.FILTER(ST[6wk avg], (ST[Code]=$C15)*(ST[Customer Name]=BB$3), ""), 1), IF(_xlpm.result=0, "", _xlpm.result) ), "")} | BJ15: =IFERROR(IF(CEILING(BI15 + (BI15 * $N$2), 1) = 0, "", CEILING(BI15 + (BI15 * $N$2), 1))*$B$3, "") | BK15: =IFERROR((BJ15*BD15),"") | BL15: =IFERROR((BJ15*BE15),"") | BN15: {=IFERROR(_xlfn._xlws.FILTER(#REF!,(#REF!=$C15) * (#REF!=BN$3),"" ),"")} | BO15: {=IFERROR(_xlfn.XLOOKUP($C15,Master_Price_Level_NZ[Code],INDEX(Master_Price_Level_NZ[], , MATCH('Promo Form'!BN$3, Master_Price_Level_NZ[#Headers], 0))),"")} | BP15: =IFERROR(((BO15*(1-BN$2))*$CN15)*BN$39,"") | BQ15: =IFERROR(((BO15*(1-BN$2))*$CN15)*BN$38,"") | BR15: =IFERROR(IF(BP15+BQ15=0,"",BP15+BQ15),"") | BS15: =IFERROR((($CL15/1.15)-(BO15-(BO15*BN$2)))/($CL15/1.15),"") | BT15: =IFERROR((($CM15/1.15)+(BP15+BQ15)-(BO15-(BO15*BN$2)))/($CM15/1.15),"") | BU15: {=IFERROR( _xlfn.LET( _xlpm.result, INDEX(_xlfn._xlws.FILTER(ST[6wk avg], (ST[Code]=$C15)*(ST[Customer Name]=BN$3), ""), 1), IF(_xlpm.result=0, "", _xlpm.result) ), "")} | BV15: =IFERROR(IF(CEILING(BU15 + (BU15 * $N$2), 1) = 0, "", CEILING(BU15 + (BU15 * $N$2), 1))*$B$3, "") | BW15: =IFERROR((BV15*BP15),"") | BX15: =IFERROR((BV15*BQ15),"") | BZ15: {=IFERROR(_xlfn._xlws.FILTER(#REF!,(#REF!=$C15) * (#REF!=BZ$3),"" ),"")} | CA15: {=IFERROR(_xlfn.XLOOKUP($C15,Master_Price_Level_NZ[Code],INDEX(Master_Price_Level_NZ[], , MATCH('Promo Form'!BZ$3, Master_Price_Level_NZ[#Headers], 0))),"")} | CB15: =IFERROR(((CA15*(1-BZ$2))*$CN15)*BZ$39,"") | CC15: =IFERROR(((CA15*(1-BZ$2))*$CN15)*BZ$38,"") | CD15: =IFERROR(IF(CB15+CC15=0,"",CB15+CC15),"") | CE15: =IFERROR((($CL15/1.15)-(CA15-(CA15*BZ$2)))/($CL15/1.15),"") | CF15: =IFERROR((($CM15/1.15)+(CB15+CC15)-(CA15-(CA15*BZ$2)))/($CM15/1.15),"") | CG15: {=IFERROR( _xlfn.LET( _xlpm.result, INDEX(_xlfn._xlws.FILTER(ST[6wk avg], (ST[Code]=$C15)*(ST[Customer Name]=BZ$3), ""), 1), IF(_xlpm.result=0, "", _xlpm.result) ), "")} | CH15: =IFERROR(IF(CEILING(CG15 + (CG15 * $N$2), 1) = 0, "", CEILING(CG15 + (CG15 * $N$2), 1))*$B$3, "") | CI15: =IFERROR((CH15*CB15),"") | CJ15: =IFERROR((CH15*CC15),"") | CL15: =IFERROR(_xlfn.XLOOKUP(C15,Master_Price_Level_NZ[Code],Master_Price_Level_NZ[Base (RRP Inc)]),"") | CM15: =IFERROR(CL15-(CL15*CN15),"") | CN15: =IF(C15="", "",CN14) | CO15: =IFERROR((CL15-CM15),"")
A16: =IF(C16="","",A15) | B16: =IF(C16="","",B15) | D16: =IF(C16="", "",_xlfn.XLOOKUP(C16,'Master Price Level NZ'!B:B,'Master Price Level NZ'!C:C)) | G16: {=IFERROR(_xlfn.XLOOKUP($C16,Master_Price_Level_NZ[Code],INDEX(Master_Price_Level_NZ[], , MATCH('Promo Form'!F$3, Master_Price_Level_NZ[#Headers], 0))),"")} | H16: =IFERROR(((G16*(1-F$2))*$CN16)*F$39,"") | I16: =IFERROR(((G16*(1-F$2))*$CN16)*F$38,"") | J16: =IFERROR(IF(H16+I16=0,"",H16+I16),"") | K16: =IFERROR((($CL16/1.15)-(G16-(G16*F$2)))/($CL16/1.15),"") | L16: =IFERROR((($CM16/1.15)+(H16+I16)-(G16-(G16*F$2)))/($CM16/1.15),"") | M16: {=IF($C16="","",IFERROR(_xlfn._xlws.FILTER(ST[6wk avg],(ST[Code]=$C16)*(ST[Customer Name]=F$3),""),""))} | N16: =IFERROR(IF(CEILING(M16 + (M16 * $N$2), 1) = 0, "", CEILING(M16 + (M16 * $N$2), 1))*$B$3, "") | O16: =IFERROR((N16*H16),"") | P16: =IFERROR((N16*I16),"") | R16: {=IFERROR(_xlfn._xlws.FILTER(#REF!,(#REF!=$C16) * (#REF!=R$3),"" ),"")} | S16: {=IFERROR(_xlfn.XLOOKUP($C16,Master_Price_Level_NZ[Code],INDEX(Master_Price_Level_NZ[], , MATCH('Promo Form'!R$3, Master_Price_Level_NZ[#Headers], 0))),"")} | T16: =IFERROR(((S16*(1-R$2))*$CN16)*R$39,"") | U16: =IFERROR(((S16*(1-R$2))*$CN16)*R$38,"") | V16: =IFERROR(IF(T16+U16=0,"",T16+U16),"") | W16: =IFERROR((($CL16/1.15)-(S16-(S16*R$2)))/($CL16/1.15),"") | X16: =IFERROR((($CM16/1.15)+(T16+U16)-(S16-(S16*R$2)))/($CM16/1.15),"") | Y16: {=IFERROR( _xlfn.LET( _xlpm.result, INDEX(_xlfn._xlws.FILTER(ST[6wk avg], (ST[Code]=$C16)*(ST[Customer Name]=R$3), ""), 1), IF(_xlpm.result=0, "", _xlpm.result) ), "")} | Z16: =IFERROR(IF(CEILING(Y16 + (Y16 * $N$2), 1) = 0, "", CEILING(Y16 + (Y16 * $N$2), 1))*$B$3, "") | AA16: =IFERROR((Z16*T16),"") | AB16: =IFERROR((Z16*U16),"") | AD16: {=IFERROR(_xlfn._xlws.FILTER(#REF!,(#REF!=$C16) * (#REF!=AD$3),"" ),"")} | AE16: {=IFERROR(_xlfn.XLOOKUP($C16,Master_Price_Level_NZ[Code],INDEX(Master_Price_Level_NZ[], , MATCH('Promo Form'!AD$3, Master_Price_Level_NZ[#Headers], 0))),"")} | AF16: =IFERROR(((AE16*(1-AD$2))*$CN16)*AD$39,"") | AG16: =IFERROR(((AE16*(1-AD$2))*$CN16)*AD$38,"") | AH16: =IFERROR(IF(AF16+AG16=0,"",AF16+AG16),"") | AI16: =IFERROR((($CL16/1.15)-(AE16-(AE16*AD$2)))/($CL16/1.15),"") | AJ16: =IFERROR((($CM16/1.15)+(AF16+AG16)-(AE16-(AE16*AD$2)))/($CM16/1.15),"") | AK16: {=IFERROR( _xlfn.LET( _xlpm.result, INDEX(_xlfn._xlws.FILTER(ST[6wk avg], (ST[Code]=$C16)*(ST[Customer Name]=AD$3), ""), 1), IF(_xlpm.result=0, "", _xlpm.result) ), "")} | AL16: =IFERROR(IF(CEILING(AK16 + (AK16 * $N$2), 1) = 0, "", CEILING(AK16 + (AK16 * $N$2), 1))*$B$3, "") | AM16: =IFERROR((AL16*AF16),"") | AN16: =IFERROR((AL16*AG16),"") | AP16: {=IFERROR(_xlfn._xlws.FILTER(#REF!,(#REF!=$C16) * (#REF!=AP$3),"" ),"")} | AQ16: {=IFERROR(_xlfn.XLOOKUP($C16,Master_Price_Level_NZ[Code],INDEX(Master_Price_Level_NZ[], , MATCH('Promo Form'!AP$3, Master_Price_Level_NZ[#Headers], 0))),"")} | AR16: =IFERROR(((AQ16*(1-AP$2))*$CN16)*AP$39,"") | AS16: =IFERROR(((AQ16*(1-AP$2))*$CN16)*AP$38,"") | AT16: =IFERROR(IF(AR16+AS16=0,"",AR16+AS16),"") | AU16: =IFERROR((($CL16/1.15)-(AQ16-(AQ16*AP$2)))/($CL16/1.15),"") | AV16: =IFERROR((($CM16/1.15)+(AR16+AS16)-(AQ16-(AQ16*AP$2)))/($CM16/1.15),"") | AW16: {=IFERROR( _xlfn.LET( _xlpm.result, INDEX(_xlfn._xlws.FILTER(ST[6wk avg], (ST[Code]=$C16)*(ST[Customer Name]=AP$3), ""), 1), IF(_xlpm.result=0, "", _xlpm.result) ), "")} | AX16: =IFERROR(IF(CEILING(AW16 + (AW16 * $N$2), 1) = 0, "", CEILING(AW16 + (AW16 * $N$2), 1))*$B$3, "") | AY16: =IFERROR((AX16*AR16),"") | AZ16: =IFERROR((AX16*AS16),"") | BB16: {=IFERROR(_xlfn._xlws.FILTER(#REF!,(#REF!=$C16) * (#REF!=BB$3),"" ),"")} | BC16: {=IFERROR(_xlfn.XLOOKUP($C16,Master_Price_Level_NZ[Code],INDEX(Master_Price_Level_NZ[], , MATCH('Promo Form'!BB$3, Master_Price_Level_NZ[#Headers], 0))),"")} | BD16: =IFERROR(((BC16*(1-BB$2))*$CN16)*BB$39,"") | BE16: =IFERROR(((BC16*(1-BB$2))*$CN16)*BB$38,"") | BF16: =IFERROR(IF(BD16+BE16=0,"",BD16+BE16),"") | BG16: =IFERROR((($CL16/1.15)-(BC16-(BC16*BB$2)))/($CL16/1.15),"") | BH16: =IFERROR((($CM16/1.15)+(BD16+BE16)-(BC16-(BC16*BB$2)))/($CM16/1.15),"") | BI16: {=IFERROR( _xlfn.LET( _xlpm.result, INDEX(_xlfn._xlws.FILTER(ST[6wk avg], (ST[Code]=$C16)*(ST[Customer Name]=BB$3), ""), 1), IF(_xlpm.result=0, "", _xlpm.result) ), "")} | BJ16: =IFERROR(IF(CEILING(BI16 + (BI16 * $N$2), 1) = 0, "", CEILING(BI16 + (BI16 * $N$2), 1))*$B$3, "") | BK16: =IFERROR((BJ16*BD16),"") | BL16: =IFERROR((BJ16*BE16),"") | BN16: {=IFERROR(_xlfn._xlws.FILTER(#REF!,(#REF!=$C16) * (#REF!=BN$3),"" ),"")} | BO16: {=IFERROR(_xlfn.XLOOKUP($C16,Master_Price_Level_NZ[Code],INDEX(Master_Price_Level_NZ[], , MATCH('Promo Form'!BN$3, Master_Price_Level_NZ[#Headers], 0))),"")} | BP16: =IFERROR(((BO16*(1-BN$2))*$CN16)*BN$39,"") | BQ16: =IFERROR(((BO16*(1-BN$2))*$CN16)*BN$38,"") | BR16: =IFERROR(IF(BP16+BQ16=0,"",BP16+BQ16),"") | BS16: =IFERROR((($CL16/1.15)-(BO16-(BO16*BN$2)))/($CL16/1.15),"") | BT16: =IFERROR((($CM16/1.15)+(BP16+BQ16)-(BO16-(BO16*BN$2)))/($CM16/1.15),"") | BU16: {=IFERROR( _xlfn.LET( _xlpm.result, INDEX(_xlfn._xlws.FILTER(ST[6wk avg], (ST[Code]=$C16)*(ST[Customer Name]=BN$3), ""), 1), IF(_xlpm.result=0, "", _xlpm.result) ), "")} | BV16: =IFERROR(IF(CEILING(BU16 + (BU16 * $N$2), 1) = 0, "", CEILING(BU16 + (BU16 * $N$2), 1))*$B$3, "") | BW16: =IFERROR((BV16*BP16),"") | BX16: =IFERROR((BV16*BQ16),"") | BZ16: {=IFERROR(_xlfn._xlws.FILTER(#REF!,(#REF!=$C16) * (#REF!=BZ$3),"" ),"")} | CA16: {=IFERROR(_xlfn.XLOOKUP($C16,Master_Price_Level_NZ[Code],INDEX(Master_Price_Level_NZ[], , MATCH('Promo Form'!BZ$3, Master_Price_Level_NZ[#Headers], 0))),"")} | CB16: =IFERROR(((CA16*(1-BZ$2))*$CN16)*BZ$39,"") | CC16: =IFERROR(((CA16*(1-BZ$2))*$CN16)*BZ$38,"") | CD16: =IFERROR(IF(CB16+CC16=0,"",CB16+CC16),"") | CE16: =IFERROR((($CL16/1.15)-(CA16-(CA16*BZ$2)))/($CL16/1.15),"") | CF16: =IFERROR((($CM16/1.15)+(CB16+CC16)-(CA16-(CA16*BZ$2)))/($CM16/1.15),"") | CG16: {=IFERROR( _xlfn.LET( _xlpm.result, INDEX(_xlfn._xlws.FILTER(ST[6wk avg], (ST[Code]=$C16)*(ST[Customer Name]=BZ$3), ""), 1), IF(_xlpm.result=0, "", _xlpm.result) ), "")} | CH16: =IFERROR(IF(CEILING(CG16 + (CG16 * $N$2), 1) = 0, "", CEILING(CG16 + (CG16 * $N$2), 1))*$B$3, "") | CI16: =IFERROR((CH16*CB16),"") | CJ16: =IFERROR((CH16*CC16),"") | CL16: =IFERROR(_xlfn.XLOOKUP(C16,Master_Price_Level_NZ[Code],Master_Price_Level_NZ[Base (RRP Inc)]),"") | CM16: =IFERROR(CL16-(CL16*CN16),"") | CN16: =IF(C16="", "",CN15) | CO16: =IFERROR((CL16-CM16),"")
A17: =IF(C17="","",A16) | B17: =IF(C17="","",B16) | D17: =IF(C17="", "",_xlfn.XLOOKUP(C17,'Master Price Level NZ'!B:B,'Master Price Level NZ'!C:C)) | G17: {=IFERROR(_xlfn.XLOOKUP($C17,Master_Price_Level_NZ[Code],INDEX(Master_Price_Level_NZ[], , MATCH('Promo Form'!F$3, Master_Price_Level_NZ[#Headers], 0))),"")} | H17: =IFERROR(((G17*(1-F$2))*$CN17)*F$39,"") | I17: =IFERROR(((G17*(1-F$2))*$CN17)*F$38,"") | J17: =IFERROR(IF(H17+I17=0,"",H17+I17),"") | K17: =IFERROR((($CL17/1.15)-(G17-(G17*F$2)))/($CL17/1.15),"") | L17: =IFERROR((($CM17/1.15)+(H17+I17)-(G17-(G17*F$2)))/($CM17/1.15),"") | M17: {=IF($C17="","",IFERROR(_xlfn._xlws.FILTER(ST[6wk avg],(ST[Code]=$C17)*(ST[Customer Name]=F$3),""),""))} | N17: =IFERROR(IF(CEILING(M17 + (M17 * $N$2), 1) = 0, "", CEILING(M17 + (M17 * $N$2), 1))*$B$3, "") | O17: =IFERROR((N17*H17),"") | P17: =IFERROR((N17*I17),"") | R17: {=IFERROR(_xlfn._xlws.FILTER(#REF!,(#REF!=$C17) * (#REF!=R$3),"" ),"")} | S17: {=IFERROR(_xlfn.XLOOKUP($C17,Master_Price_Level_NZ[Code],INDEX(Master_Price_Level_NZ[], , MATCH('Promo Form'!R$3, Master_Price_Level_NZ[#Headers], 0))),"")} | T17: =IFERROR(((S17*(1-R$2))*$CN17)*R$39,"") | U17: =IFERROR(((S17*(1-R$2))*$CN17)*R$38,"") | V17: =IFERROR(IF(T17+U17=0,"",T17+U17),"") | W17: =IFERROR((($CL17/1.15)-(S17-(S17*R$2)))/($CL17/1.15),"") | X17: =IFERROR((($CM17/1.15)+(T17+U17)-(S17-(S17*R$2)))/($CM17/1.15),"") | Y17: {=IFERROR( _xlfn.LET( _xlpm.result, INDEX(_xlfn._xlws.FILTER(ST[6wk avg], (ST[Code]=$C17)*(ST[Customer Name]=R$3), ""), 1), IF(_xlpm.result=0, "", _xlpm.result) ), "")} | Z17: =IFERROR(IF(CEILING(Y17 + (Y17 * $N$2), 1) = 0, "", CEILING(Y17 + (Y17 * $N$2), 1))*$B$3, "") | AA17: =IFERROR((Z17*T17),"") | AB17: =IFERROR((Z17*U17),"") | AD17: {=IFERROR(_xlfn._xlws.FILTER(#REF!,(#REF!=$C17) * (#REF!=AD$3),"" ),"")} | AE17: {=IFERROR(_xlfn.XLOOKUP($C17,Master_Price_Level_NZ[Code],INDEX(Master_Price_Level_NZ[], , MATCH('Promo Form'!AD$3, Master_Price_Level_NZ[#Headers], 0))),"")} | AF17: =IFERROR(((AE17*(1-AD$2))*$CN17)*AD$39,"") | AG17: =IFERROR(((AE17*(1-AD$2))*$CN17)*AD$38,"") | AH17: =IFERROR(IF(AF17+AG17=0,"",AF17+AG17),"") | AI17: =IFERROR((($CL17/1.15)-(AE17-(AE17*AD$2)))/($CL17/1.15),"") | AJ17: =IFERROR((($CM17/1.15)+(AF17+AG17)-(AE17-(AE17*AD$2)))/($CM17/1.15),"") | AK17: {=IFERROR( _xlfn.LET( _xlpm.result, INDEX(_xlfn._xlws.FILTER(ST[6wk avg], (ST[Code]=$C17)*(ST[Customer Name]=AD$3), ""), 1), IF(_xlpm.result=0, "", _xlpm.result) ), "")} | AL17: =IFERROR(IF(CEILING(AK17 + (AK17 * $N$2), 1) = 0, "", CEILING(AK17 + (AK17 * $N$2), 1))*$B$3, "") | AM17: =IFERROR((AL17*AF17),"") | AN17: =IFERROR((AL17*AG17),"") | AP17: {=IFERROR(_xlfn._xlws.FILTER(#REF!,(#REF!=$C17) * (#REF!=AP$3),"" ),"")} | AQ17: {=IFERROR(_xlfn.XLOOKUP($C17,Master_Price_Level_NZ[Code],INDEX(Master_Price_Level_NZ[], , MATCH('Promo Form'!AP$3, Master_Price_Level_NZ[#Headers], 0))),"")} | AR17: =IFERROR(((AQ17*(1-AP$2))*$CN17)*AP$39,"") | AS17: =IFERROR(((AQ17*(1-AP$2))*$CN17)*AP$38,"") | AT17: =IFERROR(IF(AR17+AS17=0,"",AR17+AS17),"") | AU17: =IFERROR((($CL17/1.15)-(AQ17-(AQ17*AP$2)))/($CL17/1.15),"") | AV17: =IFERROR((($CM17/1.15)+(AR17+AS17)-(AQ17-(AQ17*AP$2)))/($CM17/1.15),"") | AW17: {=IFERROR( _xlfn.LET( _xlpm.result, INDEX(_xlfn._xlws.FILTER(ST[6wk avg], (ST[Code]=$C17)*(ST[Customer Name]=AP$3), ""), 1), IF(_xlpm.result=0, "", _xlpm.result) ), "")} | AX17: =IFERROR(IF(CEILING(AW17 + (AW17 * $N$2), 1) = 0, "", CEILING(AW17 + (AW17 * $N$2), 1))*$B$3, "") | AY17: =IFERROR((AX17*AR17),"") | AZ17: =IFERROR((AX17*AS17),"") | BB17: {=IFERROR(_xlfn._xlws.FILTER(#REF!,(#REF!=$C17) * (#REF!=BB$3),"" ),"")} | BC17: {=IFERROR(_xlfn.XLOOKUP($C17,Master_Price_Level_NZ[Code],INDEX(Master_Price_Level_NZ[], , MATCH('Promo Form'!BB$3, Master_Price_Level_NZ[#Headers], 0))),"")} | BD17: =IFERROR(((BC17*(1-BB$2))*$CN17)*BB$39,"") | BE17: =IFERROR(((BC17*(1-BB$2))*$CN17)*BB$38,"") | BF17: =IFERROR(IF(BD17+BE17=0,"",BD17+BE17),"") | BG17: =IFERROR((($CL17/1.15)-(BC17-(BC17*BB$2)))/($CL17/1.15),"") | BH17: =IFERROR((($CM17/1.15)+(BD17+BE17)-(BC17-(BC17*BB$2)))/($CM17/1.15),"") | BI17: {=IFERROR( _xlfn.LET( _xlpm.result, INDEX(_xlfn._xlws.FILTER(ST[6wk avg], (ST[Code]=$C17)*(ST[Customer Name]=BB$3), ""), 1), IF(_xlpm.result=0, "", _xlpm.result) ), "")} | BJ17: =IFERROR(IF(CEILING(BI17 + (BI17 * $N$2), 1) = 0, "", CEILING(BI17 + (BI17 * $N$2), 1))*$B$3, "") | BK17: =IFERROR((BJ17*BD17),"") | BL17: =IFERROR((BJ17*BE17),"") | BN17: {=IFERROR(_xlfn._xlws.FILTER(#REF!,(#REF!=$C17) * (#REF!=BN$3),"" ),"")} | BO17: {=IFERROR(_xlfn.XLOOKUP($C17,Master_Price_Level_NZ[Code],INDEX(Master_Price_Level_NZ[], , MATCH('Promo Form'!BN$3, Master_Price_Level_NZ[#Headers], 0))),"")} | BP17: =IFERROR(((BO17*(1-BN$2))*$CN17)*BN$39,"") | BQ17: =IFERROR(((BO17*(1-BN$2))*$CN17)*BN$38,"") | BR17: =IFERROR(IF(BP17+BQ17=0,"",BP17+BQ17),"") | BS17: =IFERROR((($CL17/1.15)-(BO17-(BO17*BN$2)))/($CL17/1.15),"") | BT17: =IFERROR((($CM17/1.15)+(BP17+BQ17)-(BO17-(BO17*BN$2)))/($CM17/1.15),"") | BU17: {=IFERROR( _xlfn.LET( _xlpm.result, INDEX(_xlfn._xlws.FILTER(ST[6wk avg], (ST[Code]=$C17)*(ST[Customer Name]=BN$3), ""), 1), IF(_xlpm.result=0, "", _xlpm.result) ), "")} | BV17: =IFERROR(IF(CEILING(BU17 + (BU17 * $N$2), 1) = 0, "", CEILING(BU17 + (BU17 * $N$2), 1))*$B$3, "") | BW17: =IFERROR((BV17*BP17),"") | BX17: =IFERROR((BV17*BQ17),"") | BZ17: {=IFERROR(_xlfn._xlws.FILTER(#REF!,(#REF!=$C17) * (#REF!=BZ$3),"" ),"")} | CA17: {=IFERROR(_xlfn.XLOOKUP($C17,Master_Price_Level_NZ[Code],INDEX(Master_Price_Level_NZ[], , MATCH('Promo Form'!BZ$3, Master_Price_Level_NZ[#Headers], 0))),"")} | CB17: =IFERROR(((CA17*(1-BZ$2))*$CN17)*BZ$39,"") | CC17: =IFERROR(((CA17*(1-BZ$2))*$CN17)*BZ$38,"") | CD17: =IFERROR(IF(CB17+CC17=0,"",CB17+CC17),"") | CE17: =IFERROR((($CL17/1.15)-(CA17-(CA17*BZ$2)))/($CL17/1.15),"") | CF17: =IFERROR((($CM17/1.15)+(CB17+CC17)-(CA17-(CA17*BZ$2)))/($CM17/1.15),"") | CG17: {=IFERROR( _xlfn.LET( _xlpm.result, INDEX(_xlfn._xlws.FILTER(ST[6wk avg], (ST[Code]=$C17)*(ST[Customer Name]=BZ$3), ""), 1), IF(_xlpm.result=0, "", _xlpm.result) ), "")} | CH17: =IFERROR(IF(CEILING(CG17 + (CG17 * $N$2), 1) = 0, "", CEILING(CG17 + (CG17 * $N$2), 1))*$B$3, "") | CI17: =IFERROR((CH17*CB17),"") | CJ17: =IFERROR((CH17*CC17),"") | CL17: =IFERROR(_xlfn.XLOOKUP(C17,Master_Price_Level_NZ[Code],Master_Price_Level_NZ[Base (RRP Inc)]),"") | CM17: =IFERROR(CL17-(CL17*CN17),"") | CN17: =IF(C17="", "",CN16) | CO17: =IFERROR((CL17-CM17),"")
A18: =IF(C18="","",A17) | B18: =IF(C18="","",B17) | D18: =IF(C18="", "",_xlfn.XLOOKUP(C18,'Master Price Level NZ'!B:B,'Master Price Level NZ'!C:C)) | G18: {=IFERROR(_xlfn.XLOOKUP($C18,Master_Price_Level_NZ[Code],INDEX(Master_Price_Level_NZ[], , MATCH('Promo Form'!F$3, Master_Price_Level_NZ[#Headers], 0))),"")} | H18: =IFERROR(((G18*(1-F$2))*$CN18)*F$39,"") | I18: =IFERROR(((G18*(1-F$2))*$CN18)*F$38,"") | J18: =IFERROR(IF(H18+I18=0,"",H18+I18),"") | K18: =IFERROR((($CL18/1.15)-(G18-(G18*F$2)))/($CL18/1.15),"") | L18: =IFERROR((($CM18/1.15)+(H18+I18)-(G18-(G18*F$2)))/($CM18/1.15),"") | M18: {=IF($C18="","",IFERROR(_xlfn._xlws.FILTER(ST[6wk avg],(ST[Code]=$C18)*(ST[Customer Name]=F$3),""),""))} | N18: =IFERROR(IF(CEILING(M18 + (M18 * $N$2), 1) = 0, "", CEILING(M18 + (M18 * $N$2), 1))*$B$3, "") | O18: =IFERROR((N18*H18),"") | P18: =IFERROR((N18*I18),"") | R18: {=IFERROR(_xlfn._xlws.FILTER(#REF!,(#REF!=$C18) * (#REF!=R$3),"" ),"")} | S18: {=IFERROR(_xlfn.XLOOKUP($C18,Master_Price_Level_NZ[Code],INDEX(Master_Price_Level_NZ[], , MATCH('Promo Form'!R$3, Master_Price_Level_NZ[#Headers], 0))),"")} | T18: =IFERROR(((S18*(1-R$2))*$CN18)*R$39,"") | U18: =IFERROR(((S18*(1-R$2))*$CN18)*R$38,"") | V18: =IFERROR(IF(T18+U18=0,"",T18+U18),"") | W18: =IFERROR((($CL18/1.15)-(S18-(S18*R$2)))/($CL18/1.15),"") | X18: =IFERROR((($CM18/1.15)+(T18+U18)-(S18-(S18*R$2)))/($CM18/1.15),"") | Y18: {=IFERROR( _xlfn.LET( _xlpm.result, INDEX(_xlfn._xlws.FILTER(ST[6wk avg], (ST[Code]=$C18)*(ST[Customer Name]=R$3), ""), 1), IF(_xlpm.result=0, "", _xlpm.result) ), "")} | Z18: =IFERROR(IF(CEILING(Y18 + (Y18 * $N$2), 1) = 0, "", CEILING(Y18 + (Y18 * $N$2), 1))*$B$3, "") | AA18: =IFERROR((Z18*T18),"") | AB18: =IFERROR((Z18*U18),"") | AD18: {=IFERROR(_xlfn._xlws.FILTER(#REF!,(#REF!=$C18) * (#REF!=AD$3),"" ),"")} | AE18: {=IFERROR(_xlfn.XLOOKUP($C18,Master_Price_Level_NZ[Code],INDEX(Master_Price_Level_NZ[], , MATCH('Promo Form'!AD$3, Master_Price_Level_NZ[#Headers], 0))),"")} | AF18: =IFERROR(((AE18*(1-AD$2))*$CN18)*AD$39,"") | AG18: =IFERROR(((AE18*(1-AD$2))*$CN18)*AD$38,"") | AH18: =IFERROR(IF(AF18+AG18=0,"",AF18+AG18),"") | AI18: =IFERROR((($CL18/1.15)-(AE18-(AE18*AD$2)))/($CL18/1.15),"") | AJ18: =IFERROR((($CM18/1.15)+(AF18+AG18)-(AE18-(AE18*AD$2)))/($CM18/1.15),"") | AK18: {=IFERROR( _xlfn.LET( _xlpm.result, INDEX(_xlfn._xlws.FILTER(ST[6wk avg], (ST[Code]=$C18)*(ST[Customer Name]=AD$3), ""), 1), IF(_xlpm.result=0, "", _xlpm.result) ), "")} | AL18: =IFERROR(IF(CEILING(AK18 + (AK18 * $N$2), 1) = 0, "", CEILING(AK18 + (AK18 * $N$2), 1))*$B$3, "") | AM18: =IFERROR((AL18*AF18),"") | AN18: =IFERROR((AL18*AG18),"") | AP18: {=IFERROR(_xlfn._xlws.FILTER(#REF!,(#REF!=$C18) * (#REF!=AP$3),"" ),"")} | AQ18: {=IFERROR(_xlfn.XLOOKUP($C18,Master_Price_Level_NZ[Code],INDEX(Master_Price_Level_NZ[], , MATCH('Promo Form'!AP$3, Master_Price_Level_NZ[#Headers], 0))),"")} | AR18: =IFERROR(((AQ18*(1-AP$2))*$CN18)*AP$39,"") | AS18: =IFERROR(((AQ18*(1-AP$2))*$CN18)*AP$38,"") | AT18: =IFERROR(IF(AR18+AS18=0,"",AR18+AS18),"") | AU18: =IFERROR((($CL18/1.15)-(AQ18-(AQ18*AP$2)))/($CL18/1.15),"") | AV18: =IFERROR((($CM18/1.15)+(AR18+AS18)-(AQ18-(AQ18*AP$2)))/($CM18/1.15),"") | AW18: {=IFERROR( _xlfn.LET( _xlpm.result, INDEX(_xlfn._xlws.FILTER(ST[6wk avg], (ST[Code]=$C18)*(ST[Customer Name]=AP$3), ""), 1), IF(_xlpm.result=0, "", _xlpm.result) ), "")} | AX18: =IFERROR(IF(CEILING(AW18 + (AW18 * $N$2), 1) = 0, "", CEILING(AW18 + (AW18 * $N$2), 1))*$B$3, "") | AY18: =IFERROR((AX18*AR18),"") | AZ18: =IFERROR((AX18*AS18),"") | BB18: {=IFERROR(_xlfn._xlws.FILTER(#REF!,(#REF!=$C18) * (#REF!=BB$3),"" ),"")} | BC18: {=IFERROR(_xlfn.XLOOKUP($C18,Master_Price_Level_NZ[Code],INDEX(Master_Price_Level_NZ[], , MATCH('Promo Form'!BB$3, Master_Price_Level_NZ[#Headers], 0))),"")} | BD18: =IFERROR(((BC18*(1-BB$2))*$CN18)*BB$39,"") | BE18: =IFERROR(((BC18*(1-BB$2))*$CN18)*BB$38,"") | BF18: =IFERROR(IF(BD18+BE18=0,"",BD18+BE18),"") | BG18: =IFERROR((($CL18/1.15)-(BC18-(BC18*BB$2)))/($CL18/1.15),"") | BH18: =IFERROR((($CM18/1.15)+(BD18+BE18)-(BC18-(BC18*BB$2)))/($CM18/1.15),"") | BI18: {=IFERROR( _xlfn.LET( _xlpm.result, INDEX(_xlfn._xlws.FILTER(ST[6wk avg], (ST[Code]=$C18)*(ST[Customer Name]=BB$3), ""), 1), IF(_xlpm.result=0, "", _xlpm.result) ), "")} | BJ18: =IFERROR(IF(CEILING(BI18 + (BI18 * $N$2), 1) = 0, "", CEILING(BI18 + (BI18 * $N$2), 1))*$B$3, "") | BK18: =IFERROR((BJ18*BD18),"") | BL18: =IFERROR((BJ18*BE18),"") | BN18: {=IFERROR(_xlfn._xlws.FILTER(#REF!,(#REF!=$C18) * (#REF!=BN$3),"" ),"")} | BO18: {=IFERROR(_xlfn.XLOOKUP($C18,Master_Price_Level_NZ[Code],INDEX(Master_Price_Level_NZ[], , MATCH('Promo Form'!BN$3, Master_Price_Level_NZ[#Headers], 0))),"")} | BP18: =IFERROR(((BO18*(1-BN$2))*$CN18)*BN$39,"") | BQ18: =IFERROR(((BO18*(1-BN$2))*$CN18)*BN$38,"") | BR18: =IFERROR(IF(BP18+BQ18=0,"",BP18+BQ18),"") | BS18: =IFERROR((($CL18/1.15)-(BO18-(BO18*BN$2)))/($CL18/1.15),"") | BT18: =IFERROR((($CM18/1.15)+(BP18+BQ18)-(BO18-(BO18*BN$2)))/($CM18/1.15),"") | BU18: {=IFERROR( _xlfn.LET( _xlpm.result, INDEX(_xlfn._xlws.FILTER(ST[6wk avg], (ST[Code]=$C18)*(ST[Customer Name]=BN$3), ""), 1), IF(_xlpm.result=0, "", _xlpm.result) ), "")} | BV18: =IFERROR(IF(CEILING(BU18 + (BU18 * $N$2), 1) = 0, "", CEILING(BU18 + (BU18 * $N$2), 1))*$B$3, "") | BW18: =IFERROR((BV18*BP18),"") | BX18: =IFERROR((BV18*BQ18),"") | BZ18: {=IFERROR(_xlfn._xlws.FILTER(#REF!,(#REF!=$C18) * (#REF!=BZ$3),"" ),"")} | CA18: {=IFERROR(_xlfn.XLOOKUP($C18,Master_Price_Level_NZ[Code],INDEX(Master_Price_Level_NZ[], , MATCH('Promo Form'!BZ$3, Master_Price_Level_NZ[#Headers], 0))),"")} | CB18: =IFERROR(((CA18*(1-BZ$2))*$CN18)*BZ$39,"") | CC18: =IFERROR(((CA18*(1-BZ$2))*$CN18)*BZ$38,"") | CD18: =IFERROR(IF(CB18+CC18=0,"",CB18+CC18),"") | CE18: =IFERROR((($CL18/1.15)-(CA18-(CA18*BZ$2)))/($CL18/1.15),"") | CF18: =IFERROR((($CM18/1.15)+(CB18+CC18)-(CA18-(CA18*BZ$2)))/($CM18/1.15),"") | CG18: {=IFERROR( _xlfn.LET( _xlpm.result, INDEX(_xlfn._xlws.FILTER(ST[6wk avg], (ST[Code]=$C18)*(ST[Customer Name]=BZ$3), ""), 1), IF(_xlpm.result=0, "", _xlpm.result) ), "")} | CH18: =IFERROR(IF(CEILING(CG18 + (CG18 * $N$2), 1) = 0, "", CEILING(CG18 + (CG18 * $N$2), 1))*$B$3, "") | CI18: =IFERROR((CH18*CB18),"") | CJ18: =IFERROR((CH18*CC18),"") | CL18: =IFERROR(_xlfn.XLOOKUP(C18,Master_Price_Level_NZ[Code],Master_Price_Level_NZ[Base (RRP Inc)]),"") | CM18: =IFERROR(CL18-(CL18*CN18),"") | CN18: =IF(C18="", "",CN17) | CO18: =IFERROR((CL18-CM18),"")
... A27: =IF(C27="","",A26) | B27: =IF(C27="","",B26) | D27: =IF(C27="", "",_xlfn.XLOOKUP(C27,'Master Price Level NZ'!B:B,'Master Price Level NZ'!C:C)) | G27: {=IFERROR(_xlfn.XLOOKUP($C27,Master_Price_Level_NZ[Code],INDEX(Master_Price_Level_NZ[], , MATCH('Promo Form'!F$3, Master_Price_Level_NZ[#Headers], 0))),"")} | H27: =IFERROR(((G27*(1-F$2))*$CN27)*F$39,"") | I27: =IFERROR(((G27*(1-F$2))*$CN27)*F$38,"") | J27: =IFERROR(IF(H27+I27=0,"",H27+I27),"") | K27: =IFERROR((($CL27/1.15)-(G27-(G27*F$2)))/($CL27/1.15),"") | L27: =IFERROR((($CM27/1.15)+(H27+I27)-(G27-(G27*F$2)))/($CM27/1.15),"") | M27: {=IF($C27="","",IFERROR(_xlfn._xlws.FILTER(ST[6wk avg],(ST[Code]=$C27)*(ST[Customer Name]=F$3),""),""))} | N27: =IFERROR(IF(CEILING(M27 + (M27 * $N$2), 1) = 0, "", CEILING(M27 + (M27 * $N$2), 1))*$B$3, "") | O27: =IFERROR((N27*H27),"") | P27: =IFERROR((N27*I27),"") | R27: {=IFERROR(_xlfn._xlws.FILTER(#REF!,(#REF!=$C27) * (#REF!=R$3),"" ),"")} | S27: {=IFERROR(_xlfn.XLOOKUP($C27,Master_Price_Level_NZ[Code],INDEX(Master_Price_Level_NZ[], , MATCH('Promo Form'!R$3, Master_Price_Level_NZ[#Headers], 0))),"")} | T27: =IFERROR(((S27*(1-R$2))*$CN27)*R$39,"") | U27: =IFERROR(((S27*(1-R$2))*$CN27)*R$38,"") | V27: =IFERROR(IF(T27+U27=0,"",T27+U27),"") | W27: =IFERROR((($CL27/1.15)-(S27-(S27*R$2)))/($CL27/1.15),"") | X27: =IFERROR((($CM27/1.15)+(T27+U27)-(S27-(S27*R$2)))/($CM27/1.15),"") | Y27: {=IFERROR( _xlfn.LET( _xlpm.result, INDEX(_xlfn._xlws.FILTER(ST[6wk avg], (ST[Code]=$C27)*(ST[Customer Name]=R$3), ""), 1), IF(_xlpm.result=0, "", _xlpm.result) ), "")} | Z27: =IFERROR(IF(CEILING(Y27 + (Y27 * $N$2), 1) = 0, "", CEILING(Y27 + (Y27 * $N$2), 1))*$B$3, "") | AA27: =IFERROR((Z27*T27),"") | AB27: =IFERROR((Z27*U27),"") | AD27: {=IFERROR(_xlfn._xlws.FILTER(#REF!,(#REF!=$C27) * (#REF!=AD$3),"" ),"")} | AE27: {=IFERROR(_xlfn.XLOOKUP($C27,Master_Price_Level_NZ[Code],INDEX(Master_Price_Level_NZ[], , MATCH('Promo Form'!AD$3, Master_Price_Level_NZ[#Headers], 0))),"")} | AF27: =IFERROR(((AE27*(1-AD$2))*$CN27)*AD$39,"") | AG27: =IFERROR(((AE27*(1-AD$2))*$CN27)*AD$38,"") | AH27: =IFERROR(IF(AF27+AG27=0,"",AF27+AG27),"") | AI27: =IFERROR((($CL27/1.15)-(AE27-(AE27*AD$2)))/($CL27/1.15),"") | AJ27: =IFERROR((($CM27/1.15)+(AF27+AG27)-(AE27-(AE27*AD$2)))/($CM27/1.15),"") | AK27: {=IFERROR( _xlfn.LET( _xlpm.result, INDEX(_xlfn._xlws.FILTER(ST[6wk avg], (ST[Code]=$C27)*(ST[Customer Name]=AD$3), ""), 1), IF(_xlpm.result=0, "", _xlpm.result) ), "")} | AL27: =IFERROR(IF(CEILING(AK27 + (AK27 * $N$2), 1) = 0, "", CEILING(AK27 + (AK27 * $N$2), 1))*$B$3, "") | AM27: =IFERROR((AL27*AF27),"") | AN27: =IFERROR((AL27*AG27),"") | AP27: {=IFERROR(_xlfn._xlws.FILTER(#REF!,(#REF!=$C27) * (#REF!=AP$3),"" ),"")} | AQ27: {=IFERROR(_xlfn.XLOOKUP($C27,Master_Price_Level_NZ[Code],INDEX(Master_Price_Level_NZ[], , MATCH('Promo Form'!AP$3, Master_Price_Level_NZ[#Headers], 0))),"")} | AR27: =IFERROR(((AQ27*(1-AP$2))*$CN27)*AP$39,"") | AS27: =IFERROR(((AQ27*(1-AP$2))*$CN27)*AP$38,"") | AT27: =IFERROR(IF(AR27+AS27=0,"",AR27+AS27),"") | AU27: =IFERROR((($CL27/1.15)-(AQ27-(AQ27*AP$2)))/($CL27/1.15),"") | AV27: =IFERROR((($CM27/1.15)+(AR27+AS27)-(AQ27-(AQ27*AP$2)))/($CM27/1.15),"") | AW27: {=IFERROR( _xlfn.LET( _xlpm.result, INDEX(_xlfn._xlws.FILTER(ST[6wk avg], (ST[Code]=$C27)*(ST[Customer Name]=AP$3), ""), 1), IF(_xlpm.result=0, "", _xlpm.result) ), "")} | AX27: =IFERROR(IF(CEILING(AW27 + (AW27 * $N$2), 1) = 0, "", CEILING(AW27 + (AW27 * $N$2), 1))*$B$3, "") | AY27: =IFERROR((AX27*AR27),"") | AZ27: =IFERROR((AX27*AS27),"") | BB27: {=IFERROR(_xlfn._xlws.FILTER(#REF!,(#REF!=$C27) * (#REF!=BB$3),"" ),"")} | BC27: {=IFERROR(_xlfn.XLOOKUP($C27,Master_Price_Level_NZ[Code],INDEX(Master_Price_Level_NZ[], , MATCH('Promo Form'!BB$3, Master_Price_Level_NZ[#Headers], 0))),"")} | BD27: =IFERROR(((BC27*(1-BB$2))*$CN27)*BB$39,"") | BE27: =IFERROR(((BC27*(1-BB$2))*$CN27)*BB$38,"") | BF27: =IFERROR(IF(BD27+BE27=0,"",BD27+BE27),"") | BG27: =IFERROR((($CL27/1.15)-(BC27-(BC27*BB$2)))/($CL27/1.15),"") | BH27: =IFERROR((($CM27/1.15)+(BD27+BE27)-(BC27-(BC27*BB$2)))/($CM27/1.15),"") | BI27: {=IFERROR( _xlfn.LET( _xlpm.result, INDEX(_xlfn._xlws.FILTER(ST[6wk avg], (ST[Code]=$C27)*(ST[Customer Name]=BB$3), ""), 1), IF(_xlpm.result=0, "", _xlpm.result) ), "")} | BJ27: =IFERROR(IF(CEILING(BI27 + (BI27 * $N$2), 1) = 0, "", CEILING(BI27 + (BI27 * $N$2), 1))*$B$3, "") | BK27: =IFERROR((BJ27*BD27),"") | BL27: =IFERROR((BJ27*BE27),"") | BN27: {=IFERROR(_xlfn._xlws.FILTER(#REF!,(#REF!=$C27) * (#REF!=BN$3),"" ),"")} | BO27: {=IFERROR(_xlfn.XLOOKUP($C27,Master_Price_Level_NZ[Code],INDEX(Master_Price_Level_NZ[], , MATCH('Promo Form'!BN$3, Master_Price_Level_NZ[#Headers], 0))),"")} | BP27: =IFERROR(((BO27*(1-BN$2))*$CN27)*BN$39,"") | BQ27: =IFERROR(((BO27*(1-BN$2))*$CN27)*BN$38,"") | BR27: =IFERROR(IF(BP27+BQ27=0,"",BP27+BQ27),"") | BS27: =IFERROR((($CL27/1.15)-(BO27-(BO27*BN$2)))/($CL27/1.15),"") | BT27: =IFERROR((($CM27/1.15)+(BP27+BQ27)-(BO27-(BO27*BN$2)))/($CM27/1.15),"") | BU27: {=IFERROR( _xlfn.LET( _xlpm.result, INDEX(_xlfn._xlws.FILTER(ST[6wk avg], (ST[Code]=$C27)*(ST[Customer Name]=BN$3), ""), 1), IF(_xlpm.result=0, "", _xlpm.result) ), "")} | BV27: =IFERROR(IF(CEILING(BU27 + (BU27 * $N$2), 1) = 0, "", CEILING(BU27 + (BU27 * $N$2), 1))*$B$3, "") | BW27: =IFERROR((BV27*BP27),"") | BX27: =IFERROR((BV27*BQ27),"") | BZ27: {=IFERROR(_xlfn._xlws.FILTER(#REF!,(#REF!=$C27) * (#REF!=BZ$3),"" ),"")} | CA27: {=IFERROR(_xlfn.XLOOKUP($C27,Master_Price_Level_NZ[Code],INDEX(Master_Price_Level_NZ[], , MATCH('Promo Form'!BZ$3, Master_Price_Level_NZ[#Headers], 0))),"")} | CB27: =IFERROR(((CA27*(1-BZ$2))*$CN27)*BZ$39,"") | CC27: =IFERROR(((CA27*(1-BZ$2))*$CN27)*BZ$38,"") | CD27: =IFERROR(IF(CB27+CC27=0,"",CB27+CC27),"") | CE27: =IFERROR((($CL27/1.15)-(CA27-(CA27*BZ$2)))/($CL27/1.15),"") | CF27: =IFERROR((($CM27/1.15)+(CB27+CC27)-(CA27-(CA27*BZ$2)))/($CM27/1.15),"") | CG27: {=IFERROR( _xlfn.LET( _xlpm.result, INDEX(_xlfn._xlws.FILTER(ST[6wk avg], (ST[Code]=$C27)*(ST[Customer Name]=BZ$3), ""), 1), IF(_xlpm.result=0, "", _xlpm.result) ), "")} | CH27: =IFERROR(IF(CEILING(CG27 + (CG27 * $N$2), 1) = 0, "", CEILING(CG27 + (CG27 * $N$2), 1))*$B$3, "") | CI27: =IFERROR((CH27*CB27),"") | CJ27: =IFERROR((CH27*CC27),"") | CL27: =IFERROR(_xlfn.XLOOKUP(C27,Master_Price_Level_NZ[Code],Master_Price_Level_NZ[Base (RRP Inc)]),"") | CM27: =IFERROR(CL27-(CL27*CN27),"") | CN27: =IF(C27="", "",CN26) | CO27: =IFERROR((CL27-CM27),"")
A28: Last Day for Customer claims to be submitted | D28: =B5+14 -> 45686 | L28: =IFERROR((($EX28/1.1)+(H28+I28)-(G28-(G28*F$2)))/($EX28/1.1),"") | N28: =IFERROR((($EX28/1.1)+(I28+J28)-(H28-(H28*G$2)))/($EX28/1.1),"") | X28: =IFERROR((($EX28/1.1)+(T28+U28)-(S28-(S28*R$2)))/($EX28/1.1),"") | Z28: =IFERROR((($EX28/1.1)+(U28+V28)-(T28-(T28*S$2)))/($EX28/1.1),"") | AJ28: =IFERROR((($EX28/1.1)+(AF28+AG28)-(AE28-(AE28*AD$2)))/($EX28/1.1),"") | AL28: =IFERROR((($EX28/1.1)+(AG28+AH28)-(AF28-(AF28*AE$2)))/($EX28/1.1),"") | AV28: =IFERROR((($EX28/1.1)+(AR28+AS28)-(AQ28-(AQ28*AP$2)))/($EX28/1.1),"") | AX28: =IFERROR((($EX28/1.1)+(AS28+AT28)-(AR28-(AR28*AQ$2)))/($EX28/1.1),"") | BH28: =IFERROR((($EX28/1.1)+(BD28+BE28)-(BC28-(BC28*BB$2)))/($EX28/1.1),"") | BJ28: =IFERROR((($EX28/1.1)+(BE28+BF28)-(BD28-(BD28*BC$2)))/($EX28/1.1),"") | BT28: =IFERROR((($EX28/1.1)+(BP28+BQ28)-(BO28-(BO28*BN$2)))/($EX28/1.1),"") | BV28: =IFERROR((($EX28/1.1)+(BQ28+BR28)-(BP28-(BP28*BO$2)))/($EX28/1.1),"") | CF28: =IFERROR((($EX28/1.1)+(CB28+CC28)-(CA28-(CA28*BZ$2)))/($EX28/1.1),"") | CH28: =IFERROR((($EX28/1.1)+(CC28+CD28)-(CB28-(CB28*CA$2)))/($EX28/1.1),"")
F29: TRUE | N29: Total | O29: Supplier | P29: Macgear | R29: TRUE | Z29: Total | AA29: Supplier | AB29: Macgear | AD29: TRUE | AL29: Total | AM29: Supplier | AN29: Macgear | AP29: TRUE | AX29: Total | AY29: Supplier | AZ29: Macgear | BB29: FALSE | BJ29: Total | BK29: Supplier | BL29: Macgear | BN29: FALSE | BV29: Total | BW29: Supplier | BX29: Macgear | BZ29: FALSE | CH29: Total | CI29: Supplier | CJ29: Macgear
A30: TOTAL Macgear Claim NZD Ex | D30: =SUM(P30,AB30,AN30,AZ30,BL30,BX30,CJ30) -> 91.79 | F30: =IF(F29,"ACTIVE","INACTIVE") -> ACTIVE | O30: =SUM(O5:O27) -> 21.906 | P30: =SUM(P5:P27) -> 21.906 | R30: =IF(R29,"ACTIVE","INACTIVE") -> ACTIVE | AA30: =SUM(AA5:AA27) -> 0 | AB30: =SUM(AB5:AB27) -> 0 | AD30: =IF(AD29,"ACTIVE","INACTIVE") -> ACTIVE | AM30: =SUM(AM5:AM27) -> 21.906 | AN30: =SUM(AN5:AN27) -> 21.906 | AP30: =IF(AP29,"ACTIVE","INACTIVE") -> ACTIVE | AY30: =SUM(AY5:AY27) -> 47.978 | AZ30: =SUM(AZ5:AZ27) -> 47.978 | BB30: =IF(BB29,"ACTIVE","INACTIVE") -> INACTIVE | BK30: =SUM(BK5:BK27) -> 0 | BL30: =SUM(BL5:BL27) -> 0 | BN30: =IF(BN29,"ACTIVE","INACTIVE") -> INACTIVE | BW30: =SUM(BW5:BW27) -> 0 | BX30: =SUM(BX5:BX27) -> 0 | BZ30: =IF(BZ29,"ACTIVE","INACTIVE") -> INACTIVE | CI30: =SUM(CI5:CI27) -> 0 | CJ30: =SUM(CJ5:CJ27) -> 0
A31: TOTAL Brand Claim NZD Ex | D31: =SUM(O30,AA30,AM30,AY30,BK30,BW30,CI30) -> 91.79
A32: TOTAL CLAIM to USD ex | D32: =D31*D33 -> 55.074
A33: Vendor Claim | B33: Not Sent | C33: AUD to USD Rate | D33: 0.6
A34: Claim Date | C34: #VALUE! | D34: {=_FV(C34,"Price")} -> 0.573 | E34: {=_FV(C34,"Exchange")} -> #VALUE!
A35: Vendor Claim $ | E35: {=_FV(C35,"Change (%)",TRUE)} -> #VALUE!
A36: Claims and Funding | F36: Ratio | G36: Company | R36: Ratio | S36: Company | AD36: Ratio | AE36: Company | AP36: Ratio | AQ36: Company | BB36: Ratio | BC36: Company | BN36: Ratio | BO36: Company | BZ36: Ratio | CA36: Company
A37: This shows the split of funding between the Retailer, Macgear and Brand | D37: Retailer | F37: 0.5 | G37: Retailer | R37: 0.5 | S37: Retailer | AD37: 0.5 | AE37: Retailer | AP37: 0.5 | AQ37: Retailer | BB37: 0.5 | BC37: Retailer | BN37: 0.5 | BO37: Retailer | BZ37: 0.5 | CA37: Retailer
D38: MacGear | F38: 0.25 | G38: MacGear | R38: 0.25 | S38: MacGear | AD38: 0.25 | AE38: MacGear | AP38: 0.25 | AQ38: MacGear | BB38: 0.25 | BC38: MacGear | BN38: 0.25 | BO38: MacGear | BZ38: 0.25 | CA38: MacGear
D39: Brand | F39: 0.25 | G39: Supplier | R39: 0.25 | S39: Supplier | AD39: 0.25 | AE39: Supplier | AP39: 0.25 | AQ39: Supplier | BB39: 0.25 | BC39: Supplier | BN39: 0.25 | BO39: Supplier | BZ39: 0.25 | CA39: Supplier
F40: =SUM(F37:F39) -> 1 | G40: Total (should = 1) | R40: =SUM(R37:R39) -> 1 | S40: Total (should = 1) | AD40: =SUM(AD37:AD39) -> 1 | AE40: Total (should = 1) | AP40: =SUM(AP37:AP39) -> 1 | AQ40: Total (should = 1) | BB40: =SUM(BB37:BB39) -> 1 | BC40: Total (should = 1) | BN40: =SUM(BN37:BN39) -> 1 | BO40: Total (should = 1) | BZ40: =SUM(BZ37:BZ39) -> 1 | CA40: Total (should = 1)
H41: Notes: | T41: Notes: | AF41: Notes: | AR41: Notes: | BD41: Notes: | BP41: Notes: | CB41: Notes:
F42: Claim Details | R42: Claim Details | AD42: Claim Details | AP42: Claim Details | BB42: Claim Details | BN42: Claim Details | BZ42: Claim Details
A43: Date of claim | D43: Date | G43: Date | S43: Date | AE43: Date | AQ43: Date | BC43: Date | BO43: Date | CA43: Date
A44: Amount Claimed by Customer | D44: Customer Claim Amount | G44: Cust Claim $ | S44: Cust Claim $ | AE44: Cust Claim $ | AQ44: Cust Claim $ | BC44: Cust Claim $ | BO44: Cust Claim $ | CA44: Cust Claim $
A45: Check Value | D45: Check Value | F45: =O30+P30 -> 43.812 | G45: Check Value | R45: =AA30+AB30 -> 0 | S45: Check Value | AD45: =AM30+AN30 -> 43.812 | AE45: Check Value | AP45: =AY30+AZ30 -> 95.956 | AQ45: Check Value | BB45: =BK30+BL30 -> 0 | BC45: Check Value | BN45: =BW30+BX30 -> 0 | BO45: Check Value | BZ45: =CI30+CJ30 -> 0 | CA45: Check Value
A46: Status of customers claim | D46: Status | F46: Not Received | G46: Status | R46: Not Received | S46: Status | AD46: Not Received | AE46: Status | AP46: Not Received | AQ46: Status | BB46: Not Received | BC46: Status | BN46: Not Received | BO46: Status | BZ46: Not Received | CA46: Status

Sheet Sales Copy
A1: New Zealand Claim Number | C1: ='Promo Form'!C1 -> 0 | D1: Name of Promotion
A2: Brand | C2: ='Promo Form'!C2 -> 0 | D2: ='Promo Form'!D2 -> 0
A3: Promo Date(s) | C3: Code | D3: Product Description | G3: ='Promo Form'!F3 -> Harvey Norman | O3: ='Promo Form'!R3 -> JB HIFI | W3: ='Promo Form'!AD3 -> Harvey Norman | AE3: ='Promo Form'!AP3 -> PB Tech | AM3: ='Promo Form'!BB3 -> Spare | AU3: ='Promo Form'!BN3 -> Spare | BC3: ='Promo Form'!BZ3 -> Spare
A4: From | B4: To | F4: Customer Code | G4: Retailer Buy ex | H4: Total Support | I4: End to End Standard Margin | J4: End to End Promo Margin | K4: 12wk Avg | L4: Expected Sales / Actual Sales | N4: Customer Code | O4: Retailer Buy ex | P4: Total Support | Q4: End to End Standard Margin | R4: End to End Promo Margin | S4: 12wk Avg | T4: Expected Sales / Actual Sales | V4: Customer Code | W4: Retailer Buy ex | X4: Total Support | Y4: End to End Standard Margin | Z4: End to End Promo Margin | AA4: 12wk Avg | AB4: Expected Sales / Actual Sales | AD4: Customer Code | AE4: Retailer Buy ex | AF4: Total Support | AG4: End to End Standard Margin | AH4: End to End Promo Margin | AI4: 12wk Avg | AJ4: Expected Sales / Actual Sales | AL4: Customer Code | AM4: Retailer Buy ex | AN4: Total Support | AO4: End to End Standard Margin | AP4: End to End Promo Margin | AQ4: 12wk Avg | AR4: Expected Sales / Actual Sales | AT4: Customer Code | AU4: Retailer Buy ex | AV4: Total Support | AW4: End to End Standard Margin | AX4: End to End Promo Margin | AY4: 12wk Avg | AZ4: Expected Sales / Actual Sales | BB4: Customer Code | BC4: Retailer Buy ex | BD4: Total Support | BE4: End to End Standard Margin | BF4: End to End Promo Margin | BG4: 12wk Avg | BH4: Expected Sales / Actual Sales | BJ4: RRP Inc | BK4: Recommended Sale Inc | BL4: Recommended % Off | BM4: Recommended $ Off | BN4: Comments
A5: ='Promo Form'!A5 -> 45658 | B5: ='Promo Form'!B5 -> 45672 | C5: ='Promo Form'!C5 -> ADM4DG | D5: ='Promo Form'!D5 -> ADONIT Mini 4 (Grey) | F5: ='Promo Form'!F5 -> 0 | G5: ='Promo Form'!G5 -> 24.34 | H5: ='Promo Form'!J5 -> 2.434 | I5: ='Promo Form'!K5 -> 0.46803801 | J5: ='Promo Form'!L5 -> 0.42254126 | K5: ='Promo Form'!M5 -> 7.5 | L5: ='Promo Form'!N5 -> 18 | N5: ='Promo Form'!R5 | O5: ='Promo Form'!S5 -> 24.34 | P5: ='Promo Form'!V5 -> 2.434 | Q5: ='Promo Form'!W5 -> 0.44213986 | R5: ='Promo Form'!X5 -> 0.39016857 | S5: ='Promo Form'!Y5 | T5: ='Promo Form'!Z5 | V5: ='Promo Form'!AD5 | W5: ='Promo Form'!AE5 -> 24.34 | X5: ='Promo Form'!AH5 -> 2.434 | Y5: ='Promo Form'!AI5 -> 0.41904151 | Z5: ='Promo Form'!AJ5 -> 0.36129564 | AA5: ='Promo Form'!AK5 -> 7.5 | AB5: ='Promo Form'!AL5 -> 18 | AD5: ='Promo Form'!AP5 | AE5: ='Promo Form'!AQ5 -> 20.86 | AF5: ='Promo Form'!AT5 -> 2.086 | AG5: ='Promo Form'!AU5 -> 0.43011878 | AH5: ='Promo Form'!AV5 -> 0.36263285 | AI5: ='Promo Form'!AW5 -> 18.5 | AJ5: ='Promo Form'!AX5 -> 46 | AL5: ='Promo Form'!BB5 | AM5: ='Promo Form'!BC5 | AN5: ='Promo Form'!BF5 | AO5: ='Promo Form'!BG5 | AP5: ='Promo Form'!BH5 | AQ5: ='Promo Form'!BI5 | AR5: ='Promo Form'!BJ5 | AT5: ='Promo Form'!BN5 | AU5: ='Promo Form'!BO5 | AV5: ='Promo Form'!BR5 | AW5: ='Promo Form'!BS5 | AX5: ='Promo Form'!BT5 | AY5: ='Promo Form'!BU5 | AZ5: ='Promo Form'!BV5 | BB5: ='Promo Form'!BZ5 | BC5: ='Promo Form'!CA5 | BD5: ='Promo Form'!CD5 | BE5: ='Promo Form'!CE5 | BF5: ='Promo Form'!CF5 | BG5: ='Promo Form'!CG5 | BH5: ='Promo Form'!CH5 | BJ5: ='Promo Form'!CL5 -> 39.99 | BK5: ='Promo Form'!CM5 -> 31.992 | BL5: ='Promo Form'!CN5 -> 0.2 | BM5: ='Promo Form'!CO5 -> 7.998 | BN5: ='Promo Form'!CP5 -> 0
A6: ='Promo Form'!A6 | B6: ='Promo Form'!B6 | C6: ='Promo Form'!C6 -> 0 | D6: ='Promo Form'!D6 | F6: ='Promo Form'!F6 -> 0 | G6: ='Promo Form'!G6 | H6: ='Promo Form'!J6 | I6: ='Promo Form'!K6 | J6: ='Promo Form'!L6 | K6: ='Promo Form'!M6 | L6: ='Promo Form'!N6 | N6: ='Promo Form'!R6 | O6: ='Promo Form'!S6 | P6: ='Promo Form'!V6 | Q6: ='Promo Form'!W6 | R6: ='Promo Form'!X6 | S6: ='Promo Form'!Y6 | T6: ='Promo Form'!Z6 | V6: ='Promo Form'!AD6 | W6: ='Promo Form'!AE6 | X6: ='Promo Form'!AH6 | Y6: ='Promo Form'!AI6 | Z6: ='Promo Form'!AJ6 | AA6: ='Promo Form'!AK6 | AB6: ='Promo Form'!AL6 | AD6: ='Promo Form'!AD6 | AE6: ='Promo Form'!AE6 | AF6: ='Promo Form'!AT6 | AG6: ='Promo Form'!AI6 | AH6: ='Promo Form'!AJ6 | AI6: ='Promo Form'!AK6 | AJ6: ='Promo Form'!AL6 | AM6: ='Promo Form'!AM6 | AN6: ='Promo Form'!BF6 | AO6: ='Promo Form'!AQ6 | AP6: ='Promo Form'!AR6 | AQ6: ='Promo Form'!AS6 | AR6: ='Promo Form'!AT6 | AT6: ='Promo Form'!BN6 | AU6: ='Promo Form'!BO6 | AV6: ='Promo Form'!BR6 | AW6: ='Promo Form'!BS6 | AX6: ='Promo Form'!BT6 | AY6: ='Promo Form'!BU6 | AZ6: ='Promo Form'!BV6 | BB6: ='Promo Form'!BZ6 | BC6: ='Promo Form'!CA6 | BD6: ='Promo Form'!CD6 | BE6: ='Promo Form'!CE6 | BF6: ='Promo Form'!CF6 | BG6: ='Promo Form'!CG6 | BH6: ='Promo Form'!CH6 | BJ6: ='Promo Form'!CL6 | BK6: ='Promo Form'!CM6 | BL6: ='Promo Form'!CN6 | BM6: ='Promo Form'!CO6 | BN6: ='Promo Form'!CP6 -> 0
A7: ='Promo Form'!A7 | B7: ='Promo Form'!B7 | C7: ='Promo Form'!C7 -> 0 | D7: ='Promo Form'!D7 | F7: ='Promo Form'!F7 -> 0 | G7: ='Promo Form'!G7 | H7: ='Promo Form'!J7 | I7: ='Promo Form'!K7 | J7: ='Promo Form'!L7 | K7: ='Promo Form'!M7 | L7: ='Promo Form'!N7 | N7: ='Promo Form'!R7 | O7: ='Promo Form'!S7 | P7: ='Promo Form'!V7 | Q7: ='Promo Form'!W7 | R7: ='Promo Form'!X7 | S7: ='Promo Form'!Y7 | T7: ='Promo Form'!Z7 | V7: ='Promo Form'!AD7 | W7: ='Promo Form'!AE7 | X7: ='Promo Form'!AH7 | Y7: ='Promo Form'!AI7 | Z7: ='Promo Form'!AJ7 | AA7: ='Promo Form'!AK7 | AB7: ='Promo Form'!AL7 | AD7: ='Promo Form'!AD7 | AE7: ='Promo Form'!AE7 | AF7: ='Promo Form'!AT7 | AG7: ='Promo Form'!AI7 | AH7: ='Promo Form'!AJ7 | AI7: ='Promo Form'!AK7 | AJ7: ='Promo Form'!AL7 | AL7: ='Promo Form'!AL7 | AM7: ='Promo Form'!AM7 | AN7: ='Promo Form'!BF7 | AO7: ='Promo Form'!AQ7 | AP7: ='Promo Form'!AR7 | AQ7: ='Promo Form'!AS7 | AR7: ='Promo Form'!AT7 | AT7: ='Promo Form'!BN7 | AU7: ='Promo Form'!BO7 | AV7: ='Promo Form'!BR7 | AW7: ='Promo Form'!BS7 | AX7: ='Promo Form'!BT7 | AY7: ='Promo Form'!BU7 | AZ7: ='Promo Form'!BV7 | BB7: ='Promo Form'!BZ7 | BC7: ='Promo Form'!CA7 | BD7: ='Promo Form'!CD7 | BE7: ='Promo Form'!CE7 | BF7: ='Promo Form'!CF7 | BG7: ='Promo Form'!CG7 | BH7: ='Promo Form'!CH7 | BJ7: ='Promo Form'!CL7 | BK7: ='Promo Form'!CM7 | BL7: ='Promo Form'!CN7 | BM7: ='Promo Form'!CO7 | BN7: ='Promo Form'!CP7 -> 0
A8: ='Promo Form'!A8 | B8: ='Promo Form'!B8 | C8: ='Promo Form'!C8 -> 0 | D8: ='Promo Form'!D8 | F8: ='Promo Form'!F8 -> 0 | G8: ='Promo Form'!G8 | H8: ='Promo Form'!J8 | I8: ='Promo Form'!K8 | J8: ='Promo Form'!L8 | K8: ='Promo Form'!M8 | L8: ='Promo Form'!N8 | N8: ='Promo Form'!R8 | O8: ='Promo Form'!S8 | P8: ='Promo Form'!V8 | Q8: ='Promo Form'!W8 | R8: ='Promo Form'!X8 | S8: ='Promo Form'!Y8 | T8: ='Promo Form'!Z8 | V8: ='Promo Form'!AD8 | W8: ='Promo Form'!AE8 | X8: ='Promo Form'!AH8 | Y8: ='Promo Form'!AI8 | Z8: ='Promo Form'!AJ8 | AA8: ='Promo Form'!AK8 | AB8: ='Promo Form'!AL8 | AD8: ='Promo Form'!AD8 | AE8: ='Promo Form'!AE8 | AF8: ='Promo Form'!AT8 | AG8: ='Promo Form'!AI8 | AH8: ='Promo Form'!AJ8 | AI8: ='Promo Form'!AK8 | AJ8: ='Promo Form'!AL8 | AL8: ='Promo Form'!AL8 | AM8: ='Promo Form'!AM8 | AN8: ='Promo Form'!BF8 | AO8: ='Promo Form'!AQ8 | AP8: ='Promo Form'!AR8 | AQ8: ='Promo Form'!AS8 | AR8: ='Promo Form'!AT8 | AT8: ='Promo Form'!BN8 | AU8: ='Promo Form'!BO8 | AV8: ='Promo Form'!BR8 | AW8: ='Promo Form'!BS8 | AX8: ='Promo Form'!BT8 | AY8: ='Promo Form'!BU8 | AZ8: ='Promo Form'!BV8 | BB8: ='Promo Form'!BZ8 | BC8: ='Promo Form'!CA8 | BD8: ='Promo Form'!CD8 | BE8: ='Promo Form'!CE8 | BF8: ='Promo Form'!CF8 | BG8: ='Promo Form'!CG8 | BH8: ='Promo Form'!CH8 | BJ8: ='Promo Form'!CL8 | BK8: ='Promo Form'!CM8 | BL8: ='Promo Form'!CN8 | BM8: ='Promo Form'!CO8 | BN8: ='Promo Form'!CP8 -> 0
A9: ='Promo Form'!A9 | B9: ='Promo Form'!B9 | C9: ='Promo Form'!C9 -> 0 | D9: ='Promo Form'!D9 | F9: ='Promo Form'!F9 -> 0 | G9: ='Promo Form'!G9 | H9: ='Promo Form'!J9 | I9: ='Promo Form'!K9 | J9: ='Promo Form'!L9 | K9: ='Promo Form'!M9 | L9: ='Promo Form'!N9 | N9: ='Promo Form'!R9 | O9: ='Promo Form'!S9 | P9: ='Promo Form'!V9 | Q9: ='Promo Form'!W9 | R9: ='Promo Form'!X9 | S9: ='Promo Form'!Y9 | T9: ='Promo Form'!Z9 | V9: ='Promo Form'!AD9 | W9: ='Promo Form'!AE9 | X9: ='Promo Form'!AH9 | Y9: ='Promo Form'!AI9 | Z9: ='Promo Form'!AJ9 | AA9: ='Promo Form'!AK9 | AB9: ='Promo Form'!AL9 | AD9: ='Promo Form'!AD9 | AE9: ='Promo Form'!AE9 | AF9: ='Promo Form'!AT9 | AG9: ='Promo Form'!AI9 | AH9: ='Promo Form'!AJ9 | AI9: ='Promo Form'!AK9 | AJ9: ='Promo Form'!AL9 | AL9: ='Promo Form'!AL9 | AM9: ='Promo Form'!AM9 | AN9: ='Promo Form'!BF9 | AO9: ='Promo Form'!AQ9 | AP9: ='Promo Form'!AR9 | AQ9: ='Promo Form'!AS9 | AR9: ='Promo Form'!AT9 | AT9: ='Promo Form'!BN9 | AU9: ='Promo Form'!BO9 | AV9: ='Promo Form'!BR9 | AW9: ='Promo Form'!BS9 | AX9: ='Promo Form'!BT9 | AY9: ='Promo Form'!BU9 | AZ9: ='Promo Form'!BV9 | BB9: ='Promo Form'!BZ9 | BC9: ='Promo Form'!CA9 | BD9: ='Promo Form'!CD9 | BE9: ='Promo Form'!CE9 | BF9: ='Promo Form'!CF9 | BG9: ='Promo Form'!CG9 | BH9: ='Promo Form'!CH9 | BJ9: ='Promo Form'!CL9 | BK9: ='Promo Form'!CM9 | BL9: ='Promo Form'!CN9 | BM9: ='Promo Form'!CO9 | BN9: ='Promo Form'!CP9 -> 0
A10: ='Promo Form'!A10 | B10: ='Promo Form'!B10 | C10: ='Promo Form'!C10 -> 0 | D10: ='Promo Form'!D10 | F10: ='Promo Form'!F10 -> 0 | G10: ='Promo Form'!G10 | H10: ='Promo Form'!J10 | I10: ='Promo Form'!K10 | J10: ='Promo Form'!L10 | K10: ='Promo Form'!M10 | L10: ='Promo Form'!N10 | N10: ='Promo Form'!R10 | O10: ='Promo Form'!S10 | P10: ='Promo Form'!V10 | Q10: ='Promo Form'!W10 | R10: ='Promo Form'!X10 | S10: ='Promo Form'!Y10 | T10: ='Promo Form'!Z10 | V10: ='Promo Form'!AD10 | W10: ='Promo Form'!AE10 | X10: ='Promo Form'!AH10 | Y10: ='Promo Form'!AI10 | Z10: ='Promo Form'!AJ10 | AA10: ='Promo Form'!AK10 | AB10: ='Promo Form'!AL10 | AD10: ='Promo Form'!AD10 | AE10: ='Promo Form'!AE10 | AF10: ='Promo Form'!AT10 | AG10: ='Promo Form'!AI10 | AH10: ='Promo Form'!AJ10 | AI10: ='Promo Form'!AK10 | AJ10: ='Promo Form'!AL10 | AL10: ='Promo Form'!AL10 | AM10: ='Promo Form'!AM10 | AN10: ='Promo Form'!BF10 | AO10: ='Promo Form'!AQ10 | AP10: ='Promo Form'!AR10 | AQ10: ='Promo Form'!AS10 | AR10: ='Promo Form'!AT10 | AT10: ='Promo Form'!BN10 | AU10: ='Promo Form'!BO10 | AV10: ='Promo Form'!BR10 | AW10: ='Promo Form'!BS10 | AX10: ='Promo Form'!BT10 | AY10: ='Promo Form'!BU10 | AZ10: ='Promo Form'!BV10 | BB10: ='Promo Form'!BZ10 | BC10: ='Promo Form'!CA10 | BD10: ='Promo Form'!CD10 | BE10: ='Promo Form'!CE10 | BF10: ='Promo Form'!CF10 | BG10: ='Promo Form'!CG10 | BH10: ='Promo Form'!CH10 | BJ10: ='Promo Form'!CL10 | BK10: ='Promo Form'!CM10 | BL10: ='Promo Form'!CN10 | BM10: ='Promo Form'!CO10 | BN10: ='Promo Form'!CP10 -> 0
A11: ='Promo Form'!A11 | B11: ='Promo Form'!B11 | C11: ='Promo Form'!C11 -> 0 | D11: ='Promo Form'!D11 | F11: ='Promo Form'!F11 -> 0 | G11: ='Promo Form'!G11 | H11: ='Promo Form'!J11 | I11: ='Promo Form'!K11 | J11: ='Promo Form'!L11 | K11: ='Promo Form'!M11 | L11: ='Promo Form'!N11 | N11: ='Promo Form'!R11 | O11: ='Promo Form'!S11 | P11: ='Promo Form'!V11 | Q11: ='Promo Form'!W11 | R11: ='Promo Form'!X11 | S11: ='Promo Form'!Y11 | T11: ='Promo Form'!Z11 | V11: ='Promo Form'!AD11 | W11: ='Promo Form'!AE11 | X11: ='Promo Form'!AH11 | Y11: ='Promo Form'!AI11 | Z11: ='Promo Form'!AJ11 | AA11: ='Promo Form'!AK11 | AB11: ='Promo Form'!AL11 | AD11: ='Promo Form'!AD11 | AE11: ='Promo Form'!AE11 | AF11: ='Promo Form'!AT11 | AG11: ='Promo Form'!AI11 | AH11: ='Promo Form'!AJ11 | AI11: ='Promo Form'!AK11 | AJ11: ='Promo Form'!AL11 | AL11: ='Promo Form'!AL11 | AM11: ='Promo Form'!AM11 | AN11: ='Promo Form'!BF11 | AO11: ='Promo Form'!AQ11 | AP11: ='Promo Form'!AR11 | AQ11: ='Promo Form'!AS11 | AR11: ='Promo Form'!AT11 | AT11: ='Promo Form'!BN11 | AU11: ='Promo Form'!BO11 | AV11: ='Promo Form'!BR11 | AW11: ='Promo Form'!BS11 | AX11: ='Promo Form'!BT11 | AY11: ='Promo Form'!BU11 | AZ11: ='Promo Form'!BV11 | BB11: ='Promo Form'!BZ11 | BC11: ='Promo Form'!CA11 | BD11: ='Promo Form'!CD11 | BE11: ='Promo Form'!CE11 | BF11: ='Promo Form'!CF11 | BG11: ='Promo Form'!CG11 | BH11: ='Promo Form'!CH11 | BJ11: ='Promo Form'!CL11 | BK11: ='Promo Form'!CM11 | BL11: ='Promo Form'!CN11 | BM11: ='Promo Form'!CO11 | BN11: ='Promo Form'!CP11 -> 0
A12: ='Promo Form'!A12 | B12: ='Promo Form'!B12 | C12: ='Promo Form'!C12 -> 0 | D12: ='Promo Form'!D12 | F12: ='Promo Form'!F12 -> 0 | G12: ='Promo Form'!G12 | H12: ='Promo Form'!J12 | I12: ='Promo Form'!K12 | J12: ='Promo Form'!L12 | K12: ='Promo Form'!M12 | L12: ='Promo Form'!N12 | N12: ='Promo Form'!R12 | O12: ='Promo Form'!S12 | P12: ='Promo Form'!V12 | Q12: ='Promo Form'!W12 | R12: ='Promo Form'!X12 | S12: ='Promo Form'!Y12 | T12: ='Promo Form'!Z12 | V12: ='Promo Form'!AD12 | W12: ='Promo Form'!AE12 | X12: ='Promo Form'!AH12 | Y12: ='Promo Form'!AI12 | Z12: ='Promo Form'!AJ12 | AA12: ='Promo Form'!AK12 | AB12: ='Promo Form'!AL12 | AD12: ='Promo Form'!AD12 | AE12: ='Promo Form'!AE12 | AF12: ='Promo Form'!AT12 | AG12: ='Promo Form'!AI12 | AH12: ='Promo Form'!AJ12 | AI12: ='Promo Form'!AK12 | AJ12: ='Promo Form'!AL12 | AL12: ='Promo Form'!AL12 | AM12: ='Promo Form'!AM12 | AN12: ='Promo Form'!BF12 | AO12: ='Promo Form'!AQ12 | AP12: ='Promo Form'!AR12 | AQ12: ='Promo Form'!AS12 | AR12: ='Promo Form'!AT12 | AT12: ='Promo Form'!BN12 | AU12: ='Promo Form'!BO12 | AV12: ='Promo Form'!BR12 | AW12: ='Promo Form'!BS12 | AX12: ='Promo Form'!BT12 | AY12: ='Promo Form'!BU12 | AZ12: ='Promo Form'!BV12 | BB12: ='Promo Form'!BZ12 | BC12: ='Promo Form'!CA12 | BD12: ='Promo Form'!CD12 | BE12: ='Promo Form'!CE12 | BF12: ='Promo Form'!CF12 | BG12: ='Promo Form'!CG12 | BH12: ='Promo Form'!CH12 | BJ12: ='Promo Form'!CL12 | BK12: ='Promo Form'!CM12 | BL12: ='Promo Form'!CN12 | BM12: ='Promo Form'!CO12 | BN12: ='Promo Form'!CP12 -> 0
A13: ='Promo Form'!A13 | B13: ='Promo Form'!B13 | C13: ='Promo Form'!C13 -> 0 | D13: ='Promo Form'!D13 | F13: ='Promo Form'!F13 -> 0 | G13: ='Promo Form'!G13 | H13: ='Promo Form'!J13 | I13: ='Promo Form'!K13 | J13: ='Promo Form'!L13 | K13: ='Promo Form'!M13 | L13: ='Promo Form'!N13 | N13: ='Promo Form'!R13 | O13: ='Promo Form'!S13 | P13: ='Promo Form'!V13 | Q13: ='Promo Form'!W13 | R13: ='Promo Form'!X13 | S13: ='Promo Form'!Y13 | T13: ='Promo Form'!Z13 | V13: ='Promo Form'!AD13 | W13: ='Promo Form'!AE13 | X13: ='Promo Form'!AH13 | Y13: ='Promo Form'!AI13 | Z13: ='Promo Form'!AJ13 | AA13: ='Promo Form'!AK13 | AB13: ='Promo Form'!AL13 | AD13: ='Promo Form'!AD13 | AE13: ='Promo Form'!AE13 | AF13: ='Promo Form'!AT13 | AG13: ='Promo Form'!AI13 | AH13: ='Promo Form'!AJ13 | AI13: ='Promo Form'!AK13 | AJ13: ='Promo Form'!AL13 | AL13: ='Promo Form'!AL13 | AM13: ='Promo Form'!AM13 | AN13: ='Promo Form'!BF13 | AO13: ='Promo Form'!AQ13 | AP13: ='Promo Form'!AR13 | AQ13: ='Promo Form'!AS13 | AR13: ='Promo Form'!AT13 | AT13: ='Promo Form'!BN13 | AU13: ='Promo Form'!BO13 | AV13: ='Promo Form'!BR13 | AW13: ='Promo Form'!BS13 | AX13: ='Promo Form'!BT13 | AY13: ='Promo Form'!BU13 | AZ13: ='Promo Form'!BV13 | BB13: ='Promo Form'!BZ13 | BC13: ='Promo Form'!CA13 | BD13: ='Promo Form'!CD13 | BE13: ='Promo Form'!CE13 | BF13: ='Promo Form'!CF13 | BG13: ='Promo Form'!CG13 | BH13: ='Promo Form'!CH13 | BJ13: ='Promo Form'!CL13 | BK13: ='Promo Form'!CM13 | BL13: ='Promo Form'!CN13 | BM13: ='Promo Form'!CO13 | BN13: ='Promo Form'!CP13 -> 0
A14: ='Promo Form'!A14 | B14: ='Promo Form'!B14 | C14: ='Promo Form'!C14 -> 0 | D14: ='Promo Form'!D14 | F14: ='Promo Form'!F14 -> 0 | G14: ='Promo Form'!G14 | H14: ='Promo Form'!J14 | I14: ='Promo Form'!K14 | J14: ='Promo Form'!L14 | K14: ='Promo Form'!M14 | L14: ='Promo Form'!N14 | N14: ='Promo Form'!R14 | O14: ='Promo Form'!S14 | P14: ='Promo Form'!V14 | Q14: ='Promo Form'!W14 | R14: ='Promo Form'!X14 | S14: ='Promo Form'!Y14 | T14: ='Promo Form'!Z14 | V14: ='Promo Form'!AD14 | W14: ='Promo Form'!AE14 | X14: ='Promo Form'!AH14 | Y14: ='Promo Form'!AI14 | Z14: ='Promo Form'!AJ14 | AA14: ='Promo Form'!AK14 | AB14: ='Promo Form'!AL14 | AD14: ='Promo Form'!AD14 | AE14: ='Promo Form'!AE14 | AF14: ='Promo Form'!AT14 | AG14: ='Promo Form'!AI14 | AH14: ='Promo Form'!AJ14 | AI14: ='Promo Form'!AK14 | AJ14: ='Promo Form'!AL14 | AL14: ='Promo Form'!AL14 | AM14: ='Promo Form'!AM14 | AN14: ='Promo Form'!BF14 | AO14: ='Promo Form'!AQ14 | AP14: ='Promo Form'!AR14 | AQ14: ='Promo Form'!AS14 | AR14: ='Promo Form'!AT14 | AT14: ='Promo Form'!BN14 | AU14: ='Promo Form'!BO14 | AV14: ='Promo Form'!BR14 | AW14: ='Promo Form'!BS14 | AX14: ='Promo Form'!BT14 | AY14: ='Promo Form'!BU14 | AZ14: ='Promo Form'!BV14 | BB14: ='Promo Form'!BZ14 | BC14: ='Promo Form'!CA14 | BD14: ='Promo Form'!CD14 | BE14: ='Promo Form'!CE14 | BF14: ='Promo Form'!CF14 | BG14: ='Promo Form'!CG14 | BH14: ='Promo Form'!CH14 | BJ14: ='Promo Form'!CL14 | BK14: ='Promo Form'!CM14 | BL14: ='Promo Form'!CN14 | BM14: ='Promo Form'!CO14 | BN14: ='Promo Form'!CP14 -> 0
A15: ='Promo Form'!A15 | B15: ='Promo Form'!B15 | C15: ='Promo Form'!C15 -> 0 | D15: ='Promo Form'!D15 | F15: ='Promo Form'!F15 -> 0 | G15: ='Promo Form'!G15 | H15: ='Promo Form'!J15 | I15: ='Promo Form'!K15 | J15: ='Promo Form'!L15 | K15: ='Promo Form'!M15 | L15: ='Promo Form'!N15 | N15: ='Promo Form'!R15 | O15: ='Promo Form'!S15 | P15: ='Promo Form'!V15 | Q15: ='Promo Form'!W15 | R15: ='Promo Form'!X15 | S15: ='Promo Form'!Y15 | T15: ='Promo Form'!Z15 | V15: ='Promo Form'!AD15 | W15: ='Promo Form'!AE15 | X15: ='Promo Form'!AH15 | Y15: ='Promo Form'!AI15 | Z15: ='Promo Form'!AJ15 | AA15: ='Promo Form'!AK15 | AB15: ='Promo Form'!AL15 | AD15: ='Promo Form'!AD15 | AE15: ='Promo Form'!AE15 | AF15: ='Promo Form'!AT15 | AG15: ='Promo Form'!AI15 | AH15: ='Promo Form'!AJ15 | AI15: ='Promo Form'!AK15 | AJ15: ='Promo Form'!AL15 | AL15: ='Promo Form'!AL15 | AM15: ='Promo Form'!AM15 | AN15: ='Promo Form'!BF15 | AO15: ='Promo Form'!AQ15 | AP15: ='Promo Form'!AR15 | AQ15: ='Promo Form'!AS15 | AR15: ='Promo Form'!AT15 | AT15: ='Promo Form'!BN15 | AU15: ='Promo Form'!BO15 | AV15: ='Promo Form'!BR15 | AW15: ='Promo Form'!BS15 | AX15: ='Promo Form'!BT15 | AY15: ='Promo Form'!BU15 | AZ15: ='Promo Form'!BV15 | BB15: ='Promo Form'!BZ15 | BC15: ='Promo Form'!CA15 | BD15: ='Promo Form'!CD15 | BE15: ='Promo Form'!CE15 | BF15: ='Promo Form'!CF15 | BG15: ='Promo Form'!CG15 | BH15: ='Promo Form'!CH15 | BJ15: ='Promo Form'!CL15 | BK15: ='Promo Form'!CM15 | BL15: ='Promo Form'!CN15 | BM15: ='Promo Form'!CO15 | BN15: ='Promo Form'!CP15 -> 0
A16: ='Promo Form'!A16 | B16: ='Promo Form'!B16 | C16: ='Promo Form'!C16 -> 0 | D16: ='Promo Form'!D16 | F16: ='Promo Form'!F16 -> 0 | G16: ='Promo Form'!G16 | H16: ='Promo Form'!J16 | I16: ='Promo Form'!K16 | J16: ='Promo Form'!L16 | K16: ='Promo Form'!M16 | L16: ='Promo Form'!N16 | N16: ='Promo Form'!R16 | O16: ='Promo Form'!S16 | P16: ='Promo Form'!V16 | Q16: ='Promo Form'!W16 | R16: ='Promo Form'!X16 | S16: ='Promo Form'!Y16 | T16: ='Promo Form'!Z16 | V16: ='Promo Form'!AD16 | W16: ='Promo Form'!AE16 | X16: ='Promo Form'!AH16 | Y16: ='Promo Form'!AI16 | Z16: ='Promo Form'!AJ16 | AA16: ='Promo Form'!AK16 | AB16: ='Promo Form'!AL16 | AD16: ='Promo Form'!AD16 | AE16: ='Promo Form'!AE16 | AF16: ='Promo Form'!AT16 | AG16: ='Promo Form'!AI16 | AH16: ='Promo Form'!AJ16 | AI16: ='Promo Form'!AK16 | AJ16: ='Promo Form'!AL16 | AL16: ='Promo Form'!AL16 | AM16: ='Promo Form'!AM16 | AN16: ='Promo Form'!BF16 | AO16: ='Promo Form'!AQ16 | AP16: ='Promo Form'!AR16 | AQ16: ='Promo Form'!AS16 | AR16: ='Promo Form'!AT16 | AT16: ='Promo Form'!BN16 | AU16: ='Promo Form'!BO16 | AV16: ='Promo Form'!BR16 | AW16: ='Promo Form'!BS16 | AX16: ='Promo Form'!BT16 | AY16: ='Promo Form'!BU16 | AZ16: ='Promo Form'!BV16 | BB16: ='Promo Form'!BZ16 | BC16: ='Promo Form'!CA16 | BD16: ='Promo Form'!CD16 | BE16: ='Promo Form'!CE16 | BF16: ='Promo Form'!CF16 | BG16: ='Promo Form'!CG16 | BH16: ='Promo Form'!CH16 | BJ16: ='Promo Form'!CL16 | BK16: ='Promo Form'!CM16 | BL16: ='Promo Form'!CN16 | BM16: ='Promo Form'!CO16 | BN16: ='Promo Form'!CP16 -> 0
A17: ='Promo Form'!A17 | B17: ='Promo Form'!B17 | C17: ='Promo Form'!C17 -> 0 | D17: ='Promo Form'!D17 | F17: ='Promo Form'!F17 -> 0 | G17: ='Promo Form'!G17 | H17: ='Promo Form'!J17 | I17: ='Promo Form'!K17 | J17: ='Promo Form'!L17 | K17: ='Promo Form'!M17 | L17: ='Promo Form'!N17 | N17: ='Promo Form'!R17 | O17: ='Promo Form'!S17 | P17: ='Promo Form'!V17 | Q17: ='Promo Form'!W17 | R17: ='Promo Form'!X17 | S17: ='Promo Form'!Y17 | T17: ='Promo Form'!Z17 | V17: ='Promo Form'!AD17 | W17: ='Promo Form'!AE17 | X17: ='Promo Form'!AH17 | Y17: ='Promo Form'!AI17 | Z17: ='Promo Form'!AJ17 | AA17: ='Promo Form'!AK17 | AB17: ='Promo Form'!AL17 | AD17: ='Promo Form'!AD17 | AE17: ='Promo Form'!AE17 | AF17: ='Promo Form'!AT17 | AG17: ='Promo Form'!AI17 | AH17: ='Promo Form'!AJ17 | AI17: ='Promo Form'!AK17 | AJ17: ='Promo Form'!AL17 | AL17: ='Promo Form'!AL17 | AM17: ='Promo Form'!AM17 | AN17: ='Promo Form'!BF17 | AO17: ='Promo Form'!AQ17 | AP17: ='Promo Form'!AR17 | AQ17: ='Promo Form'!AS17 | AR17: ='Promo Form'!AT17 | AT17: ='Promo Form'!BN17 | AU17: ='Promo Form'!BO17 | AV17: ='Promo Form'!BR17 | AW17: ='Promo Form'!BS17 | AX17: ='Promo Form'!BT17 | AY17: ='Promo Form'!BU17 | AZ17: ='Promo Form'!BV17 | BB17: ='Promo Form'!BZ17 | BC17: ='Promo Form'!CA17 | BD17: ='Promo Form'!CD17 | BE17: ='Promo Form'!CE17 | BF17: ='Promo Form'!CF17 | BG17: ='Promo Form'!CG17 | BH17: ='Promo Form'!CH17 | BJ17: ='Promo Form'!CL17 | BK17: ='Promo Form'!CM17 | BL17: ='Promo Form'!CN17 | BM17: ='Promo Form'!CO17 | BN17: ='Promo Form'!CP17 -> 0
A18: ='Promo Form'!A18 | B18: ='Promo Form'!B18 | C18: ='Promo Form'!C18 -> 0 | D18: ='Promo Form'!D18 | F18: ='Promo Form'!F18 -> 0 | G18: ='Promo Form'!G18 | H18: ='Promo Form'!J18 | I18: ='Promo Form'!K18 | J18: ='Promo Form'!L18 | K18: ='Promo Form'!M18 | L18: ='Promo Form'!N18 | N18: ='Promo Form'!R18 | O18: ='Promo Form'!S18 | P18: ='Promo Form'!V18 | Q18: ='Promo Form'!W18 | R18: ='Promo Form'!X18 | S18: ='Promo Form'!Y18 | T18: ='Promo Form'!Z18 | V18: ='Promo Form'!AD18 | W18: ='Promo Form'!AE18 | X18: ='Promo Form'!AH18 | Y18: ='Promo Form'!AI18 | Z18: ='Promo Form'!AJ18 | AA18: ='Promo Form'!AK18 | AB18: ='Promo Form'!AL18 | AD18: ='Promo Form'!AD18 | AE18: ='Promo Form'!AE18 | AF18: ='Promo Form'!AT18 | AG18: ='Promo Form'!AI18 | AH18: ='Promo Form'!AJ18 | AI18: ='Promo Form'!AK18 | AJ18: ='Promo Form'!AL18 | AL18: ='Promo Form'!AL18 | AM18: ='Promo Form'!AM18 | AN18: ='Promo Form'!BF18 | AO18: ='Promo Form'!AQ18 | AP18: ='Promo Form'!AR18 | AQ18: ='Promo Form'!AS18 | AR18: ='Promo Form'!AT18 | AT18: ='Promo Form'!BN18 | AU18: ='Promo Form'!BO18 | AV18: ='Promo Form'!BR18 | AW18: ='Promo Form'!BS18 | AX18: ='Promo Form'!BT18 | AY18: ='Promo Form'!BU18 | AZ18: ='Promo Form'!BV18 | BB18: ='Promo Form'!BZ18 | BC18: ='Promo Form'!CA18 | BD18: ='Promo Form'!CD18 | BE18: ='Promo Form'!CE18 | BF18: ='Promo Form'!CF18 | BG18: ='Promo Form'!CG18 | BH18: ='Promo Form'!CH18 | BJ18: ='Promo Form'!CL18 | BK18: ='Promo Form'!CM18 | BL18: ='Promo Form'!CN18 | BM18: ='Promo Form'!CO18 | BN18: ='Promo Form'!CP18 -> 0
A19: ='Promo Form'!A19 | B19: ='Promo Form'!B19 | C19: ='Promo Form'!C19 -> 0 | D19: ='Promo Form'!D19 | F19: ='Promo Form'!F19 -> 0 | G19: ='Promo Form'!G19 | H19: ='Promo Form'!J19 | I19: ='Promo Form'!K19 | J19: ='Promo Form'!L19 | K19: ='Promo Form'!M19 | L19: ='Promo Form'!N19 | N19: ='Promo Form'!R19 | O19: ='Promo Form'!S19 | P19: ='Promo Form'!V19 | Q19: ='Promo Form'!W19 | R19: ='Promo Form'!X19 | S19: ='Promo Form'!Y19 | T19: ='Promo Form'!Z19 | V19: ='Promo Form'!AD19 | W19: ='Promo Form'!AE19 | X19: ='Promo Form'!AH19 | Y19: ='Promo Form'!AI19 | Z19: ='Promo Form'!AJ19 | AA19: ='Promo Form'!AK19 | AB19: ='Promo Form'!AL19 | AD19: ='Promo Form'!AD19 | AE19: ='Promo Form'!AE19 | AF19: ='Promo Form'!AT19 | AG19: ='Promo Form'!AI19 | AH19: ='Promo Form'!AJ19 | AI19: ='Promo Form'!AK19 | AJ19: ='Promo Form'!AL19 | AL19: ='Promo Form'!AL19 | AM19: ='Promo Form'!AM19 | AN19: ='Promo Form'!BF19 | AO19: ='Promo Form'!AQ19 | AP19: ='Promo Form'!AR19 | AQ19: ='Promo Form'!AS19 | AR19: ='Promo Form'!AT19 | AT19: ='Promo Form'!BN19 | AU19: ='Promo Form'!BO19 | AV19: ='Promo Form'!BR19 | AW19: ='Promo Form'!BS19 | AX19: ='Promo Form'!BT19 | AY19: ='Promo Form'!BU19 | AZ19: ='Promo Form'!BV19 | BB19: ='Promo Form'!BZ19 | BC19: ='Promo Form'!CA19 | BD19: ='Promo Form'!CD19 | BE19: ='Promo Form'!CE19 | BF19: ='Promo Form'!CF19 | BG19: ='Promo Form'!CG19 | BH19: ='Promo Form'!CH19 | BJ19: ='Promo Form'!CL19 | BK19: ='Promo Form'!CM19 | BL19: ='Promo Form'!CN19 | BM19: ='Promo Form'!CO19 | BN19: ='Promo Form'!CP19 -> 0
A20: ='Promo Form'!A20 | B20: ='Promo Form'!B20 | C20: ='Promo Form'!C20 -> 0 | D20: ='Promo Form'!D20 | F20: ='Promo Form'!F20 -> 0 | G20: ='Promo Form'!G20 | H20: ='Promo Form'!J20 | I20: ='Promo Form'!K20 | J20: ='Promo Form'!L20 | K20: ='Promo Form'!M20 | L20: ='Promo Form'!N20 | N20: ='Promo Form'!R20 | O20: ='Promo Form'!S20 | P20: ='Promo Form'!V20 | Q20: ='Promo Form'!W20 | R20: ='Promo Form'!X20 | S20: ='Promo Form'!Y20 | T20: ='Promo Form'!Z20 | V20: ='Promo Form'!AD20 | W20: ='Promo Form'!AE20 | X20: ='Promo Form'!AH20 | Y20: ='Promo Form'!AI20 | Z20: ='Promo Form'!AJ20 | AA20: ='Promo Form'!AK20 | AB20: ='Promo Form'!AL20 | AD20: ='Promo Form'!AD24 | AE20: ='Promo Form'!AE24 | AF20: ='Promo Form'!AT20 | AG20: ='Promo Form'!AI24 | AH20: ='Promo Form'!AJ24 | AI20: ='Promo Form'!AK24 | AJ20: ='Promo Form'!AL24 | AL20: ='Promo Form'!AL24 | AM20: ='Promo Form'!AM24 | AN20: ='Promo Form'!BF20 | AO20: ='Promo Form'!AQ24 | AP20: ='Promo Form'!AR24 | AQ20: ='Promo Form'!AS24 | AR20: ='Promo Form'!AT24 | AT20: ='Promo Form'!BN20 | AU20: ='Promo Form'!BO20 | AV20: ='Promo Form'!BR20 | AW20: ='Promo Form'!BS20 | AX20: ='Promo Form'!BT20 | AY20: ='Promo Form'!BU20 | AZ20: ='Promo Form'!BV20 | BB20: ='Promo Form'!BZ20 | BC20: ='Promo Form'!CA20 | BD20: ='Promo Form'!CD20 | BE20: ='Promo Form'!CE20 | BF20: ='Promo Form'!CF20 | BG20: ='Promo Form'!CG20 | BH20: ='Promo Form'!CH20 | BJ20: ='Promo Form'!CL20 | BK20: ='Promo Form'!CM20 | BL20: ='Promo Form'!CN20 | BM20: ='Promo Form'!CO20 | BN20: ='Promo Form'!CP20 -> 0
A21: ='Promo Form'!A21 | B21: ='Promo Form'!B21 | C21: ='Promo Form'!C21 -> 0 | D21: ='Promo Form'!D21 | F21: ='Promo Form'!F21 -> 0 | G21: ='Promo Form'!G21 | H21: ='Promo Form'!J21 | I21: ='Promo Form'!K21 | J21: ='Promo Form'!L21 | K21: ='Promo Form'!M21 | L21: ='Promo Form'!N21 | N21: ='Promo Form'!R21 | O21: ='Promo Form'!S21 | P21: ='Promo Form'!V21 | Q21: ='Promo Form'!W21 | R21: ='Promo Form'!X21 | S21: ='Promo Form'!Y21 | T21: ='Promo Form'!Z21 | V21: ='Promo Form'!AD21 | W21: ='Promo Form'!AE21 | X21: ='Promo Form'!AH21 | Y21: ='Promo Form'!AI21 | Z21: ='Promo Form'!AJ21 | AA21: ='Promo Form'!AK21 | AB21: ='Promo Form'!AL21 | AD21: ='Promo Form'!AD25 | AE21: ='Promo Form'!AE25 | AF21: ='Promo Form'!AT21 | AG21: ='Promo Form'!AI25 | AH21: ='Promo Form'!AJ25 | AI21: ='Promo Form'!AK25 | AJ21: ='Promo Form'!AL25 | AL21: ='Promo Form'!AL25 | AM21: ='Promo Form'!AM25 | AN21: ='Promo Form'!BF21 | AO21: ='Promo Form'!AQ25 | AP21: ='Promo Form'!AR25 | AQ21: ='Promo Form'!AS25 | AR21: ='Promo Form'!AT25 | AT21: ='Promo Form'!BN21 | AU21: ='Promo Form'!BO21 | AV21: ='Promo Form'!BR21 | AW21: ='Promo Form'!BS21 | AX21: ='Promo Form'!BT21 | AY21: ='Promo Form'!BU21 | AZ21: ='Promo Form'!BV21 | BB21: ='Promo Form'!BZ21 | BC21: ='Promo Form'!CA21 | BD21: ='Promo Form'!CD21 | BE21: ='Promo Form'!CE21 | BF21: ='Promo Form'!CF21 | BG21: ='Promo Form'!CG21 | BH21: ='Promo Form'!CH21 | BJ21: ='Promo Form'!CL21 | BK21: ='Promo Form'!CM21 | BL21: ='Promo Form'!CN21 | BM21: ='Promo Form'!CO21 | BN21: ='Promo Form'!CP21 -> 0
A22: ='Promo Form'!A22 | B22: ='Promo Form'!B22 | C22: ='Promo Form'!C22 -> 0 | D22: ='Promo Form'!D22 | F22: ='Promo Form'!F22 -> 0 | G22: ='Promo Form'!G22 | H22: ='Promo Form'!J22 | I22: ='Promo Form'!K22 | J22: ='Promo Form'!L22 | K22: ='Promo Form'!M22 | L22: ='Promo Form'!N22 | N22: ='Promo Form'!R22 | O22: ='Promo Form'!S22 | P22: ='Promo Form'!V22 | Q22: ='Promo Form'!W22 | R22: ='Promo Form'!X22 | S22: ='Promo Form'!Y22 | T22: ='Promo Form'!Z22 | V22: ='Promo Form'!AD22 | W22: ='Promo Form'!AE22 | X22: ='Promo Form'!AH22 | Y22: ='Promo Form'!AI22 | Z22: ='Promo Form'!AJ22 | AA22: ='Promo Form'!AK22 | AB22: ='Promo Form'!AL22 | AD22: ='Promo Form'!AD26 | AE22: ='Promo Form'!AE26 | AF22: ='Promo Form'!AT22 | AG22: ='Promo Form'!AI26 | AH22: ='Promo Form'!AJ26 | AI22: ='Promo Form'!AK26 | AJ22: ='Promo Form'!AL26 | AL22: ='Promo Form'!AL26 | AM22: ='Promo Form'!AM26 | AN22: ='Promo Form'!BF22 | AO22: ='Promo Form'!AQ26 | AP22: ='Promo Form'!AR26 | AQ22: ='Promo Form'!AS26 | AR22: ='Promo Form'!AT26 | AT22: ='Promo Form'!BN22 | AU22: ='Promo Form'!BO22 | AV22: ='Promo Form'!BR22 | AW22: ='Promo Form'!BS22 | AX22: ='Promo Form'!BT22 | AY22: ='Promo Form'!BU22 | AZ22: ='Promo Form'!BV22 | BB22: ='Promo Form'!BZ22 | BC22: ='Promo Form'!CA22 | BD22: ='Promo Form'!CD22 | BE22: ='Promo Form'!CE22 | BF22: ='Promo Form'!CF22 | BG22: ='Promo Form'!CG22 | BH22: ='Promo Form'!CH22 | BJ22: ='Promo Form'!CL22 | BK22: ='Promo Form'!CM22 | BL22: ='Promo Form'!CN22 | BM22: ='Promo Form'!CO22 | BN22: ='Promo Form'!CP22 -> 0
A23: ='Promo Form'!A23 | B23: ='Promo Form'!B23 | C23: ='Promo Form'!C23 -> 0 | D23: ='Promo Form'!D23 | F23: ='Promo Form'!F23 -> 0 | G23: ='Promo Form'!G23 | H23: ='Promo Form'!J23 | I23: ='Promo Form'!K23 | J23: ='Promo Form'!L23 | K23: ='Promo Form'!M23 | L23: ='Promo Form'!N23 | N23: ='Promo Form'!R23 | O23: ='Promo Form'!S23 | P23: ='Promo Form'!V23 | Q23: ='Promo Form'!W23 | R23: ='Promo Form'!X23 | S23: ='Promo Form'!Y23 | T23: ='Promo Form'!Z23 | V23: ='Promo Form'!AD23 | W23: ='Promo Form'!AE23 | X23: ='Promo Form'!AH23 | Y23: ='Promo Form'!AI23 | Z23: ='Promo Form'!AJ23 | AA23: ='Promo Form'!AK23 | AB23: ='Promo Form'!AL23 | AD23: ='Promo Form'!AD27 | AE23: ='Promo Form'!AE27 | AF23: ='Promo Form'!AT23 | AG23: ='Promo Form'!AI27 | AH23: ='Promo Form'!AJ27 | AI23: ='Promo Form'!AK27 | AJ23: ='Promo Form'!AL27 | AL23: ='Promo Form'!AL27 | AM23: ='Promo Form'!AM27 | AN23: ='Promo Form'!BF23 | AO23: ='Promo Form'!AQ27 | AP23: ='Promo Form'!AR27 | AQ23: ='Promo Form'!AS27 | AR23: ='Promo Form'!AT27 | AT23: ='Promo Form'!BN23 | AU23: ='Promo Form'!BO23 | AV23: ='Promo Form'!BR23 | AW23: ='Promo Form'!BS23 | AX23: ='Promo Form'!BT23 | AY23: ='Promo Form'!BU23 | AZ23: ='Promo Form'!BV23 | BB23: ='Promo Form'!BZ23 | BC23: ='Promo Form'!CA23 | BD23: ='Promo Form'!CD23 | BE23: ='Promo Form'!CE23 | BF23: ='Promo Form'!CF23 | BG23: ='Promo Form'!CG23 | BH23: ='Promo Form'!CH23 | BJ23: ='Promo Form'!CL23 | BK23: ='Promo Form'!CM23 | BL23: ='Promo Form'!CN23 | BM23: ='Promo Form'!CO23 | BN23: ='Promo Form'!CP23 -> 0
A24: Last Day for Customer claims to be submitted | D24: ='Promo Form'!D28 -> 45686 | J24: =IFERROR((($FR24/1.1)+(#REF!+#REF!)-(G24-(G24*F$2)))/($FR24/1.1),"") | L24: =IFERROR((($FR24/1.1)+(#REF!+H24)-(#REF!-(#REF!*G$2)))/($FR24/1.1),"") | R24: =IFERROR((($FR24/1.1)+(#REF!+#REF!)-(O24-(O24*N$2)))/($FR24/1.1),"") | T24: =IFERROR((($FR24/1.1)+(#REF!+P24)-(#REF!-(#REF!*O$2)))/($FR24/1.1),"") | Z24: =IFERROR((($FR24/1.1)+(#REF!+#REF!)-(W24-(W24*V$2)))/($FR24/1.1),"") | AB24: =IFERROR((($FR24/1.1)+(#REF!+X24)-(#REF!-(#REF!*W$2)))/($FR24/1.1),"") | AH24: =IFERROR((($FR24/1.1)+(#REF!+#REF!)-(AE24-(AE24*AD$2)))/($FR24/1.1),"") | AJ24: =IFERROR((($FR24/1.1)+(#REF!+AF24)-(#REF!-(#REF!*AE$2)))/($FR24/1.1),"") | AP24: =IFERROR((($FR24/1.1)+(#REF!+#REF!)-(AM24-(AM24*AL$2)))/($FR24/1.1),"") | AR24: =IFERROR((($FR24/1.1)+(#REF!+AN24)-(#REF!-(#REF!*AM$2)))/($FR24/1.1),"") | AX24: =IFERROR((($FR24/1.1)+(#REF!+#REF!)-(AU24-(AU24*AT$2)))/($FR24/1.1),"") | AZ24: =IFERROR((($FR24/1.1)+(#REF!+AV24)-(#REF!-(#REF!*AU$2)))/($FR24/1.1),"") | BF24: =IFERROR((($FR24/1.1)+(#REF!+#REF!)-(BC24-(BC24*BB$2)))/($FR24/1.1),"") | BH24: =IFERROR((($FR24/1.1)+(#REF!+BD24)-(#REF!-(#REF!*BC$2)))/($FR24/1.1),"")
F25: NOTES | N25: NOTES | V25: NOTES | AD25: NOTES | AL25: NOTES | AT25: NOTES | BB25: NOTES
F26: ='Promo Form'!H42 -> 0 | N26: ='Promo Form'!T42 -> 0 | V26: ='Promo Form'!AF42 -> 0 | AD26: ='Promo Form'!AR42 -> 0 | AL26: ='Promo Form'!BD42 -> 0 | AT26: ='Promo Form'!BP42 -> 0 | BB26: ='Promo Form'!CB42 -> 0

Sheet Vendor Copy
A1: New Zealand Claim Number | C1: ='Promo Form'!C1 -> 0 | D1: Name of Promotion
A2: Brand | C2: ='Promo Form'!C2 -> 0 | D2: ='Promo Form'!D2 -> 0
A3: Promo Date(s) | C3: Code | D3: Product Description | F3: ='Promo Form'!F3 -> Harvey Norman | J3: ='Promo Form'!R3 -> JB HIFI | N3: ='Promo Form'!AD3 -> Harvey Norman | R3: ='Promo Form'!AP3 -> PB Tech | V3: ='Promo Form'!BB3 -> Spare | Z3: ='Promo Form'!BN3 -> Spare | AD3: ='Promo Form'!BZ3 -> Spare
A4: From | B4: To | F4: Supplier Support | G4: Expected Sales / Actual Sales | H4: Supplier Claim Amount | J4: Supplier Support | K4: Expected Sales / Actual Sales | L4: Supplier Claim Amount | N4: Supplier Support | O4: Expected Sales / Actual Sales | P4: Supplier Claim Amount | R4: Supplier Support | S4: Expected Sales / Actual Sales | T4: Supplier Claim Amount | V4: Supplier Support | W4: Expected Sales / Actual Sales | X4: Supplier Claim Amount | Z4: Supplier Support | AA4: Expected Sales / Actual Sales | AB4: Supplier Claim Amount | AD4: Supplier Support | AE4: Expected Sales / Actual Sales | AF4: Supplier Claim Amount | AH4: RRP Inc | AI4: Recommended Sale Inc | AJ4: Recommended % Off | AK4: Recommended $ Off | AL4: Comments
A5: ='Promo Form'!A5 -> 45658 | B5: ='Promo Form'!B5 -> 45672 | C5: ='Promo Form'!C5 -> ADM4DG | D5: ='Promo Form'!D5 -> ADONIT Mini 4 (Grey) | F5: ='Promo Form'!H5 -> 1.217 | G5: ='Promo Form'!N5 -> 18 | H5: ='Promo Form'!O5 -> 21.906 | J5: ='Promo Form'!T5 -> 1.217 | K5: ='Promo Form'!Z5 | L5: ='Promo Form'!AA5 | N5: ='Promo Form'!AF5 -> 1.217 | O5: ='Promo Form'!AL5 -> 18 | P5: ='Promo Form'!AM5 -> 21.906 | R5: ='Promo Form'!AR5 -> 1.043 | S5: ='Promo Form'!AX5 -> 46 | T5: ='Promo Form'!AY5 -> 47.978 | V5: ='Promo Form'!BD5 | W5: ='Promo Form'!BJ5 | X5: ='Promo Form'!BK5 | Z5: ='Promo Form'!BP5 | AA5: ='Promo Form'!BV5 | AB5: ='Promo Form'!BW5 | AD5: ='Promo Form'!CB5 | AE5: ='Promo Form'!CH5 | AF5: ='Promo Form'!CI5 | AH5: ='Promo Form'!CL5 -> 39.99 | AI5: ='Promo Form'!CM5 -> 31.992 | AJ5: ='Promo Form'!CN5 -> 0.2 | AK5: ='Promo Form'!CO5 -> 7.998 | AL5: ='Promo Form'!CP5 -> 0
A6: ='Promo Form'!A6 | B6: ='Promo Form'!B6 | C6: ='Promo Form'!C6 -> 0 | D6: ='Promo Form'!D6 | F6: ='Promo Form'!H6 | G6: ='Promo Form'!N6 | H6: ='Promo Form'!O6 | J6: ='Promo Form'!T6 | K6: ='Promo Form'!Z6 | L6: ='Promo Form'!AA6 | N6: ='Promo Form'!AF6 | O6: ='Promo Form'!AL6 | P6: ='Promo Form'!AM6 | R6: ='Promo Form'!AR6 | S6: ='Promo Form'!AX6 | T6: ='Promo Form'!AY6 | V6: ='Promo Form'!BD6 | W6: ='Promo Form'!BJ6 | X6: ='Promo Form'!BK6 | Z6: ='Promo Form'!BP6 | AA6: ='Promo Form'!BV6 | AB6: ='Promo Form'!BW6 | AD6: ='Promo Form'!CB6 | AE6: ='Promo Form'!CH6 | AF6: ='Promo Form'!CI6 | AH6: ='Promo Form'!CL6 | AI6: ='Promo Form'!CM6 | AJ6: ='Promo Form'!CN6 | AK6: ='Promo Form'!CO6 | AL6: ='Promo Form'!CP6 -> 0
A7: ='Promo Form'!A7 | B7: ='Promo Form'!B7 | C7: ='Promo Form'!C7 -> 0 | D7: ='Promo Form'!D7 | F7: ='Promo Form'!H7 | G7: ='Promo Form'!N7 | H7: ='Promo Form'!O7 | J7: ='Promo Form'!T7 | K7: ='Promo Form'!Z7 | L7: ='Promo Form'!AA7 | N7: ='Promo Form'!AF7 | O7: ='Promo Form'!AL7 | P7: ='Promo Form'!AM7 | R7: ='Promo Form'!AR7 | S7: ='Promo Form'!AX7 | T7: ='Promo Form'!AY7 | V7: ='Promo Form'!BD7 | W7: ='Promo Form'!BJ7 | X7: ='Promo Form'!BK7 | Z7: ='Promo Form'!BP7 | AA7: ='Promo Form'!BV7 | AB7: ='Promo Form'!BW7 | AD7: ='Promo Form'!CB7 | AE7: ='Promo Form'!CH7 | AF7: ='Promo Form'!CI7 | AH7: ='Promo Form'!CL7 | AI7: ='Promo Form'!CM7 | AJ7: ='Promo Form'!CN7 | AK7: ='Promo Form'!CO7 | AL7: ='Promo Form'!CP7 -> 0
A8: ='Promo Form'!A8 | B8: ='Promo Form'!B8 | C8: ='Promo Form'!C8 -> 0 | D8: ='Promo Form'!D8 | F8: ='Promo Form'!H8 | G8: ='Promo Form'!N8 | H8: ='Promo Form'!O8 | J8: ='Promo Form'!T8 | K8: ='Promo Form'!Z8 | L8: ='Promo Form'!AA8 | N8: ='Promo Form'!AF8 | O8: ='Promo Form'!AL8 | P8: ='Promo Form'!AM8 | R8: ='Promo Form'!AR8 | S8: ='Promo Form'!AX8 | T8: ='Promo Form'!AY8 | V8: ='Promo Form'!BD8 | W8: ='Promo Form'!BJ8 | X8: ='Promo Form'!BK8 | Z8: ='Promo Form'!BP8 | AA8: ='Promo Form'!BV8 | AB8: ='Promo Form'!BW8 | AD8: ='Promo Form'!CB8 | AE8: ='Promo Form'!CH8 | AF8: ='Promo Form'!CI8 | AH8: ='Promo Form'!CL8 | AI8: ='Promo Form'!CM8 | AJ8: ='Promo Form'!CN8 | AK8: ='Promo Form'!CO8 | AL8: ='Promo Form'!CP8 -> 0
A9: ='Promo Form'!A9 | B9: ='Promo Form'!B9 | C9: ='Promo Form'!C9 -> 0 | D9: ='Promo Form'!D9 | F9: ='Promo Form'!H9 | G9: ='Promo Form'!N9 | H9: ='Promo Form'!O9 | J9: ='Promo Form'!T9 | K9: ='Promo Form'!Z9 | L9: ='Promo Form'!AA9 | N9: ='Promo Form'!AF9 | O9: ='Promo Form'!AL9 | P9: ='Promo Form'!AM9 | R9: ='Promo Form'!AR9 | S9: ='Promo Form'!AX9 | T9: ='Promo Form'!AY9 | V9: ='Promo Form'!BD9 | W9: ='Promo Form'!BJ9 | X9: ='Promo Form'!BK9 | Z9: ='Promo Form'!BP9 | AA9: ='Promo Form'!BV9 | AB9: ='Promo Form'!BW9 | AD9: ='Promo Form'!CB9 | AE9: ='Promo Form'!CH9 | AF9: ='Promo Form'!CI9 | AH9: ='Promo Form'!CL9 | AI9: ='Promo Form'!CM9 | AJ9: ='Promo Form'!CN9 | AK9: ='Promo Form'!CO9 | AL9: ='Promo Form'!CP9 -> 0
A10: ='Promo Form'!A10 | B10: ='Promo Form'!B10 | C10: ='Promo Form'!C10 -> 0 | D10: ='Promo Form'!D10 | F10: ='Promo Form'!H10 | G10: ='Promo Form'!N10 | H10: ='Promo Form'!O10 | J10: ='Promo Form'!T10 | K10: ='Promo Form'!Z10 | L10: ='Promo Form'!AA10 | N10: ='Promo Form'!AF10 | O10: ='Promo Form'!AL10 | P10: ='Promo Form'!AM10 | R10: ='Promo Form'!AR10 | S10: ='Promo Form'!AX10 | T10: ='Promo Form'!AY10 | V10: ='Promo Form'!BD10 | W10: ='Promo Form'!BJ10 | X10: ='Promo Form'!BK10 | Z10: ='Promo Form'!BP10 | AA10: ='Promo Form'!BV10 | AB10: ='Promo Form'!BW10 | AD10: ='Promo Form'!CB10 | AE10: ='Promo Form'!CH10 | AF10: ='Promo Form'!CI10 | AH10: ='Promo Form'!CL10 | AI10: ='Promo Form'!CM10 | AJ10: ='Promo Form'!CN10 | AK10: ='Promo Form'!CO10 | AL10: ='Promo Form'!CP10 -> 0
A11: ='Promo Form'!A11 | B11: ='Promo Form'!B11 | C11: ='Promo Form'!C11 -> 0 | D11: ='Promo Form'!D11 | F11: ='Promo Form'!H11 | G11: ='Promo Form'!N11 | H11: ='Promo Form'!O11 | J11: ='Promo Form'!T11 | K11: ='Promo Form'!Z11 | L11: ='Promo Form'!AA11 | N11: ='Promo Form'!AF11 | O11: ='Promo Form'!AL11 | P11: ='Promo Form'!AM11 | R11: ='Promo Form'!AR11 | S11: ='Promo Form'!AX11 | T11: ='Promo Form'!AY11 | V11: ='Promo Form'!BD11 | W11: ='Promo Form'!BJ11 | X11: ='Promo Form'!BK11 | Z11: ='Promo Form'!BP11 | AA11: ='Promo Form'!BV11 | AB11: ='Promo Form'!BW11 | AD11: ='Promo Form'!CB11 | AE11: ='Promo Form'!CH11 | AF11: ='Promo Form'!CI11 | AH11: ='Promo Form'!CL11 | AI11: ='Promo Form'!CM11 | AJ11: ='Promo Form'!CN11 | AK11: ='Promo Form'!CO11 | AL11: ='Promo Form'!CP11 -> 0
A12: ='Promo Form'!A12 | B12: ='Promo Form'!B12 | C12: ='Promo Form'!C12 -> 0 | D12: ='Promo Form'!D12 | F12: ='Promo Form'!H12 | G12: ='Promo Form'!N12 | H12: ='Promo Form'!O12 | J12: ='Promo Form'!T12 | K12: ='Promo Form'!Z12 | L12: ='Promo Form'!AA12 | N12: ='Promo Form'!AF12 | O12: ='Promo Form'!AL12 | P12: ='Promo Form'!AM12 | R12: ='Promo Form'!AR12 | S12: ='Promo Form'!AX12 | T12: ='Promo Form'!AY12 | V12: ='Promo Form'!BD12 | W12: ='Promo Form'!BJ12 | X12: ='Promo Form'!BK12 | Z12: ='Promo Form'!BP12 | AA12: ='Promo Form'!BV12 | AB12: ='Promo Form'!BW12 | AD12: ='Promo Form'!CB12 | AE12: ='Promo Form'!CH12 | AF12: ='Promo Form'!CI12 | AH12: ='Promo Form'!CL12 | AI12: ='Promo Form'!CM12 | AJ12: ='Promo Form'!CN12 | AK12: ='Promo Form'!CO12 | AL12: ='Promo Form'!CP12 -> 0
A13: ='Promo Form'!A13 | B13: ='Promo Form'!B13 | C13: ='Promo Form'!C13 -> 0 | D13: ='Promo Form'!D13 | F13: ='Promo Form'!H13 | G13: ='Promo Form'!N13 | H13: ='Promo Form'!O13 | J13: ='Promo Form'!T13 | K13: ='Promo Form'!Z13 | L13: ='Promo Form'!AA13 | N13: ='Promo Form'!AF13 | O13: ='Promo Form'!AL13 | P13: ='Promo Form'!AM13 | R13: ='Promo Form'!AR13 | S13: ='Promo Form'!AX13 | T13: ='Promo Form'!AY13 | V13: ='Promo Form'!BD13 | W13: ='Promo Form'!BJ13 | X13: ='Promo Form'!BK13 | Z13: ='Promo Form'!BP13 | AA13: ='Promo Form'!BV13 | AB13: ='Promo Form'!BW13 | AD13: ='Promo Form'!CB13 | AE13: ='Promo Form'!CH13 | AF13: ='Promo Form'!CI13 | AH13: ='Promo Form'!CL13 | AI13: ='Promo Form'!CM13 | AJ13: ='Promo Form'!CN13 | AK13: ='Promo Form'!CO13 | AL13: ='Promo Form'!CP13 -> 0
A14: ='Promo Form'!A14 | B14: ='Promo Form'!B14 | C14: ='Promo Form'!C14 -> 0 | D14: ='Promo Form'!D14 | F14: ='Promo Form'!H14 | G14: ='Promo Form'!N14 | H14: ='Promo Form'!O14 | J14: ='Promo Form'!T14 | K14: ='Promo Form'!Z14 | L14: ='Promo Form'!AA14 | N14: ='Promo Form'!AF14 | O14: ='Promo Form'!AL14 | P14: ='Promo Form'!AM14 | R14: ='Promo Form'!AR14 | S14: ='Promo Form'!AX14 | T14: ='Promo Form'!AY14 | V14: ='Promo Form'!BD14 | W14: ='Promo Form'!BJ14 | X14: ='Promo Form'!BK14 | Z14: ='Promo Form'!BP14 | AA14: ='Promo Form'!BV14 | AB14: ='Promo Form'!BW14 | AD14: ='Promo Form'!CB14 | AE14: ='Promo Form'!CH14 | AF14: ='Promo Form'!CI14 | AH14: ='Promo Form'!CL14 | AI14: ='Promo Form'!CM14 | AJ14: ='Promo Form'!CN14 | AK14: ='Promo Form'!CO14 | AL14: ='Promo Form'!CP14 -> 0
A15: ='Promo Form'!A15 | B15: ='Promo Form'!B15 | C15: ='Promo Form'!C15 -> 0 | D15: ='Promo Form'!D15 | F15: ='Promo Form'!H15 | G15: ='Promo Form'!N15 | H15: ='Promo Form'!O15 | J15: ='Promo Form'!T15 | K15: ='Promo Form'!Z15 | L15: ='Promo Form'!AA15 | N15: ='Promo Form'!AF15 | O15: ='Promo Form'!AL15 | P15: ='Promo Form'!AM15 | R15: ='Promo Form'!AR15 | S15: ='Promo Form'!AX15 | T15: ='Promo Form'!AY15 | V15: ='Promo Form'!BD15 | W15: ='Promo Form'!BJ15 | X15: ='Promo Form'!BK15 | Z15: ='Promo Form'!BP15 | AA15: ='Promo Form'!BV15 | AB15: ='Promo Form'!BW15 | AD15: ='Promo Form'!CB15 | AE15: ='Promo Form'!CH15 | AF15: ='Promo Form'!CI15 | AH15: ='Promo Form'!CL15 | AI15: ='Promo Form'!CM15 | AJ15: ='Promo Form'!CN15 | AK15: ='Promo Form'!CO15 | AL15: ='Promo Form'!CP15 -> 0
A16: ='Promo Form'!A16 | B16: ='Promo Form'!B16 | C16: ='Promo Form'!C16 -> 0 | D16: ='Promo Form'!D16 | F16: ='Promo Form'!H16 | G16: ='Promo Form'!N16 | H16: ='Promo Form'!O16 | J16: ='Promo Form'!T16 | K16: ='Promo Form'!Z16 | L16: ='Promo Form'!AA16 | N16: ='Promo Form'!AF16 | O16: ='Promo Form'!AL16 | P16: ='Promo Form'!AM16 | R16: ='Promo Form'!AR16 | S16: ='Promo Form'!AX16 | T16: ='Promo Form'!AY16 | V16: ='Promo Form'!BD16 | W16: ='Promo Form'!BJ16 | X16: ='Promo Form'!BK16 | Z16: ='Promo Form'!BP16 | AA16: ='Promo Form'!BV16 | AB16: ='Promo Form'!BW16 | AD16: ='Promo Form'!CB16 | AE16: ='Promo Form'!CH16 | AF16: ='Promo Form'!CI16 | AH16: ='Promo Form'!CL16 | AI16: ='Promo Form'!CM16 | AJ16: ='Promo Form'!CN16 | AK16: ='Promo Form'!CO16 | AL16: ='Promo Form'!CP16 -> 0
... A19: ='Promo Form'!A19 | B19: ='Promo Form'!B19 | C19: ='Promo Form'!C19 -> 0 | D19: ='Promo Form'!D19 | F19: ='Promo Form'!H19 | G19: ='Promo Form'!N19 | H19: ='Promo Form'!O19 | J19: ='Promo Form'!T19 | K19: ='Promo Form'!Z19 | L19: ='Promo Form'!AA19 | N19: ='Promo Form'!AF19 | O19: ='Promo Form'!AL19 | P19: ='Promo Form'!AM19 | R19: ='Promo Form'!AR19 | S19: ='Promo Form'!AX19 | T19: ='Promo Form'!AY19 | V19: ='Promo Form'!BD19 | W19: ='Promo Form'!BJ19 | X19: ='Promo Form'!BK19 | Z19: ='Promo Form'!BP19 | AA19: ='Promo Form'!BV19 | AB19: ='Promo Form'!BW19 | AD19: ='Promo Form'!CB19 | AE19: ='Promo Form'!CH19 | AF19: ='Promo Form'!CI19 | AH19: ='Promo Form'!CL19 | AI19: ='Promo Form'!CM19 | AJ19: ='Promo Form'!CN19 | AK19: ='Promo Form'!CO19 | AL19: ='Promo Form'!CP19 -> 0
A20: ='Promo Form'!A24 | B20: ='Promo Form'!B24 | C20: ='Promo Form'!C24 -> 0 | D20: ='Promo Form'!D24 | F20: ='Promo Form'!H20 | G20: ='Promo Form'!N20 | H20: ='Promo Form'!O20 | J20: ='Promo Form'!T20 | K20: ='Promo Form'!Z20 | L20: ='Promo Form'!AA20 | N20: ='Promo Form'!AF20 | O20: ='Promo Form'!AL20 | P20: ='Promo Form'!AM20 | R20: ='Promo Form'!AR20 | S20: ='Promo Form'!AX20 | T20: ='Promo Form'!AY20 | V20: ='Promo Form'!BD20 | W20: ='Promo Form'!BJ20 | X20: ='Promo Form'!BK20 | Z20: ='Promo Form'!BP20 | AA20: ='Promo Form'!BV20 | AB20: ='Promo Form'!BW20 | AD20: ='Promo Form'!CB20 | AE20: ='Promo Form'!CH20 | AF20: ='Promo Form'!CI20 | AH20: ='Promo Form'!CL20 | AI20: ='Promo Form'!CM20 | AJ20: ='Promo Form'!CN20 | AK20: ='Promo Form'!CO20 | AL20: ='Promo Form'!CP20 -> 0
A21: ='Promo Form'!A25 | B21: ='Promo Form'!B25 | C21: ='Promo Form'!C25 -> 0 | D21: ='Promo Form'!D25 | F21: ='Promo Form'!H21 | G21: ='Promo Form'!N21 | H21: ='Promo Form'!O21 | J21: ='Promo Form'!T21 | K21: ='Promo Form'!Z21 | L21: ='Promo Form'!AA21 | N21: ='Promo Form'!AF21 | O21: ='Promo Form'!AL21 | P21: ='Promo Form'!AM21 | R21: ='Promo Form'!AR21 | S21: ='Promo Form'!AX21 | T21: ='Promo Form'!AY21 | V21: ='Promo Form'!BD21 | W21: ='Promo Form'!BJ21 | X21: ='Promo Form'!BK21 | Z21: ='Promo Form'!BP21 | AA21: ='Promo Form'!BV21 | AB21: ='Promo Form'!BW21 | AD21: ='Promo Form'!CB21 | AE21: ='Promo Form'!CH21 | AF21: ='Promo Form'!CI21 | AH21: ='Promo Form'!CL21 | AI21: ='Promo Form'!CM21 | AJ21: ='Promo Form'!CN21 | AK21: ='Promo Form'!CO21 | AL21: ='Promo Form'!CP21 -> 0
A22: ='Promo Form'!A26 | B22: ='Promo Form'!B26 | C22: ='Promo Form'!C26 -> 0 | D22: ='Promo Form'!D26 | F22: ='Promo Form'!H22 | G22: ='Promo Form'!N22 | H22: ='Promo Form'!O22 | J22: ='Promo Form'!T22 | K22: ='Promo Form'!Z22 | L22: ='Promo Form'!AA22 | N22: ='Promo Form'!AF22 | O22: ='Promo Form'!AL22 | P22: ='Promo Form'!AM22 | R22: ='Promo Form'!AR22 | S22: ='Promo Form'!AX22 | T22: ='Promo Form'!AY22 | V22: ='Promo Form'!BD22 | W22: ='Promo Form'!BJ22 | X22: ='Promo Form'!BK22 | Z22: ='Promo Form'!BP22 | AA22: ='Promo Form'!BV22 | AB22: ='Promo Form'!BW22 | AD22: ='Promo Form'!CB22 | AE22: ='Promo Form'!CH22 | AF22: ='Promo Form'!CI22 | AH22: ='Promo Form'!CL22 | AI22: ='Promo Form'!CM22 | AJ22: ='Promo Form'!CN22 | AK22: ='Promo Form'!CO22 | AL22: ='Promo Form'!CP22 -> 0
A23: ='Promo Form'!A27 | B23: ='Promo Form'!B27 | C23: ='Promo Form'!C27 -> 0 | D23: ='Promo Form'!D27 | F23: ='Promo Form'!H23 | G23: ='Promo Form'!N23 | H23: ='Promo Form'!O23 | J23: ='Promo Form'!T23 | K23: ='Promo Form'!Z23 | L23: ='Promo Form'!AA23 | N23: ='Promo Form'!AF23 | O23: ='Promo Form'!AL23 | P23: ='Promo Form'!AM23 | R23: ='Promo Form'!AR23 | S23: ='Promo Form'!AX23 | T23: ='Promo Form'!AY23 | V23: ='Promo Form'!BD23 | W23: ='Promo Form'!BJ23 | X23: ='Promo Form'!BK23 | Z23: ='Promo Form'!BP23 | AA23: ='Promo Form'!BV23 | AB23: ='Promo Form'!BW23 | AD23: ='Promo Form'!CB23 | AE23: ='Promo Form'!CH23 | AF23: ='Promo Form'!CI23 | AH23: ='Promo Form'!CL23 | AI23: ='Promo Form'!CM23 | AJ23: ='Promo Form'!CN23 | AK23: ='Promo Form'!CO23 | AL23: ='Promo Form'!CP23 -> 0
A24: Last Day for Customer claims to be submitted | G24: Total | H24: Supplier | K24: Total | L24: Supplier | O24: Total | P24: Supplier | S24: Total | T24: Supplier | W24: Total | X24: Supplier | AA24: Total | AB24: Supplier | AE24: Total | AF24: Supplier
H25: ='Promo Form'!O30 -> 21.906 | L25: ='Promo Form'!AA30 -> 0 | P25: ='Promo Form'!AM30 -> 21.906 | T25: ='Promo Form'!AY30 -> 47.978 | X25: ='Promo Form'!BK30 -> 0 | AB25: ='Promo Form'!BW30 -> 0 | AF25: ='Promo Form'!CI30 -> 0
A26: TOTAL Brand Claim AUD Ex | D26: ='Promo Form'!D31 -> 91.79
A27: TOTAL CLAIM to USD ex | D27: ='Promo Form'!D32 -> 55.074
C28: AUD to USD Rate | D28: ='Promo Form'!D33 -> 0.6
B31: VENDOR NOTE | D31: ** Please note, Expected Sales and claim totals are a projection based on estimated sales within promo Period. Total claim will vary depending on success of promotion.

Sheet Data Validation
B2: Rebate
A3: Costco Wholesale | B3: 0.055
A4: Cyclone Computer Co Ltd | B4: 0.05
A5: EB Games (NZ) | B5: 0.05
A6: Harvey Norman | B6: 0.17
A7: NZ - Heathcotes | B7: 0.15
A8: JB HIFI | B8: 0.203
A9: JB HIFI | B9: 0.253
A10: Leading Edge | B10: 0.05
A11: Noel Leeming | B11: 0.16
A12: PB Tech | B12: 0.05
A13: Smiths City | B13: 0.05
A14: Dealer 1 | B14: 0
... A20: Spare | B20: 0

Sheet Master Price Level NZ
A1: Brand | B1: Code | C1: Description | D1: NZ Status | E1: Base (RRP Inc) | F1: RRP ex GST | G1: Clearance - MacGear + Brand Sites | H1: Dealer 1 | I1: Dealer 2 | J1: Dealer 3 | K1: Education | L1: Costco | M1: JB HIfi | N1: Harvey Norman | O1: LS travel | P1: PB Tech | Q1: NZ - HN Commercial | R1: NZ - NL Commercial | S1: Noel Leeming | T1: NZ - Spark | U1: NZ AU - AirPoints / Aciem / Collinson | V1: NZ AU - Smart Loyalty | W1: NZ AU - Fly Buys | X1: NZ AU - Qantas | Y1: NZ AU - RRP - Home Of Brands | Z1: NZ AU - RRP - List Price
A2: ADONIT | B2: ADU010WH | C2: ADONIT ADU USI (White) | D2: Inactive | E2: 139.99 | G2: 139.99 | H2: 79.12 | I2: 97.38 | J2: 109.56 | M2: 87.65 | N2: 88.86 | O2: 91.3 | P2: 73.04 | Q2: 73.04 | R2: 73.04 | S2: 91.3 | T2: 91.3 | U2: 85.21 | V2: 91.3 | W2: 103.47 | X2: 97.38 | Y2: 139.99
A3: ADONIT | B3: ADIM | C3: ADONIT Ink M (Black) | D3: Inactive | E3: 129.99 | G3: 159.99 | H3: 67.82 | I3: 90.43 | J3: 111.3 | K3: 132.17 | M3: 79.12 | N3: 79.12 | O3: 83.47 | P3: 67.82 | Q3: 67.82 | R3: 67.82 | S3: 84.78 | T3: 67.82 | U3: 79.12 | V3: 67.82 | W3: 84.78 | X3: 84.78 | Y3: 129.99
A4: ADONIT | B4: ADIBUVCV | C4: ADONIT Ink UVC | D4: Inactive | E4: 169.99 | G4: 169.99 | H4: 88.69 | I4: 118.25 | K4: 140.43 | M4: 103.47 | N4: 110.86 | O4: 88.69 | P4: 88.69 | Q4: 88.69 | R4: 88.69 | S4: 110.86 | U4: 103.47 | Y4: 169.99
A5: ADONIT | B5: ADMB | C5: ADONIT Mark (Black) | D5: Active | E5: 29.99 | F5: 26.08 | G5: 29.99 | H5: 15.65 | I5: 20.86 | J5: 20.86 | K5: 23.47 | M5: 18.25 | N5: 18.25 | O5: 14.34 | P5: 15.65 | Q5: 15.65 | R5: 15.65 | S5: 15.82 | T5: 15.65 | U5: 19.56 | V5: 15.65 | W5: 23.47 | X5: 19.56 | Y5: 29.99
A6: ADONIT | B6: ADMS | C6: ADONIT Mark (Silver) | D6: Inactive | E6: 29.99 | G6: 29.99 | H6: 15.65 | I6: 18.25 | J6: 20.86 | K6: 24.77 | M6: 18.25 | N6: 18.25 | O6: 15.65 | P6: 15.65 | Q6: 15.65 | R6: 15.65 | S6: 18.25 | T6: 15.65 | U6: 18.25 | V6: 15.65 | W6: 19.56 | X6: 19.56 | Y6: 29.99
A7: ADONIT | B7: ADM4RB | C7: ADONIT Mini 4 (Blue) | D7: Inactive | E7: 39.99 | G7: 39.99 | H7: 20.86 | I7: 27.82 | J7: 27.82 | K7: 33.04 | M7: 24.34 | N7: 24.34 | O7: 24.34 | P7: 20.86 | Q7: 20.86 | R7: 20.86 | S7: 26.08 | T7: 20.86 | U7: 24.34 | V7: 20.86 | W7: 26.08 | X7: 26.08 | Y7: 39.99
A8: ADONIT | B8: ADM4DG | C8: ADONIT Mini 4 (Grey) | D8: Active | E8: 39.99 | F8: 34.77 | G8: 39.99 | H8: 20.86 | I8: 27.82 | J8: 27.82 | K8: 31.3 | M8: 24.34 | N8: 24.34 | O8: 19.13 | P8: 20.86 | Q8: 20.86 | R8: 20.86 | S8: 26.08 | T8: 20.86 | U8: 26.08 | V8: 20.86 | W8: 31.3 | X8: 26.08 | Y8: 39.99
A9: ADONIT | B9: ADNB | C9: ADONIT Note (Black) | D9: Inactive | E9: 99.99 | G9: 49.99 | H9: 52.17 | I9: 86.95 | J9: 69.56 | K9: 82.6 | M9: 60.86 | N9: 60.86 | O9: 52.17 | P9: 52.17 | Q9: 52.17 | R9: 52.17 | S9: 65.21 | T9: 52.17 | U9: 60.86 | V9: 52.17 | W9: 65.21 | X9: 65.21 | Y9: 99.99
A10: ADONIT | B10: ADNBCF | C10: ADONIT Note Clip Free (Black) | D10: Inactive | E10: 99.99 | G10: 99.99 | H10: 52.17 | I10: 69.56 | J10: 69.56 | K10: 82.6 | M10: 60.86 | N10: 60.86 | O10: 52.17 | P10: 52.17 | Q10: 52.17 | R10: 52.17 | S10: 65.21 | T10: 52.17 | U10: 60.86 | V10: 52.17 | W10: 65.21 | X10: 65.21 | Y10: 99.99
A11: ADONIT | B11: ADNM | C11: ADONIT Note M (Black) | D11: Inactive | E11: 129.99 | G11: 159.99 | H11: 67.82 | I11: 90.43 | J11: 111.3 | K11: 132.17 | M11: 79.12 | N11: 79.12 | O11: 83.47 | P11: 67.82 | Q11: 67.82 | R11: 67.82 | S11: 84.78 | T11: 67.82 | U11: 79.12 | V11: 67.82 | W11: 84.78 | X11: 84.78 | Y11: 129.99
A12: ADONIT | B12: ADNSB | C12: ADONIT Note Plus (Black) | D12: Inactive | E12: 149.99 | G12: 149.99 | H12: 78.26 | I12: 130.43 | J12: 104.34 | K12: 123.9 | M12: 91.3 | N12: 91.3 | O12: 78.26 | P12: 78.26 | Q12: 78.26 | R12: 78.26 | S12: 97.82 | T12: 78.26 | U12: 91.3 | V12: 78.26 | W12: 97.82 | X12: 97.82 | Y12: 149.99
A13: ADONIT | B13: ADNT | C13: ADONIT Note Replacement Tips (3 Pack) | D13: Inactive | E13: 25.99 | G13: 25.99 | H13: 13.56 | I13: 22.6 | J13: 18.08 | K13: 21.47 | M13: 15.82 | N13: 15.82 | O13: 13.56 | P13: 13.56 | Q13: 13.56 | R13: 13.56 | S13: 16.95 | T13: 13.56 | U13: 15.82 | V13: 13.56 | W13: 16.95 | X13: 16.95 | Y13: 25.99
A14: ADONIT | B14: ADNP2 | C14: ADONIT Note+2 | D14: EOL | E14: 169.99 | F14: 147.82 | G14: 169.99 | H14: 96.08 | I14: 118.25 | J14: 133.04 | K14: 103.47 | M14: 106.43 | N14: 107.91 | O14: 110.86 | P14: 88.69 | Q14: 88.69 | R14: 88.69 | S14: 110.86 | T14: 110.86 | U14: 103.47 | V14: 110.86 | W14: 125.64 | X14: 118.25 | Y14: 169.99
A15: ADONIT | B15: ADP4B | C15: ADONIT Pro 4 (Black) | D15: Active | E15: 59.99 | F15: 52.17 | G15: 59.99 | H15: 31.3 | I15: 41.73 | J15: 41.73 | K15: 46.95 | M15: 36.52 | N15: 36.52 | O15: 31.3 | P15: 31.3 | Q15: 31.3 | R15: 31.3 | S15: 39.12 | T15: 31.3 | U15: 39.12 | V15: 31.3 | W15: 46.95 | X15: 39.12 | Y15: 59.99
A16: ADONIT | B16: ADP4S | C16: ADONIT Pro 4 (Silver) | D16: Inactive | E16: 59.99 | G16: 59.99 | H16: 31.3 | I16: 41.73 | J16: 41.73 | K16: 49.56 | M16: 36.52 | N16: 36.52 | O16: 31.3 | P16: 31.3 | Q16: 31.3 | R16: 31.3 | S16: 39.12 | T16: 31.3 | U16: 36.52 | V16: 31.3 | W16: 39.12 | X16: 39.12 | Y16: 59.99
A17: ADONIT | B17: DISC T | C17: ADONIT Replacement Disc Pack (3 Pack) | D17: Inactive | E17: 24.99 | G17: 24.99 | H17: 13.04 | I17: 17.38 | J17: 17.38 | K17: 20.64 | M17: 15.21 | N17: 15.21 | O17: 13.04 | P17: 13.04 | Q17: 13.04 | R17: 13.04 | S17: 16.3 | T17: 13.04 | U17: 15.21 | V17: 13.04 | W17: 16.3 | X17: 16.3 | Y17: 24.99
A18: ADONIT | B18: ADRDK | C18: ADONIT Replacement Disc Tip Mini 4 / Pro 3 / Pro 4 - 2 pack | D18: Inactive | E18: 24.99 | H18: 13.04 | I18: 17.38 | J18: 20.86 | K18: 24.77 | M18: 15.21 | N18: 15.21 | O18: 15.65 | P18: 13.04 | Q18: 13.04 | R18: 13.04 | S18: 16.3 | T18: 13.04 | U18: 15.21 | V18: 13.04 | W18: 16.3 | X18: 16.3 | Y18: 24.99
A19: ADONIT | B19: ADSEB | C19: ADONIT SE (Black) | D19: Inactive | E19: 79.99 | G19: 79.99 | H19: 45.21 | I19: 55.65 | J19: 62.6 | K19: 52.17 | M19: 50.08 | N19: 50.78 | O19: 52.17 | P19: 41.73 | Q19: 41.73 | R19: 41.73 | S19: 52.17 | T19: 52.17 | U19: 48.69 | V19: 52.17 | W19: 59.12 | X19: 55.65 | Y19: 79.99
A20: ADONIT | B20: ADSEP | C20: ADONIT SE (Pink) | D20: Inactive | E20: 79.99 | G20: 79.99 | H20: 45.21 | I20: 55.65 | J20: 62.6 | K20: 52.17 | M20: 50.08 | N20: 50.78 | O20: 52.17 | P20: 41.73 | Q20: 41.73 | R20: 41.73 | S20: 52.17 | T20: 52.17 | U20: 48.69 | V20: 52.17 | W20: 59.12 | X20: 55.65 | Y20: 79.99
A21: ADONIT | B21: ADSEG | C21: ADONIT SE (Teal) | D21: EOL | E21: 79.99 | G21: 79.99 | H21: 45.21 | I21: 55.65 | J21: 62.6 | K21: 52.17 | M21: 50.08 | N21: 50.78 | O21: 52.17 | P21: 41.73 | Q21: 41.73 | R21: 41.73 | S21: 52.17 | T21: 52.17 | U21: 48.69 | V21: 52.17 | W21: 59.12 | X21: 55.65 | Y21: 79.99
A22: ADONIT | B22: ADSEW | C22: ADONIT SE (White) | D22: Inactive | E22: 79.99 | G22: 79.99 | H22: 45.21 | I22: 55.65 | J22: 62.6 | K22: 52.17 | M22: 50.08 | N22: 50.78 | O22: 52.17 | P22: 41.73 | Q22: 41.73 | R22: 41.73 | S22: 52.17 | T22: 52.17 | U22: 48.69 | V22: 52.17 | W22: 59.12 | X22: 55.65 | Y22: 79.99
A23: ADONIT | B23: ADSE2B | C23: ADONIT SE 2 - Black | D23: Active | E23: 69.99 | F23: 60.86 | H23: 39.56 | K23: 45.65 | M23: 42.6 | N23: 42.6 | P23: 36.52 | S23: 41.39
A24: ADONIT | B24: ADSE2PK | C24: ADONIT SE 2 - Pink | D24: Inactive | E24: 69.99 | F24: 60.86 | H24: 39.56 | K24: 45.65 | M24: 42.6 | N24: 42.6 | P24: 36.52 | S24: 41.39
A25: ADONIT | B25: ADSE2W | C25: ADONIT SE 2 - White | D25: Active | E25: 69.99 | F25: 60.86 | H25: 39.56 | K25: 45.65 | M25: 42.6 | N25: 42.6 | O25: 33.47 | P25: 36.52 | S25: 41.39
A26: AMAZFIT | B26: W2437GL7N | C26: Amazfit Active 2 (Round) Standard | D26: Active | E26: 260 | F26: 299.00 | Q26: 195 | S26: 195
A27: AMAZFIT | B27: W2557AP1N | C27: Amazfit Active Max | D27: Active | E27: 433.91 | F27: 499.00 | Q27: 325.43 | S27: 325.43
A28: AMAZFIT | B28: W2430GL1N | C28: Amazfit Balance 2 | D28: Active | E28: 694.78 | F28: 799.00 | Q28: 521.09 | S28: 521.09
A29: AMAZFIT | B29: W2435AP1N | C29: Amazfit BIP 6 Black | D29: Active | E29: 190.43 | F29: 219.00 | Q29: 142.83 | S29: 142.83
A30: AMAZFIT | B30: B2445GL7N | C30: Amazfit Helio Strap | D30: Active | E30: 199.13 | F30: 229.00 | Q30: 149.35 | S30: 149.35
A31: AMAZFIT | B31: W2323GL2N | C31: Amazfit T-Rex3 Onyx | D31: Active | E31: 581.74 | F31: 669.00 | Q31: 436.3 | S31: 436.3
A32: ANTIGRAVITY | B32: 6978913850095 | C32: Antigravity 65W GaN Fast Charger | D32: Inactive | E32: 69.99 | F32: 60.86
A33: ANTIGRAVITY | B33: 6978913850019 | C33: Antigravity A1 360 Drone Explorer Bundle | D33: Active | E33: 3099 | F33: 2694.78 | H33: 2263.62 | I33: 2290.56 | M33: 2455.24 | N33: 2515.13 | S33: 2460.45
A34: ANTIGRAVITY | B34: 6978913850026 | C34: Antigravity A1 360 Drone Infinity Bundle | D34: Active | E34: 3299.99 | F34: 2869.56 | H34: 2410.43 | I34: 2439.13 | M34: 2614.49 | N34: 2678.26 | S34: 2620.03
A35: ANTIGRAVITY | B35: 6978913850002 | C35: Antigravity A1 360 Drone Standard Bundle | D35: Active | E35: 2599 | F35: 2260.00 | H35: 1898.4 | I35: 1921 | M35: 2059.11 | N35: 2109.33 | S35: 2063.48
A36: ANTIGRAVITY | B36: SA-6978913850002 | C36: Antigravity A1 360 Drone Standard Bundle SAMPLES | D36: Active | E36: 0 | F36: .00 | H36: 0 | I36: 0 | M36: 0 | N36: 0 | S36: 0
A37: ANTIGRAVITY | B37: 6978913850033 | C37: Antigravity A1 Charging Hub | D37: Active | E37: 99.99 | F37: 86.95 | I37: 73.91
A38: ANTIGRAVITY | B38: 6978913850057 | C38: Antigravity A1 Flight Battery | D38: Active | E38: 119.99 | F38: 104.34 | I38: 88.69
A39: ANTIGRAVITY | B39: 6978913850064 | C39: Antigravity A1 High-Capacity Flight Battery | D39: Active | E39: 169.99 | F39: 147.82 | H39: 110.86 | I39: 125.65 | M39: 123.18 | N39: 123.18 | S39: 120.5
A40: ANTIGRAVITY | B40: 6978913850149 | C40: Antigravity A1 Landing Pad | D40: Active | E40: 57.99 | F40: 50.43 | H40: 37.82 | I40: 42.87 | M40: 42.03 | N40: 42.03 | S40: 41.11
A41: ANTIGRAVITY | B41: 6978913850132 | C41: Antigravity A1 Propeller Guards | D41: Active | E41: 69.99 | F41: 60.86 | I41: 51.73
A42: ANTIGRAVITY | B42: 6978913850101 | C42: Antigravity A1 Propellers | D42: Active | E42: 29.99 | F42: 26.08 | I42: 22.17
A43: ANTIGRAVITY | B43: 6978913850118 | C43: Antigravity A1 Replacement Lens Kit | D43: Inactive | E43: 62.99 | F43: 54.77
A44: ANTIGRAVITY | B44: 6978913850316 | C44: Antigravity A1 Replacement Lens Kit (Double Lens) | D44: Active | E44: 89.99 | F44: 78.25 | I44: 66.51
A45: ANTIGRAVITY | B45: 6978913850125 | C45: Antigravity A1 Sling Bag | D45: Active | E45: 199.99 | F45: 173.90
A46: ANTIGRAVITY | B46: 6978913850200 | C46: Antigravity Flexi Care (1 year) Physical Card | D46: Inactive | E46: 299.99 | F46: 260.86
A47: ANTIGRAVITY | B47: 501010100014 | C47: Antigravity Flexi Care (1 year) Virtual Card | D47: Active | E47: 299.99 | F47: 260.86 | H47: 219.12 | I47: 221.73 | J47: 234.77 | M47: 237.67 | N47: 243.47 | S47: 238.18
A48: ANTIGRAVITY | B48: 6978913850293 | C48: Antigravity Flexi Care (2 year) Physical Card | D48: Inactive | E48: 499.99 | F48: 434.77
A49: ANTIGRAVITY | B49: 502010100001 | C49: Antigravity Flexi Care (2 year) Virtual Card | D49: Active | E49: 499.99 | F49: 434.77 | H49: 365.21 | I49: 369.55 | J49: 391.29 | M49: 396.12 | N49: 405.79 | S49: 396.96
A50: ANTIGRAVITY | B50: 6978913850040 | C50: Antigravity Quick Reader | D50: Inactive | E50: 105.99 | F50: 92.17
A51: ANTIGRAVITY | B51: 6978913850187 | C51: Antigravity Vision -3.0D Corrective Lenses | D51: Active | E51: 44.99 | F51: 39.12 | I51: 33.25
A52: ANTIGRAVITY | B52: 6978913850156 | C52: Antigravity Vision Battery | D52: Active | E52: 94.99 | F52: 82.60 | I52: 70.21
A53: ANTIGRAVITY | B53: 6978913850163 | C53: Antigravity Vision Head Strap | D53: Active | E53: 39.99 | F53: 34.77 | I53: 29.55
A54: ANTIGRAVITY | B54: 6978913850170 | C54: Antigravity Vision USB-C to DC Power Cable?0.65m? | D54: Inactive | E54: 19.99 | F54: 17.38
A55: ANTIGRAVITY | B55: 6978913850224 | C55: Antigravity Vision USB-C to DC Power Cable?1.2m? | D55: Inactive | E55: 24.99 | F55: 21.73
A56: AQUA MARINA | B56: B0303628 | C56: AQUA MARINA AREO II 16" Hand Pump | D56: Inactive | E56: 59.99 | G56: 41.99 | H56: 36.52 | I56: 42.6 | J56: 48.69 | K56: 57.82 | M56: 39.12 | N56: 40.17 | O56: 36.52 | P56: 32.86 | Q56: 31.3 | R56: 31.3 | S56: 39.12 | T56: 31.3 | U56: 36.52 | V56: 31.3 | W56: 39.12 | X56: 39.12 | Y56: 59.99
A57: AQUA MARINA | B57: LA-320 | C57: AQUA MARINA Laxo-320 Recreational Inflatable Kayak - 2 person | D57: Inactive | E57: 799.99 | G57: 479.99 | H57: 486.95 | I57: 608.69 | J57: 695.65 | K57: 826.08 | M57: 521.73 | N57: 535.65 | O57: 521.73 | P57: 438.26 | Q57: 417.39 | R57: 417.39 | S57: 521.73 | T57: 417.39 | U57: 486.95 | V57: 417.39 | W57: 521.73 | X57: 521.73 | Y57: 799.99
A58: AQUA MARINA | B58: B0303012 | C58: AQUA MARINA SPORTS III Adjustable Aluminium Paddle Board Paddle | D58: Active | E58: 79.99 | F58: 69.56 | G58: 55.99 | H58: 48.69 | I58: 48.69 | J58: 55.65 | K58: 66.08 | M58: 52.17 | N58: 53.56 | O58: 41.73 | P58: 43.82 | Q58: 41.73 | R58: 41.73 | S58: 52.17 | T58: 41.73 | U58: 48.69 | V58: 41.73 | W58: 52.17 | X58: 52.17 | Y58: 79.99
A59: ARLO | B59: FLW2001B-100AUS | C59: ARLO 2K Wired Floodlight Camera (Black) | D59: Inactive | E59: 289 | G59: 289 | H59: 0 | Q59: 0 | R59: 0 | U59: 0 | V59: 0 | W59: 0 | X59: 0 | Y59: 289
A60: ARLO | B60: FLW2001-100AUS | C60: ARLO 2K Wired Floodlight Camera (White) | D60: Active | E60: 289 | F60: 251.30 | G60: 289 | H60: 201.04 | Q60: 201.04 | R60: 201.04 | U60: 188.48 | V60: 201.04 | W60: 0 | X60: 201.04 | Y60: 289
A61: ARLO | B61: AC2001-100AUS | C61: ARLO Chime 2 | D61: Inactive | E61: 89 | F61: 77.39 | G61: 89 | H61: 61.91 | Q61: 61.91 | R61: 61.91 | U61: 58.04 | V61: 61.91 | W61: 0 | X61: 61.91 | Y61: 89
A62: ARLO | B62: VMC3050-100AUS | C62: ARLO Essential 2K Outdoor Security Camera (2nd Generation) - 1 Pack | D62: Inactive | E62: 169 | F62: 146.96 | G62: 179 | H62: 117.57 | Q62: 117.57 | R62: 117.57 | U62: 110.22 | V62: 117.57 | X62: 117.57 | Y62: 169
A63: ARLO | B63: VMC3250-100AUS | C63: ARLO Essential 2K Outdoor Security Camera (2nd Generation) - 2 Pack | D63: Inactive | E63: 329 | F63: 286.09 | G63: 349 | H63: 228.87 | Q63: 228.87 | R63: 228.87 | U63: 214.57 | V63: 228.87 | X63: 228.87 | Y63: 329
A64: ARLO | B64: VMC3450-100AUS | C64: ARLO Essential 2K Outdoor Security Camera (2nd Generation) - 4 Pack | D64: Inactive | E64: 619 | F64: 538.26 | G64: 669 | H64: 430.61 | Q64: 430.61 | R64: 430.61 | U64: 403.7 | V64: 430.61 | X64: 430.61 | Y64: 619
A65: ARLO | B65: VMC3073-100AUS | C65: ARLO Essential 3 2K Indoor Powered PTZ Camera - 1 Pack | D65: Active | E65: 89 | F65: 77.39 | H65: 61.91 | U65: 58.04 | V65: 61.91 | X65: 61.91 | Y65: 89
A66: ARLO | B66: VMC3083-100AUS | C66: ARLO Essential 3 2K Outdoor Powered PTZ Camera - 1 Pack | D66: Active | E66: 149 | F66: 129.57 | H66: 103.65 | U66: 97.17 | V66: 103.65 | X66: 103.65 | Y66: 149
A67: ARLO | B67: VMC3080-100AUS | C67: ARLO Essential 3 2K Outdoor Security Camera - 1 Pack | D67: Active | E67: 169 | F67: 146.96 | H67: 117.57 | U67: 110.22 | V67: 117.57 | X67: 117.57 | Y67: 169
A68: ARLO | B68: VMC3280-100AUS | C68: ARLO Essential 3 2K Outdoor Security Camera - 2 Pack | D68: Active | E68: 319 | F68: 277.39 | H68: 221.91 | U68: 208.04 | V68: 221.91 | X68: 221.91 | Y68: 319
A69: ARLO | B69: VMC3480-100AUS | C69: ARLO Essential 3 2K Outdoor Security Camera - 4 Pack | D69: Active | E69: 599 | F69: 520.87 | H69: 416.7 | U69: 390.65 | V69: 416.7 | X69: 416.7 | Y69: 599
A70: ARLO | B70: VMA6600-10000S | C70: ARLO Essential Solar Panel Charger (2nd Generation) | D70: Inactive | E70: 99 | F70: 86.09 | G70: 99 | H70: 68.87 | Q70: 68.87 | R70: 68.87 | U70: 64.57 | V70: 68.87 | W70: 0 | X70: 68.87 | Y70: 99
A71: ARLO | B71: VMC3052-100AUS | C71: ARLO Essential XL 2nd Gen Wireless Security Camera - 1pk | D71: Inactive | E71: 209 | F71: 181.74 | G71: 219 | H71: 145.39 | Q71: 145.39 | R71: 145.39 | U71: 136.3 | V71: 145.39 | X71: 145.39 | Y71: 209
A72: ARLO | B72: VMC3352-100AUS | C72: ARLO Essential XL 2nd Gen Wireless Security Camera - 3pk | D72: Inactive | E72: 579 | F72: 503.48 | G72: 579 | H72: 402.78 | Q72: 402.78 | R72: 402.78 | U72: 377.61 | V72: 402.78 | X72: 402.78 | Y72: 579
A73: ARLO | B73: VML2030-100AUS | C73: ARLO Go 2 4G/Wi-Fi Mobile Security Camera | D73: Inactive | E73: 489 | F73: 425.22 | G73: 489 | H73: 340.17 | Q73: 340.17 | R73: 340.17 | U73: 318.91 | V73: 340.17 | W73: 0 | X73: 340.17 | Y73: 489
A74: ARLO | B74: FB1001-100AUS | C74: ARLO Pro 2K Wireless Floodlight Camera | D74: EOL | E74: 299 | F74: 260.00 | G74: 459 | H74: 208 | Q74: 208 | R74: 208 | U74: 195 | V74: 208 | X74: 208 | Y74: 299
A75: ARLO | B75: VMC4060P-100AUS | C75: ARLO Pro 5 2K Wireless Security Camera - 1 Pack | D75: Inactive | E75: 229 | F75: 199.13 | G75: 319 | H75: 159.3 | Q75: 159.3 | R75: 159.3 | U75: 149.35 | V75: 159.3 | X75: 159.3 | Y75: 229
A76: ARLO | B76: VMC4260P-100AUS | C76: ARLO Pro 5 2K Wireless Security Camera - 2 Pack | D76: Inactive | E76: 399 | F76: 346.96 | G76: 569 | H76: 277.57 | Q76: 277.57 | R76: 277.57 | U76: 260.22 | V76: 277.57 | X76: 277.57 | Y76: 399
A77: ARLO | B77: VMC4460P-100AUS | C77: ARLO Pro 5 2K Wireless Security Camera - 4 Pack | D77: Inactive | E77: 749 | F77: 651.30 | G77: 1079 | H77: 521.04 | Q77: 521.04 | R77: 521.04 | U77: 488.48 | V77: 521.04 | X77: 521.04 | Y77: 749
A78: ARLO | B78: VMC4070P-100AUS | C78: ARLO Pro 6 2K Outdoor Security Camera - 1 Pack | D78: Active | E78: 229 | F78: 199.13 | H78: 159.3 | U78: 149.35 | V78: 159.3 | X78: 159.3 | Y78: 229
A79: ARLO | B79: VMC4270P-100AUS | C79: ARLO Pro 6 2K Outdoor Security Camera - 2 Pack | D79: Active | E79: 399 | F79: 346.96 | H79: 277.57 | U79: 260.22 | V79: 277.57 | X79: 277.57 | Y79: 399
A80: ARLO | B80: VMC4470P-100AUS | C80: ARLO Pro 6 2K Outdoor Security Camera - 4 Pack | D80: Active | E80: 749 | F80: 651.30 | H80: 521.04 | U80: 488.48 | V80: 521.04 | X80: 521.04 | Y80: 749
A81: ARLO | B81: VMB4540-100AUS | C81: ARLO Pro Smart Hub | D81: Active | E81: 119 | F81: 103.48 | G81: 209 | H81: 82.78 | Q81: 82.78 | R81: 82.78 | U81: 77.61 | V81: 82.78 | X81: 82.78 | Y81: 119
A82: ARLO | B82: VMC5040-200AUS | C82: ARLO Ultra 2 4K Spotlight Camera - 1 Pack | D82: Inactive | E82: 319 | F82: 277.39 | G82: 429 | H82: 221.91 | Q82: 221.91 | R82: 221.91 | U82: 208.04 | V82: 221.91 | X82: 221.91 | Y82: 319
A83: ARLO | B83: VMS5240-200AUS | C83: ARLO Ultra 2 4K Spotlight Camera - 2 Pack | D83: Inactive | E83: 699 | F83: 607.83 | G83: 899 | H83: 486.26 | Q83: 486.26 | R83: 486.26 | U83: 455.87 | V83: 486.26 | X83: 486.26 | Y83: 699
A84: ARLO | B84: VMS5340-200AUS | C84: ARLO Ultra 2 4K Spotlight Camera - 3 Pack | D84: Inactive | E84: 999 | F84: 868.70 | G84: 1299 | H84: 694.96 | Q84: 694.96 | R84: 694.96 | U84: 651.52 | V84: 694.96 | X84: 694.96 | Y84: 999
A85: ARLO | B85: VMC5050-100AUS | C85: ARLO Ultra 3 4K Outdoor Security Camera - 1 Pack | D85: Active | E85: 319 | F85: 277.39 | H85: 221.91 | U85: 208.04 | V85: 221.91 | X85: 221.91 | Y85: 319
A86: ARLO | B86: VMS5250-100AUS | C86: ARLO Ultra 3 4K Outdoor Security Camera - 2 Pack | D86: Active | E86: 699 | F86: 607.83 | H86: 486.26 | U86: 455.87 | V86: 486.26 | X86: 486.26 | Y86: 699
A87: ARLO | B87: VMS5450-100AUS | C87: ARLO Ultra 3 4K Outdoor Security Camera - 4 Pack | D87: Active | E87: 1199 | F87: 1042.61 | H87: 834.09 | U87: 781.96 | V87: 834.09 | X87: 834.09 | Y87: 1199
A88: ARLO | B88: VMA7600-10000S | C88: ARLO Universal Solar Panel Charger | D88: Active | E88: 99 | G88: 99 | H88: 0 | Q88: 0 | R88: 0 | U88: 64.57 | V88: 68.87 | W88: 0 | X88: 0 | Y88: 99
A89: ARLO | B89: AVD4001-100AUS | C89: ARLO Video Doorbell 2K (2nd Generation) | D89: Active | E89: 199 | F89: 173.04 | G89: 259 | H89: 138.43 | Q89: 138.43 | R89: 138.43 | U89: 129.78 | V89: 138.43 | X89: 138.43 | Y89: 199
A90: AVANTI | B90: 16058 | C90: AVANTI 4 Egg Poacher with Non Stick Cups 20cm | D90: Active | E90: 96.95 | F90: 84.30 | G90: 99 | H90: 60.26 | I90: 69.53 | J90: 69.53 | Q90: 60.26 | R90: 60.26 | U90: 60.84 | V90: 60.26 | W90: 63.45 | X90: 65.18 | Y90: 99
A91: AVANTI | B91: 16057 | C91: AVANTI 6 Egg Poacher with Non Stick Cups 24cm | D91: Active | E91: 119 | F91: 103.48 | G91: 119 | H91: 72.43 | I91: 87.62 | J91: 87.62 | Q91: 72.43 | R91: 72.43 | U91: 76.67 | V91: 75.48 | W91: 79.95 | X91: 82.14 | Y91: 119
A92: AVANTI | B92: 15458 | C92: AVANTI Asola Stainless Steel Whistling Kettle 2.5L | D92: Active | E92: 78.95 | F92: 68.65 | G92: 89 | H92: 54.17 | I92: 69.53 | J92: 69.53 | Q92: 54.17 | R92: 54.17 | U92: 60.84 | V92: 60.26 | W92: 63.45 | X92: 65.18 | Y92: 89
A93: AVANTI | B93: 12941 | C93: AVANTI BBQ Fork with Pre-programmed Digital Thermometer | D93: Active | E93: 41.95 | F93: 36.48 | G93: 41.95 | H93: 56.2 | I93: 83.44 | J93: 83.44 | Q93: 56.2 | R93: 56.2 | U93: 30.4 | V93: 30.4 | W93: 0 | X93: 27.36 | Y93: 41.95
A94: AVANTI | B94: 12259 | C94: AVANTI BBQ Pizza Stone 33cm with Aluminium Slider | D94: Active | E94: 55.95 | F94: 48.65 | G94: 69 | H94: 42 | I94: 46.57 | J94: 46.57 | Q94: 42 | R94: 42 | U94: 42 | V94: 42 | W94: 43.8 | X94: 45 | Y94: 69
A95: AVANTI | B95: 16925 | C95: AVANTI Deluxe Salad Spinner 3.5L | D95: Active | E95: 76.95 | F95: 66.91 | G95: 89 | H95: 54.17 | I95: 55.62 | J95: 55.62 | Q95: 54.17 | R95: 54.17 | U95: 54.17 | V95: 54.17 | W95: 56.5 | X95: 58.04 | Y95: 89
A96: AVANTI | B96: 15196 | C96: AVANTI Emperor Hobnail Cast Iron Teapot 750ml (Black) | D96: Active | E96: 66.95 | F96: 58.22 | G96: 79 | H96: 48.09 | I96: 57.01 | J96: 57.01 | Q96: 48.09 | R96: 48.09 | U96: 49.88 | V96: 48.09 | W96: 52.02 | X96: 53.45 | Y96: 79
A97: AVANTI | B97: 16258 | C97: AVANTI Essentials Cocktail Set | D97: Active | E97: 54.95 | F97: 47.78 | G97: 69 | H97: 42 | I97: 46.57 | J97: 46.57 | Q97: 42 | R97: 42 | U97: 42 | V97: 42 | W97: 43.8 | X97: 45 | Y97: 69
A98: AVANTI | B98: 16852 | C98: AVANTI Large Display Digital Kitchen Scale (Black) | D98: Active | E98: 54.95 | F98: 47.78 | G98: 69 | H98: 42 | I98: 48.66 | J98: 48.66 | Q98: 42 | R98: 42 | U98: 42.58 | V98: 42 | W98: 44.4 | X98: 45.62 | Y98: 69
A99: AVANTI | B99: 16853 | C99: AVANTI Large Display Digital Kitchen Scale (White) | D99: Active | E99: 54.95 | F99: 47.78 | G99: 69 | H99: 42 | I99: 48.66 | J99: 48.66 | Q99: 42 | R99: 42 | U99: 42.58 | V99: 42 | W99: 44.4 | X99: 45.62 | Y99: 69
A100: AVANTI | B100: 12843 | C100: AVANTI Pencil Edge Mortar and Pestle 18cm (Black Speckled) | D100: Active | E100: 72.95 | F100: 63.43 | G100: 79 | H100: 48.09 | I100: 62.57 | J100: 62.57 | Q100: 48.09 | R100: 48.09 | U100: 54.75 | V100: 54.17 | W100: 57.1 | X100: 58.66 | Y100: 79
...

Sheet Merge
A1: Name | B1: Display Name | C1: Brand | D1: NZ Status | E1: Base Price | F1: Retail Value | G1: Location On Hand | H1: Customer Name | I1: 6wk avg | J1: WOS (6wk) | K1: SOH
A2: ELK-80065-R | B2: BONELK USB-C to MicroSD/SD Adapter - (Black) | C2: BONELK | D2: Active | E2: 34.99 | F2: 1119.68 | G2: 797 | H2: Noel Leeming | I2: 62.166667 | J2: 7 | K2: 424
A3: ELK-80078-R | B3: BONELK USB-C to MicroSD/SD Adapter (Space Grey) | C3: BONELK | D3: Active | E3: 34.99 | F3: 2344.33 | G3: 126 | H3: Noel Leeming | I3: 62 | J3: 9 | K3: 568
A4: ELK-80075-R | B4: BONELK Long-Life USB-C to 3.5mm AUX Audio Adapter (Black) | C4: BONELK | D4: Active | E4: 19.99 | F4: 1339.33 | H4: Noel Leeming | I4: 68.333333 | J4: 9 | K4: 616
A5: NSC-001 | B5: BONELK Screen Cleaning Kit 30 ml | C5: BONELK | D5: Active | E5: 19.99 | F5: 1199.4 | G5: 290 | H5: Noel Leeming | I5: 54 | J5: 15 | K5: 825
A6: ELK-80063-R | B6: BONELK USB-C to 4K HDMI Adapter - (Black) | C6: BONELK | D6: Active | E6: 44.99 | F6: 1529.66 | G6: 445 | H6: Noel Leeming | I6: 57 | J6: 5 | K6: 272
A7: ELK-80061-R | B7: BONELK USB-A to USB-C 3.0 Adapter - (Black) | C7: BONELK | D7: Active | E7: 19.99 | F7: 859.57 | G7: 820 | H7: Noel Leeming | I7: 53.166667 | J7: 12 | K7: 642
A8: TS-2259 | B8: TWELVE SOUTH AirFly SE | C8: TWELVE SOUTH | D8: Active | E8: 69.99 | F8: 7208.97 | G8: 1651 | H8: JB Hifi | I8: 82.5 | J8: 5 | K8: 451
A9: ELK-80062-R | B9: BONELK USB-C to USB-A 3.0 Adapter - (Black) | C9: BONELK | D9: Active | E9: 19.99 | F9: 879.56 | G9: 1022 | H9: Noel Leeming | I9: 54.666667 | J9: 12 | K9: 646
A10: TS-2259 | B10: TWELVE SOUTH AirFly SE | C10: TWELVE SOUTH | D10: Active | E10: 69.99 | F10: 3149.55 | G10: 1651 | H10: Noel Leeming | I10: 48.833333 | J10: 10 | K10: 483
A11: ELK-80076-R | B11: BONELK Long-Life USB-C to 3.5mm AUX Audio Adapter (White) | C11: BONELK | D11: Active | E11: 19.99 | F11: 979.51 | G11: 160 | H11: Noel Leeming | I11: 42.333333 | J11: 13 | K11: 567
A12: ELK-80077-R | B12: BONELK USB-A to USB-C 3.0 Adapter (Space Grey) | C12: BONELK | D12: Active | E12: 19.99 | F12: 699.65 | G12: 884 | H12: Noel Leeming | I12: 44.833333 | J12: 14 | K12: 646
A13: ELK-80079-R | B13: BONELK USB-C to USB-A 3.0 Adapter (Space Grey) | C13: BONELK | D13: Active | E13: 19.99 | F13: 939.53 | G13: 1092 | H13: Noel Leeming | I13: 46 | J13: 14 | K13: 633
A14: ELK-80020-R | B14: BONELK Long-Life 3in1 Multiport Hub - Space Grey | C14: BONELK | D14: Active | E14: 69.99 | F14: 2519.64 | H14: Noel Leeming | I14: 34.833333 | J14: 6 | K14: 220
A15: ELK-80062-R | B15: BONELK USB-C to USB-A 3.0 Adapter - (Black) | C15: BONELK | D15: Active | E15: 19.99 | F15: 639.68 | G15: 1022 | H15: JB Hifi | I15: 36.666667 | J15: 5 | K15: 177
A16: ELK-80078-R | B16: BONELK USB-C to MicroSD/SD Adapter (Space Grey) | C16: BONELK | D16: Active | E16: 34.99 | F16: 804.77 | G16: 126 | H16: JB Hifi | I16: 29.5 | J16: 4 | K16: 132
A17: ELK-80025-R | B17: BONELK Long-Life USB-C to 4K HDMI Adapter - 15cm (Space Grey) | C17: BONELK | D17: Active | E17: 59.99 | F17: 659.89 | G17: 38 | H17: Noel Leeming | I17: 30.166667 | J17: 2 | K17: 63
A18: TS-2259 | B18: TWELVE SOUTH AirFly SE | C18: TWELVE SOUTH | D18: Active | E18: 69.99 | F18: 2659.62 | G18: 1651 | H18: PB Tech | I18: 40.333333 | J18: 10 | K18: 401
A19: TS-2010 | B19: TWELVE SOUTH AirFly Pro (Black) | C19: TWELVE SOUTH | D19: Active | E19: 89.99 | F19: 1619.82 | G19: 253 | H19: Noel Leeming | I19: 26.666667 | J19: 14 | K19: 367
A20: TW-1911 | B20: TWELVE SOUTH AirFly Pro (White) | C20: TWELVE SOUTH | D20: Active | E20: 89.99 | F20: 3329.63 | G20: 1229 | H20: PB Tech | I20: 29.666667 | J20: 12 | K20: 367
A21: NSC-003 | B21: BONELK Screen Cleaning Kit (200 ml) | C21: BONELK | D21: Active | E21: 29.99 | F21: 509.83 | G21: 1252 | H21: PB Tech | I21: 19.666667 | J21: 28 | K21: 543
A22: ELK-80019-R | B22: BONELK Long-Life USB-C to USB-A Adapter - 15cm (Space Grey) | C22: BONELK | D22: Active | E22: 29.99 | F22: 779.74 | G22: 80 | H22: Noel Leeming | I22: 24.5 | J22: 24 | K22: 588
A23: ELK-80031-R | B23: BONELK Desktop Series 9 in 1 USB-C Multiport Hub - Black | C23: BONELK | D23: Active | E23: 199.99 | F23: 9199.54 | G23: 16 | H23: Noel Leeming | I23: 29.833333 | J23: 6 | K23: 193
A24: TW-1911 | B24: TWELVE SOUTH AirFly Pro (White) | C24: TWELVE SOUTH | D24: Active | E24: 89.99 | F24: 2429.73 | G24: 1229 | H24: JB Hifi | I24: 27.166667 | J24: 5 | K24: 144
A25: ST-SALKPM | B25: SATECHI Slim Wireless Keypad (Space Grey) | C25: SATECHI | D25: Active | E25: 89.99 | F25: 7199.2 | G25: 16 | H25: PB Tech | I25: 19.5 | J25: 0 | K25: 1
A26: ELK-80061-R | B26: BONELK USB-A to USB-C 3.0 Adapter - (Black) | C26: BONELK | D26: Active | E26: 19.99 | F26: 339.83 | G26: 820 | H26: JB Hifi | I26: 20.666667 | J26: 7 | K26: 144
... A34: ELK-80077-R | B34: BONELK USB-A to USB-C 3.0 Adapter (Space Grey) | C34: BONELK | D34: Active | E34: 19.99 | F34: 299.85 | G34: 884 | H34: JB Hifi | I34: 14.333333 | J34: 6 | K34: 88
A35: ST-LPDMK | B35: SATECHI Vegan-Leather Premium Desk Mat (Black) | C35: SATECHI | D35: Active | E35: 89.99 | F35: 449.95 | H35: PB Tech | I35: 6 | J35: 7 | K35: 43
A36: TW-1911 | B36: TWELVE SOUTH AirFly Pro (White) | C36: TWELVE SOUTH | D36: Active | E36: 89.99 | F36: 2339.74 | G36: 1229 | H36: Noel Leeming | I36: 23.166667 | J36: 15 | K36: 354
A37: ELK-80079-R | B37: BONELK USB-C to USB-A 3.0 Adapter (Space Grey) | C37: BONELK | D37: Active | E37: 19.99 | F37: 479.76 | G37: 1092 | H37: JB Hifi | I37: 18.666667 | J37: 3 | K37: 63
A38: ST3-DK-1-NS | B38: SPACETALK Adventurer 2 Smartwatch - 4G - Dusk | C38: SPACETALK | D38: Active | E38: 379 | F38: 6822 | G38: 187 | H38: Noel Leeming | I38: 14 | J38: 7 | K38: 94
A39: ELK-80065-R | B39: BONELK USB-C to MicroSD/SD Adapter - (Black) | C39: BONELK | D39: Active | E39: 34.99 | F39: 314.91 | G39: 797 | H39: Harvey Norman | I39: 17.166667 | J39: 1 | K39: 16
A40: ELK-80022-R | B40: BONELK Long-Life USB-C to 4 Port USB 3.0 Slim Hub (Space Grey) | C40: BONELK | D40: Active | E40: 49.99 | F40: 499.9 | G40: 116 | H40: Noel Leeming | I40: 14.833333 | J40: 15 | K40: 221
A41: 3040-01_BD | B41: BODUM Schiuma Battery Operated Milk Frother (Black) | C41: BODUM | D41: Inactive | E41: 29.9 | F41: 508.3 | H41: JB Hifi | I41: 14 | J41: 10 | K41: 144
A42: ELK-80030-R | B42: BONELK Long-Life 6 in 1 Multiport Adaptor (Space Grey) | C42: BONELK | D42: Active | E42: 119.99 | F42: 2279.81 | G42: 83 | H42: Noel Leeming | I42: 16.666667 | J42: 9 | K42: 146
A43: ST-CMAG | B43: SATECHI USB-C Slim Multiport Adapter v1 (Gold) | C43: SATECHI | D43: Inactive | E43: 119.99 | F43: 719.94 | H43: PB Tech | I43: 6.1666667 | J43: 10 | K43: 64
A44: ELK-80020-R | B44: BONELK Long-Life 3in1 Multiport Hub - Space Grey | C44: BONELK | D44: Active | E44: 69.99 | F44: 279.96 | H44: Harvey Norman | I44: 6.6666667 | J44: 10 | K44: 64
A45: ST3-FT-1-NS | B45: SPACETALK Adventurer 2 Smartwatch - 4G - Frost | C45: SPACETALK | D45: Active | E45: 379 | F45: 2274 | G45: 132 | H45: Noel Leeming | I45: 8.5 | J45: 13 | K45: 109
A46: TS-2010 | B46: TWELVE SOUTH AirFly Pro (Black) | C46: TWELVE SOUTH | D46: Active | E46: 89.99 | F46: 899.9 | G46: 253 | H46: JB Hifi | I46: 11.333333 | J46: 6 | K46: 73
A47: NSC-001 | B47: BONELK Screen Cleaning Kit 30 ml | C47: BONELK | D47: Active | E47: 19.99 | F47: 299.85 | G47: 290 | H47: Harvey Norman | I47: 12.666667 | J47: 15 | K47: 190
A48: TS-2305 | B48: TWELVE SOUTH AirFly Pro Deluxe | C48: TWELVE SOUTH | D48: Active | E48: 119.99 | F48: 719.94 | G48: 104 | H48: PB Tech | I48: 9.5 | J48: 7 | K48: 66
A49: TS-2010 | B49: TWELVE SOUTH AirFly Pro (Black) | C49: TWELVE SOUTH | D49: Active | E49: 89.99 | F49: 359.96 | G49: 253 | H49: PB Tech | I49: 9.5 | J49: 43 | K49: 406
A50: ELK-80024-R | B50: BONELK Long-Life USB-A to 4 Port USB 3.0 Slim Hub (Space Grey) | C50: BONELK | D50: Active | E50: 44.99 | F50: 809.82 | G50: 258 | H50: Noel Leeming | I50: 18.666667 | J50: 12 | K50: 215
A51: ELK-80036-R | B51: BONELK Long-Life USB-A to 4 Port USB 3.0 Slim Hub (Black) | C51: BONELK | D51: Active | E51: 44.99 | F51: 719.84 | G51: 68 | H51: Noel Leeming | I51: 13.333333 | J51: 12 | K51: 161
A52: ELK-80063-R | B52: BONELK USB-C to 4K HDMI Adapter - (Black) | C52: BONELK | D52: Active | E52: 44.99 | F52: 179.96 | G52: 445 | H52: JB Hifi | I52: 8.1666667 | J52: 5 | K52: 42
A53: ELK-80065-R | B53: BONELK USB-C to MicroSD/SD Adapter - (Black) | C53: BONELK | D53: Active | E53: 34.99 | F53: 209.94 | G53: 797 | H53: PB Tech | I53: 12.666667 | J53: 12 | K53: 157
A54: ST-P3D13K | B54: SATECHI 13-in-1 USB-C Triple Display Multiport Adapter (Black) | C54: SATECHI | D54: Active | E54: 179.99 | F54: 2519.86 | G54: 64 | H54: PB Tech | I54: 10.666667 | J54: 6 | K54: 68
A55: CH-C21R-GY-R-EN | B55: CHIPOLO CARD Spot (Black) | C55: CHIPOLO | D55: Active | E55: 59.99 | F55: 59.99 | G55: 143 | H55: Noel Leeming | I55: 10.166667 | J55: 0 | K55: 4
A56: ELK-05010-R | B56: BONELK USB-C to HDMI Long Life Cable 1.5m (Black) | C56: BONELK | D56: Active | E56: 64.99 | F56: 389.94 | G56: 180 | H56: JB Hifi | I56: 9.3333333 | J56: 2 | K56: 23
... A59: ELK-80048-R | B59: BONELK Long-Life USB-C 4 in 1 Multiport Slim Hub (Space Grey) | C59: BONELK | D59: Active | E59: 59.99 | F59: 299.95 | G59: 61 | H59: Noel Leeming | I59: 7.5 | J59: 16 | K59: 118
A60: WBS13-Black | B60: WITHINGS Body Smart Scale - Black | C60: WITHINGS | D60: Active | E60: 219.99 | F60: 219.99 | H60: Noel Leeming | I60: 7.1666667 | J60: 5 | K60: 39
A61: PL2A-10-22 | B61: PAPERLIKE Screen Protector v2.1 for iPad 10.9" 10th Gen (2 Pack) | C61: PAPERLIKE | D61: Active | E61: 69.99 | F61: 489.93 | G61: 92 | H61: PB Tech | I61: 7 | J61: 6 | K61: 43
A62: ADMB | B62: ADONIT Mark (Black) | C62: ADONIT | D62: Active | E62: 29.99 | F62: 89.97 | G62: 18 | H62: Noel Leeming | I62: 8 | J62: 4 | K62: 31
A63: SK2-FT-1-NS | B63: SPACETALK Loop Smartwatch - 4G - Frost | C63: SPACETALK | D63: Active | E63: 249 | F63: 1245 | G63: 196 | H63: Noel Leeming | I63: 6.5 | J63: 18 | K63: 115
A64: SK2-DK-1-NS | B64: SPACETALK Loop Smartwatch - 4G - Dusk | C64: SPACETALK | D64: Active | E64: 249 | F64: 2241 | G64: 135 | H64: Noel Leeming | I64: 10.333333 | J64: 10 | K64: 104
A65: ST-TAUCM | B65: SATECHI Aluminium USB-A to USB-C Adapter (Space Grey) | C65: SATECHI | D65: Active | E65: 24.99 | F65: 74.97 | G65: 242 | H65: JB Hifi | I65: 7.1666667 | J65: 12 | K65: 86
A66: ELK-80036-R | B66: BONELK Long-Life USB-A to 4 Port USB 3.0 Slim Hub (Black) | C66: BONELK | D66: Active | E66: 44.99 | F66: 179.96 | G66: 68 | H66: PB Tech | I66: 4 | J66: 42 | K66: 168
A67: ST-BTSX1M | B67: SATECHI Slim X1 Bluetooth Keyboard (Space Grey) | C67: SATECHI | D67: Active | E67: 129.99 | F67: 649.95 | H67: PB Tech | I67: 5.5 | J67: 14 | K67: 75
A68: ELK-70408-R | B68: BONELK Elevate Laptop Stand (Black) | C68: BONELK | D68: Active | E68: 119.99 | F68: 959.92 | G68: 51 | H68: PB Tech | I68: 8.6666667 | J68: 17 | K68: 145
A69: ELK-80020-R | B69: BONELK Long-Life 3in1 Multiport Hub - Space Grey | C69: BONELK | D69: Active | E69: 69.99 | F69: 1119.84 | H69: PB Tech | I69: 9 | J69: 15 | K69: 137
A70: ELK-61012-R | B70: BONELK Slim Wireless Keyboard and Mouse Combo, KM-314 - Black | C70: BONELK | D70: Active | E70: 39.99 | F70: 439.89 | H70: PB Tech | I70: 7.6666667 | J70: 59 | K70: 451
A71: ELK-61013-R | B71: BONELK Slim Wireless Keyboard and Mouse Combo, KM-314 - White | C71: BONELK | D71: Active | E71: 39.99 | F71: 79.98 | H71: PB Tech | I71: 5.3333333 | J71: 88 | K71: 467
A72: ELK-80023-R | B72: BONELK Long-Life USB-C to 2 Port USB 3.0 Slim Hub (Space Grey) | C72: BONELK | D72: Active | E72: 39.99 | F72: 359.91 | G72: 116 | H72: Noel Leeming | I72: 9.6666667 | J72: 23 | K72: 224
A73: ELK-80061-R | B73: BONELK USB-A to USB-C 3.0 Adapter - (Black) | C73: BONELK | D73: Active | E73: 19.99 | F73: 239.88 | G73: 820 | H73: Harvey Norman | I73: 10 | J73: 8 | K73: 83
A74: ST-WCS5PM | B74: SATECHI Dock5 Multi-Device Charging Station with Wireless Charging | C74: SATECHI | D74: Active | E74: 129.99 | F74: 519.96 | G74: 51 | H74: PB Tech | I74: 5.3333333 | J74: 22 | K74: 117
A75: ST-BTSX3M | B75: SATECHI Slim X3 Bluetooth Keyboard (Space Grey) | C75: SATECHI | D75: Active | E75: 159.99 | F75: 0 | H75: PB Tech | I75: 4 | J75: 2 | K75: 8
A76: ELK-80027-R | B76: BONELK Long-Life USB-C to Gigabit Ethernet Adapter - 15cm (Space Grey) | C76: BONELK | D76: Active | E76: 59.99 | F76: 299.95 | G76: 103 | H76: Noel Leeming | I76: 8.5 | J76: 16 | K76: 133
A77: PL2A-11-18 | B77: PAPERLIKE Screen Protector v2.1 for iPad Pro 11" & iPad Air 10.9" (2 Pack) | C77: PAPERLIKE | D77: Active | E77: 69.99 | F77: 489.93 | G77: 190 | H77: JB Hifi | I77: 6 | J77: 8 | K77: 51
A78: TS-2010 | B78: TWELVE SOUTH AirFly Pro (Black) | C78: TWELVE SOUTH | D78: Active | E78: 89.99 | F78: 359.96 | G78: 253 | H78: Harvey Norman | I78: 5 | J78: 21 | K78: 103
A79: ELK-80064-R | B79: BONELK USB-C to Ethernet Adapter - (Black) | C79: BONELK | D79: Active | E79: 39.99 | F79: 239.94 | G79: 117 | H79: PB Tech | I79: 6.6666667 | J79: 25 | K79: 168
A80: ELK-61007-R | B80: BONELK Slim Wireless Keyboard and Mouse Combo, KM-322 (Salmon) | C80: BONELK | D80: Inactive | E80: 59.99 | F80: 59.99 | H80: PB Tech | I80: 3 | J80: 28 | K80: 84
A81: ELK-42002-R | B81: BONELK Fly Wireless Bluetooth Transmitter (Black) | C81: BONELK | D81: EOL | E81: 59.99 | F81: 59.99 | H81: PB Tech | I81: 3.8333333 | J81: 108 | K81: 415
A82: WBS12-Black | B82: WITHINGS Body Comp Scale - Black | C82: WITHINGS | D82: Active | E82: 379.99 | F82: 0 | H82: Noel Leeming | I82: 3.5 | J82: 8 | K82: 27
A83: ELK-80044-R | B83: BONELK Long-Life 3in1 Multiport Hub - Black | C83: BONELK | D83: Active | E83: 69.99 | F83: 1049.85 | G83: 110 | H83: Noel Leeming | I83: 14.333333 | J83: 5 | K83: 75
A84: WPM-05-AU | B84: WITHINGS BPM Connect Wireless Blood Pressure Monitor | C84: WITHINGS | D84: Active | E84: 199.99 | F84: 1399.93 | G84: 148 | H84: Noel Leeming | I84: 6.3333333 | J84: 10 | K84: 63
A85: WPM-05-AU | B85: WITHINGS BPM Connect Wireless Blood Pressure Monitor | C85: WITHINGS | D85: Active | E85: 199.99 | F85: 1399.93 | G85: 148 | H85: Noel Leeming | I85: 6.3333333 | J85: 10 | K85: 63
A86: ELK-80055-R | B86: BONELK Long-Life USB-C to 11 in 1 Multiport Hub - (Space Grey) | C86: BONELK | D86: Active | E86: 179.99 | F86: 179.99 | G86: 26 | H86: Noel Leeming | I86: 4 | J86: 18 | K86: 70
A87: ELK-70411-R | B87: BONELK Elevate Junior Stand (Black) | C87: BONELK | D87: Active | E87: 89.99 | F87: 359.96 | G87: 63 | H87: Noel Leeming | I87: 5.3333333 | J87: 24 | K87: 129
A88: WBS12-Black | B88: WITHINGS Body Comp Scale - Black | C88: WITHINGS | D88: Active | E88: 379.99 | F88: 0 | H88: JB Hifi | I88: 2.3333333 | J88: 19 | K88: 44
A89: ELK-80043-R | B89: BONELK Long-Life USB-A to 4 Port USB 3.0 Slim Hub - Blue | C89: BONELK | D89: Active | E89: 44.99 | F89: 89.98 | G89: 69 | H89: JB Hifi | I89: 2.8333333 | J89: 16 | K89: 45
A90: ADMB | B90: ADONIT Mark (Black) | C90: ADONIT | D90: Active | E90: 29.99 | F90: 59.98 | G90: 18 | H90: Harvey Norman | I90: 4.5 | J90: 12 | K90: 55
A91: WBS13-Black | B91: WITHINGS Body Smart Scale - Black | C91: WITHINGS | D91: Active | E91: 219.99 | F91: 0 | H91: Harvey Norman | I91: 3.8333333 | J91: 10 | K91: 37
A92: ELK-80063-R | B92: BONELK USB-C to 4K HDMI Adapter - (Black) | C92: BONELK | D92: Active | E92: 44.99 | F92: 179.96 | G92: 445 | H92: Harvey Norman | I92: 6.3333333 | J92: 7 | K92: 43
A93: ELK-80037-R | B93: BONELK Long-Life USB-A to 3 Port Hub + SD/TF Reader - Space Grey | C93: BONELK | D93: Active | E93: 59.99 | F93: 239.96 | G93: 41 | H93: Harvey Norman | I93: 5 | J93: 11 | K93: 54
A94: ELK-80059-R | B94: BONELK Long-Life USB-C 4 in 1 Multiport Slim Hub (Black) | C94: BONELK | D94: Active | E94: 59.99 | F94: 119.98 | G94: 34 | H94: PB Tech | I94: 2.5 | J94: 34 | K94: 85
A95: ELK-80040-R | B95: BONELK Long-Life USB-C to 4 Port USB 3.0 Slim Hub - (Black) | C95: BONELK | D95: Active | E95: 49.99 | F95: 49.99 | G95: 68 | H95: PB Tech | I95: 4 | J95: 30 | K95: 120
A96: ELK-63022-R | B96: BONELK USB Webcam, Clip On, 1080p (Black) | C96: BONELK | D96: Active | E96: 69.99 | F96: 559.92 | G96: 64 | H96: PB Tech | I96: 11 | J96: 13 | K96: 145
A97: ADM4DG | B97: ADONIT Mini 4 (Grey) | C97: ADONIT | D97: Active | E97: 39.99 | F97: 159.96 | G97: 142 | H97: PB Tech | I97: 5.6666667 | J97: 11 | K97: 64
A98: PL2A-10-22 | B98: PAPERLIKE Screen Protector v2.1 for iPad 10.9" 10th Gen (2 Pack) | C98: PAPERLIKE | D98: Active | E98: 69.99 | F98: 419.94 | G98: 92 | H98: Noel Leeming | I98: 7.3333333 | J98: 10 | K98: 77
A99: ADM4DG | B99: ADONIT Mini 4 (Grey) | C99: ADONIT | D99: Active | E99: 39.99 | F99: 199.95 | G99: 142 | H99: Noel Leeming | I99: 7.3333333 | J99: 6 | K99: 43
A100: ELK-80022-R | B100: BONELK Long-Life USB-C to 4 Port USB 3.0 Slim Hub (Space Grey) | C100: BONELK | D100: Active | E100: 49.99 | F100: 249.95 | G100: 116 | H100: JB Hifi | I100: 6.1666667 | J100: 7 | K100: 42
A101: ELK-80030-R | B101: BONELK Long-Life 6 in 1 Multiport Adaptor (Space Grey) | C101: BONELK | D101: Active | E101: 119.99 | F101: 239.98 | G101: 83 | H101: JB Hifi | I101: 3.6666667 | J101: 9 | K101: 33
A102: ELK-63022-R | B102: BONELK USB Webcam, Clip On, 1080p (Black) | C102: BONELK | D102: Active | E102: 69.99 | F102: 349.95 | G102: 64 | H102: JB Hifi | I102: 7 | J102: 8 | K102: 58
A103: ELK-80038-R | B103: BONELK Long-Life USB-A to 3 Port Hub + SD/TF Reader - Black | C103: BONELK | D103: Active | E103: 59.99 | F103: 239.96 | G103: 55 | H103: JB Hifi | I103: 5.5 | J103: 11 | K103: 58
... A105: ST-P3D13K | B105: SATECHI 13-in-1 USB-C Triple Display Multiport Adapter (Black) | C105: SATECHI | D105: Active | E105: 179.99 | F105: 899.95 | G105: 64 | H105: JB Hifi | I105: 3.1666667 | J105: 12 | K105: 37
A106: NF082K05-40LS | B106: NANOLEAF 4D TV Screen Mirror Kit for TVs up to 65"- 4 Meters | C106: NANOLEAF | D106: Active | E106: 179.99 | F106: 719.96 | H106: JB Hifi | I106: 4.3333333 | J106: 15 | K106: 63
A107: ADM4DG | B107: ADONIT Mini 4 (Grey) | C107: ADONIT | D107: Active | E107: 39.99 | F107: 199.95 | G107: 142 | H107: Harvey Norman | I107: 6.3333333 | J107: 9 | K107: 60
A108: ELK-80019-R | B108: BONELK Long-Life USB-C to USB-A Adapter - 15cm (Space Grey) | C108: BONELK | D108: Active | E108: 29.99 | F108: 59.98 | G108: 80 | H108: Harvey Norman | I108: 5.8333333 | J108: 12 | K108: 70
A109: ELK-80030-R | B109: BONELK Long-Life 6 in 1 Multiport Adaptor (Space Grey) | C109: BONELK | D109: Active | E109: 119.99 | F109: 599.95 | G109: 83 | H109: Harvey Norman | I109: 5.6666667 | J109: 10 | K109: 58
A110: TW-1911 | B110: TWELVE SOUTH AirFly Pro (White) | C110: TWELVE SOUTH | D110: Active | E110: 89.99 | F110: 359.96 | G110: 1229 | H110: Harvey Norman | I110: 4.5 | J110: 15 | K110: 66
...

Sheet ST
A1: Code | B1: Description | C1: Brand | D1: Customer Name | E1: Customer Code | F1: Retail Value | G1: 6wk avg | H1: WOS
A2: 010-02294-13 | B2: GARMIN Index S2 Wi-Fi Smart Scale (White) | C2: GARMIN | D2: Noel Leeming | E2: 227007
A3: 010-02469-20 | B3: GARMIN DriveSmart 66 MT-S | C3: GARMIN | D3: Noel Leeming | E3: 238122
A4: 010-02469-20 | B4: GARMIN DriveSmart 66 MT-S | C4: GARMIN | D4: Noel Leeming | E4: 238123
A5: 010-02746-12 | B5: GARMIN Approach S70 47mm (Black with Black Band) | C5: GARMIN | D5: Noel Leeming | E5: 242419
A6: 010-02921-01 | B6: GARMIN GPSMAP H1i Plus Premium Handheld GPS with inReachÂ® Plus Satellite Technology | C6: GARMIN | D6: Noel Leeming | E6: 248200
A7: 010201AA000795 | B7: MOVA Z60 Ultra Roller Wet and Dry Robotic Vacuum | C7: MOVA | D7: JB HIFI | E7: 471965
A8: 010201AA000795 | B8: MOVA Z60 Ultra Roller Wet and Dry Robotic Vacuum | C8: MOVA | D8: Noel Leeming | E8: 249258 | F8: 2999 | G8: 1.3333333 | H8: 35.25
A9: 010204AA000727 | B9: MOVA P50 Ultra Wet and Dry Robotic Vacuum | C9: MOVA | D9: Noel Leeming | E9: 249260 | F9: 12593 | G9: 6.6666667 | H9: 12.75
A10: 010204AA000891 | B10: MOVA E40 Ultra Robotic Vacuum | C10: MOVA | D10: JB HIFI | E10: 471964 | F10: 5495 | G10: 3.6666667 | H10: 7.0909091
A11: 010204AA000891 | B11: MOVA E40 Ultra Robotic Vacuum | C11: MOVA | D11: Noel Leeming | E11: 249259 | F11: 4396 | G11: 11.833333 | H11: 2.7887324
A12: 010204AA000891 | B12: MOVA E40 Ultra Robotic Vacuum | C12: MOVA | D12: Noel Leeming | E12: 249649 | F12: 0 | G12: 0 | H12: 0
A13: 010901AA000024 | B13: MOVA Robotic Lawn Mower 1000 | C13: MOVA | D13: Noel Leeming | E13: 248664 | F13: 4798 | G13: 0.66666667 | H13: -3
A14: 010901AA000026 | B14: MOVA Robotic Lawn Mower 600 | C14: MOVA | D14: JB HIFI | E14: 471966
A15: 010901AA000026 | B15: MOVA Robotic Lawn Mower 600 | C15: MOVA | D15: Noel Leeming | E15: 248663 | F15: 2099 | G15: 0.33333333 | H15: -3
A16: 01A001 | B16: GUMDROP DropTech Case for iPad 10.2″ (7th, 8th, 9th Gen) | C16: GUMDROP | D16: Noel Leeming | E16: 192229 | F16: 0 | G16: 0 | H16: 0
A17: 01H004 | B17: GUMDROP DropTechUSB B2 Headsets | C17: GUMDROP | D17: PB Tech
A18: 01L001 | B18: GUMDROP MTK Lenovo 300e Gen2 CB | C18: GUMDROP | D18: Noel Leeming | E18: 192224 | F18: 0 | G18: 0 | H18: 0
A19: 01M000 | B19: GUMDROP DropTech for for Microsoft Surface Pro 6 (Black) | C19: GUMDROP | D19: Noel Leeming | E19: 187569 | F19: 0 | G19: 0 | H19: 0
A20: 03A005 | B20: GUMDROP Hideaway Case for iPad 10.2″ (7th, 8th, 9th Gen) | C20: GUMDROP | D20: Noel Leeming | E20: 187568
A21: 03A008 | B21: GUMDROP HideAway Folio for iPad 10.2" (7th, 8th, 9th Gen) - Black | C21: GUMDROP | D21: PB Tech
A22: 104179 | B22: TADO Smart AC Control V3+ | C22: TADO | D22: Noel Leeming | E22: 201092 | F22: 0 | G22: 0 | H22: 0
A23: 114098.BLK00.12 | B23: MACPAC Uber Light Down Jacket Womens (12) (Black) | C23: MACPAC | D23: Noel Leeming | E23: 212052
A24: 114099.BLK00.M | B24: MACPAC Uber Light Down Vest Mens (M) (Black) | C24: MACPAC | D24: Noel Leeming | E24: 212746 | F24: 0 | G24: 0 | H24: 0
A25: 119183.BLK00.10 | B25: MACPAC Long Sleeve Geothermal Womens V2 (10) (Black) | C25: MACPAC | D25: Noel Leeming | E25: 214433 | F25: 0 | G25: 0 | H25: 0
A26: 119185.BLK00.10 | B26: MACPAC Geothermal Pant V2 Womens (10) | C26: MACPAC | D26: Noel Leeming | E26: 214432 | F26: 0 | G26: 0 | H26: 0
A27: 119249.BLKOO.10 | B27: MACPAC Tui Pullover Womens (10) (Black) | C27: MACPAC | D27: Noel Leeming | E27: 214431 | F27: 0 | G27: 0 | H27: 0
A28: 11940-01AUSBD | B28: BODUM Bistro Gooseneck Water Kettle 1L (Black) | C28: BODUM | D28: JB HIFI | E28: 437345 | F28: 170 | G28: 2.6666667 | H28: 11.625
A29: 20010100001198 | B29: MOVA Dust Bag for E40 E50 P50 P70 S70 V50 Z60 and Mobius Series | C29: MOVA | D29: JB HIFI | E29: 476152 | F29: 0 | G29: 0 | H29: 0
A30: 20010100001313 | B30: MOVA Multi-Surface Floor Cleaner 1L for E40 E50 P S V Z60 Z70 and Mobius Series | C30: MOVA | D30: Noel Leeming | E30: 251841 | F30: 0 | G30: 0.33333333 | H30: -6
A31: 2757 | B31: BRENTHAVEN Tred Always-On Sleeve 13" 2017 - w Pouch (Black) | C31: BRENTHAVEN | D31: Noel Leeming | E31: 162828 | F31: 0 | G31: 0 | H31: 0
A32: 3040-01BD | B32: BODUM Schiuma Battery Operated Milk Frother (Black) | C32: BODUM | D32: JB HIFI | E32: 398895 | F32: 200 | G32: 11.5 | H32: 16.347826
A33: 4559-10BD | B33: BODUM Pavina Double Wall 350ml 2 Piece Set | C33: BODUM | D33: JB HIFI | E33: 398899 | F33: 55 | G33: 1.3333333 | H33: 72
A34: 4560-10BD | B34: BODUM Pavina Double Wall 450ml 2 Piece Set | C34: BODUM | D34: JB HIFI | E34: 437344 | F34: 120 | G34: 1.6666667 | H34: 54
A35: 5109BYPA | B35: HONOR Magic V5 16GB+512GB Dawn Gold | C35: HONOR | D35: Harvey Norman | G35: 0.33333333 | H35: 186
A36: 5109BYPA | B36: HONOR Magic V5 16GB+512GB Dawn Gold | C36: HONOR | D36: Noel Leeming | E36: 247316 | F36: 0 | G36: 0.5 | H36: 54
A37: 5109BYPA-DEMO | B37: HONOR Magic V5 16GB+512GB Dawn Gold DEMO | C37: HONOR | D37: Harvey Norman | H37: 0
A38: 5109BYPA-DEMO | B38: HONOR Magic V5 16GB+512GB Dawn Gold DEMO | C38: HONOR | D38: Noel Leeming | E38: 247680 | F38: 0 | G38: 0 | H38: 0
A39: 5109BYPB | B39: HONOR Magic V5 16GB+512GB Black | C39: HONOR | D39: Harvey Norman | G39: 0.66666667 | H39: 97.5
A40: 5109BYPB | B40: HONOR Magic V5 16GB+512GB Black | C40: HONOR | D40: Noel Leeming | E40: 247317 | F40: 0 | G40: 0.33333333 | H40: 75
A41: 5109BYPC | B41: HONOR Magic V5 16GB+512GB Ivory White | C41: HONOR | D41: Noel Leeming | E41: 247313 | F41: 0 | G41: 0 | H41: 0
A42: 5109BYPH | B42: HONOR X9d Midnight Black | C42: HONOR | D42: Harvey Norman | F42: 6392 | G42: 2 | H42: 48
A43: 5109BYPH | B43: HONOR X9d Midnight Black | C43: HONOR | D43: JB HIFI | E43: 476082 | F43: 6392 | G43: 2.8333333 | H43: 15.176471
A44: 5109BYPH | B44: HONOR X9d Midnight Black | C44: HONOR | D44: Noel Leeming | E44: 251814 | F44: 14382 | G44: 6.1666667 | H44: 33.081081
A45: 5109BYPH-DEMO | B45: HONOR X9D MIDNIGHT BLACK DEMO | C45: HONOR | D45: Harvey Norman | H45: 0
A46: 5109BYPH-DEMO | B46: HONOR X9D MIDNIGHT BLACK DEMO | C46: HONOR | D46: JB HIFI | E46: 476073 | F46: 0 | G46: 0 | H46: 0
A47: 5109BYPK | B47: HONOR X9d Sunrise Gold | C47: HONOR | D47: Harvey Norman | F47: 7191 | G47: 1.8333333 | H47: 33.272727
A48: 5109BYPK | B48: HONOR X9d Sunrise Gold | C48: HONOR | D48: JB HIFI | E48: 476083 | F48: 4794 | G48: 1.8333333 | H48: 22.909091
A49: 5109BYPK | B49: HONOR X9d Sunrise Gold | C49: HONOR | D49: Noel Leeming | E49: 251813 | F49: 3196 | G49: 2.1666667 | H49: 29.538462
A50: 5109BYWA | B50: HONOR X9d Reddish Brown | C50: HONOR | D50: Noel Leeming | E50: 251818 | F50: 15980 | G50: 7.8333333 | H50: 25.276596
A51: 5109BYWT | B51: HONOR 400 Pro Black | C51: HONOR | D51: Harvey Norman | F51: 1099 | G51: 1.1666667 | H51: 58.285714
A52: 5109BYWT | B52: HONOR 400 Pro Black | C52: HONOR | D52: Noel Leeming | E52: 247766 | F52: 3297 | G52: 3 | H52: 38
